Workbook

Sheet Panel SyS
A1: DESARROLLO PROFESIONAL SyS · AUDIOS DEL EQUIPO
A2: Audios del equipo en el paso 1.2 · tres embudos
A3: ISO + Calidad, Manufactura y Calidad y Core Tools Premium · preguntas del 5 al 15 de octubre de 2026 · corte: 15 oct 2026, 23:59 h (Monterrey)
A4: 615 leads recibieron la pregunta «¿en qué área trabajas?». Lectura del CRM en solo lectura; los casos del 15 de octubre todavía pueden cambiar.
A6: =Resumen!H10 -> 615 | C6: =Resumen!H11 -> 236 | E6: =Resumen!H18 -> 220 | G6: =Resumen!H21 -> 6.4108167 | I6: =Resumen!H31 -> 155 | K6: =Resumen!H34 -> 85
A8: Leads con la pregunta | C8: Informaron su perfil | E8: Recibieron audio | G8: Minutos al audio (mediana) | I8: Respondieron después | K8: Bot a Negativo después
A10: • De 236 que informaron su perfil, 235 recibieron recomendación y 220 con audio (93%). 155 volvieron a responder y el bot pasó a 85 de ellos a Negativo (55%), a las 4.0 h (mediana) de su último mensaje.
A11: • La pregunta es el cuello de botella: solo 38% dice su perfil; 214 de los 342 que no contestaron sí la vieron (palomitas azules). Entre 8:00 y 22:00 contestaron 208 de 500 (42%); fuera, 28 de 115 (24%).
A12: • El audio llega en 6.4 min (mediana), dura 105 s y el 71% lo ve. Con audio en menos de 4 min respondió el 76%; con más espera, el 63% (p = 0.10).
A13: • Después de una nota de voz de una persona, el lead escribe en 24 h el 60% de las veces; después del audio automático del bot, el 11%.
A15: Tiempo a la recomendación
A16: Rango | C16: Leads | D16: Respondieron | E16: Tasa
A17: =Tiempos!B6 -> Menos de 4 min | C17: =Tiempos!C6 -> 54 | D17: =Tiempos!D6 -> 41 | E17: =IFERROR(D17/C17,0) -> 0.75925926
A18: =Tiempos!B7 -> 4 a 6 min | C18: =Tiempos!C7 -> 53 | D18: =Tiempos!D7 -> 32 | E18: =IFERROR(D18/C18,0) -> 0.60377358
A19: =Tiempos!B8 -> 6 a 10 min | C19: =Tiempos!C8 -> 52 | D19: =Tiempos!D8 -> 34 | E19: =IFERROR(D19/C19,0) -> 0.65384615
A20: =Tiempos!B9 -> 10 a 30 min | C20: =Tiempos!C9 -> 56 | D20: =Tiempos!D9 -> 37 | E20: =IFERROR(D20/C20,0) -> 0.66071429
A21: =Tiempos!B10 -> 30 min o más | C21: =Tiempos!C10 -> 20 | D21: =Tiempos!D10 -> 11 | E21: =IFERROR(D21/C21,0) -> 0.55
A31: Por embudo
A32: Embudo | C32: Con la pregunta | D32: Informaron perfil | E32: Con audio | F32: Min. al audio | G32: Respondieron | H32: Bot a Negativo | I32: Ganados (perfil)
A33: ISO + Calidad | C33: =Resumen!B10 -> 398 | D33: =Resumen!B11 -> 158 | E33: =Resumen!B18 -> 147 | F33: =Resumen!B21 -> 6.875 | G33: =Resumen!B31 -> 101 | H33: =Resumen!B34 -> 58 | I33: =Resumen!B37 -> 3
A34: Manufactura y Calidad | C34: =Resumen!D10 -> 110 | D34: =Resumen!D11 -> 41 | E34: =Resumen!D18 -> 39 | F34: =Resumen!D21 -> 5.0288167 | G34: =Resumen!D31 -> 30 | H34: =Resumen!D34 -> 14 | I34: =Resumen!D37 -> 2
A35: Core Tools Premium | C35: =Resumen!F10 -> 107 | D35: =Resumen!F11 -> 37 | E35: =Resumen!F18 -> 34 | F35: =Resumen!F21 -> 6.3731 | G35: =Resumen!F31 -> 24 | H35: =Resumen!F34 -> 13 | I35: =Resumen!F37 -> 3
A36: Tres embudos | C36: =Resumen!H10 -> 615 | D36: =Resumen!H11 -> 236 | E36: =Resumen!H18 -> 220 | F36: =Resumen!H21 -> 6.4108167 | G36: =Resumen!H31 -> 155 | H36: =Resumen!H34 -> 85 | I36: =Resumen!H37 -> 8
A38: Hora de Monterrey (central de México). «Respondieron» = escribieron después de la recomendación, hasta el corte. Detalle en las demás pestañas.

Sheet Resumen
A1: DESARROLLO PROFESIONAL SyS
A2: Paso 1.2: respuesta del lead y recomendación con audio del equipo
A3: ISO + Calidad, Manufactura y Calidad y Core Tools Premium · preguntas del 5 al 15 de octubre de 2026 · corte: 15 oct 2026, 23:59 h (Monterrey) · hora de Monterrey (central de México)
A4: El equipo manda el audio rápido (mediana de 6.4 min) y 66% de los leads vuelve a escribir. Lo que más se pierde: la pregunta que nadie contesta (56%) y los leads que el bot pasa a Negativo cuando ya estaban conversando (55%).
A6: Indicador | B6: ISO + Calidad | D6: Manufactura y Calidad | F6: Core Tools Premium | H6: Tres embudos | J6: Muestra anterior
B7: Valor | C7: % | D7: Valor | E7: % | F7: Valor | G7: % | H7: Valor | I7: % | J7: Valor | K7: %
A9: La pregunta del bot (paso 1.2)
A10: Leads que recibieron la pregunta | B10: =COUNTIFS('Detalle por lead'!$A$2:$A$616,B$6) -> 398 | D10: =COUNTIFS('Detalle por lead'!$A$2:$A$616,D$6) -> 110 | F10: =COUNTIFS('Detalle por lead'!$A$2:$A$616,F$6) -> 107 | H10: =COUNT('Detalle por lead'!$B$2:$B$616) -> 615 | J10: 70
A11: Contestaron la pregunta (dijeron su área o que estudian) | B11: =COUNTIFS('Detalle por lead'!$A$2:$A$616,B$6,'Detalle por lead'!$D$2:$D$616,"Sí") -> 158 | C11: =IFERROR(B11/B10,"—") -> 0.39698492 | D11: =COUNTIFS('Detalle por lead'!$A$2:$A$616,D$6,'Detalle por lead'!$D$2:$D$616,"Sí") -> 41 | E11: =IFERROR(D11/D10,"—") -> 0.37272727 | F11: =COUNTIFS('Detalle por lead'!$A$2:$A$616,F$6,'Detalle por lead'!$D$2:$D$616,"Sí") -> 37 | G11: =IFERROR(F11/F10,"—") -> 0.34579439 | H11: =COUNTIFS('Detalle por lead'!$D$2:$D$616,"Sí") -> 236 | I11: =IFERROR(H11/H10,"—") -> 0.38373984 | J11: 28 | K11: 0.4
A12: Respondieron otra cosa | B12: =COUNTIFS('Detalle por lead'!$A$2:$A$616,B$6,'Detalle por lead'!$D$2:$D$616,"Respondió otra cosa") -> 24 | C12: =IFERROR(B12/B10,"—") -> 0.060301508 | D12: =COUNTIFS('Detalle por lead'!$A$2:$A$616,D$6,'Detalle por lead'!$D$2:$D$616,"Respondió otra cosa") -> 7 | E12: =IFERROR(D12/D10,"—") -> 0.063636364 | F12: =COUNTIFS('Detalle por lead'!$A$2:$A$616,F$6,'Detalle por lead'!$D$2:$D$616,"Respondió otra cosa") -> 6 | G12: =IFERROR(F12/F10,"—") -> 0.056074766 | H12: =COUNTIFS('Detalle por lead'!$D$2:$D$616,"Respondió otra cosa") -> 37 | I12: =IFERROR(H12/H10,"—") -> 0.060162602 | J12: 0 | K12: 0
A13: No contestaron | B13: =COUNTIFS('Detalle por lead'!$A$2:$A$616,B$6,'Detalle por lead'!$D$2:$D$616,"No") -> 216 | C13: =IFERROR(B13/B10,"—") -> 0.54271357 | D13: =COUNTIFS('Detalle por lead'!$A$2:$A$616,D$6,'Detalle por lead'!$D$2:$D$616,"No") -> 62 | E13: =IFERROR(D13/D10,"—") -> 0.56363636 | F13: =COUNTIFS('Detalle por lead'!$A$2:$A$616,F$6,'Detalle por lead'!$D$2:$D$616,"No") -> 64 | G13: =IFERROR(F13/F10,"—") -> 0.59813084 | H13: =COUNTIFS('Detalle por lead'!$D$2:$D$616,"No") -> 342 | I13: =IFERROR(H13/H10,"—") -> 0.55609756 | J13: 42 | K13: 0.6
A14: De ellos, vieron la pregunta (palomitas azules) y no contestaron | B14: =COUNTIFS('Detalle por lead'!$A$2:$A$616,B$6,'Detalle por lead'!$D$2:$D$616,"No",'Detalle por lead'!$H$2:$H$616,"Sí") -> 138 | C14: =IFERROR(B14/B13,"—") -> 0.63888889 | D14: =COUNTIFS('Detalle por lead'!$A$2:$A$616,D$6,'Detalle por lead'!$D$2:$D$616,"No",'Detalle por lead'!$H$2:$H$616,"Sí") -> 40 | E14: =IFERROR(D14/D13,"—") -> 0.64516129 | F14: =COUNTIFS('Detalle por lead'!$A$2:$A$616,F$6,'Detalle por lead'!$D$2:$D$616,"No",'Detalle por lead'!$H$2:$H$616,"Sí") -> 36 | G14: =IFERROR(F14/F13,"—") -> 0.5625 | H14: =COUNTIFS('Detalle por lead'!$D$2:$D$616,"No",'Detalle por lead'!$H$2:$H$616,"Sí") -> 214 | I14: =IFERROR(H14/H13,"—") -> 0.62573099 | J14: 28 | K14: 0.66666667
A16: La respuesta del equipo (leads que contestaron la pregunta)
A17: Recibieron respuesta de una persona | B17: =COUNTIFS('Detalle por lead'!$A$2:$A$616,B$6,'Detalle por lead'!$D$2:$D$616,"Sí",'Detalle por lead'!$K$2:$K$616,"<>") -> 157 | C17: =IFERROR(B17/B11,"—") -> 0.99367089 | D17: =COUNTIFS('Detalle por lead'!$A$2:$A$616,D$6,'Detalle por lead'!$D$2:$D$616,"Sí",'Detalle por lead'!$K$2:$K$616,"<>") -> 41 | E17: =IFERROR(D17/D11,"—") -> 1 | F17: =COUNTIFS('Detalle por lead'!$A$2:$A$616,F$6,'Detalle por lead'!$D$2:$D$616,"Sí",'Detalle por lead'!$K$2:$K$616,"<>") -> 37 | G17: =IFERROR(F17/F11,"—") -> 1 | H17: =COUNTIFS('Detalle por lead'!$D$2:$D$616,"Sí",'Detalle por lead'!$K$2:$K$616,"<>") -> 235 | I17: =IFERROR(H17/H11,"—") -> 0.99576271 | J17: 28 | K17: 1
A18: Recibieron audio | B18: =COUNTIFS('Detalle por lead'!$A$2:$A$616,B$6,'Detalle por lead'!$D$2:$D$616,"Sí",'Detalle por lead'!$Q$2:$Q$616,"Sí") -> 147 | C18: =IFERROR(B18/B11,"—") -> 0.93037975 | D18: =COUNTIFS('Detalle por lead'!$A$2:$A$616,D$6,'Detalle por lead'!$D$2:$D$616,"Sí",'Detalle por lead'!$Q$2:$Q$616,"Sí") -> 39 | E18: =IFERROR(D18/D11,"—") -> 0.95121951 | F18: =COUNTIFS('Detalle por lead'!$A$2:$A$616,F$6,'Detalle por lead'!$D$2:$D$616,"Sí",'Detalle por lead'!$Q$2:$Q$616,"Sí") -> 34 | G18: =IFERROR(F18/F11,"—") -> 0.91891892 | H18: =COUNTIFS('Detalle por lead'!$D$2:$D$616,"Sí",'Detalle por lead'!$Q$2:$Q$616,"Sí") -> 220 | I18: =IFERROR(H18/H11,"—") -> 0.93220339 | J18: 27 | K18: 0.96428571
A19: Recibieron el paquete completo: aviso + audio + cursos | B19: =COUNTIFS('Detalle por lead'!$A$2:$A$616,B$6,'Detalle por lead'!$D$2:$D$616,"Sí",'Detalle por lead'!$P$2:$P$616,"Texto (aviso del audio) + Audio + Cursos*") -> 132 | C19: =IFERROR(B19/B11,"—") -> 0.83544304 | D19: =COUNTIFS('Detalle por lead'!$A$2:$A$616,D$6,'Detalle por lead'!$D$2:$D$616,"Sí",'Detalle por lead'!$P$2:$P$616,"Texto (aviso del audio) + Audio + Cursos*") -> 38 | E19: =IFERROR(D19/D11,"—") -> 0.92682927 | F19: =COUNTIFS('Detalle por lead'!$A$2:$A$616,F$6,'Detalle por lead'!$D$2:$D$616,"Sí",'Detalle por lead'!$P$2:$P$616,"Texto (aviso del audio) + Audio + Cursos*") -> 29 | G19: =IFERROR(F19/F11,"—") -> 0.78378378 | H19: =COUNTIFS('Detalle por lead'!$D$2:$D$616,"Sí",'Detalle por lead'!$P$2:$P$616,"Texto (aviso del audio) + Audio + Cursos*") -> 199 | I19: =IFERROR(H19/H11,"—") -> 0.84322034 | J19: —
A20: Mediana de minutos al primer mensaje del equipo | B20: {=IFERROR(MEDIAN(IF(('Detalle por lead'!$A$2:$A$616=B$6)*('Detalle por lead'!$D$2:$D$616="Sí")*ISNUMBER('Detalle por lead'!$L$2:$L$616),'Detalle por lead'!$L$2:$L$616)),"—")} -> 2.5625667 | D20: {=IFERROR(MEDIAN(IF(('Detalle por lead'!$A$2:$A$616=D$6)*('Detalle por lead'!$D$2:$D$616="Sí")*ISNUMBER('Detalle por lead'!$L$2:$L$616),'Detalle por lead'!$L$2:$L$616)),"—")} -> 1.3429666 | F20: {=IFERROR(MEDIAN(IF(('Detalle por lead'!$A$2:$A$616=F$6)*('Detalle por lead'!$D$2:$D$616="Sí")*ISNUMBER('Detalle por lead'!$L$2:$L$616),'Detalle por lead'!$L$2:$L$616)),"—")} -> 2.4578833 | H20: {=IFERROR(MEDIAN(IF(('Detalle por lead'!$D$2:$D$616="Sí")*ISNUMBER('Detalle por lead'!$L$2:$L$616),'Detalle por lead'!$L$2:$L$616)),"—")} -> 2.16335 | J20: 1.318
A21: Mediana de minutos a la recomendación (audio) | B21: {=IFERROR(MEDIAN(IF(('Detalle por lead'!$A$2:$A$616=B$6)*('Detalle por lead'!$D$2:$D$616="Sí")*ISNUMBER('Detalle por lead'!$N$2:$N$616),'Detalle por lead'!$N$2:$N$616)),"—")} -> 6.875 | D21: {=IFERROR(MEDIAN(IF(('Detalle por lead'!$A$2:$A$616=D$6)*('Detalle por lead'!$D$2:$D$616="Sí")*ISNUMBER('Detalle por lead'!$N$2:$N$616),'Detalle por lead'!$N$2:$N$616)),"—")} -> 5.0288167 | F21: {=IFERROR(MEDIAN(IF(('Detalle por lead'!$A$2:$A$616=F$6)*('Detalle por lead'!$D$2:$D$616="Sí")*ISNUMBER('Detalle por lead'!$N$2:$N$616),'Detalle por lead'!$N$2:$N$616)),"—")} -> 6.3731 | H21: {=IFERROR(MEDIAN(IF(('Detalle por lead'!$D$2:$D$616="Sí")*ISNUMBER('Detalle por lead'!$N$2:$N$616),'Detalle por lead'!$N$2:$N$616)),"—")} -> 6.4108167 | J21: 5.257
A22: Percentil 90 de minutos a la recomendación | B22: {=IFERROR(PERCENTILE(IF(('Detalle por lead'!$A$2:$A$616=B$6)*('Detalle por lead'!$D$2:$D$616="Sí")*ISNUMBER('Detalle por lead'!$N$2:$N$616),'Detalle por lead'!$N$2:$N$616),0.9),"—")} -> 22.076337 | D22: {=IFERROR(PERCENTILE(IF(('Detalle por lead'!$A$2:$A$616=D$6)*('Detalle por lead'!$D$2:$D$616="Sí")*ISNUMBER('Detalle por lead'!$N$2:$N$616),'Detalle por lead'!$N$2:$N$616),0.9),"—")} -> 12.55505 | F22: {=IFERROR(PERCENTILE(IF(('Detalle por lead'!$A$2:$A$616=F$6)*('Detalle por lead'!$D$2:$D$616="Sí")*ISNUMBER('Detalle por lead'!$N$2:$N$616),'Detalle por lead'!$N$2:$N$616),0.9),"—")} -> 37.677177 | H22: {=IFERROR(PERCENTILE(IF(('Detalle por lead'!$D$2:$D$616="Sí")*ISNUMBER('Detalle por lead'!$N$2:$N$616),'Detalle por lead'!$N$2:$N$616),0.9),"—")} -> 22.062023 | J22: 12.174
A23: Máximo de minutos a la recomendación | B23: {=IFERROR(MAX(IF(('Detalle por lead'!$A$2:$A$616=B$6)*('Detalle por lead'!$D$2:$D$616="Sí")*ISNUMBER('Detalle por lead'!$N$2:$N$616),'Detalle por lead'!$N$2:$N$616)),"—")} -> 1204.0598 | D23: {=IFERROR(MAX(IF(('Detalle por lead'!$A$2:$A$616=D$6)*('Detalle por lead'!$D$2:$D$616="Sí")*ISNUMBER('Detalle por lead'!$N$2:$N$616),'Detalle por lead'!$N$2:$N$616)),"—")} -> 843.73367 | F23: {=IFERROR(MAX(IF(('Detalle por lead'!$A$2:$A$616=F$6)*('Detalle por lead'!$D$2:$D$616="Sí")*ISNUMBER('Detalle por lead'!$N$2:$N$616),'Detalle por lead'!$N$2:$N$616)),"—")} -> 537.84313 | H23: {=IFERROR(MAX(IF(('Detalle por lead'!$D$2:$D$616="Sí")*ISNUMBER('Detalle por lead'!$N$2:$N$616),'Detalle por lead'!$N$2:$N$616)),"—")} -> 1204.0598 | J23: 23.946
A24: Recomendaciones en menos de 10 min | B24: =COUNTIFS('Detalle por lead'!$A$2:$A$616,B$6,'Detalle por lead'!$D$2:$D$616,"Sí",'Detalle por lead'!$N$2:$N$616,"<10") -> 104 | C24: =IFERROR(B24/B17,"—") -> 0.66242038 | D24: =COUNTIFS('Detalle por lead'!$A$2:$A$616,D$6,'Detalle por lead'!$D$2:$D$616,"Sí",'Detalle por lead'!$N$2:$N$616,"<10") -> 30 | E24: =IFERROR(D24/D17,"—") -> 0.73170732 | F24: =COUNTIFS('Detalle por lead'!$A$2:$A$616,F$6,'Detalle por lead'!$D$2:$D$616,"Sí",'Detalle por lead'!$N$2:$N$616,"<10") -> 25 | G24: =IFERROR(F24/F17,"—") -> 0.67567568 | H24: =COUNTIFS('Detalle por lead'!$D$2:$D$616,"Sí",'Detalle por lead'!$N$2:$N$616,"<10") -> 159 | I24: =IFERROR(H24/H17,"—") -> 0.67659574 | J24: 20 | K24: 0.71428571
A25: Mediana de minutos del aviso al audio (grabarlo y mandarlo) | B25: {=IFERROR(MEDIAN(IF(('Detalle por lead'!$A$2:$A$616=B$6)*('Detalle por lead'!$D$2:$D$616="Sí")*ISNUMBER('Detalle por lead'!$V$2:$V$616),'Detalle por lead'!$V$2:$V$616)),"—")} -> 3.84 | D25: {=IFERROR(MEDIAN(IF(('Detalle por lead'!$A$2:$A$616=D$6)*('Detalle por lead'!$D$2:$D$616="Sí")*ISNUMBER('Detalle por lead'!$V$2:$V$616),'Detalle por lead'!$V$2:$V$616)),"—")} -> 3.63 | F25: {=IFERROR(MEDIAN(IF(('Detalle por lead'!$A$2:$A$616=F$6)*('Detalle por lead'!$D$2:$D$616="Sí")*ISNUMBER('Detalle por lead'!$V$2:$V$616),'Detalle por lead'!$V$2:$V$616)),"—")} -> 3.32 | H25: {=IFERROR(MEDIAN(IF(('Detalle por lead'!$D$2:$D$616="Sí")*ISNUMBER('Detalle por lead'!$V$2:$V$616),'Detalle por lead'!$V$2:$V$616)),"—")} -> 3.78 | J25: —
A26: Duración mediana del audio (s) | B26: {=IFERROR(MEDIAN(IF(('Detalle por lead'!$A$2:$A$616=B$6)*('Detalle por lead'!$D$2:$D$616="Sí")*ISNUMBER('Detalle por lead'!$T$2:$T$616),'Detalle por lead'!$T$2:$T$616)),"—")} -> 104.7 | D26: {=IFERROR(MEDIAN(IF(('Detalle por lead'!$A$2:$A$616=D$6)*('Detalle por lead'!$D$2:$D$616="Sí")*ISNUMBER('Detalle por lead'!$T$2:$T$616),'Detalle por lead'!$T$2:$T$616)),"—")} -> 105.1 | F26: {=IFERROR(MEDIAN(IF(('Detalle por lead'!$A$2:$A$616=F$6)*('Detalle por lead'!$D$2:$D$616="Sí")*ISNUMBER('Detalle por lead'!$T$2:$T$616),'Detalle por lead'!$T$2:$T$616)),"—")} -> 103.95 | H26: {=IFERROR(MEDIAN(IF(('Detalle por lead'!$D$2:$D$616="Sí")*ISNUMBER('Detalle por lead'!$T$2:$T$616),'Detalle por lead'!$T$2:$T$616)),"—")} -> 104.8 | J26: 106.4
A27: Vieron el audio (palomitas azules) | B27: =COUNTIFS('Detalle por lead'!$A$2:$A$616,B$6,'Detalle por lead'!$D$2:$D$616,"Sí",'Detalle por lead'!$U$2:$U$616,"Sí") -> 111 | C27: =IFERROR(B27/B18,"—") -> 0.75510204 | D27: =COUNTIFS('Detalle por lead'!$A$2:$A$616,D$6,'Detalle por lead'!$D$2:$D$616,"Sí",'Detalle por lead'!$U$2:$U$616,"Sí") -> 21 | E27: =IFERROR(D27/D18,"—") -> 0.53846154 | F27: =COUNTIFS('Detalle por lead'!$A$2:$A$616,F$6,'Detalle por lead'!$D$2:$D$616,"Sí",'Detalle por lead'!$U$2:$U$616,"Sí") -> 24 | G27: =IFERROR(F27/F18,"—") -> 0.70588235 | H27: =COUNTIFS('Detalle por lead'!$D$2:$D$616,"Sí",'Detalle por lead'!$U$2:$U$616,"Sí") -> 156 | I27: =IFERROR(H27/H18,"—") -> 0.70909091 | J27: —
A28: Cursos recomendados por lead (promedio) | B28: {=IFERROR(AVERAGE(IF(('Detalle por lead'!$A$2:$A$616=B$6)*('Detalle por lead'!$D$2:$D$616="Sí")*ISNUMBER('Detalle por lead'!$X$2:$X$616),'Detalle por lead'!$X$2:$X$616)),"—")} -> 2.3566879 | D28: {=IFERROR(AVERAGE(IF(('Detalle por lead'!$A$2:$A$616=D$6)*('Detalle por lead'!$D$2:$D$616="Sí")*ISNUMBER('Detalle por lead'!$X$2:$X$616),'Detalle por lead'!$X$2:$X$616)),"—")} -> 2.4390244 | F28: {=IFERROR(AVERAGE(IF(('Detalle por lead'!$A$2:$A$616=F$6)*('Detalle por lead'!$D$2:$D$616="Sí")*ISNUMBER('Detalle por lead'!$X$2:$X$616),'Detalle por lead'!$X$2:$X$616)),"—")} -> 2.4054054 | H28: {=IFERROR(AVERAGE(IF(('Detalle por lead'!$D$2:$D$616="Sí")*ISNUMBER('Detalle por lead'!$X$2:$X$616),'Detalle por lead'!$X$2:$X$616)),"—")} -> 2.3787234 | J28: —
A30: Lo que pasó después
A31: Respondieron después de la recomendación | B31: =COUNTIFS('Detalle por lead'!$A$2:$A$616,B$6,'Detalle por lead'!$D$2:$D$616,"Sí",'Detalle por lead'!$Y$2:$Y$616,"Sí") -> 101 | C31: =IFERROR(B31/B17,"—") -> 0.6433121 | D31: =COUNTIFS('Detalle por lead'!$A$2:$A$616,D$6,'Detalle por lead'!$D$2:$D$616,"Sí",'Detalle por lead'!$Y$2:$Y$616,"Sí") -> 30 | E31: =IFERROR(D31/D17,"—") -> 0.73170732 | F31: =COUNTIFS('Detalle por lead'!$A$2:$A$616,F$6,'Detalle por lead'!$D$2:$D$616,"Sí",'Detalle por lead'!$Y$2:$Y$616,"Sí") -> 24 | G31: =IFERROR(F31/F17,"—") -> 0.64864865 | H31: =COUNTIFS('Detalle por lead'!$D$2:$D$616,"Sí",'Detalle por lead'!$Y$2:$Y$616,"Sí") -> 155 | I31: =IFERROR(H31/H17,"—") -> 0.65957447 | J31: 20 | K31: 0.71428571
A32: Mediana de minutos del lead en responder | B32: {=IFERROR(MEDIAN(IF(('Detalle por lead'!$A$2:$A$616=B$6)*('Detalle por lead'!$D$2:$D$616="Sí")*ISNUMBER('Detalle por lead'!$AA$2:$AA$616),'Detalle por lead'!$AA$2:$AA$616)),"—")} -> 10.67245 | D32: {=IFERROR(MEDIAN(IF(('Detalle por lead'!$A$2:$A$616=D$6)*('Detalle por lead'!$D$2:$D$616="Sí")*ISNUMBER('Detalle por lead'!$AA$2:$AA$616),'Detalle por lead'!$AA$2:$AA$616)),"—")} -> 8.0662667 | F32: {=IFERROR(MEDIAN(IF(('Detalle por lead'!$A$2:$A$616=F$6)*('Detalle por lead'!$D$2:$D$616="Sí")*ISNUMBER('Detalle por lead'!$AA$2:$AA$616),'Detalle por lead'!$AA$2:$AA$616)),"—")} -> 23.277525 | H32: {=IFERROR(MEDIAN(IF(('Detalle por lead'!$D$2:$D$616="Sí")*ISNUMBER('Detalle por lead'!$AA$2:$AA$616),'Detalle por lead'!$AA$2:$AA$616)),"—")} -> 10.985267 | J32: —
A33: Mediana de minutos del equipo en volver a contestarles | B33: {=IFERROR(MEDIAN(IF(('Detalle por lead'!$A$2:$A$616=B$6)*('Detalle por lead'!$D$2:$D$616="Sí")*ISNUMBER('Detalle por lead'!$AD$2:$AD$616),'Detalle por lead'!$AD$2:$AD$616)),"—")} -> 1.6471333 | D33: {=IFERROR(MEDIAN(IF(('Detalle por lead'!$A$2:$A$616=D$6)*('Detalle por lead'!$D$2:$D$616="Sí")*ISNUMBER('Detalle por lead'!$AD$2:$AD$616),'Detalle por lead'!$AD$2:$AD$616)),"—")} -> 1.9589 | F33: {=IFERROR(MEDIAN(IF(('Detalle por lead'!$A$2:$A$616=F$6)*('Detalle por lead'!$D$2:$D$616="Sí")*ISNUMBER('Detalle por lead'!$AD$2:$AD$616),'Detalle por lead'!$AD$2:$AD$616)),"—")} -> 2.3794833 | H33: {=IFERROR(MEDIAN(IF(('Detalle por lead'!$D$2:$D$616="Sí")*ISNUMBER('Detalle por lead'!$AD$2:$AD$616),'Detalle por lead'!$AD$2:$AD$616)),"—")} -> 1.87285 | J33: 1.784
A34: Respondieron y luego el bot los pasó a Negativo | B34: =COUNTIFS('Detalle por lead'!$A$2:$A$616,B$6,'Detalle por lead'!$D$2:$D$616,"Sí",'Detalle por lead'!$AG$2:$AG$616,"Sí") -> 58 | C34: =IFERROR(B34/B31,"—") -> 0.57425743 | D34: =COUNTIFS('Detalle por lead'!$A$2:$A$616,D$6,'Detalle por lead'!$D$2:$D$616,"Sí",'Detalle por lead'!$AG$2:$AG$616,"Sí") -> 14 | E34: =IFERROR(D34/D31,"—") -> 0.46666667 | F34: =COUNTIFS('Detalle por lead'!$A$2:$A$616,F$6,'Detalle por lead'!$D$2:$D$616,"Sí",'Detalle por lead'!$AG$2:$AG$616,"Sí") -> 13 | G34: =IFERROR(F34/F31,"—") -> 0.54166667 | H34: =COUNTIFS('Detalle por lead'!$D$2:$D$616,"Sí",'Detalle por lead'!$AG$2:$AG$616,"Sí") -> 85 | I34: =IFERROR(H34/H31,"—") -> 0.5483871 | J34: 10 | K34: 0.5
A35: Horas desde su último mensaje hasta que el bot los pasó a Negativo (mediana) | B35: {=IFERROR(MEDIAN(IF(('Detalle por lead'!$A$2:$A$616=B$6)*('Detalle por lead'!$D$2:$D$616="Sí")*ISNUMBER('Detalle por lead'!$AH$2:$AH$616),'Detalle por lead'!$AH$2:$AH$616)),"—")} -> 4 | D35: {=IFERROR(MEDIAN(IF(('Detalle por lead'!$A$2:$A$616=D$6)*('Detalle por lead'!$D$2:$D$616="Sí")*ISNUMBER('Detalle por lead'!$AH$2:$AH$616),'Detalle por lead'!$AH$2:$AH$616)),"—")} -> 4.05 | F35: {=IFERROR(MEDIAN(IF(('Detalle por lead'!$A$2:$A$616=F$6)*('Detalle por lead'!$D$2:$D$616="Sí")*ISNUMBER('Detalle por lead'!$AH$2:$AH$616),'Detalle por lead'!$AH$2:$AH$616)),"—")} -> 3.9 | H35: {=IFERROR(MEDIAN(IF(('Detalle por lead'!$D$2:$D$616="Sí")*ISNUMBER('Detalle por lead'!$AH$2:$AH$616),'Detalle por lead'!$AH$2:$AH$616)),"—")} -> 4 | J35: —
A36: Recibieron la recomendación y el bot los pasó a Negativo | B36: =COUNTIFS('Detalle por lead'!$A$2:$A$616,B$6,'Detalle por lead'!$D$2:$D$616,"Sí",'Detalle por lead'!$AF$2:$AF$616,"Sí") -> 124 | C36: =IFERROR(B36/B17,"—") -> 0.78980892 | D36: =COUNTIFS('Detalle por lead'!$A$2:$A$616,D$6,'Detalle por lead'!$D$2:$D$616,"Sí",'Detalle por lead'!$AF$2:$AF$616,"Sí") -> 28 | E36: =IFERROR(D36/D17,"—") -> 0.68292683 | F36: =COUNTIFS('Detalle por lead'!$A$2:$A$616,F$6,'Detalle por lead'!$D$2:$D$616,"Sí",'Detalle por lead'!$AF$2:$AF$616,"Sí") -> 33 | G36: =IFERROR(F36/F17,"—") -> 0.89189189 | H36: =COUNTIFS('Detalle por lead'!$D$2:$D$616,"Sí",'Detalle por lead'!$AF$2:$AF$616,"Sí") -> 185 | I36: =IFERROR(H36/H17,"—") -> 0.78723404 | J36: —
A37: Ganados (de los que contestaron la pregunta) | B37: =COUNTIFS('Detalle por lead'!$A$2:$A$616,B$6,'Detalle por lead'!$D$2:$D$616,"Sí",'Detalle por lead'!$AK$2:$AK$616,"Sí") -> 3 | C37: =IFERROR(B37/B11,"—") -> 0.018987342 | D37: =COUNTIFS('Detalle por lead'!$A$2:$A$616,D$6,'Detalle por lead'!$D$2:$D$616,"Sí",'Detalle por lead'!$AK$2:$AK$616,"Sí") -> 2 | E37: =IFERROR(D37/D11,"—") -> 0.048780488 | F37: =COUNTIFS('Detalle por lead'!$A$2:$A$616,F$6,'Detalle por lead'!$D$2:$D$616,"Sí",'Detalle por lead'!$AK$2:$AK$616,"Sí") -> 3 | G37: =IFERROR(F37/F11,"—") -> 0.081081081 | H37: =COUNTIFS('Detalle por lead'!$D$2:$D$616,"Sí",'Detalle por lead'!$AK$2:$AK$616,"Sí") -> 8 | I37: =IFERROR(H37/H11,"—") -> 0.033898305 | J37: 1 | K37: 0.035714286
A38: Ganados (todos los leads) | B38: =COUNTIFS('Detalle por lead'!$A$2:$A$616,B$6,'Detalle por lead'!$AK$2:$AK$616,"Sí") -> 6 | C38: =IFERROR(B38/B10,"—") -> 0.015075377 | D38: =COUNTIFS('Detalle por lead'!$A$2:$A$616,D$6,'Detalle por lead'!$AK$2:$AK$616,"Sí") -> 5 | E38: =IFERROR(D38/D10,"—") -> 0.045454545 | F38: =COUNTIFS('Detalle por lead'!$A$2:$A$616,F$6,'Detalle por lead'!$AK$2:$AK$616,"Sí") -> 4 | G38: =IFERROR(F38/F10,"—") -> 0.037383178 | H38: =COUNTIFS('Detalle por lead'!$AK$2:$AK$616,"Sí") -> 15 | I38: =IFERROR(H38/H10,"—") -> 0.024390244 | J38: 2 | K38: 0.028571429
A40: Con audio contra sin audio (de los que contestaron la pregunta)
A41: Con audio: leads | B41: =COUNTIFS('Detalle por lead'!$A$2:$A$616,B$6,'Detalle por lead'!$D$2:$D$616,"Sí",'Detalle por lead'!$Q$2:$Q$616,"Sí") -> 147 | D41: =COUNTIFS('Detalle por lead'!$A$2:$A$616,D$6,'Detalle por lead'!$D$2:$D$616,"Sí",'Detalle por lead'!$Q$2:$Q$616,"Sí") -> 39 | F41: =COUNTIFS('Detalle por lead'!$A$2:$A$616,F$6,'Detalle por lead'!$D$2:$D$616,"Sí",'Detalle por lead'!$Q$2:$Q$616,"Sí") -> 34 | H41: =COUNTIFS('Detalle por lead'!$D$2:$D$616,"Sí",'Detalle por lead'!$Q$2:$Q$616,"Sí") -> 220 | J41: —
A42: Con audio: respondieron después | B42: =COUNTIFS('Detalle por lead'!$A$2:$A$616,B$6,'Detalle por lead'!$D$2:$D$616,"Sí",'Detalle por lead'!$Q$2:$Q$616,"Sí",'Detalle por lead'!$Y$2:$Y$616,"Sí") -> 94 | C42: =IFERROR(B42/B41,"—") -> 0.63945578 | D42: =COUNTIFS('Detalle por lead'!$A$2:$A$616,D$6,'Detalle por lead'!$D$2:$D$616,"Sí",'Detalle por lead'!$Q$2:$Q$616,"Sí",'Detalle por lead'!$Y$2:$Y$616,"Sí") -> 28 | E42: =IFERROR(D42/D41,"—") -> 0.71794872 | F42: =COUNTIFS('Detalle por lead'!$A$2:$A$616,F$6,'Detalle por lead'!$D$2:$D$616,"Sí",'Detalle por lead'!$Q$2:$Q$616,"Sí",'Detalle por lead'!$Y$2:$Y$616,"Sí") -> 22 | G42: =IFERROR(F42/F41,"—") -> 0.64705882 | H42: =COUNTIFS('Detalle por lead'!$D$2:$D$616,"Sí",'Detalle por lead'!$Q$2:$Q$616,"Sí",'Detalle por lead'!$Y$2:$Y$616,"Sí") -> 144 | I42: =IFERROR(H42/H41,"—") -> 0.65454545 | J42: —
A43: Solo texto: leads | B43: =COUNTIFS('Detalle por lead'!$A$2:$A$616,B$6,'Detalle por lead'!$D$2:$D$616,"Sí",'Detalle por lead'!$Q$2:$Q$616,"No") -> 10 | D43: =COUNTIFS('Detalle por lead'!$A$2:$A$616,D$6,'Detalle por lead'!$D$2:$D$616,"Sí",'Detalle por lead'!$Q$2:$Q$616,"No") -> 2 | F43: =COUNTIFS('Detalle por lead'!$A$2:$A$616,F$6,'Detalle por lead'!$D$2:$D$616,"Sí",'Detalle por lead'!$Q$2:$Q$616,"No") -> 3 | H43: =COUNTIFS('Detalle por lead'!$D$2:$D$616,"Sí",'Detalle por lead'!$Q$2:$Q$616,"No") -> 15 | J43: —
A44: Solo texto: respondieron después | B44: =COUNTIFS('Detalle por lead'!$A$2:$A$616,B$6,'Detalle por lead'!$D$2:$D$616,"Sí",'Detalle por lead'!$Q$2:$Q$616,"No",'Detalle por lead'!$Y$2:$Y$616,"Sí") -> 7 | C44: =IFERROR(B44/B43,"—") -> 0.7 | D44: =COUNTIFS('Detalle por lead'!$A$2:$A$616,D$6,'Detalle por lead'!$D$2:$D$616,"Sí",'Detalle por lead'!$Q$2:$Q$616,"No",'Detalle por lead'!$Y$2:$Y$616,"Sí") -> 2 | E44: =IFERROR(D44/D43,"—") -> 1 | F44: =COUNTIFS('Detalle por lead'!$A$2:$A$616,F$6,'Detalle por lead'!$D$2:$D$616,"Sí",'Detalle por lead'!$Q$2:$Q$616,"No",'Detalle por lead'!$Y$2:$Y$616,"Sí") -> 2 | G44: =IFERROR(F44/F43,"—") -> 0.66666667 | H44: =COUNTIFS('Detalle por lead'!$D$2:$D$616,"Sí",'Detalle por lead'!$Q$2:$Q$616,"No",'Detalle por lead'!$Y$2:$Y$616,"Sí") -> 11 | I44: =IFERROR(H44/H43,"—") -> 0.73333333 | J44: —
A45: Vieron el audio: respondieron después | B45: =COUNTIFS('Detalle por lead'!$A$2:$A$616,B$6,'Detalle por lead'!$D$2:$D$616,"Sí",'Detalle por lead'!$U$2:$U$616,"Sí",'Detalle por lead'!$Y$2:$Y$616,"Sí") -> 74 | C45: =IFERROR(B45/B27,"—") -> 0.66666667 | D45: =COUNTIFS('Detalle por lead'!$A$2:$A$616,D$6,'Detalle por lead'!$D$2:$D$616,"Sí",'Detalle por lead'!$U$2:$U$616,"Sí",'Detalle por lead'!$Y$2:$Y$616,"Sí") -> 16 | E45: =IFERROR(D45/D27,"—") -> 0.76190476 | F45: =COUNTIFS('Detalle por lead'!$A$2:$A$616,F$6,'Detalle por lead'!$D$2:$D$616,"Sí",'Detalle por lead'!$U$2:$U$616,"Sí",'Detalle por lead'!$Y$2:$Y$616,"Sí") -> 17 | G45: =IFERROR(F45/F27,"—") -> 0.70833333 | H45: =COUNTIFS('Detalle por lead'!$D$2:$D$616,"Sí",'Detalle por lead'!$U$2:$U$616,"Sí",'Detalle por lead'!$Y$2:$Y$616,"Sí") -> 107 | I45: =IFERROR(H45/H27,"—") -> 0.68589744 | J45: —
A46: No vieron el audio: leads | B46: =COUNTIFS('Detalle por lead'!$A$2:$A$616,B$6,'Detalle por lead'!$D$2:$D$616,"Sí",'Detalle por lead'!$U$2:$U$616,"No") -> 36 | D46: =COUNTIFS('Detalle por lead'!$A$2:$A$616,D$6,'Detalle por lead'!$D$2:$D$616,"Sí",'Detalle por lead'!$U$2:$U$616,"No") -> 18 | F46: =COUNTIFS('Detalle por lead'!$A$2:$A$616,F$6,'Detalle por lead'!$D$2:$D$616,"Sí",'Detalle por lead'!$U$2:$U$616,"No") -> 10 | H46: =COUNTIFS('Detalle por lead'!$D$2:$D$616,"Sí",'Detalle por lead'!$U$2:$U$616,"No") -> 64 | J46: —
A47: No vieron el audio: respondieron después | B47: =COUNTIFS('Detalle por lead'!$A$2:$A$616,B$6,'Detalle por lead'!$D$2:$D$616,"Sí",'Detalle por lead'!$U$2:$U$616,"No",'Detalle por lead'!$Y$2:$Y$616,"Sí") -> 20 | C47: =IFERROR(B47/B46,"—") -> 0.55555556 | D47: =COUNTIFS('Detalle por lead'!$A$2:$A$616,D$6,'Detalle por lead'!$D$2:$D$616,"Sí",'Detalle por lead'!$U$2:$U$616,"No",'Detalle por lead'!$Y$2:$Y$616,"Sí") -> 12 | E47: =IFERROR(D47/D46,"—") -> 0.66666667 | F47: =COUNTIFS('Detalle por lead'!$A$2:$A$616,F$6,'Detalle por lead'!$D$2:$D$616,"Sí",'Detalle por lead'!$U$2:$U$616,"No",'Detalle por lead'!$Y$2:$Y$616,"Sí") -> 5 | G47: =IFERROR(F47/F46,"—") -> 0.5 | H47: =COUNTIFS('Detalle por lead'!$D$2:$D$616,"Sí",'Detalle por lead'!$U$2:$U$616,"No",'Detalle por lead'!$Y$2:$Y$616,"Sí") -> 37 | I47: =IFERROR(H47/H46,"—") -> 0.578125 | J47: —
A49: La hora de la pregunta
A50: Pregunta entre 8:00 y 22:00: leads | B50: =COUNTIFS('Detalle por lead'!$A$2:$A$616,B$6,'Detalle por lead'!$G$2:$G$616,"No") -> 325 | D50: =COUNTIFS('Detalle por lead'!$A$2:$A$616,D$6,'Detalle por lead'!$G$2:$G$616,"No") -> 90 | F50: =COUNTIFS('Detalle por lead'!$A$2:$A$616,F$6,'Detalle por lead'!$G$2:$G$616,"No") -> 85 | H50: =COUNTIFS('Detalle por lead'!$G$2:$G$616,"No") -> 500 | J50: 51
A51: Pregunta entre 8:00 y 22:00: contestaron | B51: =COUNTIFS('Detalle por lead'!$A$2:$A$616,B$6,'Detalle por lead'!$G$2:$G$616,"No",'Detalle por lead'!$D$2:$D$616,"Sí") -> 137 | C51: =IFERROR(B51/B50,"—") -> 0.42153846 | D51: =COUNTIFS('Detalle por lead'!$A$2:$A$616,D$6,'Detalle por lead'!$G$2:$G$616,"No",'Detalle por lead'!$D$2:$D$616,"Sí") -> 40 | E51: =IFERROR(D51/D50,"—") -> 0.44444444 | F51: =COUNTIFS('Detalle por lead'!$A$2:$A$616,F$6,'Detalle por lead'!$G$2:$G$616,"No",'Detalle por lead'!$D$2:$D$616,"Sí") -> 31 | G51: =IFERROR(F51/F50,"—") -> 0.36470588 | H51: =COUNTIFS('Detalle por lead'!$G$2:$G$616,"No",'Detalle por lead'!$D$2:$D$616,"Sí") -> 208 | I51: =IFERROR(H51/H50,"—") -> 0.416 | J51: 27 | K51: 0.52941176
A52: Pregunta antes de las 8:00 o desde las 22:00: leads | B52: =COUNTIFS('Detalle por lead'!$A$2:$A$616,B$6,'Detalle por lead'!$G$2:$G$616,"Sí") -> 73 | D52: =COUNTIFS('Detalle por lead'!$A$2:$A$616,D$6,'Detalle por lead'!$G$2:$G$616,"Sí") -> 20 | F52: =COUNTIFS('Detalle por lead'!$A$2:$A$616,F$6,'Detalle por lead'!$G$2:$G$616,"Sí") -> 22 | H52: =COUNTIFS('Detalle por lead'!$G$2:$G$616,"Sí") -> 115 | J52: 19
A53: Pregunta antes de las 8:00 o desde las 22:00: contestaron | B53: =COUNTIFS('Detalle por lead'!$A$2:$A$616,B$6,'Detalle por lead'!$G$2:$G$616,"Sí",'Detalle por lead'!$D$2:$D$616,"Sí") -> 21 | C53: =IFERROR(B53/B52,"—") -> 0.28767123 | D53: =COUNTIFS('Detalle por lead'!$A$2:$A$616,D$6,'Detalle por lead'!$G$2:$G$616,"Sí",'Detalle por lead'!$D$2:$D$616,"Sí") -> 1 | E53: =IFERROR(D53/D52,"—") -> 0.05 | F53: =COUNTIFS('Detalle por lead'!$A$2:$A$616,F$6,'Detalle por lead'!$G$2:$G$616,"Sí",'Detalle por lead'!$D$2:$D$616,"Sí") -> 6 | G53: =IFERROR(F53/F52,"—") -> 0.27272727 | H53: =COUNTIFS('Detalle por lead'!$G$2:$G$616,"Sí",'Detalle por lead'!$D$2:$D$616,"Sí") -> 28 | I53: =IFERROR(H53/H52,"—") -> 0.24347826 | J53: 1 | K53: 0.052631579
A55: Muestra anterior: valores de la hoja «Analisis_Muestra_SyS» (Manufactura y Calidad, preguntas del 5 al 12 oct, leída el 13 oct), escritos tal cual en gris. Esos leads están incluidos en la columna Manufactura y Calidad, medidos de nuevo al corte del 15 oct.
A56: Todo lo demás son fórmulas sobre la pestaña Detalle por lead. Los % se calculan contra el renglón de arriba que les corresponde (por ejemplo, «Recibieron audio» contra «Contestaron la pregunta»).

Sheet Tiempos
A1: DESARROLLO PROFESIONAL SyS
A2: Minutos a la recomendación y si después el lead volvió a escribir
A3: Solo los 236 leads que contestaron la pregunta · corte: 15 oct 2026, 23:59 h (Monterrey)
A4: Rangos (desde, en minutos). Puedes cambiar los límites de la columna A y todo se recalcula.
A5: Desde (min) | B5: Rango | C5: Leads | D5: Respondieron después | E5: % que respondió | F5: Ganados | G5: ISO: leads | H5: ISO: % respondió | I5: Manufactura: leads | J5: Manufactura: % respondió | K5: Core Tools: leads | L5: Core Tools: % respondió
A6: 0 | B6: Menos de 4 min | C6: =COUNTIFS('Detalle por lead'!$D$2:$D$616,"Sí",'Detalle por lead'!$O$2:$O$616,B6) -> 54 | D6: =COUNTIFS('Detalle por lead'!$D$2:$D$616,"Sí",'Detalle por lead'!$O$2:$O$616,B6,'Detalle por lead'!$Y$2:$Y$616,"Sí") -> 41 | E6: =IFERROR(D6/C6,"—") -> 0.75925926 | F6: =COUNTIFS('Detalle por lead'!$D$2:$D$616,"Sí",'Detalle por lead'!$O$2:$O$616,B6,'Detalle por lead'!$AK$2:$AK$616,"Sí") -> 1 | G6: =COUNTIFS('Detalle por lead'!$D$2:$D$616,"Sí",'Detalle por lead'!$A$2:$A$616,"ISO + Calidad",'Detalle por lead'!$O$2:$O$616,B6) -> 32 | H6: =IFERROR(COUNTIFS('Detalle por lead'!$D$2:$D$616,"Sí",'Detalle por lead'!$A$2:$A$616,"ISO + Calidad",'Detalle por lead'!$O$2:$O$616,B6,'Detalle por lead'!$Y$2:$Y$616,"Sí")/G6,"—") -> 0.65625 | I6: =COUNTIFS('Detalle por lead'!$D$2:$D$616,"Sí",'Detalle por lead'!$A$2:$A$616,"Manufactura y Calidad",'Detalle por lead'!$O$2:$O$616,B6) -> 15 | J6: =IFERROR(COUNTIFS('Detalle por lead'!$D$2:$D$616,"Sí",'Detalle por lead'!$A$2:$A$616,"Manufactura y Calidad",'Detalle por lead'!$O$2:$O$616,B6,'Detalle por lead'!$Y$2:$Y$616,"Sí")/I6,"—") -> 0.86666667 | K6: =COUNTIFS('Detalle por lead'!$D$2:$D$616,"Sí",'Detalle por lead'!$A$2:$A$616,"Core Tools Premium",'Detalle por lead'!$O$2:$O$616,B6) -> 7 | L6: =IFERROR(COUNTIFS('Detalle por lead'!$D$2:$D$616,"Sí",'Detalle por lead'!$A$2:$A$616,"Core Tools Premium",'Detalle por lead'!$O$2:$O$616,B6,'Detalle por lead'!$Y$2:$Y$616,"Sí")/K6,"—") -> 1
A7: 4 | B7: 4 a 6 min | C7: =COUNTIFS('Detalle por lead'!$D$2:$D$616,"Sí",'Detalle por lead'!$O$2:$O$616,B7) -> 53 | D7: =COUNTIFS('Detalle por lead'!$D$2:$D$616,"Sí",'Detalle por lead'!$O$2:$O$616,B7,'Detalle por lead'!$Y$2:$Y$616,"Sí") -> 32 | E7: =IFERROR(D7/C7,"—") -> 0.60377358 | F7: =COUNTIFS('Detalle por lead'!$D$2:$D$616,"Sí",'Detalle por lead'!$O$2:$O$616,B7,'Detalle por lead'!$AK$2:$AK$616,"Sí") -> 2 | G7: =COUNTIFS('Detalle por lead'!$D$2:$D$616,"Sí",'Detalle por lead'!$A$2:$A$616,"ISO + Calidad",'Detalle por lead'!$O$2:$O$616,B7) -> 33 | H7: =IFERROR(COUNTIFS('Detalle por lead'!$D$2:$D$616,"Sí",'Detalle por lead'!$A$2:$A$616,"ISO + Calidad",'Detalle por lead'!$O$2:$O$616,B7,'Detalle por lead'!$Y$2:$Y$616,"Sí")/G7,"—") -> 0.66666667 | I7: =COUNTIFS('Detalle por lead'!$D$2:$D$616,"Sí",'Detalle por lead'!$A$2:$A$616,"Manufactura y Calidad",'Detalle por lead'!$O$2:$O$616,B7) -> 10 | J7: =IFERROR(COUNTIFS('Detalle por lead'!$D$2:$D$616,"Sí",'Detalle por lead'!$A$2:$A$616,"Manufactura y Calidad",'Detalle por lead'!$O$2:$O$616,B7,'Detalle por lead'!$Y$2:$Y$616,"Sí")/I7,"—") -> 0.6 | K7: =COUNTIFS('Detalle por lead'!$D$2:$D$616,"Sí",'Detalle por lead'!$A$2:$A$616,"Core Tools Premium",'Detalle por lead'!$O$2:$O$616,B7) -> 10 | L7: =IFERROR(COUNTIFS('Detalle por lead'!$D$2:$D$616,"Sí",'Detalle por lead'!$A$2:$A$616,"Core Tools Premium",'Detalle por lead'!$O$2:$O$616,B7,'Detalle por lead'!$Y$2:$Y$616,"Sí")/K7,"—") -> 0.4
A8: 6 | B8: 6 a 10 min | C8: =COUNTIFS('Detalle por lead'!$D$2:$D$616,"Sí",'Detalle por lead'!$O$2:$O$616,B8) -> 52 | D8: =COUNTIFS('Detalle por lead'!$D$2:$D$616,"Sí",'Detalle por lead'!$O$2:$O$616,B8,'Detalle por lead'!$Y$2:$Y$616,"Sí") -> 34 | E8: =IFERROR(D8/C8,"—") -> 0.65384615 | F8: =COUNTIFS('Detalle por lead'!$D$2:$D$616,"Sí",'Detalle por lead'!$O$2:$O$616,B8,'Detalle por lead'!$AK$2:$AK$616,"Sí") -> 0 | G8: =COUNTIFS('Detalle por lead'!$D$2:$D$616,"Sí",'Detalle por lead'!$A$2:$A$616,"ISO + Calidad",'Detalle por lead'!$O$2:$O$616,B8) -> 39 | H8: =IFERROR(COUNTIFS('Detalle por lead'!$D$2:$D$616,"Sí",'Detalle por lead'!$A$2:$A$616,"ISO + Calidad",'Detalle por lead'!$O$2:$O$616,B8,'Detalle por lead'!$Y$2:$Y$616,"Sí")/G8,"—") -> 0.64102564 | I8: =COUNTIFS('Detalle por lead'!$D$2:$D$616,"Sí",'Detalle por lead'!$A$2:$A$616,"Manufactura y Calidad",'Detalle por lead'!$O$2:$O$616,B8) -> 5 | J8: =IFERROR(COUNTIFS('Detalle por lead'!$D$2:$D$616,"Sí",'Detalle por lead'!$A$2:$A$616,"Manufactura y Calidad",'Detalle por lead'!$O$2:$O$616,B8,'Detalle por lead'!$Y$2:$Y$616,"Sí")/I8,"—") -> 0.6 | K8: =COUNTIFS('Detalle por lead'!$D$2:$D$616,"Sí",'Detalle por lead'!$A$2:$A$616,"Core Tools Premium",'Detalle por lead'!$O$2:$O$616,B8) -> 8 | L8: =IFERROR(COUNTIFS('Detalle por lead'!$D$2:$D$616,"Sí",'Detalle por lead'!$A$2:$A$616,"Core Tools Premium",'Detalle por lead'!$O$2:$O$616,B8,'Detalle por lead'!$Y$2:$Y$616,"Sí")/K8,"—") -> 0.75
A9: 10 | B9: 10 a 30 min | C9: =COUNTIFS('Detalle por lead'!$D$2:$D$616,"Sí",'Detalle por lead'!$O$2:$O$616,B9) -> 56 | D9: =COUNTIFS('Detalle por lead'!$D$2:$D$616,"Sí",'Detalle por lead'!$O$2:$O$616,B9,'Detalle por lead'!$Y$2:$Y$616,"Sí") -> 37 | E9: =IFERROR(D9/C9,"—") -> 0.66071429 | F9: =COUNTIFS('Detalle por lead'!$D$2:$D$616,"Sí",'Detalle por lead'!$O$2:$O$616,B9,'Detalle por lead'!$AK$2:$AK$616,"Sí") -> 5 | G9: =COUNTIFS('Detalle por lead'!$D$2:$D$616,"Sí",'Detalle por lead'!$A$2:$A$616,"ISO + Calidad",'Detalle por lead'!$O$2:$O$616,B9) -> 40 | H9: =IFERROR(COUNTIFS('Detalle por lead'!$D$2:$D$616,"Sí",'Detalle por lead'!$A$2:$A$616,"ISO + Calidad",'Detalle por lead'!$O$2:$O$616,B9,'Detalle por lead'!$Y$2:$Y$616,"Sí")/G9,"—") -> 0.65 | I9: =COUNTIFS('Detalle por lead'!$D$2:$D$616,"Sí",'Detalle por lead'!$A$2:$A$616,"Manufactura y Calidad",'Detalle por lead'!$O$2:$O$616,B9) -> 9 | J9: =IFERROR(COUNTIFS('Detalle por lead'!$D$2:$D$616,"Sí",'Detalle por lead'!$A$2:$A$616,"Manufactura y Calidad",'Detalle por lead'!$O$2:$O$616,B9,'Detalle por lead'!$Y$2:$Y$616,"Sí")/I9,"—") -> 0.66666667 | K9: =COUNTIFS('Detalle por lead'!$D$2:$D$616,"Sí",'Detalle por lead'!$A$2:$A$616,"Core Tools Premium",'Detalle por lead'!$O$2:$O$616,B9) -> 7 | L9: =IFERROR(COUNTIFS('Detalle por lead'!$D$2:$D$616,"Sí",'Detalle por lead'!$A$2:$A$616,"Core Tools Premium",'Detalle por lead'!$O$2:$O$616,B9,'Detalle por lead'!$Y$2:$Y$616,"Sí")/K9,"—") -> 0.71428571
A10: 30 | B10: 30 min o más | C10: =COUNTIFS('Detalle por lead'!$D$2:$D$616,"Sí",'Detalle por lead'!$O$2:$O$616,B10) -> 20 | D10: =COUNTIFS('Detalle por lead'!$D$2:$D$616,"Sí",'Detalle por lead'!$O$2:$O$616,B10,'Detalle por lead'!$Y$2:$Y$616,"Sí") -> 11 | E10: =IFERROR(D10/C10,"—") -> 0.55 | F10: =COUNTIFS('Detalle por lead'!$D$2:$D$616,"Sí",'Detalle por lead'!$O$2:$O$616,B10,'Detalle por lead'!$AK$2:$AK$616,"Sí") -> 0 | G10: =COUNTIFS('Detalle por lead'!$D$2:$D$616,"Sí",'Detalle por lead'!$A$2:$A$616,"ISO + Calidad",'Detalle por lead'!$O$2:$O$616,B10) -> 13 | H10: =IFERROR(COUNTIFS('Detalle por lead'!$D$2:$D$616,"Sí",'Detalle por lead'!$A$2:$A$616,"ISO + Calidad",'Detalle por lead'!$O$2:$O$616,B10,'Detalle por lead'!$Y$2:$Y$616,"Sí")/G10,"—") -> 0.53846154 | I10: =COUNTIFS('Detalle por lead'!$D$2:$D$616,"Sí",'Detalle por lead'!$A$2:$A$616,"Manufactura y Calidad",'Detalle por lead'!$O$2:$O$616,B10) -> 2 | J10: =IFERROR(COUNTIFS('Detalle por lead'!$D$2:$D$616,"Sí",'Detalle por lead'!$A$2:$A$616,"Manufactura y Calidad",'Detalle por lead'!$O$2:$O$616,B10,'Detalle por lead'!$Y$2:$Y$616,"Sí")/I10,"—") -> 1 | K10: =COUNTIFS('Detalle por lead'!$D$2:$D$616,"Sí",'Detalle por lead'!$A$2:$A$616,"Core Tools Premium",'Detalle por lead'!$O$2:$O$616,B10) -> 5 | L10: =IFERROR(COUNTIFS('Detalle por lead'!$D$2:$D$616,"Sí",'Detalle por lead'!$A$2:$A$616,"Core Tools Premium",'Detalle por lead'!$O$2:$O$616,B10,'Detalle por lead'!$Y$2:$Y$616,"Sí")/K10,"—") -> 0.4
B11: Total | C11: =SUM(C6:C10) -> 235 | D11: =SUM(D6:D10) -> 155 | E11: =IFERROR(D11/C11,"—") -> 0.65957447 | F11: =SUM(F6:F10) -> 8 | G11: =SUM(G6:G10) -> 157 | I11: =SUM(I6:I10) -> 41 | K11: =SUM(K6:K10) -> 37
A12: Con recomendación en menos de 4 min respondió el 75.9% (41 de 54); con más espera, el 63.0% (114 de 181). Prueba exacta de Fisher: p = 0.10. La diferencia se repite en los tres embudos, pero todavía no es concluyente.
A14: Medida | B14: Primer mensaje del equipo | C14: Recomendación (audio) | D14: Del aviso al audio | E14: Lead en responder la recomendación | F14: Equipo en volver a contestar
A15: Mediana | B15: {=IFERROR(MEDIAN(IF(('Detalle por lead'!$D$2:$D$616="Sí")*ISNUMBER('Detalle por lead'!$L$2:$L$616),'Detalle por lead'!$L$2:$L$616)),"—")} -> 2.16335 | C15: {=IFERROR(MEDIAN(IF(('Detalle por lead'!$D$2:$D$616="Sí")*ISNUMBER('Detalle por lead'!$N$2:$N$616),'Detalle por lead'!$N$2:$N$616)),"—")} -> 6.4108167 | D15: {=IFERROR(MEDIAN(IF(('Detalle por lead'!$D$2:$D$616="Sí")*ISNUMBER('Detalle por lead'!$V$2:$V$616),'Detalle por lead'!$V$2:$V$616)),"—")} -> 3.78 | E15: {=IFERROR(MEDIAN(IF(('Detalle por lead'!$D$2:$D$616="Sí")*ISNUMBER('Detalle por lead'!$AA$2:$AA$616),'Detalle por lead'!$AA$2:$AA$616)),"—")} -> 10.985267 | F15: {=IFERROR(MEDIAN(IF(('Detalle por lead'!$D$2:$D$616="Sí")*ISNUMBER('Detalle por lead'!$AD$2:$AD$616),'Detalle por lead'!$AD$2:$AD$616)),"—")} -> 1.87285
A16: Promedio | B16: {=IFERROR(AVERAGE(IF(('Detalle por lead'!$D$2:$D$616="Sí")*ISNUMBER('Detalle por lead'!$L$2:$L$616),'Detalle por lead'!$L$2:$L$616)),"—")} -> 17.984247 | C16: {=IFERROR(AVERAGE(IF(('Detalle por lead'!$D$2:$D$616="Sí")*ISNUMBER('Detalle por lead'!$N$2:$N$616),'Detalle por lead'!$N$2:$N$616)),"—")} -> 35.994497 | D16: {=IFERROR(AVERAGE(IF(('Detalle por lead'!$D$2:$D$616="Sí")*ISNUMBER('Detalle por lead'!$V$2:$V$616),'Detalle por lead'!$V$2:$V$616)),"—")} -> 8.011194 | E16: {=IFERROR(AVERAGE(IF(('Detalle por lead'!$D$2:$D$616="Sí")*ISNUMBER('Detalle por lead'!$AA$2:$AA$616),'Detalle por lead'!$AA$2:$AA$616)),"—")} -> 392.09678 | F16: {=IFERROR(AVERAGE(IF(('Detalle por lead'!$D$2:$D$616="Sí")*ISNUMBER('Detalle por lead'!$AD$2:$AD$616),'Detalle por lead'!$AD$2:$AD$616)),"—")} -> 172.93293
A17: Percentil 75 | B17: {=IFERROR(PERCENTILE(IF(('Detalle por lead'!$D$2:$D$616="Sí")*ISNUMBER('Detalle por lead'!$L$2:$L$616),'Detalle por lead'!$L$2:$L$616),0.75),"—")} -> 6.1430417 | C17: {=IFERROR(PERCENTILE(IF(('Detalle por lead'!$D$2:$D$616="Sí")*ISNUMBER('Detalle por lead'!$N$2:$N$616),'Detalle por lead'!$N$2:$N$616),0.75),"—")} -> 11.922458 | D17: {=IFERROR(PERCENTILE(IF(('Detalle por lead'!$D$2:$D$616="Sí")*ISNUMBER('Detalle por lead'!$V$2:$V$616),'Detalle por lead'!$V$2:$V$616),0.75),"—")} -> 5.22 | E17: {=IFERROR(PERCENTILE(IF(('Detalle por lead'!$D$2:$D$616="Sí")*ISNUMBER('Detalle por lead'!$AA$2:$AA$616),'Detalle por lead'!$AA$2:$AA$616),0.75),"—")} -> 43.540733 | F17: {=IFERROR(PERCENTILE(IF(('Detalle por lead'!$D$2:$D$616="Sí")*ISNUMBER('Detalle por lead'!$AD$2:$AD$616),'Detalle por lead'!$AD$2:$AD$616),0.75),"—")} -> 4.5486167
A18: Percentil 90 | B18: {=IFERROR(PERCENTILE(IF(('Detalle por lead'!$D$2:$D$616="Sí")*ISNUMBER('Detalle por lead'!$L$2:$L$616),'Detalle por lead'!$L$2:$L$616),0.9),"—")} -> 17.21212 | C18: {=IFERROR(PERCENTILE(IF(('Detalle por lead'!$D$2:$D$616="Sí")*ISNUMBER('Detalle por lead'!$N$2:$N$616),'Detalle por lead'!$N$2:$N$616),0.9),"—")} -> 22.062023 | D18: {=IFERROR(PERCENTILE(IF(('Detalle por lead'!$D$2:$D$616="Sí")*ISNUMBER('Detalle por lead'!$V$2:$V$616),'Detalle por lead'!$V$2:$V$616),0.9),"—")} -> 7.04 | E18: {=IFERROR(PERCENTILE(IF(('Detalle por lead'!$D$2:$D$616="Sí")*ISNUMBER('Detalle por lead'!$AA$2:$AA$616),'Detalle por lead'!$AA$2:$AA$616),0.9),"—")} -> 1040.8782 | F18: {=IFERROR(PERCENTILE(IF(('Detalle por lead'!$D$2:$D$616="Sí")*ISNUMBER('Detalle por lead'!$AD$2:$AD$616),'Detalle por lead'!$AD$2:$AD$616),0.9),"—")} -> 11.53254
A19: Mínimo | B19: {=IFERROR(MIN(IF(('Detalle por lead'!$D$2:$D$616="Sí")*ISNUMBER('Detalle por lead'!$L$2:$L$616),'Detalle por lead'!$L$2:$L$616)),"—")} -> 0.038133332 | C19: {=IFERROR(MIN(IF(('Detalle por lead'!$D$2:$D$616="Sí")*ISNUMBER('Detalle por lead'!$N$2:$N$616),'Detalle por lead'!$N$2:$N$616)),"—")} -> 0.16340002 | D19: {=IFERROR(MIN(IF(('Detalle por lead'!$D$2:$D$616="Sí")*ISNUMBER('Detalle por lead'!$V$2:$V$616),'Detalle por lead'!$V$2:$V$616)),"—")} -> 0.21 | E19: {=IFERROR(MIN(IF(('Detalle por lead'!$D$2:$D$616="Sí")*ISNUMBER('Detalle por lead'!$AA$2:$AA$616),'Detalle por lead'!$AA$2:$AA$616)),"—")} -> 0.20384999 | F19: {=IFERROR(MIN(IF(('Detalle por lead'!$D$2:$D$616="Sí")*ISNUMBER('Detalle por lead'!$AD$2:$AD$616),'Detalle por lead'!$AD$2:$AD$616)),"—")} -> 0.16093333
A20: Máximo | B20: {=IFERROR(MAX(IF(('Detalle por lead'!$D$2:$D$616="Sí")*ISNUMBER('Detalle por lead'!$L$2:$L$616),'Detalle por lead'!$L$2:$L$616)),"—")} -> 573.03305 | C20: {=IFERROR(MAX(IF(('Detalle por lead'!$D$2:$D$616="Sí")*ISNUMBER('Detalle por lead'!$N$2:$N$616),'Detalle por lead'!$N$2:$N$616)),"—")} -> 1204.0598 | D20: {=IFERROR(MAX(IF(('Detalle por lead'!$D$2:$D$616="Sí")*ISNUMBER('Detalle por lead'!$V$2:$V$616),'Detalle por lead'!$V$2:$V$616)),"—")} -> 652.87 | E20: {=IFERROR(MAX(IF(('Detalle por lead'!$D$2:$D$616="Sí")*ISNUMBER('Detalle por lead'!$AA$2:$AA$616),'Detalle por lead'!$AA$2:$AA$616)),"—")} -> 7156.4426 | F20: {=IFERROR(MAX(IF(('Detalle por lead'!$D$2:$D$616="Sí")*ISNUMBER('Detalle por lead'!$AD$2:$AD$616),'Detalle por lead'!$AD$2:$AD$616)),"—")} -> 6977.7025
A21: Leads medidos | B21: =SUMPRODUCT(('Detalle por lead'!$D$2:$D$616="Sí")*ISNUMBER('Detalle por lead'!$L$2:$L$616)) -> 235 | C21: =SUMPRODUCT(('Detalle por lead'!$D$2:$D$616="Sí")*ISNUMBER('Detalle por lead'!$N$2:$N$616)) -> 235 | D21: =SUMPRODUCT(('Detalle por lead'!$D$2:$D$616="Sí")*ISNUMBER('Detalle por lead'!$V$2:$V$616)) -> 201 | E21: =SUMPRODUCT(('Detalle por lead'!$D$2:$D$616="Sí")*ISNUMBER('Detalle por lead'!$AA$2:$AA$616)) -> 155 | F21: =SUMPRODUCT(('Detalle por lead'!$D$2:$D$616="Sí")*ISNUMBER('Detalle por lead'!$AD$2:$AD$616)) -> 153
A22: Minutos de reloj desde la respuesta del lead. «Del aviso al audio» = del «te mando un audio» al audio (grabarlo y subirlo).

Sheet Por persona
A1: DESARROLLO PROFESIONAL SyS
A2: Quién dio la recomendación
A3: Solo leads que contestaron la pregunta. Minutos desde la respuesta del lead hasta la recomendación · corte: 15 oct 2026, 23:59 h (Monterrey)
A5: Persona | B5: Recomendaciones | C5: Mediana de minutos | D5: Promedio de minutos | E5: Máximo de minutos | F5: Respondieron después | G5: % que respondió | H5: Duración media del audio (s) | I5: % que vio el audio | J5: Cursos por recomendación | K5: El bot los pasó a Negativo después de que respondieron | L5: Ganados
A6: Salma | B6: =COUNTIFS('Detalle por lead'!$D$2:$D$616,"Sí",'Detalle por lead'!$R$2:$R$616,$A6) -> 84 | C6: {=IFERROR(MEDIAN(IF(('Detalle por lead'!$D$2:$D$616="Sí")*('Detalle por lead'!$R$2:$R$616=$A6)*ISNUMBER('Detalle por lead'!$N$2:$N$616),'Detalle por lead'!$N$2:$N$616)),"—")} -> 6.0998417 | D6: {=IFERROR(AVERAGE(IF(('Detalle por lead'!$D$2:$D$616="Sí")*('Detalle por lead'!$R$2:$R$616=$A6)*ISNUMBER('Detalle por lead'!$N$2:$N$616),'Detalle por lead'!$N$2:$N$616)),"—")} -> 54.598876 | E6: {=IFERROR(MAX(IF(('Detalle por lead'!$D$2:$D$616="Sí")*('Detalle por lead'!$R$2:$R$616=$A6)*ISNUMBER('Detalle por lead'!$N$2:$N$616),'Detalle por lead'!$N$2:$N$616)),"—")} -> 843.73367 | F6: =COUNTIFS('Detalle por lead'!$D$2:$D$616,"Sí",'Detalle por lead'!$R$2:$R$616,$A6,'Detalle por lead'!$Y$2:$Y$616,"Sí") -> 56 | G6: =IFERROR(F6/B6,"—") -> 0.66666667 | H6: {=IFERROR(AVERAGE(IF(('Detalle por lead'!$D$2:$D$616="Sí")*('Detalle por lead'!$R$2:$R$616=$A6)*ISNUMBER('Detalle por lead'!$T$2:$T$616),'Detalle por lead'!$T$2:$T$616)),"—")} -> 111.51084 | I6: =IFERROR(COUNTIFS('Detalle por lead'!$D$2:$D$616,"Sí",'Detalle por lead'!$R$2:$R$616,$A6,'Detalle por lead'!$U$2:$U$616,"Sí")/COUNTIFS('Detalle por lead'!$D$2:$D$616,"Sí",'Detalle por lead'!$R$2:$R$616,$A6,'Detalle por lead'!$Q$2:$Q$616,"Sí"),"—") -> 0.78313253 | J6: {=IFERROR(AVERAGE(IF(('Detalle por lead'!$D$2:$D$616="Sí")*('Detalle por lead'!$R$2:$R$616=$A6)*ISNUMBER('Detalle por lead'!$X$2:$X$616),'Detalle por lead'!$X$2:$X$616)),"—")} -> 1.9404762 | K6: =COUNTIFS('Detalle por lead'!$D$2:$D$616,"Sí",'Detalle por lead'!$R$2:$R$616,$A6,'Detalle por lead'!$AG$2:$AG$616,"Sí") -> 31 | L6: =COUNTIFS('Detalle por lead'!$D$2:$D$616,"Sí",'Detalle por lead'!$R$2:$R$616,$A6,'Detalle por lead'!$AK$2:$AK$616,"Sí") -> 1
A7: Alexander | B7: =COUNTIFS('Detalle por lead'!$D$2:$D$616,"Sí",'Detalle por lead'!$R$2:$R$616,$A7) -> 64 | C7: {=IFERROR(MEDIAN(IF(('Detalle por lead'!$D$2:$D$616="Sí")*('Detalle por lead'!$R$2:$R$616=$A7)*ISNUMBER('Detalle por lead'!$N$2:$N$616),'Detalle por lead'!$N$2:$N$616)),"—")} -> 7.2016583 | D7: {=IFERROR(AVERAGE(IF(('Detalle por lead'!$D$2:$D$616="Sí")*('Detalle por lead'!$R$2:$R$616=$A7)*ISNUMBER('Detalle por lead'!$N$2:$N$616),'Detalle por lead'!$N$2:$N$616)),"—")} -> 37.581215 | E7: {=IFERROR(MAX(IF(('Detalle por lead'!$D$2:$D$616="Sí")*('Detalle por lead'!$R$2:$R$616=$A7)*ISNUMBER('Detalle por lead'!$N$2:$N$616),'Detalle por lead'!$N$2:$N$616)),"—")} -> 1204.0598 | F7: =COUNTIFS('Detalle por lead'!$D$2:$D$616,"Sí",'Detalle por lead'!$R$2:$R$616,$A7,'Detalle por lead'!$Y$2:$Y$616,"Sí") -> 40 | G7: =IFERROR(F7/B7,"—") -> 0.625 | H7: {=IFERROR(AVERAGE(IF(('Detalle por lead'!$D$2:$D$616="Sí")*('Detalle por lead'!$R$2:$R$616=$A7)*ISNUMBER('Detalle por lead'!$T$2:$T$616),'Detalle por lead'!$T$2:$T$616)),"—")} -> 84.55082 | I7: =IFERROR(COUNTIFS('Detalle por lead'!$D$2:$D$616,"Sí",'Detalle por lead'!$R$2:$R$616,$A7,'Detalle por lead'!$U$2:$U$616,"Sí")/COUNTIFS('Detalle por lead'!$D$2:$D$616,"Sí",'Detalle por lead'!$R$2:$R$616,$A7,'Detalle por lead'!$Q$2:$Q$616,"Sí"),"—") -> 0.67213115 | J7: {=IFERROR(AVERAGE(IF(('Detalle por lead'!$D$2:$D$616="Sí")*('Detalle por lead'!$R$2:$R$616=$A7)*ISNUMBER('Detalle por lead'!$X$2:$X$616),'Detalle por lead'!$X$2:$X$616)),"—")} -> 2.75 | K7: =COUNTIFS('Detalle por lead'!$D$2:$D$616,"Sí",'Detalle por lead'!$R$2:$R$616,$A7,'Detalle por lead'!$AG$2:$AG$616,"Sí") -> 20 | L7: =COUNTIFS('Detalle por lead'!$D$2:$D$616,"Sí",'Detalle por lead'!$R$2:$R$616,$A7,'Detalle por lead'!$AK$2:$AK$616,"Sí") -> 3
A8: Victoria | B8: =COUNTIFS('Detalle por lead'!$D$2:$D$616,"Sí",'Detalle por lead'!$R$2:$R$616,$A8) -> 48 | C8: {=IFERROR(MEDIAN(IF(('Detalle por lead'!$D$2:$D$616="Sí")*('Detalle por lead'!$R$2:$R$616=$A8)*ISNUMBER('Detalle por lead'!$N$2:$N$616),'Detalle por lead'!$N$2:$N$616)),"—")} -> 4.8918833 | D8: {=IFERROR(AVERAGE(IF(('Detalle por lead'!$D$2:$D$616="Sí")*('Detalle por lead'!$R$2:$R$616=$A8)*ISNUMBER('Detalle por lead'!$N$2:$N$616),'Detalle por lead'!$N$2:$N$616)),"—")} -> 7.3510229 | E8: {=IFERROR(MAX(IF(('Detalle por lead'!$D$2:$D$616="Sí")*('Detalle por lead'!$R$2:$R$616=$A8)*ISNUMBER('Detalle por lead'!$N$2:$N$616),'Detalle por lead'!$N$2:$N$616)),"—")} -> 42.176817 | F8: =COUNTIFS('Detalle por lead'!$D$2:$D$616,"Sí",'Detalle por lead'!$R$2:$R$616,$A8,'Detalle por lead'!$Y$2:$Y$616,"Sí") -> 34 | G8: =IFERROR(F8/B8,"—") -> 0.70833333 | H8: {=IFERROR(AVERAGE(IF(('Detalle por lead'!$D$2:$D$616="Sí")*('Detalle por lead'!$R$2:$R$616=$A8)*ISNUMBER('Detalle por lead'!$T$2:$T$616),'Detalle por lead'!$T$2:$T$616)),"—")} -> 100.555 | I8: =IFERROR(COUNTIFS('Detalle por lead'!$D$2:$D$616,"Sí",'Detalle por lead'!$R$2:$R$616,$A8,'Detalle por lead'!$U$2:$U$616,"Sí")/COUNTIFS('Detalle por lead'!$D$2:$D$616,"Sí",'Detalle por lead'!$R$2:$R$616,$A8,'Detalle por lead'!$Q$2:$Q$616,"Sí"),"—") -> 0.725 | J8: {=IFERROR(AVERAGE(IF(('Detalle por lead'!$D$2:$D$616="Sí")*('Detalle por lead'!$R$2:$R$616=$A8)*ISNUMBER('Detalle por lead'!$X$2:$X$616),'Detalle por lead'!$X$2:$X$616)),"—")} -> 3.0833333 | K8: =COUNTIFS('Detalle por lead'!$D$2:$D$616,"Sí",'Detalle por lead'!$R$2:$R$616,$A8,'Detalle por lead'!$AG$2:$AG$616,"Sí") -> 23 | L8: =COUNTIFS('Detalle por lead'!$D$2:$D$616,"Sí",'Detalle por lead'!$R$2:$R$616,$A8,'Detalle por lead'!$AK$2:$AK$616,"Sí") -> 2
A9: Joceline | B9: =COUNTIFS('Detalle por lead'!$D$2:$D$616,"Sí",'Detalle por lead'!$R$2:$R$616,$A9) -> 39 | C9: {=IFERROR(MEDIAN(IF(('Detalle por lead'!$D$2:$D$616="Sí")*('Detalle por lead'!$R$2:$R$616=$A9)*ISNUMBER('Detalle por lead'!$N$2:$N$616),'Detalle por lead'!$N$2:$N$616)),"—")} -> 8.4338833 | D9: {=IFERROR(AVERAGE(IF(('Detalle por lead'!$D$2:$D$616="Sí")*('Detalle por lead'!$R$2:$R$616=$A9)*ISNUMBER('Detalle por lead'!$N$2:$N$616),'Detalle por lead'!$N$2:$N$616)),"—")} -> 28.573189 | E9: {=IFERROR(MAX(IF(('Detalle por lead'!$D$2:$D$616="Sí")*('Detalle por lead'!$R$2:$R$616=$A9)*ISNUMBER('Detalle por lead'!$N$2:$N$616),'Detalle por lead'!$N$2:$N$616)),"—")} -> 573.03305 | F9: =COUNTIFS('Detalle por lead'!$D$2:$D$616,"Sí",'Detalle por lead'!$R$2:$R$616,$A9,'Detalle por lead'!$Y$2:$Y$616,"Sí") -> 25 | G9: =IFERROR(F9/B9,"—") -> 0.64102564 | H9: {=IFERROR(AVERAGE(IF(('Detalle por lead'!$D$2:$D$616="Sí")*('Detalle por lead'!$R$2:$R$616=$A9)*ISNUMBER('Detalle por lead'!$T$2:$T$616),'Detalle por lead'!$T$2:$T$616)),"—")} -> 113.63056 | I9: =IFERROR(COUNTIFS('Detalle por lead'!$D$2:$D$616,"Sí",'Detalle por lead'!$R$2:$R$616,$A9,'Detalle por lead'!$U$2:$U$616,"Sí")/COUNTIFS('Detalle por lead'!$D$2:$D$616,"Sí",'Detalle por lead'!$R$2:$R$616,$A9,'Detalle por lead'!$Q$2:$Q$616,"Sí"),"—") -> 0.58333333 | J9: {=IFERROR(AVERAGE(IF(('Detalle por lead'!$D$2:$D$616="Sí")*('Detalle por lead'!$R$2:$R$616=$A9)*ISNUMBER('Detalle por lead'!$X$2:$X$616),'Detalle por lead'!$X$2:$X$616)),"—")} -> 1.8461538 | K9: =COUNTIFS('Detalle por lead'!$D$2:$D$616,"Sí",'Detalle por lead'!$R$2:$R$616,$A9,'Detalle por lead'!$AG$2:$AG$616,"Sí") -> 11 | L9: =COUNTIFS('Detalle por lead'!$D$2:$D$616,"Sí",'Detalle por lead'!$R$2:$R$616,$A9,'Detalle por lead'!$AK$2:$AK$616,"Sí") -> 2
A10: Total | B10: =SUM(B6:B9) -> 235 | F10: =SUM(F6:F9) -> 155 | G10: =IFERROR(F10/B10,"—") -> 0.65957447 | K10: =SUM(K6:K9) -> 85 | L10: =SUM(L6:L9) -> 8
A11: Joceline es auxiliar (apoya el chat); los demás son asesores. Con pocos casos por persona, un solo lead mueve mucho los porcentajes.
A13: Recomendaciones por persona y embudo
A14: Persona | B14: ISO + Calidad: recomendaciones | C14: Manufactura y Calidad: recomendaciones | D14: Core Tools Premium: recomendaciones | E14: ISO + Calidad: mediana de min | F14: Manufactura y Calidad: mediana de min | G14: Core Tools Premium: mediana de min
A15: Salma | B15: =COUNTIFS('Detalle por lead'!$D$2:$D$616,"Sí",'Detalle por lead'!$R$2:$R$616,"Salma",'Detalle por lead'!$A$2:$A$616,"ISO + Calidad") -> 56 | C15: =COUNTIFS('Detalle por lead'!$D$2:$D$616,"Sí",'Detalle por lead'!$R$2:$R$616,"Salma",'Detalle por lead'!$A$2:$A$616,"Manufactura y Calidad") -> 16 | D15: =COUNTIFS('Detalle por lead'!$D$2:$D$616,"Sí",'Detalle por lead'!$R$2:$R$616,"Salma",'Detalle por lead'!$A$2:$A$616,"Core Tools Premium") -> 12 | E15: {=IFERROR(MEDIAN(IF(('Detalle por lead'!$D$2:$D$616="Sí")*('Detalle por lead'!$R$2:$R$616="Salma")*('Detalle por lead'!$A$2:$A$616="ISO + Calidad")*ISNUMBER('Detalle por lead'!$N$2:$N$616),'Detalle por lead'!$N$2:$N$616)),"—")} -> 6.0998417 | F15: {=IFERROR(MEDIAN(IF(('Detalle por lead'!$D$2:$D$616="Sí")*('Detalle por lead'!$R$2:$R$616="Salma")*('Detalle por lead'!$A$2:$A$616="Manufactura y Calidad")*ISNUMBER('Detalle por lead'!$N$2:$N$616),'Detalle por lead'!$N$2:$N$616)),"—")} -> 4.6318833 | G15: {=IFERROR(MEDIAN(IF(('Detalle por lead'!$D$2:$D$616="Sí")*('Detalle por lead'!$R$2:$R$616="Salma")*('Detalle por lead'!$A$2:$A$616="Core Tools Premium")*ISNUMBER('Detalle por lead'!$N$2:$N$616),'Detalle por lead'!$N$2:$N$616)),"—")} -> 6.5289167
A16: Alexander | B16: =COUNTIFS('Detalle por lead'!$D$2:$D$616,"Sí",'Detalle por lead'!$R$2:$R$616,"Alexander",'Detalle por lead'!$A$2:$A$616,"ISO + Calidad") -> 42 | C16: =COUNTIFS('Detalle por lead'!$D$2:$D$616,"Sí",'Detalle por lead'!$R$2:$R$616,"Alexander",'Detalle por lead'!$A$2:$A$616,"Manufactura y Calidad") -> 11 | D16: =COUNTIFS('Detalle por lead'!$D$2:$D$616,"Sí",'Detalle por lead'!$R$2:$R$616,"Alexander",'Detalle por lead'!$A$2:$A$616,"Core Tools Premium") -> 11 | E16: {=IFERROR(MEDIAN(IF(('Detalle por lead'!$D$2:$D$616="Sí")*('Detalle por lead'!$R$2:$R$616="Alexander")*('Detalle por lead'!$A$2:$A$616="ISO + Calidad")*ISNUMBER('Detalle por lead'!$N$2:$N$616),'Detalle por lead'!$N$2:$N$616)),"—")} -> 7.2510917 | F16: {=IFERROR(MEDIAN(IF(('Detalle por lead'!$D$2:$D$616="Sí")*('Detalle por lead'!$R$2:$R$616="Alexander")*('Detalle por lead'!$A$2:$A$616="Manufactura y Calidad")*ISNUMBER('Detalle por lead'!$N$2:$N$616),'Detalle por lead'!$N$2:$N$616)),"—")} -> 5.0288167 | G16: {=IFERROR(MEDIAN(IF(('Detalle por lead'!$D$2:$D$616="Sí")*('Detalle por lead'!$R$2:$R$616="Alexander")*('Detalle por lead'!$A$2:$A$616="Core Tools Premium")*ISNUMBER('Detalle por lead'!$N$2:$N$616),'Detalle por lead'!$N$2:$N$616)),"—")} -> 8.6577834
A17: Victoria | B17: =COUNTIFS('Detalle por lead'!$D$2:$D$616,"Sí",'Detalle por lead'!$R$2:$R$616,"Victoria",'Detalle por lead'!$A$2:$A$616,"ISO + Calidad") -> 30 | C17: =COUNTIFS('Detalle por lead'!$D$2:$D$616,"Sí",'Detalle por lead'!$R$2:$R$616,"Victoria",'Detalle por lead'!$A$2:$A$616,"Manufactura y Calidad") -> 9 | D17: =COUNTIFS('Detalle por lead'!$D$2:$D$616,"Sí",'Detalle por lead'!$R$2:$R$616,"Victoria",'Detalle por lead'!$A$2:$A$616,"Core Tools Premium") -> 9 | E17: {=IFERROR(MEDIAN(IF(('Detalle por lead'!$D$2:$D$616="Sí")*('Detalle por lead'!$R$2:$R$616="Victoria")*('Detalle por lead'!$A$2:$A$616="ISO + Calidad")*ISNUMBER('Detalle por lead'!$N$2:$N$616),'Detalle por lead'!$N$2:$N$616)),"—")} -> 5.036525 | F17: {=IFERROR(MEDIAN(IF(('Detalle por lead'!$D$2:$D$616="Sí")*('Detalle por lead'!$R$2:$R$616="Victoria")*('Detalle por lead'!$A$2:$A$616="Manufactura y Calidad")*ISNUMBER('Detalle por lead'!$N$2:$N$616),'Detalle por lead'!$N$2:$N$616)),"—")} -> 3.24605 | G17: {=IFERROR(MEDIAN(IF(('Detalle por lead'!$D$2:$D$616="Sí")*('Detalle por lead'!$R$2:$R$616="Victoria")*('Detalle por lead'!$A$2:$A$616="Core Tools Premium")*ISNUMBER('Detalle por lead'!$N$2:$N$616),'Detalle por lead'!$N$2:$N$616)),"—")} -> 5.0849833
A18: Joceline | B18: =COUNTIFS('Detalle por lead'!$D$2:$D$616,"Sí",'Detalle por lead'!$R$2:$R$616,"Joceline",'Detalle por lead'!$A$2:$A$616,"ISO + Calidad") -> 29 | C18: =COUNTIFS('Detalle por lead'!$D$2:$D$616,"Sí",'Detalle por lead'!$R$2:$R$616,"Joceline",'Detalle por lead'!$A$2:$A$616,"Manufactura y Calidad") -> 5 | D18: =COUNTIFS('Detalle por lead'!$D$2:$D$616,"Sí",'Detalle por lead'!$R$2:$R$616,"Joceline",'Detalle por lead'!$A$2:$A$616,"Core Tools Premium") -> 5 | E18: {=IFERROR(MEDIAN(IF(('Detalle por lead'!$D$2:$D$616="Sí")*('Detalle por lead'!$R$2:$R$616="Joceline")*('Detalle por lead'!$A$2:$A$616="ISO + Calidad")*ISNUMBER('Detalle por lead'!$N$2:$N$616),'Detalle por lead'!$N$2:$N$616)),"—")} -> 11.05665 | F18: {=IFERROR(MEDIAN(IF(('Detalle por lead'!$D$2:$D$616="Sí")*('Detalle por lead'!$R$2:$R$616="Joceline")*('Detalle por lead'!$A$2:$A$616="Manufactura y Calidad")*ISNUMBER('Detalle por lead'!$N$2:$N$616),'Detalle por lead'!$N$2:$N$616)),"—")} -> 6.9695833 | G18: {=IFERROR(MEDIAN(IF(('Detalle por lead'!$D$2:$D$616="Sí")*('Detalle por lead'!$R$2:$R$616="Joceline")*('Detalle por lead'!$A$2:$A$616="Core Tools Premium")*ISNUMBER('Detalle por lead'!$N$2:$N$616),'Detalle por lead'!$N$2:$N$616)),"—")} -> 5.8677667

Sheet Audios del equipo
A1: DESARROLLO PROFESIONAL SyS
A2: Todos los audios que mandó el equipo
A3: Notas de voz de las personas y audio automático del bot, del 5 al 15 de octubre · tres embudos · corte: 15 oct 2026, 23:59 h (Monterrey)
A5: Audio de una persona contra audio automático del bot
A6: Quién lo mandó | B6: Audios | C6: % de los audios | D6: Duración mediana (s) | E6: % que el lead vio | F6: Min. hasta que lo vio (mediana) | G6: % en que el lead escribió en 24 h | H6: Min. hasta que escribió (mediana)
A7: Persona (nota de voz) | B7: =COUNTIFS('Detalle de audios'!$G$2:$G$810,"Persona") -> 257 | C7: =IFERROR(B7/COUNT('Detalle de audios'!$B$2:$B$810),"—") -> 0.31767614 | D7: {=IFERROR(MEDIAN(IF(('Detalle de audios'!$G$2:$G$810="Persona")*ISNUMBER('Detalle de audios'!$K$2:$K$810),'Detalle de audios'!$K$2:$K$810)),"—")} -> 103.7 | E7: =IFERROR(COUNTIFS('Detalle de audios'!$G$2:$G$810,"Persona",'Detalle de audios'!$N$2:$N$810,"Sí")/B7,"—") -> 0.71595331 | F7: {=IFERROR(MEDIAN(IF(('Detalle de audios'!$G$2:$G$810="Persona")*ISNUMBER('Detalle de audios'!$O$2:$O$810),'Detalle de audios'!$O$2:$O$810)),"—")} -> 5.05 | G7: =IFERROR(COUNTIFS('Detalle de audios'!$G$2:$G$810,"Persona",'Detalle de audios'!$P$2:$P$810,"Sí")/B7,"—") -> 0.59533074 | H7: {=IFERROR(MEDIAN(IF(('Detalle de audios'!$G$2:$G$810="Persona")*ISNUMBER('Detalle de audios'!$Q$2:$Q$810),'Detalle de audios'!$Q$2:$Q$810)),"—")} -> 8.8
A8: Bot (audio automático en Negativo) | B8: =COUNTIFS('Detalle de audios'!$G$2:$G$810,"Bot (automático)") -> 552 | C8: =IFERROR(B8/COUNT('Detalle de audios'!$B$2:$B$810),"—") -> 0.68232386 | D8: {=IFERROR(MEDIAN(IF(('Detalle de audios'!$G$2:$G$810="Bot (automático)")*ISNUMBER('Detalle de audios'!$K$2:$K$810),'Detalle de audios'!$K$2:$K$810)),"—")} -> 72 | E8: =IFERROR(COUNTIFS('Detalle de audios'!$G$2:$G$810,"Bot (automático)",'Detalle de audios'!$N$2:$N$810,"Sí")/B8,"—") -> 0.64311594 | F8: {=IFERROR(MEDIAN(IF(('Detalle de audios'!$G$2:$G$810="Bot (automático)")*ISNUMBER('Detalle de audios'!$O$2:$O$810),'Detalle de audios'!$O$2:$O$810)),"—")} -> 92.3 | G8: =IFERROR(COUNTIFS('Detalle de audios'!$G$2:$G$810,"Bot (automático)",'Detalle de audios'!$P$2:$P$810,"Sí")/B8,"—") -> 0.11231884 | H8: {=IFERROR(MEDIAN(IF(('Detalle de audios'!$G$2:$G$810="Bot (automático)")*ISNUMBER('Detalle de audios'!$Q$2:$Q$810),'Detalle de audios'!$Q$2:$Q$810)),"—")} -> 137.35
A10: Por persona
A11: Persona | B11: Audios | C11: % de los audios | D11: Duración mediana (s) | E11: % que el lead vio | F11: Min. hasta que lo vio (mediana) | G11: % en que el lead escribió en 24 h | H11: Min. hasta que escribió (mediana)
A12: Salma | B12: =COUNTIFS('Detalle de audios'!$G$2:$G$810,"Persona",'Detalle de audios'!$F$2:$F$810,"Salma") -> 105 | C12: =IFERROR(B12/COUNTIFS('Detalle de audios'!$G$2:$G$810,"Persona"),"—") -> 0.40856031 | D12: {=IFERROR(MEDIAN(IF(('Detalle de audios'!$G$2:$G$810="Persona")*('Detalle de audios'!$F$2:$F$810="Salma")*ISNUMBER('Detalle de audios'!$K$2:$K$810),'Detalle de audios'!$K$2:$K$810)),"—")} -> 108.8 | E12: =IFERROR(COUNTIFS('Detalle de audios'!$G$2:$G$810,"Persona",'Detalle de audios'!$F$2:$F$810,"Salma",'Detalle de audios'!$N$2:$N$810,"Sí")/B12,"—") -> 0.8 | F12: {=IFERROR(MEDIAN(IF(('Detalle de audios'!$G$2:$G$810="Persona")*('Detalle de audios'!$F$2:$F$810="Salma")*ISNUMBER('Detalle de audios'!$O$2:$O$810),'Detalle de audios'!$O$2:$O$810)),"—")} -> 7.4 | G12: =IFERROR(COUNTIFS('Detalle de audios'!$G$2:$G$810,"Persona",'Detalle de audios'!$F$2:$F$810,"Salma",'Detalle de audios'!$P$2:$P$810,"Sí")/B12,"—") -> 0.61904762 | H12: {=IFERROR(MEDIAN(IF(('Detalle de audios'!$G$2:$G$810="Persona")*('Detalle de audios'!$F$2:$F$810="Salma")*ISNUMBER('Detalle de audios'!$Q$2:$Q$810),'Detalle de audios'!$Q$2:$Q$810)),"—")} -> 13.4
A13: Alexander | B13: =COUNTIFS('Detalle de audios'!$G$2:$G$810,"Persona",'Detalle de audios'!$F$2:$F$810,"Alexander") -> 62 | C13: =IFERROR(B13/COUNTIFS('Detalle de audios'!$G$2:$G$810,"Persona"),"—") -> 0.24124514 | D13: {=IFERROR(MEDIAN(IF(('Detalle de audios'!$G$2:$G$810="Persona")*('Detalle de audios'!$F$2:$F$810="Alexander")*ISNUMBER('Detalle de audios'!$K$2:$K$810),'Detalle de audios'!$K$2:$K$810)),"—")} -> 83.7 | E13: =IFERROR(COUNTIFS('Detalle de audios'!$G$2:$G$810,"Persona",'Detalle de audios'!$F$2:$F$810,"Alexander",'Detalle de audios'!$N$2:$N$810,"Sí")/B13,"—") -> 0.66129032 | F13: {=IFERROR(MEDIAN(IF(('Detalle de audios'!$G$2:$G$810="Persona")*('Detalle de audios'!$F$2:$F$810="Alexander")*ISNUMBER('Detalle de audios'!$O$2:$O$810),'Detalle de audios'!$O$2:$O$810)),"—")} -> 4.4 | G13: =IFERROR(COUNTIFS('Detalle de audios'!$G$2:$G$810,"Persona",'Detalle de audios'!$F$2:$F$810,"Alexander",'Detalle de audios'!$P$2:$P$810,"Sí")/B13,"—") -> 0.58064516 | H13: {=IFERROR(MEDIAN(IF(('Detalle de audios'!$G$2:$G$810="Persona")*('Detalle de audios'!$F$2:$F$810="Alexander")*ISNUMBER('Detalle de audios'!$Q$2:$Q$810),'Detalle de audios'!$Q$2:$Q$810)),"—")} -> 9.75
A14: Victoria | B14: =COUNTIFS('Detalle de audios'!$G$2:$G$810,"Persona",'Detalle de audios'!$F$2:$F$810,"Victoria") -> 50 | C14: =IFERROR(B14/COUNTIFS('Detalle de audios'!$G$2:$G$810,"Persona"),"—") -> 0.19455253 | D14: {=IFERROR(MEDIAN(IF(('Detalle de audios'!$G$2:$G$810="Persona")*('Detalle de audios'!$F$2:$F$810="Victoria")*ISNUMBER('Detalle de audios'!$K$2:$K$810),'Detalle de audios'!$K$2:$K$810)),"—")} -> 97.45 | E14: =IFERROR(COUNTIFS('Detalle de audios'!$G$2:$G$810,"Persona",'Detalle de audios'!$F$2:$F$810,"Victoria",'Detalle de audios'!$N$2:$N$810,"Sí")/B14,"—") -> 0.72 | F14: {=IFERROR(MEDIAN(IF(('Detalle de audios'!$G$2:$G$810="Persona")*('Detalle de audios'!$F$2:$F$810="Victoria")*ISNUMBER('Detalle de audios'!$O$2:$O$810),'Detalle de audios'!$O$2:$O$810)),"—")} -> 3.45 | G14: =IFERROR(COUNTIFS('Detalle de audios'!$G$2:$G$810,"Persona",'Detalle de audios'!$F$2:$F$810,"Victoria",'Detalle de audios'!$P$2:$P$810,"Sí")/B14,"—") -> 0.64 | H14: {=IFERROR(MEDIAN(IF(('Detalle de audios'!$G$2:$G$810="Persona")*('Detalle de audios'!$F$2:$F$810="Victoria")*ISNUMBER('Detalle de audios'!$Q$2:$Q$810),'Detalle de audios'!$Q$2:$Q$810)),"—")} -> 10.35
A15: Joceline | B15: =COUNTIFS('Detalle de audios'!$G$2:$G$810,"Persona",'Detalle de audios'!$F$2:$F$810,"Joceline") -> 40 | C15: =IFERROR(B15/COUNTIFS('Detalle de audios'!$G$2:$G$810,"Persona"),"—") -> 0.15564202 | D15: {=IFERROR(MEDIAN(IF(('Detalle de audios'!$G$2:$G$810="Persona")*('Detalle de audios'!$F$2:$F$810="Joceline")*ISNUMBER('Detalle de audios'!$K$2:$K$810),'Detalle de audios'!$K$2:$K$810)),"—")} -> 107.25 | E15: =IFERROR(COUNTIFS('Detalle de audios'!$G$2:$G$810,"Persona",'Detalle de audios'!$F$2:$F$810,"Joceline",'Detalle de audios'!$N$2:$N$810,"Sí")/B15,"—") -> 0.575 | F15: {=IFERROR(MEDIAN(IF(('Detalle de audios'!$G$2:$G$810="Persona")*('Detalle de audios'!$F$2:$F$810="Joceline")*ISNUMBER('Detalle de audios'!$O$2:$O$810),'Detalle de audios'!$O$2:$O$810)),"—")} -> 5 | G15: =IFERROR(COUNTIFS('Detalle de audios'!$G$2:$G$810,"Persona",'Detalle de audios'!$F$2:$F$810,"Joceline",'Detalle de audios'!$P$2:$P$810,"Sí")/B15,"—") -> 0.5 | H15: {=IFERROR(MEDIAN(IF(('Detalle de audios'!$G$2:$G$810="Persona")*('Detalle de audios'!$F$2:$F$810="Joceline")*ISNUMBER('Detalle de audios'!$Q$2:$Q$810),'Detalle de audios'!$Q$2:$Q$810)),"—")} -> 4.75
A17: Para qué se mandó (audios de personas)
A18: Uso | B18: Audios | C18: % de los audios | D18: Duración mediana (s) | E18: % que el lead vio | F18: Min. hasta que lo vio (mediana) | G18: % en que el lead escribió en 24 h | H18: Min. hasta que escribió (mediana)
A19: Recomendación del paso 1.2 | B19: =COUNTIFS('Detalle de audios'!$G$2:$G$810,"Persona",'Detalle de audios'!$M$2:$M$810,"Sí") -> 225 | C19: =IFERROR(B19/COUNTIFS('Detalle de audios'!$G$2:$G$810,"Persona"),"—") -> 0.87548638 | D19: {=IFERROR(MEDIAN(IF(('Detalle de audios'!$G$2:$G$810="Persona")*('Detalle de audios'!$M$2:$M$810="Sí")*ISNUMBER('Detalle de audios'!$K$2:$K$810),'Detalle de audios'!$K$2:$K$810)),"—")} -> 104.5 | E19: =IFERROR(COUNTIFS('Detalle de audios'!$G$2:$G$810,"Persona",'Detalle de audios'!$M$2:$M$810,"Sí",'Detalle de audios'!$N$2:$N$810,"Sí")/B19,"—") -> 0.70222222 | F19: {=IFERROR(MEDIAN(IF(('Detalle de audios'!$G$2:$G$810="Persona")*('Detalle de audios'!$M$2:$M$810="Sí")*ISNUMBER('Detalle de audios'!$O$2:$O$810),'Detalle de audios'!$O$2:$O$810)),"—")} -> 5.4 | G19: =IFERROR(COUNTIFS('Detalle de audios'!$G$2:$G$810,"Persona",'Detalle de audios'!$M$2:$M$810,"Sí",'Detalle de audios'!$P$2:$P$810,"Sí")/B19,"—") -> 0.6 | H19: {=IFERROR(MEDIAN(IF(('Detalle de audios'!$G$2:$G$810="Persona")*('Detalle de audios'!$M$2:$M$810="Sí")*ISNUMBER('Detalle de audios'!$Q$2:$Q$810),'Detalle de audios'!$Q$2:$Q$810)),"—")} -> 8.8
A20: Otro momento de la conversación | B20: =COUNTIFS('Detalle de audios'!$G$2:$G$810,"Persona",'Detalle de audios'!$M$2:$M$810,"No") -> 32 | C20: =IFERROR(B20/COUNTIFS('Detalle de audios'!$G$2:$G$810,"Persona"),"—") -> 0.12451362 | D20: {=IFERROR(MEDIAN(IF(('Detalle de audios'!$G$2:$G$810="Persona")*('Detalle de audios'!$M$2:$M$810="No")*ISNUMBER('Detalle de audios'!$K$2:$K$810),'Detalle de audios'!$K$2:$K$810)),"—")} -> 57 | E20: =IFERROR(COUNTIFS('Detalle de audios'!$G$2:$G$810,"Persona",'Detalle de audios'!$M$2:$M$810,"No",'Detalle de audios'!$N$2:$N$810,"Sí")/B20,"—") -> 0.8125 | F20: {=IFERROR(MEDIAN(IF(('Detalle de audios'!$G$2:$G$810="Persona")*('Detalle de audios'!$M$2:$M$810="No")*ISNUMBER('Detalle de audios'!$O$2:$O$810),'Detalle de audios'!$O$2:$O$810)),"—")} -> 1.75 | G20: =IFERROR(COUNTIFS('Detalle de audios'!$G$2:$G$810,"Persona",'Detalle de audios'!$M$2:$M$810,"No",'Detalle de audios'!$P$2:$P$810,"Sí")/B20,"—") -> 0.5625 | H20: {=IFERROR(MEDIAN(IF(('Detalle de audios'!$G$2:$G$810="Persona")*('Detalle de audios'!$M$2:$M$810="No")*ISNUMBER('Detalle de audios'!$Q$2:$Q$810),'Detalle de audios'!$Q$2:$Q$810)),"—")} -> 9.4
A22: Por duración (audios de personas)
A23: Duración | B23: Audios | C23: % de los audios | D23: Duración mediana (s) | E23: % que el lead vio | F23: Min. hasta que lo vio (mediana) | G23: % en que el lead escribió en 24 h | H23: Min. hasta que escribió (mediana)
A24: Menos de 60 s | B24: =COUNTIFS('Detalle de audios'!$G$2:$G$810,"Persona",'Detalle de audios'!$K$2:$K$810,"<60") -> 25 | C24: =IFERROR(B24/COUNTIFS('Detalle de audios'!$G$2:$G$810,"Persona"),"—") -> 0.097276265 | D24: {=IFERROR(MEDIAN(IF(('Detalle de audios'!$G$2:$G$810="Persona")*('Detalle de audios'!$K$2:$K$810<60)*ISNUMBER('Detalle de audios'!$K$2:$K$810),'Detalle de audios'!$K$2:$K$810)),"—")} -> 57 | E24: =IFERROR(COUNTIFS('Detalle de audios'!$G$2:$G$810,"Persona",'Detalle de audios'!$K$2:$K$810,"<60",'Detalle de audios'!$N$2:$N$810,"Sí")/B24,"—") -> 0.8 | F24: {=IFERROR(MEDIAN(IF(('Detalle de audios'!$G$2:$G$810="Persona")*('Detalle de audios'!$K$2:$K$810<60)*ISNUMBER('Detalle de audios'!$O$2:$O$810),'Detalle de audios'!$O$2:$O$810)),"—")} -> 0.8 | G24: =IFERROR(COUNTIFS('Detalle de audios'!$G$2:$G$810,"Persona",'Detalle de audios'!$K$2:$K$810,"<60",'Detalle de audios'!$P$2:$P$810,"Sí")/B24,"—") -> 0.64 | H24: {=IFERROR(MEDIAN(IF(('Detalle de audios'!$G$2:$G$810="Persona")*('Detalle de audios'!$K$2:$K$810<60)*ISNUMBER('Detalle de audios'!$Q$2:$Q$810),'Detalle de audios'!$Q$2:$Q$810)),"—")} -> 11.45
A25: 60 a 90 s | B25: =COUNTIFS('Detalle de audios'!$G$2:$G$810,"Persona",'Detalle de audios'!$K$2:$K$810,">=60",'Detalle de audios'!$K$2:$K$810,"<90") -> 54 | C25: =IFERROR(B25/COUNTIFS('Detalle de audios'!$G$2:$G$810,"Persona"),"—") -> 0.21011673 | D25: {=IFERROR(MEDIAN(IF(('Detalle de audios'!$G$2:$G$810="Persona")*('Detalle de audios'!$K$2:$K$810>=60)*('Detalle de audios'!$K$2:$K$810<90)*ISNUMBER('Detalle de audios'!$K$2:$K$810),'Detalle de audios'!$K$2:$K$810)),"—")} -> 81.75 | E25: =IFERROR(COUNTIFS('Detalle de audios'!$G$2:$G$810,"Persona",'Detalle de audios'!$K$2:$K$810,">=60",'Detalle de audios'!$K$2:$K$810,"<90",'Detalle de audios'!$N$2:$N$810,"Sí")/B25,"—") -> 0.62962963 | F25: {=IFERROR(MEDIAN(IF(('Detalle de audios'!$G$2:$G$810="Persona")*('Detalle de audios'!$K$2:$K$810>=60)*('Detalle de audios'!$K$2:$K$810<90)*ISNUMBER('Detalle de audios'!$O$2:$O$810),'Detalle de audios'!$O$2:$O$810)),"—")} -> 4.85 | G25: =IFERROR(COUNTIFS('Detalle de audios'!$G$2:$G$810,"Persona",'Detalle de audios'!$K$2:$K$810,">=60",'Detalle de audios'!$K$2:$K$810,"<90",'Detalle de audios'!$P$2:$P$810,"Sí")/B25,"—") -> 0.59259259 | H25: {=IFERROR(MEDIAN(IF(('Detalle de audios'!$G$2:$G$810="Persona")*('Detalle de audios'!$K$2:$K$810>=60)*('Detalle de audios'!$K$2:$K$810<90)*ISNUMBER('Detalle de audios'!$Q$2:$Q$810),'Detalle de audios'!$Q$2:$Q$810)),"—")} -> 12.1
A26: 90 a 120 s | B26: =COUNTIFS('Detalle de audios'!$G$2:$G$810,"Persona",'Detalle de audios'!$K$2:$K$810,">=90",'Detalle de audios'!$K$2:$K$810,"<120") -> 158 | C26: =IFERROR(B26/COUNTIFS('Detalle de audios'!$G$2:$G$810,"Persona"),"—") -> 0.61478599 | D26: {=IFERROR(MEDIAN(IF(('Detalle de audios'!$G$2:$G$810="Persona")*('Detalle de audios'!$K$2:$K$810>=90)*('Detalle de audios'!$K$2:$K$810<120)*ISNUMBER('Detalle de audios'!$K$2:$K$810),'Detalle de audios'!$K$2:$K$810)),"—")} -> 106.85 | E26: =IFERROR(COUNTIFS('Detalle de audios'!$G$2:$G$810,"Persona",'Detalle de audios'!$K$2:$K$810,">=90",'Detalle de audios'!$K$2:$K$810,"<120",'Detalle de audios'!$N$2:$N$810,"Sí")/B26,"—") -> 0.74050633 | F26: {=IFERROR(MEDIAN(IF(('Detalle de audios'!$G$2:$G$810="Persona")*('Detalle de audios'!$K$2:$K$810>=90)*('Detalle de audios'!$K$2:$K$810<120)*ISNUMBER('Detalle de audios'!$O$2:$O$810),'Detalle de audios'!$O$2:$O$810)),"—")} -> 5.9 | G26: =IFERROR(COUNTIFS('Detalle de audios'!$G$2:$G$810,"Persona",'Detalle de audios'!$K$2:$K$810,">=90",'Detalle de audios'!$K$2:$K$810,"<120",'Detalle de audios'!$P$2:$P$810,"Sí")/B26,"—") -> 0.59493671 | H26: {=IFERROR(MEDIAN(IF(('Detalle de audios'!$G$2:$G$810="Persona")*('Detalle de audios'!$K$2:$K$810>=90)*('Detalle de audios'!$K$2:$K$810<120)*ISNUMBER('Detalle de audios'!$Q$2:$Q$810),'Detalle de audios'!$Q$2:$Q$810)),"—")} -> 8.4
A27: 120 s o más | B27: =COUNTIFS('Detalle de audios'!$G$2:$G$810,"Persona",'Detalle de audios'!$K$2:$K$810,">=120") -> 20 | C27: =IFERROR(B27/COUNTIFS('Detalle de audios'!$G$2:$G$810,"Persona"),"—") -> 0.077821012 | D27: {=IFERROR(MEDIAN(IF(('Detalle de audios'!$G$2:$G$810="Persona")*('Detalle de audios'!$K$2:$K$810>=120)*ISNUMBER('Detalle de audios'!$K$2:$K$810),'Detalle de audios'!$K$2:$K$810)),"—")} -> 128.2 | E27: =IFERROR(COUNTIFS('Detalle de audios'!$G$2:$G$810,"Persona",'Detalle de audios'!$K$2:$K$810,">=120",'Detalle de audios'!$N$2:$N$810,"Sí")/B27,"—") -> 0.65 | F27: {=IFERROR(MEDIAN(IF(('Detalle de audios'!$G$2:$G$810="Persona")*('Detalle de audios'!$K$2:$K$810>=120)*ISNUMBER('Detalle de audios'!$O$2:$O$810),'Detalle de audios'!$O$2:$O$810)),"—")} -> 5.1 | G27: =IFERROR(COUNTIFS('Detalle de audios'!$G$2:$G$810,"Persona",'Detalle de audios'!$K$2:$K$810,">=120",'Detalle de audios'!$P$2:$P$810,"Sí")/B27,"—") -> 0.55 | H27: {=IFERROR(MEDIAN(IF(('Detalle de audios'!$G$2:$G$810="Persona")*('Detalle de audios'!$K$2:$K$810>=120)*ISNUMBER('Detalle de audios'!$Q$2:$Q$810),'Detalle de audios'!$Q$2:$Q$810)),"—")} -> 6.8
A29: Según la hora (audios de personas)
A30: Hora | B30: Audios | C30: % de los audios | D30: Duración mediana (s) | E30: % que el lead vio | F30: Min. hasta que lo vio (mediana) | G30: % en que el lead escribió en 24 h | H30: Min. hasta que escribió (mediana)
A31: De 8:00 a 22:00 | B31: =COUNTIFS('Detalle de audios'!$G$2:$G$810,"Persona",'Detalle de audios'!$E$2:$E$810,"Sí") -> 234 | C31: =IFERROR(B31/COUNTIFS('Detalle de audios'!$G$2:$G$810,"Persona"),"—") -> 0.91050584 | D31: {=IFERROR(MEDIAN(IF(('Detalle de audios'!$G$2:$G$810="Persona")*('Detalle de audios'!$E$2:$E$810="Sí")*ISNUMBER('Detalle de audios'!$K$2:$K$810),'Detalle de audios'!$K$2:$K$810)),"—")} -> 103.2 | E31: =IFERROR(COUNTIFS('Detalle de audios'!$G$2:$G$810,"Persona",'Detalle de audios'!$E$2:$E$810,"Sí",'Detalle de audios'!$N$2:$N$810,"Sí")/B31,"—") -> 0.70512821 | F31: {=IFERROR(MEDIAN(IF(('Detalle de audios'!$G$2:$G$810="Persona")*('Detalle de audios'!$E$2:$E$810="Sí")*ISNUMBER('Detalle de audios'!$O$2:$O$810),'Detalle de audios'!$O$2:$O$810)),"—")} -> 5.1 | G31: =IFERROR(COUNTIFS('Detalle de audios'!$G$2:$G$810,"Persona",'Detalle de audios'!$E$2:$E$810,"Sí",'Detalle de audios'!$P$2:$P$810,"Sí")/B31,"—") -> 0.58974359 | H31: {=IFERROR(MEDIAN(IF(('Detalle de audios'!$G$2:$G$810="Persona")*('Detalle de audios'!$E$2:$E$810="Sí")*ISNUMBER('Detalle de audios'!$Q$2:$Q$810),'Detalle de audios'!$Q$2:$Q$810)),"—")} -> 8.75
A32: Antes de 8:00 o desde 22:00 | B32: =COUNTIFS('Detalle de audios'!$G$2:$G$810,"Persona",'Detalle de audios'!$E$2:$E$810,"No") -> 23 | C32: =IFERROR(B32/COUNTIFS('Detalle de audios'!$G$2:$G$810,"Persona"),"—") -> 0.089494163 | D32: {=IFERROR(MEDIAN(IF(('Detalle de audios'!$G$2:$G$810="Persona")*('Detalle de audios'!$E$2:$E$810="No")*ISNUMBER('Detalle de audios'!$K$2:$K$810),'Detalle de audios'!$K$2:$K$810)),"—")} -> 109.4 | E32: =IFERROR(COUNTIFS('Detalle de audios'!$G$2:$G$810,"Persona",'Detalle de audios'!$E$2:$E$810,"No",'Detalle de audios'!$N$2:$N$810,"Sí")/B32,"—") -> 0.82608696 | F32: {=IFERROR(MEDIAN(IF(('Detalle de audios'!$G$2:$G$810="Persona")*('Detalle de audios'!$E$2:$E$810="No")*ISNUMBER('Detalle de audios'!$O$2:$O$810),'Detalle de audios'!$O$2:$O$810)),"—")} -> 4.7 | G32: =IFERROR(COUNTIFS('Detalle de audios'!$G$2:$G$810,"Persona",'Detalle de audios'!$E$2:$E$810,"No",'Detalle de audios'!$P$2:$P$810,"Sí")/B32,"—") -> 0.65217391 | H32: {=IFERROR(MEDIAN(IF(('Detalle de audios'!$G$2:$G$810="Persona")*('Detalle de audios'!$E$2:$E$810="No")*ISNUMBER('Detalle de audios'!$Q$2:$Q$810),'Detalle de audios'!$Q$2:$Q$810)),"—")} -> 45.4
A34: Por embudo (audios de personas)
A35: Embudo | B35: Audios | C35: % de los audios | D35: Duración mediana (s) | E35: % que el lead vio | F35: Min. hasta que lo vio (mediana) | G35: % en que el lead escribió en 24 h | H35: Min. hasta que escribió (mediana)
A36: ISO + Calidad | B36: =COUNTIFS('Detalle de audios'!$G$2:$G$810,"Persona",'Detalle de audios'!$A$2:$A$810,"ISO + Calidad") -> 170 | C36: =IFERROR(B36/COUNTIFS('Detalle de audios'!$G$2:$G$810,"Persona"),"—") -> 0.6614786 | D36: {=IFERROR(MEDIAN(IF(('Detalle de audios'!$G$2:$G$810="Persona")*('Detalle de audios'!$A$2:$A$810="ISO + Calidad")*ISNUMBER('Detalle de audios'!$K$2:$K$810),'Detalle de audios'!$K$2:$K$810)),"—")} -> 103.75 | E36: =IFERROR(COUNTIFS('Detalle de audios'!$G$2:$G$810,"Persona",'Detalle de audios'!$A$2:$A$810,"ISO + Calidad",'Detalle de audios'!$N$2:$N$810,"Sí")/B36,"—") -> 0.77058824 | F36: {=IFERROR(MEDIAN(IF(('Detalle de audios'!$G$2:$G$810="Persona")*('Detalle de audios'!$A$2:$A$810="ISO + Calidad")*ISNUMBER('Detalle de audios'!$O$2:$O$810),'Detalle de audios'!$O$2:$O$810)),"—")} -> 5 | G36: =IFERROR(COUNTIFS('Detalle de audios'!$G$2:$G$810,"Persona",'Detalle de audios'!$A$2:$A$810,"ISO + Calidad",'Detalle de audios'!$P$2:$P$810,"Sí")/B36,"—") -> 0.59411765 | H36: {=IFERROR(MEDIAN(IF(('Detalle de audios'!$G$2:$G$810="Persona")*('Detalle de audios'!$A$2:$A$810="ISO + Calidad")*ISNUMBER('Detalle de audios'!$Q$2:$Q$810),'Detalle de audios'!$Q$2:$Q$810)),"—")} -> 8.8
A37: Manufactura y Calidad | B37: =COUNTIFS('Detalle de audios'!$G$2:$G$810,"Persona",'Detalle de audios'!$A$2:$A$810,"Manufactura y Calidad") -> 48 | C37: =IFERROR(B37/COUNTIFS('Detalle de audios'!$G$2:$G$810,"Persona"),"—") -> 0.18677043 | D37: {=IFERROR(MEDIAN(IF(('Detalle de audios'!$G$2:$G$810="Persona")*('Detalle de audios'!$A$2:$A$810="Manufactura y Calidad")*ISNUMBER('Detalle de audios'!$K$2:$K$810),'Detalle de audios'!$K$2:$K$810)),"—")} -> 104.7 | E37: =IFERROR(COUNTIFS('Detalle de audios'!$G$2:$G$810,"Persona",'Detalle de audios'!$A$2:$A$810,"Manufactura y Calidad",'Detalle de audios'!$N$2:$N$810,"Sí")/B37,"—") -> 0.5625 | F37: {=IFERROR(MEDIAN(IF(('Detalle de audios'!$G$2:$G$810="Persona")*('Detalle de audios'!$A$2:$A$810="Manufactura y Calidad")*ISNUMBER('Detalle de audios'!$O$2:$O$810),'Detalle de audios'!$O$2:$O$810)),"—")} -> 8 | G37: =IFERROR(COUNTIFS('Detalle de audios'!$G$2:$G$810,"Persona",'Detalle de audios'!$A$2:$A$810,"Manufactura y Calidad",'Detalle de audios'!$P$2:$P$810,"Sí")/B37,"—") -> 0.64583333 | H37: {=IFERROR(MEDIAN(IF(('Detalle de audios'!$G$2:$G$810="Persona")*('Detalle de audios'!$A$2:$A$810="Manufactura y Calidad")*ISNUMBER('Detalle de audios'!$Q$2:$Q$810),'Detalle de audios'!$Q$2:$Q$810)),"—")} -> 8.1
A38: Core Tools Premium | B38: =COUNTIFS('Detalle de audios'!$G$2:$G$810,"Persona",'Detalle de audios'!$A$2:$A$810,"Core Tools Premium") -> 39 | C38: =IFERROR(B38/COUNTIFS('Detalle de audios'!$G$2:$G$810,"Persona"),"—") -> 0.15175097 | D38: {=IFERROR(MEDIAN(IF(('Detalle de audios'!$G$2:$G$810="Persona")*('Detalle de audios'!$A$2:$A$810="Core Tools Premium")*ISNUMBER('Detalle de audios'!$K$2:$K$810),'Detalle de audios'!$K$2:$K$810)),"—")} -> 100.4 | E38: =IFERROR(COUNTIFS('Detalle de audios'!$G$2:$G$810,"Persona",'Detalle de audios'!$A$2:$A$810,"Core Tools Premium",'Detalle de audios'!$N$2:$N$810,"Sí")/B38,"—") -> 0.66666667 | F38: {=IFERROR(MEDIAN(IF(('Detalle de audios'!$G$2:$G$810="Persona")*('Detalle de audios'!$A$2:$A$810="Core Tools Premium")*ISNUMBER('Detalle de audios'!$O$2:$O$810),'Detalle de audios'!$O$2:$O$810)),"—")} -> 4.7 | G38: =IFERROR(COUNTIFS('Detalle de audios'!$G$2:$G$810,"Persona",'Detalle de audios'!$A$2:$A$810,"Core Tools Premium",'Detalle de audios'!$P$2:$P$810,"Sí")/B38,"—") -> 0.53846154 | H38: {=IFERROR(MEDIAN(IF(('Detalle de audios'!$G$2:$G$810="Persona")*('Detalle de audios'!$A$2:$A$810="Core Tools Premium")*ISNUMBER('Detalle de audios'!$Q$2:$Q$810),'Detalle de audios'!$Q$2:$Q$810)),"—")} -> 11.5
A40: Por embudo (audio automático del bot)
A41: Embudo | B41: Audios | C41: % de los audios | D41: Duración mediana (s) | E41: % que el lead vio | F41: Min. hasta que lo vio (mediana) | G41: % en que el lead escribió en 24 h | H41: Min. hasta que escribió (mediana)
A42: ISO + Calidad | B42: =COUNTIFS('Detalle de audios'!$G$2:$G$810,"Bot (automático)",'Detalle de audios'!$A$2:$A$810,"ISO + Calidad") -> 360 | C42: =IFERROR(B42/COUNTIFS('Detalle de audios'!$G$2:$G$810,"Bot (automático)"),"—") -> 0.65217391 | D42: {=IFERROR(MEDIAN(IF(('Detalle de audios'!$G$2:$G$810="Bot (automático)")*('Detalle de audios'!$A$2:$A$810="ISO + Calidad")*ISNUMBER('Detalle de audios'!$K$2:$K$810),'Detalle de audios'!$K$2:$K$810)),"—")} -> 72 | E42: =IFERROR(COUNTIFS('Detalle de audios'!$G$2:$G$810,"Bot (automático)",'Detalle de audios'!$A$2:$A$810,"ISO + Calidad",'Detalle de audios'!$N$2:$N$810,"Sí")/B42,"—") -> 0.66666667 | F42: {=IFERROR(MEDIAN(IF(('Detalle de audios'!$G$2:$G$810="Bot (automático)")*('Detalle de audios'!$A$2:$A$810="ISO + Calidad")*ISNUMBER('Detalle de audios'!$O$2:$O$810),'Detalle de audios'!$O$2:$O$810)),"—")} -> 86.3 | G42: =IFERROR(COUNTIFS('Detalle de audios'!$G$2:$G$810,"Bot (automático)",'Detalle de audios'!$A$2:$A$810,"ISO + Calidad",'Detalle de audios'!$P$2:$P$810,"Sí")/B42,"—") -> 0.11944444 | H42: {=IFERROR(MEDIAN(IF(('Detalle de audios'!$G$2:$G$810="Bot (automático)")*('Detalle de audios'!$A$2:$A$810="ISO + Calidad")*ISNUMBER('Detalle de audios'!$Q$2:$Q$810),'Detalle de audios'!$Q$2:$Q$810)),"—")} -> 122.7
A43: Manufactura y Calidad | B43: =COUNTIFS('Detalle de audios'!$G$2:$G$810,"Bot (automático)",'Detalle de audios'!$A$2:$A$810,"Manufactura y Calidad") -> 92 | C43: =IFERROR(B43/COUNTIFS('Detalle de audios'!$G$2:$G$810,"Bot (automático)"),"—") -> 0.16666667 | D43: {=IFERROR(MEDIAN(IF(('Detalle de audios'!$G$2:$G$810="Bot (automático)")*('Detalle de audios'!$A$2:$A$810="Manufactura y Calidad")*ISNUMBER('Detalle de audios'!$K$2:$K$810),'Detalle de audios'!$K$2:$K$810)),"—")} -> 72.4 | E43: =IFERROR(COUNTIFS('Detalle de audios'!$G$2:$G$810,"Bot (automático)",'Detalle de audios'!$A$2:$A$810,"Manufactura y Calidad",'Detalle de audios'!$N$2:$N$810,"Sí")/B43,"—") -> 0.59782609 | F43: {=IFERROR(MEDIAN(IF(('Detalle de audios'!$G$2:$G$810="Bot (automático)")*('Detalle de audios'!$A$2:$A$810="Manufactura y Calidad")*ISNUMBER('Detalle de audios'!$O$2:$O$810),'Detalle de audios'!$O$2:$O$810)),"—")} -> 177.3 | G43: =IFERROR(COUNTIFS('Detalle de audios'!$G$2:$G$810,"Bot (automático)",'Detalle de audios'!$A$2:$A$810,"Manufactura y Calidad",'Detalle de audios'!$P$2:$P$810,"Sí")/B43,"—") -> 0.086956522 | H43: {=IFERROR(MEDIAN(IF(('Detalle de audios'!$G$2:$G$810="Bot (automático)")*('Detalle de audios'!$A$2:$A$810="Manufactura y Calidad")*ISNUMBER('Detalle de audios'!$Q$2:$Q$810),'Detalle de audios'!$Q$2:$Q$810)),"—")} -> 141.8
A44: Core Tools Premium | B44: =COUNTIFS('Detalle de audios'!$G$2:$G$810,"Bot (automático)",'Detalle de audios'!$A$2:$A$810,"Core Tools Premium") -> 100 | C44: =IFERROR(B44/COUNTIFS('Detalle de audios'!$G$2:$G$810,"Bot (automático)"),"—") -> 0.18115942 | D44: {=IFERROR(MEDIAN(IF(('Detalle de audios'!$G$2:$G$810="Bot (automático)")*('Detalle de audios'!$A$2:$A$810="Core Tools Premium")*ISNUMBER('Detalle de audios'!$K$2:$K$810),'Detalle de audios'!$K$2:$K$810)),"—")} -> 76.7 | E44: =IFERROR(COUNTIFS('Detalle de audios'!$G$2:$G$810,"Bot (automático)",'Detalle de audios'!$A$2:$A$810,"Core Tools Premium",'Detalle de audios'!$N$2:$N$810,"Sí")/B44,"—") -> 0.6 | F44: {=IFERROR(MEDIAN(IF(('Detalle de audios'!$G$2:$G$810="Bot (automático)")*('Detalle de audios'!$A$2:$A$810="Core Tools Premium")*ISNUMBER('Detalle de audios'!$O$2:$O$810),'Detalle de audios'!$O$2:$O$810)),"—")} -> 78.85 | G44: =IFERROR(COUNTIFS('Detalle de audios'!$G$2:$G$810,"Bot (automático)",'Detalle de audios'!$A$2:$A$810,"Core Tools Premium",'Detalle de audios'!$P$2:$P$810,"Sí")/B44,"—") -> 0.11 | H44: {=IFERROR(MEDIAN(IF(('Detalle de audios'!$G$2:$G$810="Bot (automático)")*('Detalle de audios'!$A$2:$A$810="Core Tools Premium")*ISNUMBER('Detalle de audios'!$Q$2:$Q$810),'Detalle de audios'!$Q$2:$Q$810)),"—")} -> 426.8
A46: Audio grabado para el lead o reutilizado (audios de personas)
A47: Audio | B47: Audios | C47: % de los audios | D47: Duración mediana (s) | E47: % que el lead vio | F47: Min. hasta que lo vio (mediana) | G47: % en que el lead escribió en 24 h | H47: Min. hasta que escribió (mediana)
A48: Grabado para ese lead | B48: =COUNTIFS('Detalle de audios'!$G$2:$G$810,"Persona",'Detalle de audios'!$L$2:$L$810,"No") -> 243 | C48: =IFERROR(B48/COUNTIFS('Detalle de audios'!$G$2:$G$810,"Persona"),"—") -> 0.94552529 | D48: {=IFERROR(MEDIAN(IF(('Detalle de audios'!$G$2:$G$810="Persona")*('Detalle de audios'!$L$2:$L$810="No")*ISNUMBER('Detalle de audios'!$K$2:$K$810),'Detalle de audios'!$K$2:$K$810)),"—")} -> 104.3 | E48: =IFERROR(COUNTIFS('Detalle de audios'!$G$2:$G$810,"Persona",'Detalle de audios'!$L$2:$L$810,"No",'Detalle de audios'!$N$2:$N$810,"Sí")/B48,"—") -> 0.71193416 | F48: {=IFERROR(MEDIAN(IF(('Detalle de audios'!$G$2:$G$810="Persona")*('Detalle de audios'!$L$2:$L$810="No")*ISNUMBER('Detalle de audios'!$O$2:$O$810),'Detalle de audios'!$O$2:$O$810)),"—")} -> 5.1 | G48: =IFERROR(COUNTIFS('Detalle de audios'!$G$2:$G$810,"Persona",'Detalle de audios'!$L$2:$L$810,"No",'Detalle de audios'!$P$2:$P$810,"Sí")/B48,"—") -> 0.58436214 | H48: {=IFERROR(MEDIAN(IF(('Detalle de audios'!$G$2:$G$810="Persona")*('Detalle de audios'!$L$2:$L$810="No")*ISNUMBER('Detalle de audios'!$Q$2:$Q$810),'Detalle de audios'!$Q$2:$Q$810)),"—")} -> 10.35
A49: El mismo archivo mandado a varios leads | B49: =COUNTIFS('Detalle de audios'!$G$2:$G$810,"Persona",'Detalle de audios'!$L$2:$L$810,"Sí") -> 14 | C49: =IFERROR(B49/COUNTIFS('Detalle de audios'!$G$2:$G$810,"Persona"),"—") -> 0.054474708 | D49: {=IFERROR(MEDIAN(IF(('Detalle de audios'!$G$2:$G$810="Persona")*('Detalle de audios'!$L$2:$L$810="Sí")*ISNUMBER('Detalle de audios'!$K$2:$K$810),'Detalle de audios'!$K$2:$K$810)),"—")} -> 57 | E49: =IFERROR(COUNTIFS('Detalle de audios'!$G$2:$G$810,"Persona",'Detalle de audios'!$L$2:$L$810,"Sí",'Detalle de audios'!$N$2:$N$810,"Sí")/B49,"—") -> 0.78571429 | F49: {=IFERROR(MEDIAN(IF(('Detalle de audios'!$G$2:$G$810="Persona")*('Detalle de audios'!$L$2:$L$810="Sí")*ISNUMBER('Detalle de audios'!$O$2:$O$810),'Detalle de audios'!$O$2:$O$810)),"—")} -> 1.2 | G49: =IFERROR(COUNTIFS('Detalle de audios'!$G$2:$G$810,"Persona",'Detalle de audios'!$L$2:$L$810,"Sí",'Detalle de audios'!$P$2:$P$810,"Sí")/B49,"—") -> 0.78571429 | H49: {=IFERROR(MEDIAN(IF(('Detalle de audios'!$G$2:$G$810="Persona")*('Detalle de audios'!$L$2:$L$810="Sí")*ISNUMBER('Detalle de audios'!$Q$2:$Q$810),'Detalle de audios'!$Q$2:$Q$810)),"—")} -> 4.6
A51: «Lo vio» = palomitas azules en WhatsApp antes del corte (no garantiza que lo haya escuchado completo). «Escribió en 24 h» = el lead mandó cualquier mensaje en las 24 h siguientes al audio.
A52: Ojo al comparar persona contra bot: el audio de una persona casi siempre llega en plena conversación y el del bot cuando el lead ya no contesta. Relación, no causa.

Sheet Detalle por lead
A1: Embudo | B1: Lead # (CRM) | C1: Asesor | D1: Contestó la pregunta | E1: Perfil | F1: Hora en que el bot hizo la pregunta | G1: ¿Pregunta fuera de 8 a 22 h? | H1: ¿Vio la pregunta? (palomitas azules) | I1: Lo que contestó a la pregunta | J1: Hora en la que respondió la pregunta | K1: Hora del primer mensaje del equipo | L1: Minutos al primer mensaje del equipo | M1: Hora de la recomendación | N1: Minutos a la recomendación | O1: Rango de minutos a la recomendación | P1: Qué se envió | Q1: ¿Recibió audio? | R1: ¿Quién dio la recomendación? | S1: Rol de quien recomendó | T1: Duración del audio (s) | U1: ¿Vio el audio? (palomitas azules) | V1: Minutos del aviso al audio | W1: Cursos recomendados | X1: Núm. de cursos recomendados | Y1: ¿Respondió después de la recomendación? | Z1: Hora en que respondió a la recomendación | AA1: Minutos que tardó el lead en responder | AB1: Lo que respondió a la recomendación | AC1: Hora en que el equipo le volvió a contestar | AD1: Minutos del equipo en volver a contestarle | AE1: Paso al que se mandó después de su respuesta | AF1: ¿El bot lo pasó a Negativo después de la recomendación? | AG1: ¿El bot lo pasó a Negativo después de que respondió? | AH1: Horas desde su último mensaje hasta que el bot lo pasó a Negativo | AI1: Mensajes del lead antes de la pregunta | AJ1: Etapa al corte | AK1: Ganado
A2: Core Tools Premium | B2: 268 | C2: Salma | D2: Respondió otra cosa | F2: 46300.489 | G2: No | H2: No | I2: Oigan, una duda. En la publicidad de Facebook vi que el paquete tiene el 80% de descuento, pero en la información que me mandan el precio de $3,999 solo tiene $200 de diferencia contra el precio anterior ($4,199). ¿Cuál es el precio real aplicando el 80% de descuento de la publicidad? / También me i | J2: 46301.438 | K2: 46301.446 | L2: =IF(AND(ISNUMBER(J2),ISNUMBER(K2)),IF(K2>=J2,(K2-J2)*1440,""),"") -> 10.680083 | M2: 46301.446 | N2: =IF(AND(ISNUMBER(J2),ISNUMBER(M2)),IF(M2>=J2,(M2-J2)*1440,""),"") -> 10.680083 | O2: =IF(N2="","",LOOKUP(N2,Tiempos!$A$6:$A$10,Tiempos!$B$6:$B$10)) -> 10 a 30 min | P2: Audio | Q2: Sí | R2: Joceline | S2: auxiliar | T2: 70.5 | U2: No | X2: 0 | Y2: No | AA2: =IF(AND(ISNUMBER(M2),ISNUMBER(Z2)),IF(Z2>=M2,(Z2-M2)*1440,""),"") | AD2: =IF(AND(ISNUMBER(Z2),ISNUMBER(AC2)),IF(AC2>=Z2,(AC2-Z2)*1440,""),"") | AF2: No | AI2: 2 | AJ2: Perdido | AK2: No
A3: Core Tools Premium | B3: 286 | C3: Victoria | D3: Sí | E3: Producción u operaciones | F3: 46300.573 | G3: No | H3: Sí | I3: En industria petrolera / Vale gracias | J3: 46300.573 | K3: 46300.573 | L3: =IF(AND(ISNUMBER(J3),ISNUMBER(K3)),IF(K3>=J3,(K3-J3)*1440,""),"") -> 0.19631667 | M3: 46300.577 | N3: =IF(AND(ISNUMBER(J3),ISNUMBER(M3)),IF(M3>=J3,(M3-J3)*1440,""),"") -> 5.0849833 | O3: =IF(N3="","",LOOKUP(N3,Tiempos!$A$6:$A$10,Tiempos!$B$6:$B$10)) -> 4 a 6 min | P3: Texto (aviso del audio) + Audio + Cursos (4) | Q3: Sí | R3: Victoria | S3: asesor | T3: 97.6 | U3: Sí | V3: 4.89 | W3: AMEF, Plan de Control, Solución de Problemas para Ingenieros, Liderazgo para Líderes y Supervisores | X3: 4 | Y3: Sí | Z3: 46300.595 | AA3: =IF(AND(ISNUMBER(M3),ISNUMBER(Z3)),IF(Z3>=M3,(Z3-M3)*1440,""),"") -> 26.15485 | AB3: Me puede contar un poco mas de las facilidades de pago? | AC3: 46300.596 | AD3: =IF(AND(ISNUMBER(Z3),ISNUMBER(AC3)),IF(AC3>=Z3,(AC3-Z3)*1440,""),"") -> 0.93273331 | AE3: 1.4 Facilidades de pago (lo pasó Victoria) | AF3: Sí | AG3: Sí | AH3: 4 | AI3: 4 | AJ3: Perdido | AK3: No
A4: Core Tools Premium | B4: 294 | C4: Alexander | D4: No | F4: 46300.619 | G4: No | H4: Sí | L4: =IF(AND(ISNUMBER(J4),ISNUMBER(K4)),IF(K4>=J4,(K4-J4)*1440,""),"") | N4: =IF(AND(ISNUMBER(J4),ISNUMBER(M4)),IF(M4>=J4,(M4-J4)*1440,""),"") | O4: =IF(N4="","",LOOKUP(N4,Tiempos!$A$6:$A$10,Tiempos!$B$6:$B$10)) | AA4: =IF(AND(ISNUMBER(M4),ISNUMBER(Z4)),IF(Z4>=M4,(Z4-M4)*1440,""),"") | AD4: =IF(AND(ISNUMBER(Z4),ISNUMBER(AC4)),IF(AC4>=Z4,(AC4-Z4)*1440,""),"") | AI4: 1 | AJ4: Perdido | AK4: No
A5: Core Tools Premium | B5: 301 | C5: Salma | D5: No | F5: 46300.642 | G5: No | H5: Sí | L5: =IF(AND(ISNUMBER(J5),ISNUMBER(K5)),IF(K5>=J5,(K5-J5)*1440,""),"") | N5: =IF(AND(ISNUMBER(J5),ISNUMBER(M5)),IF(M5>=J5,(M5-J5)*1440,""),"") | O5: =IF(N5="","",LOOKUP(N5,Tiempos!$A$6:$A$10,Tiempos!$B$6:$B$10)) | AA5: =IF(AND(ISNUMBER(M5),ISNUMBER(Z5)),IF(Z5>=M5,(Z5-M5)*1440,""),"") | AD5: =IF(AND(ISNUMBER(Z5),ISNUMBER(AC5)),IF(AC5>=Z5,(AC5-Z5)*1440,""),"") | AI5: 2 | AJ5: Perdido | AK5: No
A6: Core Tools Premium | B6: 300 | C6: Salma | D6: No | F6: 46300.657 | G6: No | H6: No | L6: =IF(AND(ISNUMBER(J6),ISNUMBER(K6)),IF(K6>=J6,(K6-J6)*1440,""),"") | N6: =IF(AND(ISNUMBER(J6),ISNUMBER(M6)),IF(M6>=J6,(M6-J6)*1440,""),"") | O6: =IF(N6="","",LOOKUP(N6,Tiempos!$A$6:$A$10,Tiempos!$B$6:$B$10)) | AA6: =IF(AND(ISNUMBER(M6),ISNUMBER(Z6)),IF(Z6>=M6,(Z6-M6)*1440,""),"") | AD6: =IF(AND(ISNUMBER(Z6),ISNUMBER(AC6)),IF(AC6>=Z6,(AC6-Z6)*1440,""),"") | AI6: 1 | AJ6: Perdido | AK6: No
A7: Core Tools Premium | B7: 310 | C7: Victoria | D7: No | F7: 46300.678 | G7: No | H7: No | L7: =IF(AND(ISNUMBER(J7),ISNUMBER(K7)),IF(K7>=J7,(K7-J7)*1440,""),"") | N7: =IF(AND(ISNUMBER(J7),ISNUMBER(M7)),IF(M7>=J7,(M7-J7)*1440,""),"") | O7: =IF(N7="","",LOOKUP(N7,Tiempos!$A$6:$A$10,Tiempos!$B$6:$B$10)) | AA7: =IF(AND(ISNUMBER(M7),ISNUMBER(Z7)),IF(Z7>=M7,(Z7-M7)*1440,""),"") | AD7: =IF(AND(ISNUMBER(Z7),ISNUMBER(AC7)),IF(AC7>=Z7,(AC7-Z7)*1440,""),"") | AI7: 2 | AJ7: Perdido | AK7: No
A8: Core Tools Premium | B8: 327 | C8: Victoria | D8: Sí | E8: Supervisión o jefatura | F8: 46300.867 | G8: No | H8: Sí | I8: Sup de producción | J8: 46300.87 | K8: 46300.879 | L8: =IF(AND(ISNUMBER(J8),ISNUMBER(K8)),IF(K8>=J8,(K8-J8)*1440,""),"") -> 12.174717 | M8: 46300.879 | N8: =IF(AND(ISNUMBER(J8),ISNUMBER(M8)),IF(M8>=J8,(M8-J8)*1440,""),"") -> 12.174717 | O8: =IF(N8="","",LOOKUP(N8,Tiempos!$A$6:$A$10,Tiempos!$B$6:$B$10)) -> 10 a 30 min | P8: Texto | Q8: No | R8: Victoria | S8: asesor | X8: 0 | Y8: Sí | Z8: 46300.88 | AA8: =IF(AND(ISNUMBER(M8),ISNUMBER(Z8)),IF(Z8>=M8,(Z8-M8)*1440,""),"") -> 1.1101 | AB8: Esta promoción aplicaría entonces? | AC8: 46300.881 | AD8: =IF(AND(ISNUMBER(Z8),ISNUMBER(AC8)),IF(AC8>=Z8,(AC8-Z8)*1440,""),"") -> 1.6526667 | AE8: 1.4 Facilidades de pago (lo pasó Victoria) | AF8: Sí | AG8: Sí | AH8: 4.3 | AI8: 3 | AJ8: Ganado | AK8: Sí
A9: Core Tools Premium | B9: 337 | C9: Alexander | D9: No | F9: 46300.904 | G9: No | H9: Sí | L9: =IF(AND(ISNUMBER(J9),ISNUMBER(K9)),IF(K9>=J9,(K9-J9)*1440,""),"") | N9: =IF(AND(ISNUMBER(J9),ISNUMBER(M9)),IF(M9>=J9,(M9-J9)*1440,""),"") | O9: =IF(N9="","",LOOKUP(N9,Tiempos!$A$6:$A$10,Tiempos!$B$6:$B$10)) | AA9: =IF(AND(ISNUMBER(M9),ISNUMBER(Z9)),IF(Z9>=M9,(Z9-M9)*1440,""),"") | AD9: =IF(AND(ISNUMBER(Z9),ISNUMBER(AC9)),IF(AC9>=Z9,(AC9-Z9)*1440,""),"") | AI9: 2 | AJ9: Perdido | AK9: No
A10: Core Tools Premium | B10: 341 | C10: Salma | D10: No | F10: 46300.969 | G10: Sí | H10: No | L10: =IF(AND(ISNUMBER(J10),ISNUMBER(K10)),IF(K10>=J10,(K10-J10)*1440,""),"") | N10: =IF(AND(ISNUMBER(J10),ISNUMBER(M10)),IF(M10>=J10,(M10-J10)*1440,""),"") | O10: =IF(N10="","",LOOKUP(N10,Tiempos!$A$6:$A$10,Tiempos!$B$6:$B$10)) | AA10: =IF(AND(ISNUMBER(M10),ISNUMBER(Z10)),IF(Z10>=M10,(Z10-M10)*1440,""),"") | AD10: =IF(AND(ISNUMBER(Z10),ISNUMBER(AC10)),IF(AC10>=Z10,(AC10-Z10)*1440,""),"") | AI10: 1 | AJ10: Perdido | AK10: No
A11: Core Tools Premium | B11: 343 | C11: Salma | D11: Sí | E11: Producción u operaciones | F11: 46301.297 | G11: Sí | H11: Sí | I11: Trabajo en inyeccion de plastico | J11: 46301.297 | K11: 46301.298 | L11: =IF(AND(ISNUMBER(J11),ISNUMBER(K11)),IF(K11>=J11,(K11-J11)*1440,""),"") -> 0.26381665 | M11: 46301.301 | N11: =IF(AND(ISNUMBER(J11),ISNUMBER(M11)),IF(M11>=J11,(M11-J11)*1440,""),"") -> 5.6475667 | O11: =IF(N11="","",LOOKUP(N11,Tiempos!$A$6:$A$10,Tiempos!$B$6:$B$10)) -> 4 a 6 min | P11: Texto (aviso del audio) + Audio + Cursos (2) | Q11: Sí | R11: Salma | S11: asesor | T11: 118.1 | U11: Sí | V11: 5.38 | W11: 7 Herramientas de la Calidad, Poka Yoke | X11: 2 | Y11: Sí | Z11: 46301.403 | AA11: =IF(AND(ISNUMBER(M11),ISNUMBER(Z11)),IF(Z11>=M11,(Z11-M11)*1440,""),"") -> 146.77918 | AB11: Si me interesa, que otros cursos hay que deriven en la inyeccion de plastico? | AC11: 46301.408 | AD11: =IF(AND(ISNUMBER(Z11),ISNUMBER(AC11)),IF(AC11>=Z11,(AC11-Z11)*1440,""),"") -> 7.2591 | AE11: Negativo 1 (lo pasó el bot) | AF11: Sí | AG11: Sí | AH11: 1.8 | AI11: 2 | AJ11: Perdido | AK11: No
A12: Core Tools Premium | B12: 355 | C12: Salma | D12: No | F12: 46301.354 | G12: No | H12: No | L12: =IF(AND(ISNUMBER(J12),ISNUMBER(K12)),IF(K12>=J12,(K12-J12)*1440,""),"") | N12: =IF(AND(ISNUMBER(J12),ISNUMBER(M12)),IF(M12>=J12,(M12-J12)*1440,""),"") | O12: =IF(N12="","",LOOKUP(N12,Tiempos!$A$6:$A$10,Tiempos!$B$6:$B$10)) | AA12: =IF(AND(ISNUMBER(M12),ISNUMBER(Z12)),IF(Z12>=M12,(Z12-M12)*1440,""),"") | AD12: =IF(AND(ISNUMBER(Z12),ISNUMBER(AC12)),IF(AC12>=Z12,(AC12-Z12)*1440,""),"") | AI12: 2 | AJ12: Perdido | AK12: No
A13: Core Tools Premium | B13: 371 | C13: Salma | D13: No | F13: 46301.466 | G13: No | H13: Sí | L13: =IF(AND(ISNUMBER(J13),ISNUMBER(K13)),IF(K13>=J13,(K13-J13)*1440,""),"") | N13: =IF(AND(ISNUMBER(J13),ISNUMBER(M13)),IF(M13>=J13,(M13-J13)*1440,""),"") | O13: =IF(N13="","",LOOKUP(N13,Tiempos!$A$6:$A$10,Tiempos!$B$6:$B$10)) | AA13: =IF(AND(ISNUMBER(M13),ISNUMBER(Z13)),IF(Z13>=M13,(Z13-M13)*1440,""),"") | AD13: =IF(AND(ISNUMBER(Z13),ISNUMBER(AC13)),IF(AC13>=Z13,(AC13-Z13)*1440,""),"") | AI13: 2 | AJ13: Perdido | AK13: No
A14: Core Tools Premium | B14: 373 | C14: Salma | D14: No | F14: 46301.503 | G14: No | H14: No | L14: =IF(AND(ISNUMBER(J14),ISNUMBER(K14)),IF(K14>=J14,(K14-J14)*1440,""),"") | N14: =IF(AND(ISNUMBER(J14),ISNUMBER(M14)),IF(M14>=J14,(M14-J14)*1440,""),"") | O14: =IF(N14="","",LOOKUP(N14,Tiempos!$A$6:$A$10,Tiempos!$B$6:$B$10)) | AA14: =IF(AND(ISNUMBER(M14),ISNUMBER(Z14)),IF(Z14>=M14,(Z14-M14)*1440,""),"") | AD14: =IF(AND(ISNUMBER(Z14),ISNUMBER(AC14)),IF(AC14>=Z14,(AC14-Z14)*1440,""),"") | AI14: 1 | AJ14: Perdido | AK14: No
A15: Core Tools Premium | B15: 445 | C15: Victoria | D15: No | F15: 46301.73 | G15: No | H15: No | L15: =IF(AND(ISNUMBER(J15),ISNUMBER(K15)),IF(K15>=J15,(K15-J15)*1440,""),"") | N15: =IF(AND(ISNUMBER(J15),ISNUMBER(M15)),IF(M15>=J15,(M15-J15)*1440,""),"") | O15: =IF(N15="","",LOOKUP(N15,Tiempos!$A$6:$A$10,Tiempos!$B$6:$B$10)) | AA15: =IF(AND(ISNUMBER(M15),ISNUMBER(Z15)),IF(Z15>=M15,(Z15-M15)*1440,""),"") | AD15: =IF(AND(ISNUMBER(Z15),ISNUMBER(AC15)),IF(AC15>=Z15,(AC15-Z15)*1440,""),"") | AI15: 2 | AJ15: Perdido | AK15: No
A16: Core Tools Premium | B16: 446 | C16: Alexander | D16: Sí | E16: Calidad | F16: 46301.732 | G16: No | H16: Sí | I16: Calidad | J16: 46301.762 | K16: 46301.766 | L16: =IF(AND(ISNUMBER(J16),ISNUMBER(K16)),IF(K16>=J16,(K16-J16)*1440,""),"") -> 5.5195833 | M16: 46301.766 | N16: =IF(AND(ISNUMBER(J16),ISNUMBER(M16)),IF(M16>=J16,(M16-J16)*1440,""),"") -> 5.5195833 | O16: =IF(N16="","",LOOKUP(N16,Tiempos!$A$6:$A$10,Tiempos!$B$6:$B$10)) -> 4 a 6 min | P16: Audio + Cursos (2) | Q16: Sí | R16: Alexander | S16: asesor | T16: 84.2 | U16: Sí | W16: Yellow Belt – Six Sigma, Liderazgo para Líderes y Supervisores | X16: 2 | Y16: Sí | Z16: 46302.381 | AA16: =IF(AND(ISNUMBER(M16),ISNUMBER(Z16)),IF(Z16>=M16,(Z16-M16)*1440,""),"") -> 886.0139 | AB16: Disculpa, veo que también tienen un plan de un mes, ese plan también incluye las certificaciones dc3 | AC16: 46302.386 | AD16: =IF(AND(ISNUMBER(Z16),ISNUMBER(AC16)),IF(AC16>=Z16,(AC16-Z16)*1440,""),"") -> 7.4628667 | AE16: Perdido (lo pasó Alexander) | AF16: Sí | AG16: Sí | AH16: 2.1 | AI16: 2 | AJ16: Perdido | AK16: No
A17: Core Tools Premium | B17: 449 | C17: Alexander | D17: Sí | E17: Calidad | F17: 46301.735 | G17: No | H17: Sí | I17: Calidad | J17: 46301.735 | K17: 46301.739 | L17: =IF(AND(ISNUMBER(J17),ISNUMBER(K17)),IF(K17>=J17,(K17-J17)*1440,""),"") -> 5.6438167 | M17: 46301.742 | N17: =IF(AND(ISNUMBER(J17),ISNUMBER(M17)),IF(M17>=J17,(M17-J17)*1440,""),"") -> 10.574267 | O17: =IF(N17="","",LOOKUP(N17,Tiempos!$A$6:$A$10,Tiempos!$B$6:$B$10)) -> 10 a 30 min | P17: Texto (aviso del audio) + Audio + Cursos (2) | Q17: Sí | R17: Alexander | S17: asesor | T17: 86.5 | U17: Sí | V17: 4.93 | W17: Yellow Belt – Six Sigma, Liderazgo para Líderes y Supervisores | X17: 2 | Y17: No | AA17: =IF(AND(ISNUMBER(M17),ISNUMBER(Z17)),IF(Z17>=M17,(Z17-M17)*1440,""),"") | AD17: =IF(AND(ISNUMBER(Z17),ISNUMBER(AC17)),IF(AC17>=Z17,(AC17-Z17)*1440,""),"") | AF17: Sí | AI17: 2 | AJ17: Perdido | AK17: No
A18: Core Tools Premium | B18: 470 | C18: Victoria | D18: Sí | E18: Supervisión o jefatura | F18: 46301.848 | G18: No | H18: Sí | I18: Estoy estudiando Ingeniería Industrial y actualmente soy supervisor de Logística en embarques y recibos | J18: 46301.848 | K18: 46301.85 | L18: =IF(AND(ISNUMBER(J18),ISNUMBER(K18)),IF(K18>=J18,(K18-J18)*1440,""),"") -> 2.2907 | M18: 46301.85 | N18: =IF(AND(ISNUMBER(J18),ISNUMBER(M18)),IF(M18>=J18,(M18-J18)*1440,""),"") -> 2.2907 | O18: =IF(N18="","",LOOKUP(N18,Tiempos!$A$6:$A$10,Tiempos!$B$6:$B$10)) -> Menos de 4 min | P18: Audio + Cursos (4) | Q18: Sí | R18: Victoria | S18: asesor | T18: 114.7 | U18: Sí | W18: AMEF, Kaizen – Mejora Continua, Yellow Belt – Six Sigma, Microsoft Excel Completo | X18: 4 | Y18: Sí | Z18: 46301.856 | AA18: =IF(AND(ISNUMBER(M18),ISNUMBER(Z18)),IF(Z18>=M18,(Z18-M18)*1440,""),"") -> 8.7311167 | AB18: Hola Victoria mucho gusto, si me interesa iniciar con estos cursos. / Justo mi Jefe me solicitó cotizar algunos cursos de corte tools, para que sean pagados por mi compañía | AC18: 46301.857 | AD18: =IF(AND(ISNUMBER(Z18),ISNUMBER(AC18)),IF(AC18>=Z18,(AC18-Z18)*1440,""),"") -> 0.99013335 | AE18: Negativo 1 (lo pasó el bot) | AF18: Sí | AG18: Sí | AH18: 4.1 | AI18: 2 | AJ18: Perdido | AK18: No
A19: Core Tools Premium | B19: 481 | C19: Salma | D19: No | F19: 46301.903 | G19: No | H19: Sí | L19: =IF(AND(ISNUMBER(J19),ISNUMBER(K19)),IF(K19>=J19,(K19-J19)*1440,""),"") | N19: =IF(AND(ISNUMBER(J19),ISNUMBER(M19)),IF(M19>=J19,(M19-J19)*1440,""),"") | O19: =IF(N19="","",LOOKUP(N19,Tiempos!$A$6:$A$10,Tiempos!$B$6:$B$10)) | AA19: =IF(AND(ISNUMBER(M19),ISNUMBER(Z19)),IF(Z19>=M19,(Z19-M19)*1440,""),"") | AD19: =IF(AND(ISNUMBER(Z19),ISNUMBER(AC19)),IF(AC19>=Z19,(AC19-Z19)*1440,""),"") | AI19: 1 | AJ19: Perdido | AK19: No
A20: Core Tools Premium | B20: 488 | C20: Victoria | D20: Sí | E20: Estudiante o recién egresado | F20: 46301.915 | G20: No | H20: Sí | I20: Aún me encuentro estudiando / Seré ingeniero industrial / Por lo que me interesa conocer más de Lean / No gracias jaja, es algo tarde, sin embargo sí quería info / Es algo que he estado alargando / Y quiero comenzar | J20: 46301.915 | K20: 46301.916 | L20: =IF(AND(ISNUMBER(J20),ISNUMBER(K20)),IF(K20>=J20,(K20-J20)*1440,""),"") -> 1.5828333 | M20: 46301.92 | N20: =IF(AND(ISNUMBER(J20),ISNUMBER(M20)),IF(M20>=J20,(M20-J20)*1440,""),"") -> 7.9024667 | O20: =IF(N20="","",LOOKUP(N20,Tiempos!$A$6:$A$10,Tiempos!$B$6:$B$10)) -> 6 a 10 min | P20: Texto (aviso del audio) + Audio + Cursos (3) | Q20: Sí | R20: Victoria | S20: asesor | T20: 94.1 | U20: Sí | V20: 6.32 | W20: AMEF, Kaizen – Mejora Continua, Comunicación Efectiva | X20: 3 | Y20: Sí | Z20: 46302.417 | AA20: =IF(AND(ISNUMBER(M20),ISNUMBER(Z20)),IF(Z20>=M20,(Z20-M20)*1440,""),"") -> 715.49813 | AB20: Buenos días, Muéstreme las formas de pago por favor | AC20: 46302.419 | AD20: =IF(AND(ISNUMBER(Z20),ISNUMBER(AC20)),IF(AC20>=Z20,(AC20-Z20)*1440,""),"") -> 3.1580833 | AE20: Perdido (lo pasó Salma) | AF20: Sí | AG20: No | AI20: 2 | AJ20: Perdido | AK20: No
A21: Core Tools Premium | B21: 493 | C21: Salma | D21: No | F21: 46301.939 | G21: Sí | H21: No | L21: =IF(AND(ISNUMBER(J21),ISNUMBER(K21)),IF(K21>=J21,(K21-J21)*1440,""),"") | N21: =IF(AND(ISNUMBER(J21),ISNUMBER(M21)),IF(M21>=J21,(M21-J21)*1440,""),"") | O21: =IF(N21="","",LOOKUP(N21,Tiempos!$A$6:$A$10,Tiempos!$B$6:$B$10)) | AA21: =IF(AND(ISNUMBER(M21),ISNUMBER(Z21)),IF(Z21>=M21,(Z21-M21)*1440,""),"") | AD21: =IF(AND(ISNUMBER(Z21),ISNUMBER(AC21)),IF(AC21>=Z21,(AC21-Z21)*1440,""),"") | AI21: 2 | AJ21: Perdido | AK21: No
A22: Core Tools Premium | B22: 517 | C22: Salma | D22: No | F22: 46302.224 | G22: Sí | H22: Sí | L22: =IF(AND(ISNUMBER(J22),ISNUMBER(K22)),IF(K22>=J22,(K22-J22)*1440,""),"") | N22: =IF(AND(ISNUMBER(J22),ISNUMBER(M22)),IF(M22>=J22,(M22-J22)*1440,""),"") | O22: =IF(N22="","",LOOKUP(N22,Tiempos!$A$6:$A$10,Tiempos!$B$6:$B$10)) | AA22: =IF(AND(ISNUMBER(M22),ISNUMBER(Z22)),IF(Z22>=M22,(Z22-M22)*1440,""),"") | AD22: =IF(AND(ISNUMBER(Z22),ISNUMBER(AC22)),IF(AC22>=Z22,(AC22-Z22)*1440,""),"") | AI22: 1 | AJ22: Perdido | AK22: No
A23: Core Tools Premium | B23: 497 | C23: Salma | D23: No | F23: 46302.295 | G23: Sí | H23: Sí | L23: =IF(AND(ISNUMBER(J23),ISNUMBER(K23)),IF(K23>=J23,(K23-J23)*1440,""),"") | N23: =IF(AND(ISNUMBER(J23),ISNUMBER(M23)),IF(M23>=J23,(M23-J23)*1440,""),"") | O23: =IF(N23="","",LOOKUP(N23,Tiempos!$A$6:$A$10,Tiempos!$B$6:$B$10)) | AA23: =IF(AND(ISNUMBER(M23),ISNUMBER(Z23)),IF(Z23>=M23,(Z23-M23)*1440,""),"") | AD23: =IF(AND(ISNUMBER(Z23),ISNUMBER(AC23)),IF(AC23>=Z23,(AC23-Z23)*1440,""),"") | AI23: 2 | AJ23: Perdido | AK23: No
A24: Core Tools Premium | B24: 508 | C24: Salma | D24: No | F24: 46302.296 | G24: Sí | H24: No | L24: =IF(AND(ISNUMBER(J24),ISNUMBER(K24)),IF(K24>=J24,(K24-J24)*1440,""),"") | N24: =IF(AND(ISNUMBER(J24),ISNUMBER(M24)),IF(M24>=J24,(M24-J24)*1440,""),"") | O24: =IF(N24="","",LOOKUP(N24,Tiempos!$A$6:$A$10,Tiempos!$B$6:$B$10)) | AA24: =IF(AND(ISNUMBER(M24),ISNUMBER(Z24)),IF(Z24>=M24,(Z24-M24)*1440,""),"") | AD24: =IF(AND(ISNUMBER(Z24),ISNUMBER(AC24)),IF(AC24>=Z24,(AC24-Z24)*1440,""),"") | AI24: 2 | AJ24: Perdido | AK24: No
A25: Core Tools Premium | B25: 545 | C25: Salma | D25: Sí | E25: Calidad | F25: 46302.376 | G25: No | H25: Sí | I25: Costo de membresía ISO+Calidad / Estoy trabajando en el depto de calidad, auditando proveedores y liberando material metal mecanico | J25: 46302.547 | K25: 46302.555 | L25: =IF(AND(ISNUMBER(J25),ISNUMBER(K25)),IF(K25>=J25,(K25-J25)*1440,""),"") -> 10.562183 | M25: 46302.562 | N25: =IF(AND(ISNUMBER(J25),ISNUMBER(M25)),IF(M25>=J25,(M25-J25)*1440,""),"") -> 21.866383 | O25: =IF(N25="","",LOOKUP(N25,Tiempos!$A$6:$A$10,Tiempos!$B$6:$B$10)) -> 10 a 30 min | P25: Texto (aviso del audio) + Audio + Cursos (2) | Q25: Sí | R25: Salma | S25: asesor | T25: 104.3 | U25: Sí | V25: 11.3 | W25: Microsoft Excel Completo, Yellow Belt – Six Sigma | X25: 2 | Y25: Sí | Z25: 46303.499 | AA25: =IF(AND(ISNUMBER(M25),ISNUMBER(Z25)),IF(Z25>=M25,(Z25-M25)*1440,""),"") -> 1347.9792 | AB25: Me puedes dar más información de las modalidad de pago porfavor | AC25: 46303.499 | AD25: =IF(AND(ISNUMBER(Z25),ISNUMBER(AC25)),IF(AC25>=Z25,(AC25-Z25)*1440,""),"") -> 0.98806666 | AE25: Perdido (lo pasó Salma) | AF25: Sí | AG25: No | AI25: 2 | AJ25: Ganado | AK25: Sí
A26: Core Tools Premium | B26: 565 | C26: Salma | D26: No | F26: 46302.438 | G26: No | H26: No | L26: =IF(AND(ISNUMBER(J26),ISNUMBER(K26)),IF(K26>=J26,(K26-J26)*1440,""),"") | N26: =IF(AND(ISNUMBER(J26),ISNUMBER(M26)),IF(M26>=J26,(M26-J26)*1440,""),"") | O26: =IF(N26="","",LOOKUP(N26,Tiempos!$A$6:$A$10,Tiempos!$B$6:$B$10)) | AA26: =IF(AND(ISNUMBER(M26),ISNUMBER(Z26)),IF(Z26>=M26,(Z26-M26)*1440,""),"") | AD26: =IF(AND(ISNUMBER(Z26),ISNUMBER(AC26)),IF(AC26>=Z26,(AC26-Z26)*1440,""),"") | AI26: 1 | AJ26: Perdido | AK26: No
A27: Core Tools Premium | B27: 589 | C27: Salma | D27: No | F27: 46302.517 | G27: No | H27: Sí | L27: =IF(AND(ISNUMBER(J27),ISNUMBER(K27)),IF(K27>=J27,(K27-J27)*1440,""),"") | N27: =IF(AND(ISNUMBER(J27),ISNUMBER(M27)),IF(M27>=J27,(M27-J27)*1440,""),"") | O27: =IF(N27="","",LOOKUP(N27,Tiempos!$A$6:$A$10,Tiempos!$B$6:$B$10)) | AA27: =IF(AND(ISNUMBER(M27),ISNUMBER(Z27)),IF(Z27>=M27,(Z27-M27)*1440,""),"") | AD27: =IF(AND(ISNUMBER(Z27),ISNUMBER(AC27)),IF(AC27>=Z27,(AC27-Z27)*1440,""),"") | AI27: 1 | AJ27: Perdido | AK27: No
A28: Core Tools Premium | B28: 602 | C28: Salma | D28: No | F28: 46302.558 | G28: No | H28: Sí | L28: =IF(AND(ISNUMBER(J28),ISNUMBER(K28)),IF(K28>=J28,(K28-J28)*1440,""),"") | N28: =IF(AND(ISNUMBER(J28),ISNUMBER(M28)),IF(M28>=J28,(M28-J28)*1440,""),"") | O28: =IF(N28="","",LOOKUP(N28,Tiempos!$A$6:$A$10,Tiempos!$B$6:$B$10)) | AA28: =IF(AND(ISNUMBER(M28),ISNUMBER(Z28)),IF(Z28>=M28,(Z28-M28)*1440,""),"") | AD28: =IF(AND(ISNUMBER(Z28),ISNUMBER(AC28)),IF(AC28>=Z28,(AC28-Z28)*1440,""),"") | AI28: 1 | AJ28: Perdido | AK28: No
A29: Core Tools Premium | B29: 634 | C29: Salma | D29: Sí | E29: Estudiante o recién egresado | F29: 46302.618 | G29: No | H29: Sí | I29: En el sector automotriz / Estudiando Ingeniería Industrial / [imagen] / Aun cuentan con dicho descuento? / Ok va | J29: 46302.618 | K29: 46302.619 | L29: =IF(AND(ISNUMBER(J29),ISNUMBER(K29)),IF(K29>=J29,(K29-J29)*1440,""),"") -> 0.33935 | M29: 46302.623 | N29: =IF(AND(ISNUMBER(J29),ISNUMBER(M29)),IF(M29>=J29,(M29-J29)*1440,""),"") -> 6.7951667 | O29: =IF(N29="","",LOOKUP(N29,Tiempos!$A$6:$A$10,Tiempos!$B$6:$B$10)) -> 6 a 10 min | P29: Texto (aviso del audio) + Audio + Cursos (2) | Q29: Sí | R29: Salma | S29: asesor | T29: 137 | U29: Sí | V29: 6.46 | W29: Cómo hablar en una entrevista de trabajo, PPAP – Proceso de Aprobación de Piezas de Producción | X29: 2 | Y29: Sí | Z29: 46302.628 | AA29: =IF(AND(ISNUMBER(M29),ISNUMBER(Z29)),IF(Z29>=M29,(Z29-M29)*1440,""),"") -> 6.8230833 | AB29: Si, solo dime oportunidad que entrare a unas juntas y de ahi me vuelvo a comunicar | AC29: 46307.393 | AD29: =IF(AND(ISNUMBER(Z29),ISNUMBER(AC29)),IF(AC29>=Z29,(AC29-Z29)*1440,""),"") -> 6861.3009 | AE29: Negativo 1 (lo pasó el bot) | AF29: Sí | AG29: Sí | AH29: 4.2 | AI29: 2 | AJ29: Perdido | AK29: No
A30: Core Tools Premium | B30: 646 | C30: Salma | D30: No | F30: 46302.682 | G30: No | H30: No | L30: =IF(AND(ISNUMBER(J30),ISNUMBER(K30)),IF(K30>=J30,(K30-J30)*1440,""),"") | N30: =IF(AND(ISNUMBER(J30),ISNUMBER(M30)),IF(M30>=J30,(M30-J30)*1440,""),"") | O30: =IF(N30="","",LOOKUP(N30,Tiempos!$A$6:$A$10,Tiempos!$B$6:$B$10)) | AA30: =IF(AND(ISNUMBER(M30),ISNUMBER(Z30)),IF(Z30>=M30,(Z30-M30)*1440,""),"") | AD30: =IF(AND(ISNUMBER(Z30),ISNUMBER(AC30)),IF(AC30>=Z30,(AC30-Z30)*1440,""),"") | AI30: 1 | AJ30: Perdido | AK30: No
A31: Core Tools Premium | B31: 701 | C31: Alexander | D31: Sí | E31: Estudiante o recién egresado | F31: 46302.816 | G31: No | H31: Sí | I31: Estoy estudiando | J31: 46302.818 | K31: 46302.829 | L31: =IF(AND(ISNUMBER(J31),ISNUMBER(K31)),IF(K31>=J31,(K31-J31)*1440,""),"") -> 15.873167 | M31: 46302.829 | N31: =IF(AND(ISNUMBER(J31),ISNUMBER(M31)),IF(M31>=J31,(M31-J31)*1440,""),"") -> 15.873167 | O31: =IF(N31="","",LOOKUP(N31,Tiempos!$A$6:$A$10,Tiempos!$B$6:$B$10)) -> 10 a 30 min | P31: Texto | Q31: No | R31: Alexander | S31: asesor | X31: 0 | Y31: No | AA31: =IF(AND(ISNUMBER(M31),ISNUMBER(Z31)),IF(Z31>=M31,(Z31-M31)*1440,""),"") | AD31: =IF(AND(ISNUMBER(Z31),ISNUMBER(AC31)),IF(AC31>=Z31,(AC31-Z31)*1440,""),"") | AF31: Sí | AI31: 1 | AJ31: Perdido | AK31: No
A32: Core Tools Premium | B32: 712 | C32: Alexander | D32: Sí | E32: Producción u operaciones | F32: 46302.843 | G32: No | H32: No | I32: Estoy como ingeniero de manufactura de SMT / Una duda, es que aquí aparece una promoción del 80% | J32: 46302.843 | K32: 46302.871 | L32: =IF(AND(ISNUMBER(J32),ISNUMBER(K32)),IF(K32>=J32,(K32-J32)*1440,""),"") -> 39.882083 | M32: 46302.873 | N32: =IF(AND(ISNUMBER(J32),ISNUMBER(M32)),IF(M32>=J32,(M32-J32)*1440,""),"") -> 42.176817 | O32: =IF(N32="","",LOOKUP(N32,Tiempos!$A$6:$A$10,Tiempos!$B$6:$B$10)) -> 30 min o más | P32: Texto (aviso del audio) + Audio + Cursos (3) | Q32: Sí | R32: Victoria | S32: asesor | T32: 83 | U32: No | V32: 2.12 | W32: AMEF, Kaizen – Mejora Continua, Microsoft Excel Completo | X32: 3 | Y32: Sí | Z32: 46304.384 | AA32: =IF(AND(ISNUMBER(M32),ISNUMBER(Z32)),IF(Z32>=M32,(Z32-M32)*1440,""),"") -> 2176.1867 | AB32: Hola buenas | AC32: 46304.389 | AD32: =IF(AND(ISNUMBER(Z32),ISNUMBER(AC32)),IF(AC32>=Z32,(AC32-Z32)*1440,""),"") -> 7.5088667 | AE32: Perdido (lo pasó Joceline) | AF32: Sí | AG32: No | AI32: 4 | AJ32: Perdido | AK32: No
A33: Core Tools Premium | B33: 729 | C33: Alexander | D33: Sí | E33: Estudiante o recién egresado | F33: 46302.885 | G33: No | H33: Sí | I33: Soy recién egresado y me quiero dedicar a un área de supply chain | J33: 46302.891 | K33: 46302.9 | L33: =IF(AND(ISNUMBER(J33),ISNUMBER(K33)),IF(K33>=J33,(K33-J33)*1440,""),"") -> 12.792167 | M33: 46302.901 | N33: =IF(AND(ISNUMBER(J33),ISNUMBER(M33)),IF(M33>=J33,(M33-J33)*1440,""),"") -> 14.215367 | O33: =IF(N33="","",LOOKUP(N33,Tiempos!$A$6:$A$10,Tiempos!$B$6:$B$10)) -> 10 a 30 min | P33: Texto (aviso del audio) + Audio + Cursos (3) | Q33: Sí | R33: Alexander | S33: asesor | T33: 76.7 | U33: Sí | V33: 1.42 | W33: Gestión de Inventarios, Metodología Kanban, Value Stream Mapping | X33: 3 | Y33: Sí | Z33: 46302.915 | AA33: =IF(AND(ISNUMBER(M33),ISNUMBER(Z33)),IF(Z33>=M33,(Z33-M33)*1440,""),"") -> 20.4002 | AB33: Me parece super bien las certificaciones! | AC33: 46302.918 | AD33: =IF(AND(ISNUMBER(Z33),ISNUMBER(AC33)),IF(AC33>=Z33,(AC33-Z33)*1440,""),"") -> 5.12375 | AE33: Negativo 1 (lo pasó el bot) | AF33: Sí | AG33: Sí | AH33: 3.9 | AI33: 2 | AJ33: Perdido | AK33: No
A34: Core Tools Premium | B34: 738 | C34: Salma | D34: Sí | E34: Supervisión o jefatura | F34: 46302.931 | G34: Sí | H34: No | I34: Buenas noches gracias por la información, actualmente me desempeño como Supervisor de Producción , mi nombre es Armando Sanchez Guerrero | J34: 46302.932 | K34: 46303.304 | L34: =IF(AND(ISNUMBER(J34),ISNUMBER(K34)),IF(K34>=J34,(K34-J34)*1440,""),"") -> 535.25577 | M34: 46303.306 | N34: =IF(AND(ISNUMBER(J34),ISNUMBER(M34)),IF(M34>=J34,(M34-J34)*1440,""),"") -> 537.84313 | O34: =IF(N34="","",LOOKUP(N34,Tiempos!$A$6:$A$10,Tiempos!$B$6:$B$10)) -> 30 min o más | P34: Texto (aviso del audio) + Audio + Cursos (2) | Q34: Sí | R34: Salma | S34: asesor | T34: 106.6 | U34: No | V34: 2.59 | W34: Liderazgo para Líderes y Supervisores, Lean Manufacturing | X34: 2 | Y34: No | AA34: =IF(AND(ISNUMBER(M34),ISNUMBER(Z34)),IF(Z34>=M34,(Z34-M34)*1440,""),"") | AD34: =IF(AND(ISNUMBER(Z34),ISNUMBER(AC34)),IF(AC34>=Z34,(AC34-Z34)*1440,""),"") | AF34: Sí | AI34: 1 | AJ34: Perdido | AK34: No
A35: Core Tools Premium | B35: 760 | C35: Salma | D35: No | F35: 46303.091 | G35: Sí | H35: Sí | L35: =IF(AND(ISNUMBER(J35),ISNUMBER(K35)),IF(K35>=J35,(K35-J35)*1440,""),"") | N35: =IF(AND(ISNUMBER(J35),ISNUMBER(M35)),IF(M35>=J35,(M35-J35)*1440,""),"") | O35: =IF(N35="","",LOOKUP(N35,Tiempos!$A$6:$A$10,Tiempos!$B$6:$B$10)) | AA35: =IF(AND(ISNUMBER(M35),ISNUMBER(Z35)),IF(Z35>=M35,(Z35-M35)*1440,""),"") | AD35: =IF(AND(ISNUMBER(Z35),ISNUMBER(AC35)),IF(AC35>=Z35,(AC35-Z35)*1440,""),"") | AI35: 1 | AJ35: Perdido | AK35: No
A36: Core Tools Premium | B36: 753 | C36: Salma | D36: No | F36: 46303.313 | G36: Sí | H36: No | L36: =IF(AND(ISNUMBER(J36),ISNUMBER(K36)),IF(K36>=J36,(K36-J36)*1440,""),"") | N36: =IF(AND(ISNUMBER(J36),ISNUMBER(M36)),IF(M36>=J36,(M36-J36)*1440,""),"") | O36: =IF(N36="","",LOOKUP(N36,Tiempos!$A$6:$A$10,Tiempos!$B$6:$B$10)) | AA36: =IF(AND(ISNUMBER(M36),ISNUMBER(Z36)),IF(Z36>=M36,(Z36-M36)*1440,""),"") | AD36: =IF(AND(ISNUMBER(Z36),ISNUMBER(AC36)),IF(AC36>=Z36,(AC36-Z36)*1440,""),"") | AI36: 4 | AJ36: Perdido | AK36: No
A37: Core Tools Premium | B37: 802 | C37: Salma | D37: No | F37: 46303.402 | G37: No | H37: Sí | L37: =IF(AND(ISNUMBER(J37),ISNUMBER(K37)),IF(K37>=J37,(K37-J37)*1440,""),"") | N37: =IF(AND(ISNUMBER(J37),ISNUMBER(M37)),IF(M37>=J37,(M37-J37)*1440,""),"") | O37: =IF(N37="","",LOOKUP(N37,Tiempos!$A$6:$A$10,Tiempos!$B$6:$B$10)) | AA37: =IF(AND(ISNUMBER(M37),ISNUMBER(Z37)),IF(Z37>=M37,(Z37-M37)*1440,""),"") | AD37: =IF(AND(ISNUMBER(Z37),ISNUMBER(AC37)),IF(AC37>=Z37,(AC37-Z37)*1440,""),"") | AI37: 2 | AJ37: Perdido | AK37: No
A38: Core Tools Premium | B38: 828 | C38: Salma | D38: No | F38: 46303.455 | G38: No | H38: No | L38: =IF(AND(ISNUMBER(J38),ISNUMBER(K38)),IF(K38>=J38,(K38-J38)*1440,""),"") | N38: =IF(AND(ISNUMBER(J38),ISNUMBER(M38)),IF(M38>=J38,(M38-J38)*1440,""),"") | O38: =IF(N38="","",LOOKUP(N38,Tiempos!$A$6:$A$10,Tiempos!$B$6:$B$10)) | AA38: =IF(AND(ISNUMBER(M38),ISNUMBER(Z38)),IF(Z38>=M38,(Z38-M38)*1440,""),"") | AD38: =IF(AND(ISNUMBER(Z38),ISNUMBER(AC38)),IF(AC38>=Z38,(AC38-Z38)*1440,""),"") | AI38: 2 | AJ38: Perdido | AK38: No
A39: Core Tools Premium | B39: 833 | C39: Salma | D39: No | F39: 46303.468 | G39: No | H39: Sí | L39: =IF(AND(ISNUMBER(J39),ISNUMBER(K39)),IF(K39>=J39,(K39-J39)*1440,""),"") | N39: =IF(AND(ISNUMBER(J39),ISNUMBER(M39)),IF(M39>=J39,(M39-J39)*1440,""),"") | O39: =IF(N39="","",LOOKUP(N39,Tiempos!$A$6:$A$10,Tiempos!$B$6:$B$10)) | AA39: =IF(AND(ISNUMBER(M39),ISNUMBER(Z39)),IF(Z39>=M39,(Z39-M39)*1440,""),"") | AD39: =IF(AND(ISNUMBER(Z39),ISNUMBER(AC39)),IF(AC39>=Z39,(AC39-Z39)*1440,""),"") | AI39: 2 | AJ39: Perdido | AK39: No
A40: Core Tools Premium | B40: 842 | C40: Salma | D40: No | F40: 46303.513 | G40: No | H40: Sí | L40: =IF(AND(ISNUMBER(J40),ISNUMBER(K40)),IF(K40>=J40,(K40-J40)*1440,""),"") | N40: =IF(AND(ISNUMBER(J40),ISNUMBER(M40)),IF(M40>=J40,(M40-J40)*1440,""),"") | O40: =IF(N40="","",LOOKUP(N40,Tiempos!$A$6:$A$10,Tiempos!$B$6:$B$10)) | AA40: =IF(AND(ISNUMBER(M40),ISNUMBER(Z40)),IF(Z40>=M40,(Z40-M40)*1440,""),"") | AD40: =IF(AND(ISNUMBER(Z40),ISNUMBER(AC40)),IF(AC40>=Z40,(AC40-Z40)*1440,""),"") | AI40: 1 | AJ40: Perdido | AK40: No
A41: Core Tools Premium | B41: 864 | C41: Salma | D41: No | F41: 46303.588 | G41: No | H41: Sí | L41: =IF(AND(ISNUMBER(J41),ISNUMBER(K41)),IF(K41>=J41,(K41-J41)*1440,""),"") | N41: =IF(AND(ISNUMBER(J41),ISNUMBER(M41)),IF(M41>=J41,(M41-J41)*1440,""),"") | O41: =IF(N41="","",LOOKUP(N41,Tiempos!$A$6:$A$10,Tiempos!$B$6:$B$10)) | AA41: =IF(AND(ISNUMBER(M41),ISNUMBER(Z41)),IF(Z41>=M41,(Z41-M41)*1440,""),"") | AD41: =IF(AND(ISNUMBER(Z41),ISNUMBER(AC41)),IF(AC41>=Z41,(AC41-Z41)*1440,""),"") | AI41: 1 | AJ41: Perdido | AK41: No
A42: Core Tools Premium | B42: 877 | C42: Salma | D42: No | F42: 46303.609 | G42: No | H42: Sí | L42: =IF(AND(ISNUMBER(J42),ISNUMBER(K42)),IF(K42>=J42,(K42-J42)*1440,""),"") | N42: =IF(AND(ISNUMBER(J42),ISNUMBER(M42)),IF(M42>=J42,(M42-J42)*1440,""),"") | O42: =IF(N42="","",LOOKUP(N42,Tiempos!$A$6:$A$10,Tiempos!$B$6:$B$10)) | AA42: =IF(AND(ISNUMBER(M42),ISNUMBER(Z42)),IF(Z42>=M42,(Z42-M42)*1440,""),"") | AD42: =IF(AND(ISNUMBER(Z42),ISNUMBER(AC42)),IF(AC42>=Z42,(AC42-Z42)*1440,""),"") | AI42: 2 | AJ42: Perdido | AK42: No
A43: Core Tools Premium | B43: 909 | C43: Salma | D43: No | F43: 46303.751 | G43: No | H43: No | L43: =IF(AND(ISNUMBER(J43),ISNUMBER(K43)),IF(K43>=J43,(K43-J43)*1440,""),"") | N43: =IF(AND(ISNUMBER(J43),ISNUMBER(M43)),IF(M43>=J43,(M43-J43)*1440,""),"") | O43: =IF(N43="","",LOOKUP(N43,Tiempos!$A$6:$A$10,Tiempos!$B$6:$B$10)) | AA43: =IF(AND(ISNUMBER(M43),ISNUMBER(Z43)),IF(Z43>=M43,(Z43-M43)*1440,""),"") | AD43: =IF(AND(ISNUMBER(Z43),ISNUMBER(AC43)),IF(AC43>=Z43,(AC43-Z43)*1440,""),"") | AI43: 2 | AJ43: Perdido | AK43: No
A44: Core Tools Premium | B44: 925 | C44: Salma | D44: No | F44: 46303.837 | G44: No | H44: No | L44: =IF(AND(ISNUMBER(J44),ISNUMBER(K44)),IF(K44>=J44,(K44-J44)*1440,""),"") | N44: =IF(AND(ISNUMBER(J44),ISNUMBER(M44)),IF(M44>=J44,(M44-J44)*1440,""),"") | O44: =IF(N44="","",LOOKUP(N44,Tiempos!$A$6:$A$10,Tiempos!$B$6:$B$10)) | AA44: =IF(AND(ISNUMBER(M44),ISNUMBER(Z44)),IF(Z44>=M44,(Z44-M44)*1440,""),"") | AD44: =IF(AND(ISNUMBER(Z44),ISNUMBER(AC44)),IF(AC44>=Z44,(AC44-Z44)*1440,""),"") | AI44: 1 | AJ44: Perdido | AK44: No
A45: Core Tools Premium | B45: 960 | C45: Salma | D45: No | F45: 46304.028 | G45: Sí | H45: No | L45: =IF(AND(ISNUMBER(J45),ISNUMBER(K45)),IF(K45>=J45,(K45-J45)*1440,""),"") | N45: =IF(AND(ISNUMBER(J45),ISNUMBER(M45)),IF(M45>=J45,(M45-J45)*1440,""),"") | O45: =IF(N45="","",LOOKUP(N45,Tiempos!$A$6:$A$10,Tiempos!$B$6:$B$10)) | AA45: =IF(AND(ISNUMBER(M45),ISNUMBER(Z45)),IF(Z45>=M45,(Z45-M45)*1440,""),"") | AD45: =IF(AND(ISNUMBER(Z45),ISNUMBER(AC45)),IF(AC45>=Z45,(AC45-Z45)*1440,""),"") | AI45: 1 | AJ45: Perdido | AK45: No
A46: Core Tools Premium | B46: 992 | C46: Salma | D46: Sí | E46: Calidad | F46: 46304.348 | G46: No | H46: Sí | I46: Soy tecnico de calidad | J46: 46304.351 | K46: 46304.351 | L46: =IF(AND(ISNUMBER(J46),ISNUMBER(K46)),IF(K46>=J46,(K46-J46)*1440,""),"") -> 0.92171667 | M46: 46304.355 | N46: =IF(AND(ISNUMBER(J46),ISNUMBER(M46)),IF(M46>=J46,(M46-J46)*1440,""),"") -> 5.8696 | O46: =IF(N46="","",LOOKUP(N46,Tiempos!$A$6:$A$10,Tiempos!$B$6:$B$10)) -> 4 a 6 min | P46: Texto (aviso del audio) + Audio + Cursos (2) | Q46: Sí | R46: Joceline | S46: auxiliar | T46: 105 | U46: Sí | V46: 4.95 | W46: 7 Herramientas de la Calidad, Liderazgo para Líderes y Supervisores | X46: 2 | Y46: No | AA46: =IF(AND(ISNUMBER(M46),ISNUMBER(Z46)),IF(Z46>=M46,(Z46-M46)*1440,""),"") | AD46: =IF(AND(ISNUMBER(Z46),ISNUMBER(AC46)),IF(AC46>=Z46,(AC46-Z46)*1440,""),"") | AF46: Sí | AI46: 2 | AJ46: Perdido | AK46: No
A47: Core Tools Premium | B47: 1008 | C47: Salma | D47: No | F47: 46304.451 | G47: No | H47: No | L47: =IF(AND(ISNUMBER(J47),ISNUMBER(K47)),IF(K47>=J47,(K47-J47)*1440,""),"") | N47: =IF(AND(ISNUMBER(J47),ISNUMBER(M47)),IF(M47>=J47,(M47-J47)*1440,""),"") | O47: =IF(N47="","",LOOKUP(N47,Tiempos!$A$6:$A$10,Tiempos!$B$6:$B$10)) | AA47: =IF(AND(ISNUMBER(M47),ISNUMBER(Z47)),IF(Z47>=M47,(Z47-M47)*1440,""),"") | AD47: =IF(AND(ISNUMBER(Z47),ISNUMBER(AC47)),IF(AC47>=Z47,(AC47-Z47)*1440,""),"") | AI47: 1 | AJ47: Perdido | AK47: No
A48: Core Tools Premium | B48: 1018 | C48: Salma | D48: Sí | E48: Supervisión o jefatura | F48: 46304.47 | G48: No | H48: Sí | I48: Gerente de Linea de Producción de una empresa Metalmecanica que procesa, Rollos de acero, Fabricación de / Chasis para camiones de carga / claro | J48: 46304.471 | K48: 46304.473 | L48: =IF(AND(ISNUMBER(J48),ISNUMBER(K48)),IF(K48>=J48,(K48-J48)*1440,""),"") -> 3.9318 | M48: 46304.475 | N48: =IF(AND(ISNUMBER(J48),ISNUMBER(M48)),IF(M48>=J48,(M48-J48)*1440,""),"") -> 7.0721667 | O48: =IF(N48="","",LOOKUP(N48,Tiempos!$A$6:$A$10,Tiempos!$B$6:$B$10)) -> 6 a 10 min | P48: Texto (aviso del audio) + Audio + Cursos (2) | Q48: Sí | R48: Salma | S48: asesor | T48: 107.3 | U48: Sí | V48: 3.14 | W48: Yellow Belt – Six Sigma, Lean Manufacturing | X48: 2 | Y48: Sí | Z48: 46304.478 | AA48: =IF(AND(ISNUMBER(M48),ISNUMBER(Z48)),IF(Z48>=M48,(Z48-M48)*1440,""),"") -> 3.1022833 | AB48: ya tengo lean manufacturing y me certifique en green belt con una empresa de saltillo, coahuila. | AC48: 46304.479 | AD48: =IF(AND(ISNUMBER(Z48),ISNUMBER(AC48)),IF(AC48>=Z48,(AC48-Z48)*1440,""),"") -> 2.47305 | AE48: Negativo 1 (lo pasó el bot) | AF48: Sí | AG48: Sí | AH48: 4.2 | AI48: 6 | AJ48: Perdido | AK48: No
A49: Core Tools Premium | B49: 1037 | C49: Salma | D49: Respondió otra cosa | F49: 46304.536 | G49: No | H49: No | I49: Es solo un pago o es anual? Si solo quiero cuidarlo una vez y ya?. / O como funciona?. / Mmm entonces ya seria como aun subscripcion como Netflix ,pero y si quiero cancelar? | J49: 46304.537 | K49: 46304.538 | L49: =IF(AND(ISNUMBER(J49),ISNUMBER(K49)),IF(K49>=J49,(K49-J49)*1440,""),"") -> 1.1608333 | M49: 46304.538 | N49: =IF(AND(ISNUMBER(J49),ISNUMBER(M49)),IF(M49>=J49,(M49-J49)*1440,""),"") -> 1.1608333 | O49: =IF(N49="","",LOOKUP(N49,Tiempos!$A$6:$A$10,Tiempos!$B$6:$B$10)) -> Menos de 4 min | P49: Texto | Q49: No | R49: Salma | S49: asesor | X49: 0 | Y49: Sí | Z49: 46304.54 | AA49: =IF(AND(ISNUMBER(M49),ISNUMBER(Z49)),IF(Z49>=M49,(Z49-M49)*1440,""),"") -> 2.6092667 | AB49: Mmm entonces ya seria como aun subscripcion como Netflix ,pero y si quiero cancelar? | AC49: 46304.544 | AD49: =IF(AND(ISNUMBER(Z49),ISNUMBER(AC49)),IF(AC49>=Z49,(AC49-Z49)*1440,""),"") -> 5.7620833 | AE49: Negativo 1 (lo pasó el bot) | AF49: Sí | AG49: Sí | AH49: 1.9 | AI49: 2 | AJ49: Perdido | AK49: No
A50: Core Tools Premium | B50: 1038 | C50: Salma | D50: No | F50: 46304.567 | G50: No | H50: Sí | L50: =IF(AND(ISNUMBER(J50),ISNUMBER(K50)),IF(K50>=J50,(K50-J50)*1440,""),"") | N50: =IF(AND(ISNUMBER(J50),ISNUMBER(M50)),IF(M50>=J50,(M50-J50)*1440,""),"") | O50: =IF(N50="","",LOOKUP(N50,Tiempos!$A$6:$A$10,Tiempos!$B$6:$B$10)) | AA50: =IF(AND(ISNUMBER(M50),ISNUMBER(Z50)),IF(Z50>=M50,(Z50-M50)*1440,""),"") | AD50: =IF(AND(ISNUMBER(Z50),ISNUMBER(AC50)),IF(AC50>=Z50,(AC50-Z50)*1440,""),"") | AI50: 1 | AJ50: Perdido | AK50: No
A51: Core Tools Premium | B51: 1075 | C51: Alexander | D51: Sí | E51: Calidad | F51: 46304.714 | G51: No | H51: Sí | I51: Trabajo ahorita en proceso como inspector en una fábrica de medicamentos y quiero meterme a trabajar en una fábrica donde fabrican las tarjetas electrónicas / Como calidad también | J51: 46304.715 | K51: 46304.718 | L51: =IF(AND(ISNUMBER(J51),ISNUMBER(K51)),IF(K51>=J51,(K51-J51)*1440,""),"") -> 4.378 | M51: 46304.718 | N51: =IF(AND(ISNUMBER(J51),ISNUMBER(M51)),IF(M51>=J51,(M51-J51)*1440,""),"") -> 4.378 | O51: =IF(N51="","",LOOKUP(N51,Tiempos!$A$6:$A$10,Tiempos!$B$6:$B$10)) -> 4 a 6 min | P51: Audio + Cursos (3) | Q51: Sí | R51: Alexander | S51: asesor | T51: 91.2 | U51: Sí | W51: Control Estadístico de Procesos (SPC), Solución de Problemas 8 D's, Poka Yoke | X51: 3 | Y51: No | AA51: =IF(AND(ISNUMBER(M51),ISNUMBER(Z51)),IF(Z51>=M51,(Z51-M51)*1440,""),"") | AD51: =IF(AND(ISNUMBER(Z51),ISNUMBER(AC51)),IF(AC51>=Z51,(AC51-Z51)*1440,""),"") | AF51: Sí | AI51: 2 | AJ51: Perdido | AK51: No
A52: Core Tools Premium | B52: 1086 | C52: Salma | D52: No | F52: 46304.76 | G52: No | H52: No | L52: =IF(AND(ISNUMBER(J52),ISNUMBER(K52)),IF(K52>=J52,(K52-J52)*1440,""),"") | N52: =IF(AND(ISNUMBER(J52),ISNUMBER(M52)),IF(M52>=J52,(M52-J52)*1440,""),"") | O52: =IF(N52="","",LOOKUP(N52,Tiempos!$A$6:$A$10,Tiempos!$B$6:$B$10)) | AA52: =IF(AND(ISNUMBER(M52),ISNUMBER(Z52)),IF(Z52>=M52,(Z52-M52)*1440,""),"") | AD52: =IF(AND(ISNUMBER(Z52),ISNUMBER(AC52)),IF(AC52>=Z52,(AC52-Z52)*1440,""),"") | AI52: 1 | AJ52: Perdido | AK52: No
A53: Core Tools Premium | B53: 1113 | C53: Alexander | D53: Sí | E53: Producción u operaciones | F53: 46304.879 | G53: No | H53: Sí | I53: Vale / Ing mecatrónica, para entrar en manufactura / La membresía expert 12 meses acepta MSI? | J53: 46304.88 | K53: 46304.881 | L53: =IF(AND(ISNUMBER(J53),ISNUMBER(K53)),IF(K53>=J53,(K53-J53)*1440,""),"") -> 2.1086333 | M53: 46304.881 | N53: =IF(AND(ISNUMBER(J53),ISNUMBER(M53)),IF(M53>=J53,(M53-J53)*1440,""),"") -> 2.1086333 | O53: =IF(N53="","",LOOKUP(N53,Tiempos!$A$6:$A$10,Tiempos!$B$6:$B$10)) -> Menos de 4 min | P53: Audio + Cursos (3) | Q53: Sí | R53: Alexander | S53: asesor | T53: 77.8 | U53: Sí | W53: Lean Manufacturing, TPM – Mantenimiento Total Productivo, Solución de Problemas 8 D's | X53: 3 | Y53: Sí | Z53: 46304.882 | AA53: =IF(AND(ISNUMBER(M53),ISNUMBER(Z53)),IF(Z53>=M53,(Z53-M53)*1440,""),"") -> 1.5754167 | AB53: La membresía expert 12 meses acepta MSI? | AC53: 46304.883 | AD53: =IF(AND(ISNUMBER(Z53),ISNUMBER(AC53)),IF(AC53>=Z53,(AC53-Z53)*1440,""),"") -> 0.47831668 | AE53: 1.4 Facilidades de pago (lo pasó Alexander) | AF53: Sí | AG53: Sí | AH53: 4 | AI53: 2 | AJ53: Ganado | AK53: Sí
A54: Core Tools Premium | B54: 1134 | C54: Alexander | D54: Sí | E54: Ingeniería | F54: 46305.33 | G54: Sí | H54: No | I54: Soy ingeniera Industrial / Solo tengo una pregunta, tienen un horario para tomar las clases del curso, ya que actualmente me encuentro trabajando. | J54: 46305.331 | K54: 46305.353 | L54: =IF(AND(ISNUMBER(J54),ISNUMBER(K54)),IF(K54>=J54,(K54-J54)*1440,""),"") -> 31.35705 | M54: 46305.355 | N54: =IF(AND(ISNUMBER(J54),ISNUMBER(M54)),IF(M54>=J54,(M54-J54)*1440,""),"") -> 34.677417 | O54: =IF(N54="","",LOOKUP(N54,Tiempos!$A$6:$A$10,Tiempos!$B$6:$B$10)) -> 30 min o más | P54: Texto (aviso del audio) + Audio + Cursos (2) | Q54: Sí | R54: Joceline | S54: auxiliar | T54: 98.3 | U54: No | V54: 3.32 | W54: Liderazgo para Líderes y Supervisores, Comunicación Efectiva | X54: 2 | Y54: Sí | Z54: 46305.358 | AA54: =IF(AND(ISNUMBER(M54),ISNUMBER(Z54)),IF(Z54>=M54,(Z54-M54)*1440,""),"") -> 4.6013333 | AB54: Ok gracias | AC54: 46305.36 | AD54: =IF(AND(ISNUMBER(Z54),ISNUMBER(AC54)),IF(AC54>=Z54,(AC54-Z54)*1440,""),"") -> 2.36815 | AE54: Perdido (lo pasó Alexander) | AF54: No | AG54: No | AI54: 4 | AJ54: Perdido | AK54: No
A55: Core Tools Premium | B55: 1136 | C55: Alexander | D55: No | F55: 46305.33 | G55: Sí | H55: No | L55: =IF(AND(ISNUMBER(J55),ISNUMBER(K55)),IF(K55>=J55,(K55-J55)*1440,""),"") | N55: =IF(AND(ISNUMBER(J55),ISNUMBER(M55)),IF(M55>=J55,(M55-J55)*1440,""),"") | O55: =IF(N55="","",LOOKUP(N55,Tiempos!$A$6:$A$10,Tiempos!$B$6:$B$10)) | AA55: =IF(AND(ISNUMBER(M55),ISNUMBER(Z55)),IF(Z55>=M55,(Z55-M55)*1440,""),"") | AD55: =IF(AND(ISNUMBER(Z55),ISNUMBER(AC55)),IF(AC55>=Z55,(AC55-Z55)*1440,""),"") | AI55: 2 | AJ55: Perdido | AK55: No
A56: Core Tools Premium | B56: 1159 | C56: Alexander | D56: No | F56: 46305.377 | G56: No | H56: Sí | L56: =IF(AND(ISNUMBER(J56),ISNUMBER(K56)),IF(K56>=J56,(K56-J56)*1440,""),"") | N56: =IF(AND(ISNUMBER(J56),ISNUMBER(M56)),IF(M56>=J56,(M56-J56)*1440,""),"") | O56: =IF(N56="","",LOOKUP(N56,Tiempos!$A$6:$A$10,Tiempos!$B$6:$B$10)) | AA56: =IF(AND(ISNUMBER(M56),ISNUMBER(Z56)),IF(Z56>=M56,(Z56-M56)*1440,""),"") | AD56: =IF(AND(ISNUMBER(Z56),ISNUMBER(AC56)),IF(AC56>=Z56,(AC56-Z56)*1440,""),"") | AI56: 2 | AJ56: Perdido | AK56: No
A57: Core Tools Premium | B57: 1215 | C57: Salma | D57: No | F57: 46305.76 | G57: No | H57: Sí | L57: =IF(AND(ISNUMBER(J57),ISNUMBER(K57)),IF(K57>=J57,(K57-J57)*1440,""),"") | N57: =IF(AND(ISNUMBER(J57),ISNUMBER(M57)),IF(M57>=J57,(M57-J57)*1440,""),"") | O57: =IF(N57="","",LOOKUP(N57,Tiempos!$A$6:$A$10,Tiempos!$B$6:$B$10)) | AA57: =IF(AND(ISNUMBER(M57),ISNUMBER(Z57)),IF(Z57>=M57,(Z57-M57)*1440,""),"") | AD57: =IF(AND(ISNUMBER(Z57),ISNUMBER(AC57)),IF(AC57>=Z57,(AC57-Z57)*1440,""),"") | AI57: 1 | AJ57: Perdido | AK57: No
A58: Core Tools Premium | B58: 1226 | C58: Salma | D58: No | F58: 46305.787 | G58: No | H58: Sí | L58: =IF(AND(ISNUMBER(J58),ISNUMBER(K58)),IF(K58>=J58,(K58-J58)*1440,""),"") | N58: =IF(AND(ISNUMBER(J58),ISNUMBER(M58)),IF(M58>=J58,(M58-J58)*1440,""),"") | O58: =IF(N58="","",LOOKUP(N58,Tiempos!$A$6:$A$10,Tiempos!$B$6:$B$10)) | AA58: =IF(AND(ISNUMBER(M58),ISNUMBER(Z58)),IF(Z58>=M58,(Z58-M58)*1440,""),"") | AD58: =IF(AND(ISNUMBER(Z58),ISNUMBER(AC58)),IF(AC58>=Z58,(AC58-Z58)*1440,""),"") | AI58: 2 | AJ58: Perdido | AK58: No
A59: Core Tools Premium | B59: 1236 | C59: Salma | D59: No | F59: 46305.853 | G59: No | H59: No | L59: =IF(AND(ISNUMBER(J59),ISNUMBER(K59)),IF(K59>=J59,(K59-J59)*1440,""),"") | N59: =IF(AND(ISNUMBER(J59),ISNUMBER(M59)),IF(M59>=J59,(M59-J59)*1440,""),"") | O59: =IF(N59="","",LOOKUP(N59,Tiempos!$A$6:$A$10,Tiempos!$B$6:$B$10)) | AA59: =IF(AND(ISNUMBER(M59),ISNUMBER(Z59)),IF(Z59>=M59,(Z59-M59)*1440,""),"") | AD59: =IF(AND(ISNUMBER(Z59),ISNUMBER(AC59)),IF(AC59>=Z59,(AC59-Z59)*1440,""),"") | AI59: 1 | AJ59: Perdido | AK59: No
A60: Core Tools Premium | B60: 1311 | C60: Salma | D60: No | F60: 46306.642 | G60: No | H60: Sí | L60: =IF(AND(ISNUMBER(J60),ISNUMBER(K60)),IF(K60>=J60,(K60-J60)*1440,""),"") | N60: =IF(AND(ISNUMBER(J60),ISNUMBER(M60)),IF(M60>=J60,(M60-J60)*1440,""),"") | O60: =IF(N60="","",LOOKUP(N60,Tiempos!$A$6:$A$10,Tiempos!$B$6:$B$10)) | AA60: =IF(AND(ISNUMBER(M60),ISNUMBER(Z60)),IF(Z60>=M60,(Z60-M60)*1440,""),"") | AD60: =IF(AND(ISNUMBER(Z60),ISNUMBER(AC60)),IF(AC60>=Z60,(AC60-Z60)*1440,""),"") | AI60: 1 | AJ60: Perdido | AK60: No
A61: Core Tools Premium | B61: 1313 | C61: Salma | D61: Sí | E61: Producción u operaciones | F61: 46306.644 | G61: No | H61: Sí | I61: Estoy en el área de PE / Ingeniería de procesos / En una planta de componentes automotrices | J61: 46306.645 | K61: 46306.645 | L61: =IF(AND(ISNUMBER(J61),ISNUMBER(K61)),IF(K61>=J61,(K61-J61)*1440,""),"") -> 0.081683333 | M61: 46306.647 | N61: =IF(AND(ISNUMBER(J61),ISNUMBER(M61)),IF(M61>=J61,(M61-J61)*1440,""),"") -> 3.3650167 | O61: =IF(N61="","",LOOKUP(N61,Tiempos!$A$6:$A$10,Tiempos!$B$6:$B$10)) -> Menos de 4 min | P61: Texto (aviso del audio) + Audio + Cursos (2) | Q61: Sí | R61: Salma | S61: asesor | T61: 103.6 | U61: Sí | V61: 3.28 | W61: Liderazgo para Líderes y Supervisores, Yellow Belt – Six Sigma | X61: 2 | Y61: Sí | Z61: 46308.644 | AA61: =IF(AND(ISNUMBER(M61),ISNUMBER(Z61)),IF(Z61>=M61,(Z61-M61)*1440,""),"") -> 2876.1397 | AB61: Si me interesa | AC61: 46308.645 | AD61: =IF(AND(ISNUMBER(Z61),ISNUMBER(AC61)),IF(AC61>=Z61,(AC61-Z61)*1440,""),"") -> 0.99004999 | AE61: Perdido (lo pasó Salma) | AF61: Sí | AG61: No | AI61: 1 | AJ61: Perdido | AK61: No
A62: Core Tools Premium | B62: 1318 | C62: Salma | D62: Sí | E62: Producción u operaciones | F62: 46306.659 | G62: No | H62: Sí | I62: Soy ingeniero industrial recién egresado, estoy en el área de producción, igual apoyo en una actividades de manufactura / Gracias | J62: 46306.674 | K62: 46306.674 | L62: =IF(AND(ISNUMBER(J62),ISNUMBER(K62)),IF(K62>=J62,(K62-J62)*1440,""),"") -> 0.3416 | M62: 46306.677 | N62: =IF(AND(ISNUMBER(J62),ISNUMBER(M62)),IF(M62>=J62,(M62-J62)*1440,""),"") -> 5.1943333 | O62: =IF(N62="","",LOOKUP(N62,Tiempos!$A$6:$A$10,Tiempos!$B$6:$B$10)) -> 4 a 6 min | P62: Texto (aviso del audio) + Audio + Cursos (2) | Q62: Sí | R62: Salma | S62: asesor | T62: 100.4 | U62: Sí | V62: 4.85 | W62: Microsoft Excel Completo, Lean Manufacturing | X62: 2 | Y62: Sí | Z62: 46306.822 | AA62: =IF(AND(ISNUMBER(M62),ISNUMBER(Z62)),IF(Z62>=M62,(Z62-M62)*1440,""),"") -> 207.9452 | AB62: Muy bien Salma , permíteme un momento, para revisar he estado algo ocupado / Cuando lo revise te comento | AC62: 46306.827 | AD62: =IF(AND(ISNUMBER(Z62),ISNUMBER(AC62)),IF(AC62>=Z62,(AC62-Z62)*1440,""),"") -> 7.5643333 | AE62: Negativo 1 (lo pasó el bot) | AF62: Sí | AG62: Sí | AH62: 0.8 | AI62: 2 | AJ62: Negativo 1 | AK62: No
A63: Core Tools Premium | B63: 1326 | C63: Victoria | D63: Sí | E63: Sin empleo o buscando | F63: 46306.692 | G63: No | H63: No | I63: Desempleado / Conozco casi todo solo quería una refrescada | J63: 46306.698 | K63: 46306.7 | L63: =IF(AND(ISNUMBER(J63),ISNUMBER(K63)),IF(K63>=J63,(K63-J63)*1440,""),"") -> 2.5076833 | M63: 46306.706 | N63: =IF(AND(ISNUMBER(J63),ISNUMBER(M63)),IF(M63>=J63,(M63-J63)*1440,""),"") -> 11.8603 | O63: =IF(N63="","",LOOKUP(N63,Tiempos!$A$6:$A$10,Tiempos!$B$6:$B$10)) -> 10 a 30 min | P63: Texto (aviso del audio) + Audio + Cursos (4) | Q63: Sí | R63: Victoria | S63: asesor | T63: 103.6 | U63: No | V63: 5.23 | W63: AMEF, Plan de Control, Liderazgo para Líderes y Supervisores, Inteligencia Emocional | X63: 4 | Y63: Sí | Z63: 46308.419 | AA63: =IF(AND(ISNUMBER(M63),ISNUMBER(Z63)),IF(Z63>=M63,(Z63-M63)*1440,""),"") -> 2466.6968 | AB63: Cómo serían las facilidades de pago? | AC63: 46308.422 | AD63: =IF(AND(ISNUMBER(Z63),ISNUMBER(AC63)),IF(AC63>=Z63,(AC63-Z63)*1440,""),"") -> 4.32195 | AE63: 1.4 Facilidades de pago (lo pasó Salma) | AF63: Sí | AG63: No | AI63: 2 | AJ63: 2. MSI 3999 | AK63: No
A64: Core Tools Premium | B64: 1328 | C64: Victoria | D64: Sí | E64: Calidad | F64: 46306.717 | G64: No | H64: No | I64: Estudié ingeniería industrial y actualmente estoy en área de calidad y laboratorio de Metrologia / Perfecto / Lo revisaré me llama mucho la atención / El pago es inmediato o se divide en cada sección de las 8 certificaciones? / Si me gustaría analizarlas para organizarme / El de las tres parcialidad | J64: 46306.718 | K64: 46306.719 | L64: =IF(AND(ISNUMBER(J64),ISNUMBER(K64)),IF(K64>=J64,(K64-J64)*1440,""),"") -> 1.1142333 | M64: 46306.721 | N64: =IF(AND(ISNUMBER(J64),ISNUMBER(M64)),IF(M64>=J64,(M64-J64)*1440,""),"") -> 3.8793 | O64: =IF(N64="","",LOOKUP(N64,Tiempos!$A$6:$A$10,Tiempos!$B$6:$B$10)) -> Menos de 4 min | P64: Texto (aviso del audio) + Audio + Cursos (4) | Q64: Sí | R64: Victoria | S64: asesor | T64: 106.4 | U64: No | V64: 2.77 | W64: AMEF, Plan de Control, Inteligencia Emocional, Comunicación Efectiva | X64: 4 | Y64: Sí | Z64: 46306.722 | AA64: =IF(AND(ISNUMBER(M64),ISNUMBER(Z64)),IF(Z64>=M64,(Z64-M64)*1440,""),"") -> 1.3165 | AB64: Perfecto / Lo revisaré me llama mucho la atención | AC64: 46306.722 | AD64: =IF(AND(ISNUMBER(Z64),ISNUMBER(AC64)),IF(AC64>=Z64,(AC64-Z64)*1440,""),"") -> 0.41298334 | AE64: 1.4 Facilidades de pago (lo pasó Victoria) | AF64: Sí | AG64: Sí | AH64: 3.4 | AI64: 1 | AJ64: Negativo 1 | AK64: No
A65: Core Tools Premium | B65: 1335 | C65: Victoria | D65: Respondió otra cosa | F65: 46306.739 | G65: No | H65: No | I65: Área de innovación / Por esa cantidad tengo acceso al resto de las rutas que se muestran? / [imagen] | J65: 46306.742 | K65: 46306.742 | L65: =IF(AND(ISNUMBER(J65),ISNUMBER(K65)),IF(K65>=J65,(K65-J65)*1440,""),"") -> 0.21988333 | M65: 46306.747 | N65: =IF(AND(ISNUMBER(J65),ISNUMBER(M65)),IF(M65>=J65,(M65-J65)*1440,""),"") -> 7.1022333 | O65: =IF(N65="","",LOOKUP(N65,Tiempos!$A$6:$A$10,Tiempos!$B$6:$B$10)) -> 6 a 10 min | P65: Texto (aviso del audio) + Audio + Cursos (4) | Q65: Sí | R65: Victoria | S65: asesor | T65: 99.8 | U65: No | V65: 6.88 | W65: AMEF, Plan de Control, Liderazgo para Líderes y Supervisores, Inteligencia Emocional | X65: 4 | Y65: Sí | Z65: 46306.754 | AA65: =IF(AND(ISNUMBER(M65),ISNUMBER(Z65)),IF(Z65>=M65,(Z65-M65)*1440,""),"") -> 10.329067 | AB65: Los cursos son videos grabados? En vivo? O como funciona? | AC65: 46306.754 | AD65: =IF(AND(ISNUMBER(Z65),ISNUMBER(AC65)),IF(AC65>=Z65,(AC65-Z65)*1440,""),"") -> 0.97584999 | AE65: 1.4 Facilidades de pago (lo pasó Victoria) | AF65: Sí | AG65: Sí | AH65: 2.7 | AI65: 2 | AJ65: Ganado | AK65: Sí
A66: Core Tools Premium | B66: 1353 | C66: Victoria | D66: Sí | E66: Producción u operaciones | F66: 46306.836 | G66: No | H66: Sí | I66: Existe becas ? / Si me interesaría ver una demostración y soy ingeniero industrial en una planta automotriz | J66: 46306.839 | K66: 46306.84 | L66: =IF(AND(ISNUMBER(J66),ISNUMBER(K66)),IF(K66>=J66,(K66-J66)*1440,""),"") -> 1.00075 | M66: 46306.84 | N66: =IF(AND(ISNUMBER(J66),ISNUMBER(M66)),IF(M66>=J66,(M66-J66)*1440,""),"") -> 1.00075 | O66: =IF(N66="","",LOOKUP(N66,Tiempos!$A$6:$A$10,Tiempos!$B$6:$B$10)) -> Menos de 4 min | P66: Texto | Q66: No | R66: Victoria | S66: asesor | X66: 0 | Y66: Sí | Z66: 46309.785 | AA66: =IF(AND(ISNUMBER(M66),ISNUMBER(Z66)),IF(Z66>=M66,(Z66-M66)*1440,""),"") -> 4240.5768 | AB66: Q plazo tengo para aprovecharla ? S2 | AC66: 46309.786 | AD66: =IF(AND(ISNUMBER(Z66),ISNUMBER(AC66)),IF(AC66>=Z66,(AC66-Z66)*1440,""),"") -> 2.37695 | AE66: Sin cambio de etapa | AF66: Sí | AG66: No | AI66: 3 | AJ66: Negativo 1 | AK66: No
A67: Core Tools Premium | B67: 1372 | C67: Salma | D67: No | F67: 46306.933 | G67: Sí | H67: Sí | L67: =IF(AND(ISNUMBER(J67),ISNUMBER(K67)),IF(K67>=J67,(K67-J67)*1440,""),"") | N67: =IF(AND(ISNUMBER(J67),ISNUMBER(M67)),IF(M67>=J67,(M67-J67)*1440,""),"") | O67: =IF(N67="","",LOOKUP(N67,Tiempos!$A$6:$A$10,Tiempos!$B$6:$B$10)) | AA67: =IF(AND(ISNUMBER(M67),ISNUMBER(Z67)),IF(Z67>=M67,(Z67-M67)*1440,""),"") | AD67: =IF(AND(ISNUMBER(Z67),ISNUMBER(AC67)),IF(AC67>=Z67,(AC67-Z67)*1440,""),"") | AI67: 1 | AJ67: Perdido | AK67: No
A68: Core Tools Premium | B68: 1482 | C68: Sin asignar | D68: No | F68: 46307.573 | G68: No | H68: Sí | L68: =IF(AND(ISNUMBER(J68),ISNUMBER(K68)),IF(K68>=J68,(K68-J68)*1440,""),"") | N68: =IF(AND(ISNUMBER(J68),ISNUMBER(M68)),IF(M68>=J68,(M68-J68)*1440,""),"") | O68: =IF(N68="","",LOOKUP(N68,Tiempos!$A$6:$A$10,Tiempos!$B$6:$B$10)) | AA68: =IF(AND(ISNUMBER(M68),ISNUMBER(Z68)),IF(Z68>=M68,(Z68-M68)*1440,""),"") | AD68: =IF(AND(ISNUMBER(Z68),ISNUMBER(AC68)),IF(AC68>=Z68,(AC68-Z68)*1440,""),"") | AI68: 2 | AJ68: Negativo 1 | AK68: No
A69: Core Tools Premium | B69: 1477 | C69: Salma | D69: No | F69: 46307.587 | G69: No | H69: Sí | L69: =IF(AND(ISNUMBER(J69),ISNUMBER(K69)),IF(K69>=J69,(K69-J69)*1440,""),"") | N69: =IF(AND(ISNUMBER(J69),ISNUMBER(M69)),IF(M69>=J69,(M69-J69)*1440,""),"") | O69: =IF(N69="","",LOOKUP(N69,Tiempos!$A$6:$A$10,Tiempos!$B$6:$B$10)) | AA69: =IF(AND(ISNUMBER(M69),ISNUMBER(Z69)),IF(Z69>=M69,(Z69-M69)*1440,""),"") | AD69: =IF(AND(ISNUMBER(Z69),ISNUMBER(AC69)),IF(AC69>=Z69,(AC69-Z69)*1440,""),"") | AI69: 1 | AJ69: Perdido | AK69: No
A70: Core Tools Premium | B70: 1497 | C70: Alexander | D70: Sí | E70: Estudiante o recién egresado | F70: 46307.626 | G70: No | H70: Sí | I70: Estoy estudiando manufactura avanzada / La carrera es manufactura avanzada | J70: 46307.626 | K70: 46307.628 | L70: =IF(AND(ISNUMBER(J70),ISNUMBER(K70)),IF(K70>=J70,(K70-J70)*1440,""),"") -> 2.4578833 | M70: 46307.632 | N70: =IF(AND(ISNUMBER(J70),ISNUMBER(M70)),IF(M70>=J70,(M70-J70)*1440,""),"") -> 8.6577834 | O70: =IF(N70="","",LOOKUP(N70,Tiempos!$A$6:$A$10,Tiempos!$B$6:$B$10)) -> 6 a 10 min | P70: Texto (aviso del audio) + Audio + Cursos (3) | Q70: Sí | R70: Alexander | S70: asesor | T70: 77.2 | U70: Sí | V70: 2.85 | W70: TPM – Mantenimiento Total Productivo, Control Estadístico de Procesos (SPC), Solución de Problemas 8 D's | X70: 3 | Y70: Sí | Z70: 46307.634 | AA70: =IF(AND(ISNUMBER(M70),ISNUMBER(Z70)),IF(Z70>=M70,(Z70-M70)*1440,""),"") -> 2.2183333 | AB70: Oke deja lo checo y te aviso muchas gtacias | AC70: 46307.635 | AD70: =IF(AND(ISNUMBER(Z70),ISNUMBER(AC70)),IF(AC70>=Z70,(AC70-Z70)*1440,""),"") -> 2.1306667 | AE70: Sin cambio de etapa | AF70: No | AG70: No | AI70: 3 | AJ70: 1.3 Llamadita y facilidad pago | AK70: No
A71: Core Tools Premium | B71: 1536 | C71: Salma | D71: No | F71: 46307.783 | G71: No | H71: Sí | L71: =IF(AND(ISNUMBER(J71),ISNUMBER(K71)),IF(K71>=J71,(K71-J71)*1440,""),"") | N71: =IF(AND(ISNUMBER(J71),ISNUMBER(M71)),IF(M71>=J71,(M71-J71)*1440,""),"") | O71: =IF(N71="","",LOOKUP(N71,Tiempos!$A$6:$A$10,Tiempos!$B$6:$B$10)) | AA71: =IF(AND(ISNUMBER(M71),ISNUMBER(Z71)),IF(Z71>=M71,(Z71-M71)*1440,""),"") | AD71: =IF(AND(ISNUMBER(Z71),ISNUMBER(AC71)),IF(AC71>=Z71,(AC71-Z71)*1440,""),"") | AI71: 1 | AJ71: Negativo 1 | AK71: No
A72: Core Tools Premium | B72: 1554 | C72: Alexander | D72: Sí | E72: Producción u operaciones | F72: 46307.817 | G72: No | H72: Sí | I72: Ahorita estoy en área de mantenimiento | J72: 46307.818 | K72: 46307.822 | L72: =IF(AND(ISNUMBER(J72),ISNUMBER(K72)),IF(K72>=J72,(K72-J72)*1440,""),"") -> 5.7206167 | M72: 46307.823 | N72: =IF(AND(ISNUMBER(J72),ISNUMBER(M72)),IF(M72>=J72,(M72-J72)*1440,""),"") -> 7.1911333 | O72: =IF(N72="","",LOOKUP(N72,Tiempos!$A$6:$A$10,Tiempos!$B$6:$B$10)) -> 6 a 10 min | P72: Texto (aviso del audio) + Audio + Cursos (3) | Q72: Sí | R72: Alexander | S72: asesor | T72: 80.6 | U72: Sí | V72: 1.47 | W72: TPM – Mantenimiento Total Productivo, OEE, Solución de Problemas para Ingenieros | X72: 3 | Y72: No | AA72: =IF(AND(ISNUMBER(M72),ISNUMBER(Z72)),IF(Z72>=M72,(Z72-M72)*1440,""),"") | AD72: =IF(AND(ISNUMBER(Z72),ISNUMBER(AC72)),IF(AC72>=Z72,(AC72-Z72)*1440,""),"") | AF72: Sí | AI72: 2 | AJ72: Perdido | AK72: No
A73: Core Tools Premium | B73: 1566 | C73: Salma | D73: No | F73: 46307.893 | G73: No | H73: No | L73: =IF(AND(ISNUMBER(J73),ISNUMBER(K73)),IF(K73>=J73,(K73-J73)*1440,""),"") | N73: =IF(AND(ISNUMBER(J73),ISNUMBER(M73)),IF(M73>=J73,(M73-J73)*1440,""),"") | O73: =IF(N73="","",LOOKUP(N73,Tiempos!$A$6:$A$10,Tiempos!$B$6:$B$10)) | AA73: =IF(AND(ISNUMBER(M73),ISNUMBER(Z73)),IF(Z73>=M73,(Z73-M73)*1440,""),"") | AD73: =IF(AND(ISNUMBER(Z73),ISNUMBER(AC73)),IF(AC73>=Z73,(AC73-Z73)*1440,""),"") | AI73: 1 | AJ73: Negativo 1 | AK73: No
A74: Core Tools Premium | B74: 1576 | C74: Alexander | D74: Sí | E74: Calidad | F74: 46307.905 | G74: No | H74: Sí | I74: Trabajo en el área de calidad, me gradué en el 2022 y he trabajado también en área de ingeniería y producción, más que nada estandarización de procesos y operaciones también capacitación de personal / El paquete de core tools es de clases pregravadas o las imparte un instructor? | J74: 46307.906 | K74: 46307.911 | L74: =IF(AND(ISNUMBER(J74),ISNUMBER(K74)),IF(K74>=J74,(K74-J74)*1440,""),"") -> 7.2288667 | M74: 46307.914 | N74: =IF(AND(ISNUMBER(J74),ISNUMBER(M74)),IF(M74>=J74,(M74-J74)*1440,""),"") -> 11.600317 | O74: =IF(N74="","",LOOKUP(N74,Tiempos!$A$6:$A$10,Tiempos!$B$6:$B$10)) -> 10 a 30 min | P74: Texto (aviso del audio) + Audio + Cursos (4) | Q74: Sí | R74: Alexander | S74: asesor | T74: 82.1 | U74: Sí | V74: 4.37 | W74: SMED, TPM – Mantenimiento Total Productivo, Solución de Problemas 8 D's, Trabajo Estándar | X74: 4 | Y74: Sí | Z74: 46307.922 | AA74: =IF(AND(ISNUMBER(M74),ISNUMBER(Z74)),IF(Z74>=M74,(Z74-M74)*1440,""),"") -> 11.487833 | AB74: Entonces con el pago de 3900 se tiene acceso a todas las certificaciones, no hay necesidad de pagar más? por ejemplo si quisiera tomar también la de 8d's y TPM | AC74: 46307.962 | AD74: =IF(AND(ISNUMBER(Z74),ISNUMBER(AC74)),IF(AC74>=Z74,(AC74-Z74)*1440,""),"") -> 57.638933 | AE74: 1.4 Facilidades de pago (lo pasó Victoria) | AF74: Sí | AG74: Sí | AH74: 3.4 | AI74: 2 | AJ74: Negativo 1 | AK74: No
A75: Core Tools Premium | B75: 1584 | C75: Salma | D75: No | F75: 46307.922 | G75: Sí | H75: Sí | L75: =IF(AND(ISNUMBER(J75),ISNUMBER(K75)),IF(K75>=J75,(K75-J75)*1440,""),"") | N75: =IF(AND(ISNUMBER(J75),ISNUMBER(M75)),IF(M75>=J75,(M75-J75)*1440,""),"") | O75: =IF(N75="","",LOOKUP(N75,Tiempos!$A$6:$A$10,Tiempos!$B$6:$B$10)) | AA75: =IF(AND(ISNUMBER(M75),ISNUMBER(Z75)),IF(Z75>=M75,(Z75-M75)*1440,""),"") | AD75: =IF(AND(ISNUMBER(Z75),ISNUMBER(AC75)),IF(AC75>=Z75,(AC75-Z75)*1440,""),"") | AI75: 2 | AJ75: Negativo 1 | AK75: No
A76: Core Tools Premium | B76: 1592 | C76: Salma | D76: Sí | E76: Supervisión o jefatura | F76: 46307.958 | G76: Sí | H76: Sí | I76: Soy supervisor de Calidad industrial, en refinería | J76: 46307.959 | K76: 46308.3 | L76: =IF(AND(ISNUMBER(J76),ISNUMBER(K76)),IF(K76>=J76,(K76-J76)*1440,""),"") -> 490.97722 | M76: 46308.301 | N76: =IF(AND(ISNUMBER(J76),ISNUMBER(M76)),IF(M76>=J76,(M76-J76)*1440,""),"") -> 493.13367 | O76: =IF(N76="","",LOOKUP(N76,Tiempos!$A$6:$A$10,Tiempos!$B$6:$B$10)) -> 30 min o más | P76: Texto (aviso del audio) + Audio + Cursos (2) | Q76: Sí | R76: Salma | S76: asesor | T76: 114.7 | U76: Sí | V76: 2.16 | W76: ISO 9001:2015 Auditor Interno, Liderazgo para Líderes y Supervisores | X76: 2 | Y76: No | AA76: =IF(AND(ISNUMBER(M76),ISNUMBER(Z76)),IF(Z76>=M76,(Z76-M76)*1440,""),"") | AD76: =IF(AND(ISNUMBER(Z76),ISNUMBER(AC76)),IF(AC76>=Z76,(AC76-Z76)*1440,""),"") | AF76: Sí | AI76: 2 | AJ76: Negativo 1 | AK76: No
A77: Core Tools Premium | B77: 1619 | C77: Salma | D77: No | F77: 46308.384 | G77: No | H77: No | L77: =IF(AND(ISNUMBER(J77),ISNUMBER(K77)),IF(K77>=J77,(K77-J77)*1440,""),"") | N77: =IF(AND(ISNUMBER(J77),ISNUMBER(M77)),IF(M77>=J77,(M77-J77)*1440,""),"") | O77: =IF(N77="","",LOOKUP(N77,Tiempos!$A$6:$A$10,Tiempos!$B$6:$B$10)) | AA77: =IF(AND(ISNUMBER(M77),ISNUMBER(Z77)),IF(Z77>=M77,(Z77-M77)*1440,""),"") | AD77: =IF(AND(ISNUMBER(Z77),ISNUMBER(AC77)),IF(AC77>=Z77,(AC77-Z77)*1440,""),"") | AI77: 2 | AJ77: Negativo 1 | AK77: No
A78: Core Tools Premium | B78: 1637 | C78: Salma | D78: Sí | E78: Estudiante o recién egresado | F78: 46308.451 | G78: No | H78: No | I78: Estoy estudiando una ingeniería mecánica | J78: 46308.453 | K78: 46308.454 | L78: =IF(AND(ISNUMBER(J78),ISNUMBER(K78)),IF(K78>=J78,(K78-J78)*1440,""),"") -> 1.7984667 | M78: 46308.457 | N78: =IF(AND(ISNUMBER(J78),ISNUMBER(M78)),IF(M78>=J78,(M78-J78)*1440,""),"") -> 5.8677667 | O78: =IF(N78="","",LOOKUP(N78,Tiempos!$A$6:$A$10,Tiempos!$B$6:$B$10)) -> 4 a 6 min | P78: Texto (aviso del audio) + Audio + Cursos (2) | Q78: Sí | R78: Joceline | S78: auxiliar | T78: 146.7 | U78: No | V78: 4.07 | W78: Curriculum Vitae de Alto Impacto, Cómo hablar en una entrevista de trabajo | X78: 2 | Y78: No | AA78: =IF(AND(ISNUMBER(M78),ISNUMBER(Z78)),IF(Z78>=M78,(Z78-M78)*1440,""),"") | AD78: =IF(AND(ISNUMBER(Z78),ISNUMBER(AC78)),IF(AC78>=Z78,(AC78-Z78)*1440,""),"") | AF78: Sí | AI78: 2 | AJ78: Negativo 1 | AK78: No
A79: Core Tools Premium | B79: 1655 | C79: Salma | D79: Sí | E79: Sin empleo o buscando | F79: 46308.531 | G79: No | H79: No | I79: Hay curso de IATF O ISO ? / Trabajo en el área automotriz de ingeniera / Bueno, ahora estoy desempleada / Pero tengo tres años de experiencia en esa área | J79: 46308.532 | K79: 46308.533 | L79: =IF(AND(ISNUMBER(J79),ISNUMBER(K79)),IF(K79>=J79,(K79-J79)*1440,""),"") -> 1.8427833 | M79: 46308.536 | N79: =IF(AND(ISNUMBER(J79),ISNUMBER(M79)),IF(M79>=J79,(M79-J79)*1440,""),"") -> 5.4192166 | O79: =IF(N79="","",LOOKUP(N79,Tiempos!$A$6:$A$10,Tiempos!$B$6:$B$10)) -> 4 a 6 min | P79: Audio + Cursos (2) | Q79: Sí | R79: Salma | S79: asesor | T79: 136.3 | U79: No | W79: Green Belt – Six Sigma, Lean Manufacturing | X79: 2 | Y79: No | AA79: =IF(AND(ISNUMBER(M79),ISNUMBER(Z79)),IF(Z79>=M79,(Z79-M79)*1440,""),"") | AD79: =IF(AND(ISNUMBER(Z79),ISNUMBER(AC79)),IF(AC79>=Z79,(AC79-Z79)*1440,""),"") | AF79: Sí | AI79: 2 | AJ79: Negativo 1 | AK79: No
A80: Core Tools Premium | B80: 1656 | C80: Salma | D80: Sí | E80: Producción u operaciones | F80: 46308.538 | G80: No | H80: Sí | I80: Trabajando actualmente, en produccion de maquinados | J80: 46308.538 | K80: 46308.538 | L80: =IF(AND(ISNUMBER(J80),ISNUMBER(K80)),IF(K80>=J80,(K80-J80)*1440,""),"") -> 0.27208333 | M80: 46308.542 | N80: =IF(AND(ISNUMBER(J80),ISNUMBER(M80)),IF(M80>=J80,(M80-J80)*1440,""),"") -> 6.2626667 | O80: =IF(N80="","",LOOKUP(N80,Tiempos!$A$6:$A$10,Tiempos!$B$6:$B$10)) -> 6 a 10 min | P80: Texto (aviso del audio) + Audio + Cursos (2) | Q80: Sí | R80: Salma | S80: asesor | T80: 111.9 | U80: Sí | V80: 5.99 | W80: Lean Manufacturing, Yellow Belt – Six Sigma | X80: 2 | Y80: No | AA80: =IF(AND(ISNUMBER(M80),ISNUMBER(Z80)),IF(Z80>=M80,(Z80-M80)*1440,""),"") | AD80: =IF(AND(ISNUMBER(Z80),ISNUMBER(AC80)),IF(AC80>=Z80,(AC80-Z80)*1440,""),"") | AF80: Sí | AI80: 2 | AJ80: Negativo 1 | AK80: No
A81: Core Tools Premium | B81: 1657 | C81: Victoria | D81: No | F81: 46308.538 | G81: No | H81: Sí | L81: =IF(AND(ISNUMBER(J81),ISNUMBER(K81)),IF(K81>=J81,(K81-J81)*1440,""),"") | N81: =IF(AND(ISNUMBER(J81),ISNUMBER(M81)),IF(M81>=J81,(M81-J81)*1440,""),"") | O81: =IF(N81="","",LOOKUP(N81,Tiempos!$A$6:$A$10,Tiempos!$B$6:$B$10)) | AA81: =IF(AND(ISNUMBER(M81),ISNUMBER(Z81)),IF(Z81>=M81,(Z81-M81)*1440,""),"") | AD81: =IF(AND(ISNUMBER(Z81),ISNUMBER(AC81)),IF(AC81>=Z81,(AC81-Z81)*1440,""),"") | AI81: 3 | AJ81: Negativo 1 | AK81: No
A82: Core Tools Premium | B82: 1680 | C82: Alexander | D82: No | F82: 46308.662 | G82: No | H82: Sí | L82: =IF(AND(ISNUMBER(J82),ISNUMBER(K82)),IF(K82>=J82,(K82-J82)*1440,""),"") | N82: =IF(AND(ISNUMBER(J82),ISNUMBER(M82)),IF(M82>=J82,(M82-J82)*1440,""),"") | O82: =IF(N82="","",LOOKUP(N82,Tiempos!$A$6:$A$10,Tiempos!$B$6:$B$10)) | AA82: =IF(AND(ISNUMBER(M82),ISNUMBER(Z82)),IF(Z82>=M82,(Z82-M82)*1440,""),"") | AD82: =IF(AND(ISNUMBER(Z82),ISNUMBER(AC82)),IF(AC82>=Z82,(AC82-Z82)*1440,""),"") | AI82: 2 | AJ82: Perdido | AK82: No
A83: Core Tools Premium | B83: 1688 | C83: Victoria | D83: Sí | E83: Producción u operaciones | F83: 46308.688 | G83: No | H83: Sí | I83: Estoy en el ramo automotriz, área de mantenimiento pero busco crecer como Ing P0 procesos industriales / Por favor | J83: 46308.69 | K83: 46308.69 | L83: =IF(AND(ISNUMBER(J83),ISNUMBER(K83)),IF(K83>=J83,(K83-J83)*1440,""),"") -> 0.64723335 | M83: 46308.692 | N83: =IF(AND(ISNUMBER(J83),ISNUMBER(M83)),IF(M83>=J83,(M83-J83)*1440,""),"") -> 3.4216167 | O83: =IF(N83="","",LOOKUP(N83,Tiempos!$A$6:$A$10,Tiempos!$B$6:$B$10)) -> Menos de 4 min | P83: Texto (aviso del audio) + Audio + Cursos (4) | Q83: Sí | R83: Victoria | S83: asesor | T83: 118.4 | U83: Sí | V83: 2.77 | W83: AMEF, FODA, Kaizen – Mejora Continua, Liderazgo para Ingenieros | X83: 4 | Y83: Sí | Z83: 46308.697 | AA83: =IF(AND(ISNUMBER(M83),ISNUMBER(Z83)),IF(Z83>=M83,(Z83-M83)*1440,""),"") -> 6.7522 | AB83: Me podrías brindar información respecto a las facilidades de pago que manejas ? | AC83: 46308.699 | AD83: =IF(AND(ISNUMBER(Z83),ISNUMBER(AC83)),IF(AC83>=Z83,(AC83-Z83)*1440,""),"") -> 2.3820167 | AE83: 1.4 Facilidades de pago (lo pasó Victoria) | AF83: Sí | AG83: Sí | AH83: 3.8 | AI83: 2 | AJ83: Negativo 1 | AK83: No
A84: Core Tools Premium | B84: 1694 | C84: Victoria | D84: No | F84: 46308.697 | G84: No | H84: Sí | L84: =IF(AND(ISNUMBER(J84),ISNUMBER(K84)),IF(K84>=J84,(K84-J84)*1440,""),"") | N84: =IF(AND(ISNUMBER(J84),ISNUMBER(M84)),IF(M84>=J84,(M84-J84)*1440,""),"") | O84: =IF(N84="","",LOOKUP(N84,Tiempos!$A$6:$A$10,Tiempos!$B$6:$B$10)) | AA84: =IF(AND(ISNUMBER(M84),ISNUMBER(Z84)),IF(Z84>=M84,(Z84-M84)*1440,""),"") | AD84: =IF(AND(ISNUMBER(Z84),ISNUMBER(AC84)),IF(AC84>=Z84,(AC84-Z84)*1440,""),"") | AI84: 2 | AJ84: Negativo 1 | AK84: No
A85: Core Tools Premium | B85: 1726 | C85: Alexander | D85: No | F85: 46308.832 | G85: No | H85: Sí | L85: =IF(AND(ISNUMBER(J85),ISNUMBER(K85)),IF(K85>=J85,(K85-J85)*1440,""),"") | N85: =IF(AND(ISNUMBER(J85),ISNUMBER(M85)),IF(M85>=J85,(M85-J85)*1440,""),"") | O85: =IF(N85="","",LOOKUP(N85,Tiempos!$A$6:$A$10,Tiempos!$B$6:$B$10)) | AA85: =IF(AND(ISNUMBER(M85),ISNUMBER(Z85)),IF(Z85>=M85,(Z85-M85)*1440,""),"") | AD85: =IF(AND(ISNUMBER(Z85),ISNUMBER(AC85)),IF(AC85>=Z85,(AC85-Z85)*1440,""),"") | AI85: 2 | AJ85: Negativo 1 | AK85: No
A86: Core Tools Premium | B86: 1723 | C86: Salma | D86: No | F86: 46308.844 | G86: No | H86: No | L86: =IF(AND(ISNUMBER(J86),ISNUMBER(K86)),IF(K86>=J86,(K86-J86)*1440,""),"") | N86: =IF(AND(ISNUMBER(J86),ISNUMBER(M86)),IF(M86>=J86,(M86-J86)*1440,""),"") | O86: =IF(N86="","",LOOKUP(N86,Tiempos!$A$6:$A$10,Tiempos!$B$6:$B$10)) | AA86: =IF(AND(ISNUMBER(M86),ISNUMBER(Z86)),IF(Z86>=M86,(Z86-M86)*1440,""),"") | AD86: =IF(AND(ISNUMBER(Z86),ISNUMBER(AC86)),IF(AC86>=Z86,(AC86-Z86)*1440,""),"") | AI86: 1 | AJ86: Negativo 1 | AK86: No
A87: Core Tools Premium | B87: 1744 | C87: Alexander | D87: Sí | E87: Producción u operaciones | F87: 46308.874 | G87: No | H87: No | I87: Empezando ramo automotriz | J87: 46308.874 | K87: 46308.877 | L87: =IF(AND(ISNUMBER(J87),ISNUMBER(K87)),IF(K87>=J87,(K87-J87)*1440,""),"") -> 3.2710667 | M87: 46308.879 | N87: =IF(AND(ISNUMBER(J87),ISNUMBER(M87)),IF(M87>=J87,(M87-J87)*1440,""),"") -> 6.3731 | O87: =IF(N87="","",LOOKUP(N87,Tiempos!$A$6:$A$10,Tiempos!$B$6:$B$10)) -> 6 a 10 min | P87: Texto (aviso del audio) + Audio + Cursos (3) | Q87: Sí | R87: Alexander | S87: asesor | T87: 76.2 | U87: No | V87: 3.1 | W87: Solución de Problemas 8 D's, Trabajo Estándar, Poka Yoke | X87: 3 | Y87: Sí | Z87: 46308.883 | AA87: =IF(AND(ISNUMBER(M87),ISNUMBER(Z87)),IF(Z87>=M87,(Z87-M87)*1440,""),"") -> 6.5071333 | AB87: Me interesa pero mañana acabo de entrar a trabajar | AC87: 46308.885 | AD87: =IF(AND(ISNUMBER(Z87),ISNUMBER(AC87)),IF(AC87>=Z87,(AC87-Z87)*1440,""),"") -> 3.2057667 | AE87: Sin cambio de etapa | AF87: No | AG87: No | AI87: 2 | AJ87: 1.3 Llamadita y facilidad pago | AK87: No
A88: Core Tools Premium | B88: 1760 | C88: Salma | D88: No | F88: 46308.958 | G88: Sí | H88: No | L88: =IF(AND(ISNUMBER(J88),ISNUMBER(K88)),IF(K88>=J88,(K88-J88)*1440,""),"") | N88: =IF(AND(ISNUMBER(J88),ISNUMBER(M88)),IF(M88>=J88,(M88-J88)*1440,""),"") | O88: =IF(N88="","",LOOKUP(N88,Tiempos!$A$6:$A$10,Tiempos!$B$6:$B$10)) | AA88: =IF(AND(ISNUMBER(M88),ISNUMBER(Z88)),IF(Z88>=M88,(Z88-M88)*1440,""),"") | AD88: =IF(AND(ISNUMBER(Z88),ISNUMBER(AC88)),IF(AC88>=Z88,(AC88-Z88)*1440,""),"") | AI88: 1 | AJ88: Negativo 1 | AK88: No
A89: Core Tools Premium | B89: 1774 | C89: Salma | D89: Respondió otra cosa | F89: 46309.105 | G89: Sí | H89: Sí | I89: Gracias, lo estaré checando | J89: 46309.877 | K89: 46309.878 | L89: =IF(AND(ISNUMBER(J89),ISNUMBER(K89)),IF(K89>=J89,(K89-J89)*1440,""),"") -> 1.9991833 | M89: 46309.878 | N89: =IF(AND(ISNUMBER(J89),ISNUMBER(M89)),IF(M89>=J89,(M89-J89)*1440,""),"") -> 1.9991833 | O89: =IF(N89="","",LOOKUP(N89,Tiempos!$A$6:$A$10,Tiempos!$B$6:$B$10)) -> Menos de 4 min | P89: Texto | Q89: No | R89: Salma | S89: asesor | X89: 0 | Y89: No | AA89: =IF(AND(ISNUMBER(M89),ISNUMBER(Z89)),IF(Z89>=M89,(Z89-M89)*1440,""),"") | AD89: =IF(AND(ISNUMBER(Z89),ISNUMBER(AC89)),IF(AC89>=Z89,(AC89-Z89)*1440,""),"") | AF89: No | AI89: 1 | AJ89: Negativo 1 | AK89: No
A90: Core Tools Premium | B90: 1756 | C90: Salma | D90: No | F90: 46309.297 | G90: Sí | H90: Sí | L90: =IF(AND(ISNUMBER(J90),ISNUMBER(K90)),IF(K90>=J90,(K90-J90)*1440,""),"") | N90: =IF(AND(ISNUMBER(J90),ISNUMBER(M90)),IF(M90>=J90,(M90-J90)*1440,""),"") | O90: =IF(N90="","",LOOKUP(N90,Tiempos!$A$6:$A$10,Tiempos!$B$6:$B$10)) | AA90: =IF(AND(ISNUMBER(M90),ISNUMBER(Z90)),IF(Z90>=M90,(Z90-M90)*1440,""),"") | AD90: =IF(AND(ISNUMBER(Z90),ISNUMBER(AC90)),IF(AC90>=Z90,(AC90-Z90)*1440,""),"") | AI90: 3 | AJ90: Negativo 1 | AK90: No
A91: Core Tools Premium | B91: 1775 | C91: Salma | D91: No | F91: 46309.308 | G91: Sí | H91: Sí | L91: =IF(AND(ISNUMBER(J91),ISNUMBER(K91)),IF(K91>=J91,(K91-J91)*1440,""),"") | N91: =IF(AND(ISNUMBER(J91),ISNUMBER(M91)),IF(M91>=J91,(M91-J91)*1440,""),"") | O91: =IF(N91="","",LOOKUP(N91,Tiempos!$A$6:$A$10,Tiempos!$B$6:$B$10)) | AA91: =IF(AND(ISNUMBER(M91),ISNUMBER(Z91)),IF(Z91>=M91,(Z91-M91)*1440,""),"") | AD91: =IF(AND(ISNUMBER(Z91),ISNUMBER(AC91)),IF(AC91>=Z91,(AC91-Z91)*1440,""),"") | AI91: 2 | AJ91: Negativo 1 | AK91: No
A92: Core Tools Premium | B92: 1807 | C92: Sin asignar | D92: Respondió otra cosa | F92: 46309.392 | G92: No | H92: Sí | I92: Ok | J92: 46309.571 | K92: 46309.572 | L92: =IF(AND(ISNUMBER(J92),ISNUMBER(K92)),IF(K92>=J92,(K92-J92)*1440,""),"") -> 1.3620667 | M92: 46309.572 | N92: =IF(AND(ISNUMBER(J92),ISNUMBER(M92)),IF(M92>=J92,(M92-J92)*1440,""),"") -> 1.3620667 | O92: =IF(N92="","",LOOKUP(N92,Tiempos!$A$6:$A$10,Tiempos!$B$6:$B$10)) -> Menos de 4 min | P92: Texto | Q92: No | R92: Joceline | S92: auxiliar | X92: 0 | Y92: No | AA92: =IF(AND(ISNUMBER(M92),ISNUMBER(Z92)),IF(Z92>=M92,(Z92-M92)*1440,""),"") | AD92: =IF(AND(ISNUMBER(Z92),ISNUMBER(AC92)),IF(AC92>=Z92,(AC92-Z92)*1440,""),"") | AF92: No | AI92: 3 | AJ92: Negativo 1 | AK92: No
A93: Core Tools Premium | B93: 1812 | C93: Salma | D93: No | F93: 46309.402 | G93: No | H93: Sí | L93: =IF(AND(ISNUMBER(J93),ISNUMBER(K93)),IF(K93>=J93,(K93-J93)*1440,""),"") | N93: =IF(AND(ISNUMBER(J93),ISNUMBER(M93)),IF(M93>=J93,(M93-J93)*1440,""),"") | O93: =IF(N93="","",LOOKUP(N93,Tiempos!$A$6:$A$10,Tiempos!$B$6:$B$10)) | AA93: =IF(AND(ISNUMBER(M93),ISNUMBER(Z93)),IF(Z93>=M93,(Z93-M93)*1440,""),"") | AD93: =IF(AND(ISNUMBER(Z93),ISNUMBER(AC93)),IF(AC93>=Z93,(AC93-Z93)*1440,""),"") | AI93: 2 | AJ93: Negativo 1 | AK93: No
A94: Core Tools Premium | B94: 1821 | C94: Salma | D94: No | F94: 46309.449 | G94: No | H94: No | L94: =IF(AND(ISNUMBER(J94),ISNUMBER(K94)),IF(K94>=J94,(K94-J94)*1440,""),"") | N94: =IF(AND(ISNUMBER(J94),ISNUMBER(M94)),IF(M94>=J94,(M94-J94)*1440,""),"") | O94: =IF(N94="","",LOOKUP(N94,Tiempos!$A$6:$A$10,Tiempos!$B$6:$B$10)) | AA94: =IF(AND(ISNUMBER(M94),ISNUMBER(Z94)),IF(Z94>=M94,(Z94-M94)*1440,""),"") | AD94: =IF(AND(ISNUMBER(Z94),ISNUMBER(AC94)),IF(AC94>=Z94,(AC94-Z94)*1440,""),"") | AI94: 1 | AJ94: Negativo 1 | AK94: No
A95: Core Tools Premium | B95: 1841 | C95: Salma | D95: No | F95: 46309.494 | G95: No | H95: Sí | L95: =IF(AND(ISNUMBER(J95),ISNUMBER(K95)),IF(K95>=J95,(K95-J95)*1440,""),"") | N95: =IF(AND(ISNUMBER(J95),ISNUMBER(M95)),IF(M95>=J95,(M95-J95)*1440,""),"") | O95: =IF(N95="","",LOOKUP(N95,Tiempos!$A$6:$A$10,Tiempos!$B$6:$B$10)) | AA95: =IF(AND(ISNUMBER(M95),ISNUMBER(Z95)),IF(Z95>=M95,(Z95-M95)*1440,""),"") | AD95: =IF(AND(ISNUMBER(Z95),ISNUMBER(AC95)),IF(AC95>=Z95,(AC95-Z95)*1440,""),"") | AI95: 2 | AJ95: Negativo 1 | AK95: No
A96: Core Tools Premium | B96: 1838 | C96: Salma | D96: No | F96: 46309.506 | G96: No | H96: Sí | L96: =IF(AND(ISNUMBER(J96),ISNUMBER(K96)),IF(K96>=J96,(K96-J96)*1440,""),"") | N96: =IF(AND(ISNUMBER(J96),ISNUMBER(M96)),IF(M96>=J96,(M96-J96)*1440,""),"") | O96: =IF(N96="","",LOOKUP(N96,Tiempos!$A$6:$A$10,Tiempos!$B$6:$B$10)) | AA96: =IF(AND(ISNUMBER(M96),ISNUMBER(Z96)),IF(Z96>=M96,(Z96-M96)*1440,""),"") | AD96: =IF(AND(ISNUMBER(Z96),ISNUMBER(AC96)),IF(AC96>=Z96,(AC96-Z96)*1440,""),"") | AI96: 1 | AJ96: Negativo 1 | AK96: No
A97: Core Tools Premium | B97: 1853 | C97: Salma | D97: No | F97: 46309.566 | G97: No | H97: No | L97: =IF(AND(ISNUMBER(J97),ISNUMBER(K97)),IF(K97>=J97,(K97-J97)*1440,""),"") | N97: =IF(AND(ISNUMBER(J97),ISNUMBER(M97)),IF(M97>=J97,(M97-J97)*1440,""),"") | O97: =IF(N97="","",LOOKUP(N97,Tiempos!$A$6:$A$10,Tiempos!$B$6:$B$10)) | AA97: =IF(AND(ISNUMBER(M97),ISNUMBER(Z97)),IF(Z97>=M97,(Z97-M97)*1440,""),"") | AD97: =IF(AND(ISNUMBER(Z97),ISNUMBER(AC97)),IF(AC97>=Z97,(AC97-Z97)*1440,""),"") | AI97: 1 | AJ97: Negativo 1 | AK97: No
A98: Core Tools Premium | B98: 1893 | C98: Alexander | D98: Respondió otra cosa | F98: 46309.747 | G98: No | H98: Sí | I98: Buenas tardds / Yo solo quiero yellowbelt / Y greenbelt / Se.puede? | J98: 46310.68 | K98: 46310.685 | L98: =IF(AND(ISNUMBER(J98),ISNUMBER(K98)),IF(K98>=J98,(K98-J98)*1440,""),"") -> 6.5580833 | M98: 46310.685 | N98: =IF(AND(ISNUMBER(J98),ISNUMBER(M98)),IF(M98>=J98,(M98-J98)*1440,""),"") -> 6.5580833 | O98: =IF(N98="","",LOOKUP(N98,Tiempos!$A$6:$A$10,Tiempos!$B$6:$B$10)) -> 6 a 10 min | P98: Texto | Q98: No | R98: Alexander | S98: asesor | X98: 0 | Y98: Sí | Z98: 46310.689 | AA98: =IF(AND(ISNUMBER(M98),ISNUMBER(Z98)),IF(Z98>=M98,(Z98-M98)*1440,""),"") -> 5.0364667 | AB98: Me habian ofrecido este | AC98: 46310.691 | AD98: =IF(AND(ISNUMBER(Z98),ISNUMBER(AC98)),IF(AC98>=Z98,(AC98-Z98)*1440,""),"") -> 3.4784167 | AE98: 3 Transferencia / OXXO (lo pasó Alexander) | AF98: No | AG98: No | AI98: 2 | AJ98: 3 Transferencia / OXXO | AK98: No
A99: Core Tools Premium | B99: 1898 | C99: Victoria | D99: No | F99: 46309.769 | G99: No | H99: Sí | L99: =IF(AND(ISNUMBER(J99),ISNUMBER(K99)),IF(K99>=J99,(K99-J99)*1440,""),"") | N99: =IF(AND(ISNUMBER(J99),ISNUMBER(M99)),IF(M99>=J99,(M99-J99)*1440,""),"") | O99: =IF(N99="","",LOOKUP(N99,Tiempos!$A$6:$A$10,Tiempos!$B$6:$B$10)) | AA99: =IF(AND(ISNUMBER(M99),ISNUMBER(Z99)),IF(Z99>=M99,(Z99-M99)*1440,""),"") | AD99: =IF(AND(ISNUMBER(Z99),ISNUMBER(AC99)),IF(AC99>=Z99,(AC99-Z99)*1440,""),"") | AI99: 2 | AJ99: Negativo 1 | AK99: No
A100: Core Tools Premium | B100: 1912 | C100: Alexander | D100: Sí | E100: Calidad | F100: 46309.857 | G100: No | H100: Sí | I100: Hola buenas noches soy Daniela, actualmente estoy trabajando / Estoy trabajando en el área de calidad y sistema de gestión / Si gracias | J100: 46309.881 | K100: 46309.883 | L100: =IF(AND(ISNUMBER(J100),ISNUMBER(K100)),IF(K100>=J100,(K100-J100)*1440,""),"") -> 2.0334 | M100: 46309.887 | N100: =IF(AND(ISNUMBER(J100),ISNUMBER(M100)),IF(M100>=J100,(M100-J100)*1440,""),"") -> 8.7706667 | O100: =IF(N100="","",LOOKUP(N100,Tiempos!$A$6:$A$10,Tiempos!$B$6:$B$10)) -> 6 a 10 min | P100: Texto (aviso del audio) + Audio + Cursos (3) | Q100: Sí | R100: Alexander | S100: asesor | T100: 80.6 | U100: Sí | V100: 6.74 | W100: ISO 9001:2015 Auditor Interno, ISO 19011:2018 Auditorías de Sistemas de Gestión, Solución de Problemas 8 D's | X100: 3 | Y100: Sí | Z100: 46310.305 | AA100: =IF(AND(ISNUMBER(M100),ISNUMBER(Z100)),IF(Z100>=M100,(Z100-M100)*1440,""),"") -> 600.73033 | AB100: Hola buenos días! Disculpa una duda son clases grabadas o son en vivo y cuáles son los precios que manejan? | AC100: 46310.305 | AD100: =IF(AND(ISNUMBER(Z100),ISNUMBER(AC100)),IF(AC100>=Z100,(AC100-Z100)*1440,""),"") -> 0.60553335 | AE100: Sin cambio de etapa | AF100: Sí | AG100: No | AI100: 1 | AJ100: Negativo 1 | AK100: No
...

Sheet Detalle de audios
A1: Embudo | B1: Lead # (CRM) | C1: Enviado | D1: Hora | E1: ¿De 8 a 22 h? | F1: Lo mandó | G1: Tipo | H1: Rol | I1: Etapa del lead | J1: Etapa (grupo) | K1: Duración (s) | L1: ¿Audio reutilizado? | M1: ¿Es la recomendación del paso 1.2? | N1: ¿Lo vio? (palomitas azules) | O1: Minutos hasta que lo vio | P1: ¿El lead escribió en las 24 h siguientes? | Q1: Minutos hasta que el lead escribió
A2: Core Tools Premium | B2: 268 | C2: 46300.572 | D2: 13 | E2: Sí | F2: Bot | G2: Bot (automático) | H2: bot | I2: Negativo 1 | J2: Negativo | K2: 76.7 | L2: Sí (el mismo para todos) | M2: No | N2: No | P2: Sí | Q2: 1247.6
A3: Core Tools Premium | B3: 286 | C3: 46300.577 | D3: 13 | E3: Sí | F3: Victoria | G3: Persona | H3: asesor | I3: 1.2 Lista de cursos | J3: 1.1 / 1.2 Informes y lista | K3: 97.6 | L3: No | M3: Sí | N3: Sí | O3: 24.9 | P3: Sí | Q3: 26.2
A4: Core Tools Premium | B4: 294 | C4: 46300.703 | D4: 16 | E4: Sí | F4: Bot | G4: Bot (automático) | H4: bot | I4: Negativo 1 | J4: Negativo | K4: 76.7 | L4: Sí (el mismo para todos) | M4: No | N4: Sí | O4: 1482.6 | P4: No
A5: Core Tools Premium | B5: 301 | C5: 46300.726 | D5: 17 | E5: Sí | F5: Bot | G5: Bot (automático) | H5: bot | I5: Negativo 1 | J5: Negativo | K5: 76.7 | L5: Sí (el mismo para todos) | M5: No | N5: Sí | O5: 183.7 | P5: No
A6: Core Tools Premium | B6: 300 | C6: 46300.74 | D6: 17 | E6: Sí | F6: Bot | G6: Bot (automático) | H6: bot | I6: Negativo 1 | J6: Negativo | K6: 76.7 | L6: Sí (el mismo para todos) | M6: No | N6: No | P6: No
A7: Core Tools Premium | B7: 310 | C7: 46300.762 | D7: 18 | E7: Sí | F7: Bot | G7: Bot (automático) | H7: bot | I7: Negativo 1 | J7: Negativo | K7: 76.7 | L7: Sí (el mismo para todos) | M7: No | N7: No | P7: No
A8: Core Tools Premium | B8: 286 | C8: 46300.775 | D8: 18 | E8: Sí | F8: Bot | G8: Bot (automático) | H8: bot | I8: Negativo 1 | J8: Negativo | K8: 76.7 | L8: Sí (el mismo para todos) | M8: No | N8: Sí | O8: 25.2 | P8: Sí | Q8: 1280.2
A9: Core Tools Premium | B9: 343 | C9: 46301.301 | D9: 7 | E9: No | F9: Salma | G9: Persona | H9: asesor | I9: 1.2 Lista de cursos | J9: 1.1 / 1.2 Informes y lista | K9: 118.1 | L9: No | M9: Sí | N9: Sí | O9: 6.8 | P9: Sí | Q9: 146.8
A10: Core Tools Premium | B10: 337 | C10: 46301.375 | D10: 9 | E10: Sí | F10: Bot | G10: Bot (automático) | H10: bot | I10: Negativo 1 | J10: Negativo | K10: 76.7 | L10: Sí (el mismo para todos) | M10: No | N10: Sí | O10: 15.2 | P10: No
A11: Core Tools Premium | B11: 341 | C11: 46301.376 | D11: 9 | E11: Sí | F11: Bot | G11: Bot (automático) | H11: bot | I11: Negativo 1 | J11: Negativo | K11: 76.7 | L11: Sí (el mismo para todos) | M11: No | N11: No | P11: No
A12: Core Tools Premium | B12: 355 | C12: 46301.438 | D12: 10 | E12: Sí | F12: Bot | G12: Bot (automático) | H12: bot | I12: Negativo 1 | J12: Negativo | K12: 76.7 | L12: Sí (el mismo para todos) | M12: No | N12: No | P12: Sí | Q12: 1438.2
A13: Core Tools Premium | B13: 268 | C13: 46301.446 | D13: 10 | E13: Sí | F13: Joceline | G13: Persona | H13: auxiliar | I13: Negativo 1 | J13: Negativo | K13: 70.5 | L13: No | M13: Sí | N13: No | P13: No
A14: Core Tools Premium | B14: 343 | C14: 46301.479 | D14: 11 | E14: Sí | F14: Bot | G14: Bot (automático) | H14: bot | I14: Negativo 1 | J14: Negativo | K14: 76.7 | L14: Sí (el mismo para todos) | M14: No | N14: Sí | O14: 11.9 | P14: No
A15: Core Tools Premium | B15: 371 | C15: 46301.55 | D15: 13 | E15: Sí | F15: Bot | G15: Bot (automático) | H15: bot | I15: Negativo 1 | J15: Negativo | K15: 76.7 | L15: Sí (el mismo para todos) | M15: No | N15: Sí | O15: 113 | P15: No
A16: Core Tools Premium | B16: 373 | C16: 46301.587 | D16: 14 | E16: Sí | F16: Bot | G16: Bot (automático) | H16: bot | I16: Negativo 1 | J16: Negativo | K16: 76.7 | L16: Sí (el mismo para todos) | M16: No | N16: No | P16: No
A17: Core Tools Premium | B17: 449 | C17: 46301.742 | D17: 17 | E17: Sí | F17: Alexander | G17: Persona | H17: asesor | I17: 1.3 Llamadita y facilidad pago | J17: Facilidades de pago (1.3 y 1.4) | K17: 86.5 | L17: No | M17: Sí | N17: Sí | O17: 927.5 | P17: No
A18: Core Tools Premium | B18: 446 | C18: 46301.766 | D18: 18 | E18: Sí | F18: Alexander | G18: Persona | H18: asesor | I18: 1.3 Llamadita y facilidad pago | J18: Facilidades de pago (1.3 y 1.4) | K18: 84.2 | L18: No | M18: Sí | N18: Sí | O18: 4.7 | P18: Sí | Q18: 886
A19: Core Tools Premium | B19: 445 | C19: 46301.813 | D19: 19 | E19: Sí | F19: Bot | G19: Bot (automático) | H19: bot | I19: Negativo 1 | J19: Negativo | K19: 76.7 | L19: Sí (el mismo para todos) | M19: No | N19: No | P19: No
A20: Core Tools Premium | B20: 470 | C20: 46301.85 | D20: 20 | E20: Sí | F20: Victoria | G20: Persona | H20: asesor | I20: 1.2 Lista de cursos | J20: 1.1 / 1.2 Informes y lista | K20: 114.7 | L20: No | M20: Sí | N20: Sí | O20: 0.1 | P20: Sí | Q20: 8.7
A21: Core Tools Premium | B21: 488 | C21: 46301.92 | D21: 22 | E21: No | F21: Victoria | G21: Persona | H21: asesor | I21: 1.3 Llamadita y facilidad pago | J21: Facilidades de pago (1.3 y 1.4) | K21: 94.1 | L21: No | M21: Sí | N21: Sí | O21: 0.1 | P21: Sí | Q21: 715.5
A22: Core Tools Premium | B22: 488 | C22: 46301.921 | D22: 22 | E22: No | F22: Victoria | G22: Persona | H22: asesor | I22: 1.3 Llamadita y facilidad pago | J22: Facilidades de pago (1.3 y 1.4) | K22: 12.7 | L22: No | M22: No | N22: Sí | O22: 0 | P22: Sí | Q22: 714.1
A23: Core Tools Premium | B23: 517 | C23: 46302.375 | D23: 9 | E23: Sí | F23: Bot | G23: Bot (automático) | H23: bot | I23: Negativo 1 | J23: Negativo | K23: 76.7 | L23: Sí (el mismo para todos) | M23: No | N23: Sí | O23: 1460 | P23: No
A24: Core Tools Premium | B24: 470 | C24: 46302.375 | D24: 9 | E24: Sí | F24: Bot | G24: Bot (automático) | H24: bot | I24: Negativo 1 | J24: Negativo | K24: 76.7 | L24: Sí (el mismo para todos) | M24: No | N24: Sí | O24: 2002.9 | P24: No
A25: Core Tools Premium | B25: 446 | C25: 46302.375 | D25: 9 | E25: Sí | F25: Bot | G25: Bot (automático) | H25: bot | I25: Negativo 1 | J25: Negativo | K25: 76.7 | L25: Sí (el mismo para todos) | M25: No | N25: Sí | O25: 7.6 | P25: Sí | Q25: 8.4
A26: Core Tools Premium | B26: 481 | C26: 46302.376 | D26: 9 | E26: Sí | F26: Bot | G26: Bot (automático) | H26: bot | I26: Negativo 1 | J26: Negativo | K26: 76.7 | L26: Sí (el mismo para todos) | M26: No | N26: Sí | O26: 4885 | P26: No
A27: Core Tools Premium | B27: 488 | C27: 46302.376 | D27: 9 | E27: Sí | F27: Bot | G27: Bot (automático) | H27: bot | I27: Negativo 1 | J27: Negativo | K27: 76.7 | L27: Sí (el mismo para todos) | M27: No | N27: Sí | O27: 59.3 | P27: Sí | Q27: 60
A28: Core Tools Premium | B28: 493 | C28: 46302.376 | D28: 9 | E28: Sí | F28: Bot | G28: Bot (automático) | H28: bot | I28: Negativo 1 | J28: Negativo | K28: 76.7 | L28: Sí (el mismo para todos) | M28: No | N28: No | P28: No
A29: Core Tools Premium | B29: 449 | C29: 46302.376 | D29: 9 | E29: Sí | F29: Bot | G29: Bot (automático) | H29: bot | I29: Negativo 1 | J29: Negativo | K29: 76.7 | L29: Sí (el mismo para todos) | M29: No | N29: Sí | O29: 15.6 | P29: No
A30: Core Tools Premium | B30: 497 | C30: 46302.378 | D30: 9 | E30: Sí | F30: Bot | G30: Bot (automático) | H30: bot | I30: Negativo 1 | J30: Negativo | K30: 76.7 | L30: Sí (el mismo para todos) | M30: No | N30: Sí | O30: 4.3 | P30: No
A31: Core Tools Premium | B31: 508 | C31: 46302.379 | D31: 9 | E31: Sí | F31: Bot | G31: Bot (automático) | H31: bot | I31: Negativo 1 | J31: Negativo | K31: 76.7 | L31: Sí (el mismo para todos) | M31: No | N31: No | P31: No
A32: Core Tools Premium | B32: 545 | C32: 46302.46 | D32: 11 | E32: Sí | F32: Bot | G32: Bot (automático) | H32: bot | I32: Negativo 1 | J32: Negativo | K32: 76.7 | L32: Sí (el mismo para todos) | M32: No | N32: Sí | O32: 100.1 | P32: Sí | Q32: 100.7
A33: Core Tools Premium | B33: 565 | C33: 46302.521 | D33: 12 | E33: Sí | F33: Bot | G33: Bot (automático) | H33: bot | I33: Negativo 1 | J33: Negativo | K33: 76.7 | L33: Sí (el mismo para todos) | M33: No | N33: No | P33: No
A34: Core Tools Premium | B34: 545 | C34: 46302.562 | D34: 13 | E34: Sí | F34: Salma | G34: Persona | H34: asesor | I34: 1.2 Lista de cursos | J34: 1.1 / 1.2 Informes y lista | K34: 104.3 | L34: No | M34: Sí | N34: Sí | O34: 1338.6 | P34: Sí | Q34: 1348
A35: Core Tools Premium | B35: 589 | C35: 46302.6 | D35: 14 | E35: Sí | F35: Bot | G35: Bot (automático) | H35: bot | I35: Negativo 1 | J35: Negativo | K35: 76.7 | L35: Sí (el mismo para todos) | M35: No | N35: Sí | O35: 312 | P35: No
A36: Core Tools Premium | B36: 634 | C36: 46302.623 | D36: 14 | E36: Sí | F36: Salma | G36: Persona | H36: asesor | I36: 1.2 Lista de cursos | J36: 1.1 / 1.2 Informes y lista | K36: 137 | L36: No | M36: Sí | N36: Sí | O36: 4.2 | P36: Sí | Q36: 6.8
A37: Core Tools Premium | B37: 602 | C37: 46302.641 | D37: 15 | E37: Sí | F37: Bot | G37: Bot (automático) | H37: bot | I37: Negativo 1 | J37: Negativo | K37: 76.7 | L37: Sí (el mismo para todos) | M37: No | N37: Sí | O37: 88.2 | P37: No
A38: Core Tools Premium | B38: 646 | C38: 46302.765 | D38: 18 | E38: Sí | F38: Bot | G38: Bot (automático) | H38: bot | I38: Negativo 1 | J38: Negativo | K38: 76.7 | L38: Sí (el mismo para todos) | M38: No | N38: No | P38: No
A39: Core Tools Premium | B39: 634 | C39: 46302.801 | D39: 19 | E39: Sí | F39: Bot | G39: Bot (automático) | H39: bot | I39: Negativo 1 | J39: Negativo | K39: 76.7 | L39: Sí (el mismo para todos) | M39: No | N39: Sí | O39: 863.1 | P39: No
A40: Core Tools Premium | B40: 712 | C40: 46302.873 | D40: 20 | E40: Sí | F40: Victoria | G40: Persona | H40: asesor | I40: 1.2 Lista de cursos | J40: 1.1 / 1.2 Informes y lista | K40: 83 | L40: No | M40: Sí | N40: No | P40: No
A41: Core Tools Premium | B41: 729 | C41: 46302.901 | D41: 21 | E41: Sí | F41: Alexander | G41: Persona | H41: asesor | I41: 1.3 Llamadita y facilidad pago | J41: Facilidades de pago (1.3 y 1.4) | K41: 76.7 | L41: No | M41: Sí | N41: Sí | O41: 18.9 | P41: Sí | Q41: 20.4
A42: Core Tools Premium | B42: 738 | C42: 46303.306 | D42: 7 | E42: No | F42: Salma | G42: Persona | H42: asesor | I42: Negativo 1 | J42: Negativo | K42: 106.6 | L42: No | M42: Sí | N42: No | P42: No
A43: Core Tools Premium | B43: 753 | C43: 46303.311 | D43: 7 | E43: No | F43: Salma | G43: Persona | H43: asesor | I43: 1.2 Lista de cursos | J43: 1.1 / 1.2 Informes y lista | K43: 57 | L43: Sí | M43: No | N43: No | P43: No
A44: Core Tools Premium | B44: 712 | C44: 46303.375 | D44: 9 | E44: Sí | F44: Bot | G44: Bot (automático) | H44: bot | I44: Negativo 1 | J44: Negativo | K44: 76.7 | L44: Sí (el mismo para todos) | M44: No | N44: No | P44: No
A45: Core Tools Premium | B45: 760 | C45: 46303.375 | D45: 9 | E45: Sí | F45: Bot | G45: Bot (automático) | H45: bot | I45: Negativo 1 | J45: Negativo | K45: 76.7 | L45: Sí (el mismo para todos) | M45: No | N45: No | P45: No
A46: Core Tools Premium | B46: 729 | C46: 46303.375 | D46: 9 | E46: Sí | F46: Bot | G46: Bot (automático) | H46: bot | I46: Negativo 1 | J46: Negativo | K46: 76.7 | L46: Sí (el mismo para todos) | M46: No | N46: Sí | O46: 292.5 | P46: No
A47: Core Tools Premium | B47: 701 | C47: 46303.376 | D47: 9 | E47: Sí | F47: Bot | G47: Bot (automático) | H47: bot | I47: Negativo 1 | J47: Negativo | K47: 76.7 | L47: Sí (el mismo para todos) | M47: No | N47: Sí | O47: 1735.1 | P47: No
A48: Core Tools Premium | B48: 753 | C48: 46303.396 | D48: 9 | E48: Sí | F48: Bot | G48: Bot (automático) | H48: bot | I48: Negativo 1 | J48: Negativo | K48: 76.7 | L48: Sí (el mismo para todos) | M48: No | N48: No | P48: No
A49: Core Tools Premium | B49: 738 | C49: 46303.483 | D49: 11 | E49: Sí | F49: Bot | G49: Bot (automático) | H49: bot | I49: Negativo 1 | J49: Negativo | K49: 76.7 | L49: Sí (el mismo para todos) | M49: No | N49: No | P49: No
A50: Core Tools Premium | B50: 802 | C50: 46303.485 | D50: 11 | E50: Sí | F50: Bot | G50: Bot (automático) | H50: bot | I50: Negativo 1 | J50: Negativo | K50: 76.7 | L50: Sí (el mismo para todos) | M50: No | N50: Sí | O50: 10.3 | P50: No
A51: Core Tools Premium | B51: 828 | C51: 46303.538 | D51: 12 | E51: Sí | F51: Bot | G51: Bot (automático) | H51: bot | I51: Negativo 1 | J51: Negativo | K51: 76.7 | L51: Sí (el mismo para todos) | M51: No | N51: No | P51: No
A52: Core Tools Premium | B52: 833 | C52: 46303.551 | D52: 13 | E52: Sí | F52: Bot | G52: Bot (automático) | H52: bot | I52: Negativo 1 | J52: Negativo | K52: 76.7 | L52: Sí (el mismo para todos) | M52: No | N52: Sí | O52: 0.6 | P52: No
A53: Core Tools Premium | B53: 842 | C53: 46303.596 | D53: 14 | E53: Sí | F53: Bot | G53: Bot (automático) | H53: bot | I53: Negativo 1 | J53: Negativo | K53: 76.7 | L53: Sí (el mismo para todos) | M53: No | N53: Sí | O53: 0.7 | P53: No
A54: Core Tools Premium | B54: 864 | C54: 46303.672 | D54: 16 | E54: Sí | F54: Bot | G54: Bot (automático) | H54: bot | I54: Negativo 1 | J54: Negativo | K54: 76.7 | L54: Sí (el mismo para todos) | M54: No | N54: No | P54: No
A55: Core Tools Premium | B55: 877 | C55: 46303.692 | D55: 16 | E55: Sí | F55: Bot | G55: Bot (automático) | H55: bot | I55: Negativo 1 | J55: Negativo | K55: 76.7 | L55: Sí (el mismo para todos) | M55: No | N55: Sí | O55: 101.9 | P55: No
A56: Core Tools Premium | B56: 909 | C56: 46303.834 | D56: 20 | E56: Sí | F56: Bot | G56: Bot (automático) | H56: bot | I56: Negativo 1 | J56: Negativo | K56: 76.7 | L56: Sí (el mismo para todos) | M56: No | N56: No | P56: No
A57: Core Tools Premium | B57: 992 | C57: 46304.355 | D57: 8 | E57: Sí | F57: Joceline | G57: Persona | H57: auxiliar | I57: 1.2 Lista de cursos | J57: 1.1 / 1.2 Informes y lista | K57: 105 | L57: No | M57: Sí | N57: Sí | O57: 1739.6 | P57: No
A58: Core Tools Premium | B58: 960 | C58: 46304.375 | D58: 9 | E58: Sí | F58: Bot | G58: Bot (automático) | H58: bot | I58: Negativo 1 | J58: Negativo | K58: 76.7 | L58: Sí (el mismo para todos) | M58: No | N58: No | P58: No
A59: Core Tools Premium | B59: 925 | C59: 46304.376 | D59: 9 | E59: Sí | F59: Bot | G59: Bot (automático) | H59: bot | I59: Negativo 1 | J59: Negativo | K59: 76.7 | L59: Sí (el mismo para todos) | M59: No | N59: No | P59: No
A60: Core Tools Premium | B60: 992 | C60: 46304.431 | D60: 10 | E60: Sí | F60: Bot | G60: Bot (automático) | H60: bot | I60: Negativo 1 | J60: Negativo | K60: 76.7 | L60: Sí (el mismo para todos) | M60: No | N60: Sí | O60: 1629.3 | P60: No
A61: Core Tools Premium | B61: 1018 | C61: 46304.475 | D61: 11 | E61: Sí | F61: Salma | G61: Persona | H61: asesor | I61: 1.2 Lista de cursos | J61: 1.1 / 1.2 Informes y lista | K61: 107.3 | L61: No | M61: Sí | N61: Sí | O61: 0.4 | P61: Sí | Q61: 3.1
A62: Core Tools Premium | B62: 1008 | C62: 46304.535 | D62: 12 | E62: Sí | F62: Bot | G62: Bot (automático) | H62: bot | I62: Negativo 1 | J62: Negativo | K62: 76.7 | L62: Sí (el mismo para todos) | M62: No | N62: No | P62: No
A63: Core Tools Premium | B63: 1037 | C63: 46304.62 | D63: 14 | E63: Sí | F63: Bot | G63: Bot (automático) | H63: bot | I63: Negativo 1 | J63: Negativo | K63: 76.7 | L63: Sí (el mismo para todos) | M63: No | N63: No | P63: No
A64: Core Tools Premium | B64: 1038 | C64: 46304.65 | D64: 15 | E64: Sí | F64: Bot | G64: Bot (automático) | H64: bot | I64: Negativo 1 | J64: Negativo | K64: 76.7 | L64: Sí (el mismo para todos) | M64: No | N64: Sí | O64: 1638.3 | P64: No
A65: Core Tools Premium | B65: 1018 | C65: 46304.653 | D65: 15 | E65: Sí | F65: Bot | G65: Bot (automático) | H65: bot | I65: Negativo 1 | J65: Negativo | K65: 76.7 | L65: Sí (el mismo para todos) | M65: No | N65: Sí | O65: 25 | P65: No
A66: Core Tools Premium | B66: 1075 | C66: 46304.718 | D66: 17 | E66: Sí | F66: Alexander | G66: Persona | H66: asesor | I66: 1.3 Llamadita y facilidad pago | J66: Facilidades de pago (1.3 y 1.4) | K66: 91.2 | L66: No | M66: Sí | N66: Sí | O66: 10.2 | P66: No
A67: Core Tools Premium | B67: 1086 | C67: 46304.844 | D67: 20 | E67: Sí | F67: Bot | G67: Bot (automático) | H67: bot | I67: Negativo 1 | J67: Negativo | K67: 76.7 | L67: Sí (el mismo para todos) | M67: No | N67: No | P67: No
A68: Core Tools Premium | B68: 1113 | C68: 46304.881 | D68: 21 | E68: Sí | F68: Alexander | G68: Persona | H68: asesor | I68: 1.3 Llamadita y facilidad pago | J68: Facilidades de pago (1.3 y 1.4) | K68: 77.8 | L68: No | M68: Sí | N68: Sí | O68: 0.7 | P68: Sí | Q68: 1.6
A69: Core Tools Premium | B69: 1134 | C69: 46305.355 | D69: 8 | E69: Sí | F69: Joceline | G69: Persona | H69: auxiliar | I69: 1.2 Lista de cursos | J69: 1.1 / 1.2 Informes y lista | K69: 98.3 | L69: No | M69: Sí | N69: No | P69: Sí | Q69: 4.6
A70: Core Tools Premium | B70: 1075 | C70: 46305.376 | D70: 9 | E70: Sí | F70: Bot | G70: Bot (automático) | H70: bot | I70: Negativo 1 | J70: Negativo | K70: 76.7 | L70: Sí (el mismo para todos) | M70: No | N70: Sí | O70: 311.1 | P70: No
A71: Core Tools Premium | B71: 1113 | C71: 46305.376 | D71: 9 | E71: Sí | F71: Bot | G71: Bot (automático) | H71: bot | I71: Negativo 1 | J71: Negativo | K71: 76.7 | L71: Sí (el mismo para todos) | M71: No | N71: Sí | O71: 30.4 | P71: Sí | Q71: 426.8
A72: Core Tools Premium | B72: 1136 | C72: 46305.413 | D72: 9 | E72: Sí | F72: Bot | G72: Bot (automático) | H72: bot | I72: Negativo 1 | J72: Negativo | K72: 76.7 | L72: Sí (el mismo para todos) | M72: No | N72: No | P72: No
A73: Core Tools Premium | B73: 446 | C73: 46305.422 | D73: 10 | E73: Sí | F73: Joceline | G73: Persona | H73: auxiliar | I73: Negativo 1 | J73: Negativo | K73: 46.5 | L73: No | M73: No | N73: Sí | O73: 0.3 | P73: No
A74: Core Tools Premium | B74: 1159 | C74: 46305.46 | D74: 11 | E74: Sí | F74: Bot | G74: Bot (automático) | H74: bot | I74: Negativo 1 | J74: Negativo | K74: 76.7 | L74: Sí (el mismo para todos) | M74: No | N74: Sí | O74: 126.9 | P74: No
A75: Core Tools Premium | B75: 1215 | C75: 46305.844 | D75: 20 | E75: Sí | F75: Bot | G75: Bot (automático) | H75: bot | I75: Negativo 1 | J75: Negativo | K75: 76.7 | L75: Sí (el mismo para todos) | M75: No | N75: Sí | O75: 2451.1 | P75: No
A76: Core Tools Premium | B76: 1226 | C76: 46305.87 | D76: 20 | E76: Sí | F76: Bot | G76: Bot (automático) | H76: bot | I76: Negativo 1 | J76: Negativo | K76: 76.7 | L76: Sí (el mismo para todos) | M76: No | N76: Sí | O76: 94.3 | P76: No
A77: Core Tools Premium | B77: 1236 | C77: 46306.375 | D77: 9 | E77: Sí | F77: Bot | G77: Bot (automático) | H77: bot | I77: Negativo 1 | J77: Negativo | K77: 76.7 | L77: Sí (el mismo para todos) | M77: No | N77: No | P77: No
A78: Core Tools Premium | B78: 1313 | C78: 46306.647 | D78: 15 | E78: Sí | F78: Salma | G78: Persona | H78: asesor | I78: 1.2 Lista de cursos | J78: 1.1 / 1.2 Informes y lista | K78: 103.6 | L78: No | M78: Sí | N78: Sí | O78: 2874.9 | P78: No
A79: Core Tools Premium | B79: 1318 | C79: 46306.677 | D79: 16 | E79: Sí | F79: Salma | G79: Persona | H79: asesor | I79: 1.2 Lista de cursos | J79: 1.1 / 1.2 Informes y lista | K79: 100.4 | L79: No | M79: Sí | N79: Sí | O79: 205.4 | P79: Sí | Q79: 207.9
A80: Core Tools Premium | B80: 1326 | C80: 46306.706 | D80: 16 | E80: Sí | F80: Victoria | G80: Persona | H80: asesor | I80: 1.2 Lista de cursos | J80: 1.1 / 1.2 Informes y lista | K80: 103.6 | L80: No | M80: Sí | N80: No | P80: No
A81: Core Tools Premium | B81: 1328 | C81: 46306.721 | D81: 17 | E81: Sí | F81: Victoria | G81: Persona | H81: asesor | I81: 1.2 Lista de cursos | J81: 1.1 / 1.2 Informes y lista | K81: 106.4 | L81: No | M81: Sí | N81: No | P81: Sí | Q81: 1.3
A82: Core Tools Premium | B82: 1311 | C82: 46306.725 | D82: 17 | E82: Sí | F82: Bot | G82: Bot (automático) | H82: bot | I82: Negativo 1 | J82: Negativo | K82: 76.7 | L82: Sí (el mismo para todos) | M82: No | N82: Sí | O82: 106.7 | P82: No
A83: Core Tools Premium | B83: 1335 | C83: 46306.747 | D83: 17 | E83: Sí | F83: Victoria | G83: Persona | H83: asesor | I83: 1.2 Lista de cursos | J83: 1.1 / 1.2 Informes y lista | K83: 99.8 | L83: No | M83: Sí | N83: No | P83: Sí | Q83: 10.3
A84: Core Tools Premium | B84: 1313 | C84: 46306.824 | D84: 19 | E84: Sí | F84: Bot | G84: Bot (automático) | H84: bot | I84: Negativo 1 | J84: Negativo | K84: 76.7 | L84: Sí (el mismo para todos) | M84: No | N84: Sí | O84: 2619.6 | P84: No
A85: Core Tools Premium | B85: 1318 | C85: 46306.855 | D85: 20 | E85: Sí | F85: Bot | G85: Bot (automático) | H85: bot | I85: Negativo 1 | J85: Negativo | K85: 76.7 | L85: Sí (el mismo para todos) | M85: No | N85: Sí | O85: 9.5 | P85: No
A86: Core Tools Premium | B86: 1328 | C86: 46306.863 | D86: 20 | E86: Sí | F86: Bot | G86: Bot (automático) | H86: bot | I86: Negativo 1 | J86: Negativo | K86: 76.7 | L86: Sí (el mismo para todos) | M86: No | N86: No | P86: No
A87: Core Tools Premium | B87: 1353 | C87: 46307.375 | D87: 9 | E87: Sí | F87: Bot | G87: Bot (automático) | H87: bot | I87: Negativo 1 | J87: Negativo | K87: 76.7 | L87: Sí (el mismo para todos) | M87: No | N87: Sí | O87: 36.8 | P87: No
A88: Core Tools Premium | B88: 1372 | C88: 46307.375 | D88: 9 | E88: Sí | F88: Bot | G88: Bot (automático) | H88: bot | I88: Negativo 1 | J88: Negativo | K88: 76.7 | L88: Sí (el mismo para todos) | M88: No | N88: Sí | O88: 5.5 | P88: No
A89: Core Tools Premium | B89: 1326 | C89: 46307.376 | D89: 9 | E89: Sí | F89: Bot | G89: Bot (automático) | H89: bot | I89: Negativo 1 | J89: Negativo | K89: 76.7 | L89: Sí (el mismo para todos) | M89: No | N89: No | P89: No
A90: Core Tools Premium | B90: 1335 | C90: 46307.376 | D90: 9 | E90: Sí | F90: Bot | G90: Bot (automático) | H90: bot | I90: Negativo 1 | J90: Negativo | K90: 76.7 | L90: Sí (el mismo para todos) | M90: No | N90: No | P90: Sí | Q90: 153.7
A91: Core Tools Premium | B91: 1497 | C91: 46307.632 | D91: 15 | E91: Sí | F91: Alexander | G91: Persona | H91: asesor | I91: 1.2 Lista de cursos | J91: 1.1 / 1.2 Informes y lista | K91: 77.2 | L91: No | M91: Sí | N91: Sí | O91: 0.6 | P91: Sí | Q91: 2.2
A92: Core Tools Premium | B92: 1482 | C92: 46307.656 | D92: 15 | E92: Sí | F92: Bot | G92: Bot (automático) | H92: bot | I92: Negativo 1 | J92: Negativo | K92: 76.7 | L92: Sí (el mismo para todos) | M92: No | N92: No | P92: No
A93: Core Tools Premium | B93: 1477 | C93: 46307.67 | D93: 16 | E93: Sí | F93: Bot | G93: Bot (automático) | H93: bot | I93: Negativo 1 | J93: Negativo | K93: 76.7 | L93: Sí (el mismo para todos) | M93: No | N93: Sí | O93: 0.2 | P93: No
A94: Core Tools Premium | B94: 1554 | C94: 46307.823 | D94: 19 | E94: Sí | F94: Alexander | G94: Persona | H94: asesor | I94: 1.2 Lista de cursos | J94: 1.1 / 1.2 Informes y lista | K94: 80.6 | L94: No | M94: Sí | N94: Sí | O94: 0.4 | P94: No
A95: Core Tools Premium | B95: 1536 | C95: 46307.867 | D95: 20 | E95: Sí | F95: Bot | G95: Bot (automático) | H95: bot | I95: Negativo 1 | J95: Negativo | K95: 76.7 | L95: Sí (el mismo para todos) | M95: No | N95: Sí | O95: 875.7 | P95: No
A96: Core Tools Premium | B96: 1576 | C96: 46307.914 | D96: 21 | E96: Sí | F96: Alexander | G96: Persona | H96: asesor | I96: 1.2 Lista de cursos | J96: 1.1 / 1.2 Informes y lista | K96: 82.1 | L96: No | M96: Sí | N96: Sí | O96: 4.4 | P96: Sí | Q96: 11.5
A97: Core Tools Premium | B97: 1592 | C97: 46308.301 | D97: 7 | E97: No | F97: Salma | G97: Persona | H97: asesor | I97: Negativo 1 | J97: Negativo | K97: 114.7 | L97: No | M97: Sí | N97: Sí | O97: 453.5 | P97: No
A98: Core Tools Premium | B98: 1554 | C98: 46308.375 | D98: 9 | E98: Sí | F98: Bot | G98: Bot (automático) | H98: bot | I98: Negativo 1 | J98: Negativo | K98: 76.7 | L98: Sí (el mismo para todos) | M98: No | N98: Sí | O98: 29.8 | P98: No
A99: Core Tools Premium | B99: 1584 | C99: 46308.375 | D99: 9 | E99: Sí | F99: Bot | G99: Bot (automático) | H99: bot | I99: Negativo 1 | J99: Negativo | K99: 76.7 | L99: Sí (el mismo para todos) | M99: No | N99: Sí | O99: 79.8 | P99: No
A100: Core Tools Premium | B100: 1576 | C100: 46308.376 | D100: 9 | E100: Sí | F100: Bot | G100: Bot (automático) | H100: bot | I100: Negativo 1 | J100: Negativo | K100: 76.7 | L100: Sí (el mismo para todos) | M100: No | N100: Sí | O100: 39.6 | P100: No
...

Sheet Notas
A1: DESARROLLO PROFESIONAL SyS
A2: Notas y definiciones
A3: Cómo se midió cada dato
A5: Período y corte | B5: Leads de ISO + Calidad, Manufactura y Calidad y Core Tools Premium a los que el bot les hizo la pregunta del paso 1.2 entre el 5 y el 15 de octubre de 2026. Todo se mide hasta el 15 de octubre a las 23:59 h (Monterrey). Son los mismos leads de los libros de línea base (As Is).
A6: La pregunta | B6: «Solo una pregunta, ¿en qué área trabajas actualmente? o ¿estás estudiando?», que manda el bot en 1.2 Lista de cursos. Si nadie mueve al lead, el bot lo pasa a Negativo 2 h después.
A7: Contestó la pregunta | B7: «Sí» = en 24 h dijo su área o que estudia (agrupado por palabras en la columna Perfil). «Respondió otra cosa» = escribió en 24 h pero no su perfil (una duda, el precio, «gracias»). «No» = no escribió en 24 h. En la muestra anterior «Respondió otra cosa» se contaba dentro de «No».
A8: Vio la pregunta o el audio | B8: Palomitas azules de WhatsApp antes del corte. En un audio no garantiza que lo haya escuchado completo.
A9: Recomendación | B9: La primera nota de voz de una persona en las 24 h siguientes a la respuesta del lead. Si no hubo audio, el primer mensaje de una persona. «Qué se envió» resume los mensajes de las personas hasta 30 min después: aviso («te mando un audio»), audio y cursos (links a academy.dpsys.com.mx).
A10: Minutos | B10: Minutos de reloj, con fórmula sobre las horas de la pestaña Detalle por lead. «Del aviso al audio» = del «te mando un audio» al audio (grabarlo y subirlo).
A11: Respondió después | B11: El lead escribió algo después de la recomendación, hasta el corte. «Paso al que se mandó» = el primer cambio de etapa después de esa respuesta y quién lo hizo.
A12: El bot lo pasó a Negativo | B12: Movimiento automático (no manual) a la etapa Negativo del embudo después de la recomendación o después de que el lead respondió. «Horas desde su último mensaje» se mide contra el último mensaje del lead antes de ese movimiento.
A13: Duración del audio | B13: Medida sobre cada archivo de audio (ffprobe). «Reutilizado» = el mismo archivo se mandó a más de un lead.
A14: Audios del equipo | B14: Todas las notas de voz de personas y el audio automático del bot (uno por embudo, al entrar a Negativo) del período, con lo que hizo el lead en las 24 h siguientes.
A15: Hora | B15: Hora de Monterrey (central de México). Se usa la ventana de 8:00 a antes de 22:00 de la muestra anterior.
A16: Ganado | B16: Lead en la etapa Ganado al corte.
... A19: Límites | B19: Pocos ganados: un solo caso mueve mucho los porcentajes. Las diferencias por tiempo de respuesta todavía no son concluyentes. Las relaciones entre audio y respuesta no prueban causa.

Sheet Fuente de datos
A1: Escrito en | B1: Fuente | C1: Objeto | D1: Obtenido con | E1: Consulta | F1: Parámetros | G1: Leído | H1: Pedido por | I1: Renglones | J1: Cambios después de leerlo | K1: Notas
A2: 'Detalle por lead'!A1:AK616 | B2: CRM SyS | C2: crm-web-production-3b33.up.railway.app: /embudos, /embudos/:id/tablero, /conversaciones/:id, /conversaciones/:id/mensajes, /conversaciones/:id/movimientos, /equipo, /archivos/:id | D2: Leído por Claude con la API del CRM, solo consultas de lectura (GET), con la cuenta de Joceline (vendedor, eje Cursos) | E2: Paso 1.2 de los tres embudos: respuesta a «¿en qué área trabajas?», recomendación con audio del equipo y lo que pasó después | F2: Embudos ISO + Calidad, Manufactura y Calidad y Core Tools Premium; leads con la pregunta del 5 al 15 de oct 2026; corte 15 oct 23:59 h | G2: 16 oct 2026 (hora de Monterrey) | H2: Rosbel | I2: 615 | J2: Una fila por lead; perfil agrupado por palabras; textos con correos y teléfonos ocultos; duración de audios con ffprobe | K2: Actualiza la hoja «Analisis_Muestra_SyS» (Manufactura, 5 al 12 oct, 70 leads).
A3: 'Detalle de audios'!A1:Q810 | B3: CRM SyS | C3: crm-web-production-3b33.up.railway.app: /embudos, /embudos/:id/tablero, /conversaciones/:id, /conversaciones/:id/mensajes, /conversaciones/:id/movimientos, /equipo, /archivos/:id | D3: Leído por Claude con la API del CRM, solo consultas de lectura (GET), con la cuenta de Joceline (vendedor, eje Cursos) | E3: Todas las notas de voz de personas y el audio automático del bot en los tres embudos | F3: Mismos leads y corte | G3: 16 oct 2026 (hora de Monterrey) | H3: Rosbel | I3: 809 | J3: Una fila por audio; duración con ffprobe
