Workbook

Sheet Resumen
B1: DESARROLLO PROFESIONAL SyS
B2: Línea base (As Is) · Embudo ISO + Calidad
B3: CRM · 407 leads del 5 al 15 de octubre de 2026 · corte: 15 oct 2026, 23:59 h (Monterrey) · medido en solo lectura, sin mover ni enviar nada
B5: Los números
B6: Qué medimos | C6: Valor | D6: Cómo leerlo
B7: Leads que entraron | C7: =COUNT(Datos!$B$2:$B$408) -> 407 | D7: Del 5 al 15 de octubre de 2026. Semana completa del 5 al 11 y 4 días de la siguiente.
B8: Contestaron el saludo | C8: =IFERROR(COUNTIFS(Datos!$G$2:$G$408,"Sí")/COUNT(Datos!$B$2:$B$408),"—") -> 0.62899263 | D8: Escribieron después de que el bot pidió el nombre.
B9: Dejaron de escribir en el saludo o antes | C9: =IFERROR((COUNTIFS(Datos!$AJ$2:$AJ$408,"Solo su primer mensaje")+COUNTIFS(Datos!$AJ$2:$AJ$408,"Saludo: contestó y no volvió"))/COUNT(Datos!$B$2:$B$408),"—") -> 0.5012285 | D9: La caída más grande del embudo.
B10: Llegaron a facilidades de pago | C10: =IFERROR(COUNTIFS(Datos!$P$2:$P$408,"Sí")/COUNT(Datos!$B$2:$B$408),"—") -> 0.34152334 | D10: Etapa 1.3 o más lejos.
B11: Recibieron al menos una oferta | C11: =IFERROR(COUNTIFS(Datos!$Z$2:$Z$408,"Sí")/COUNT(Datos!$B$2:$B$408),"—") -> 0.86486486 | D11: $3,799, $3,400, $2,799 o $1,950.
B12: Primeras ofertas que manda el bot | C12: =IFERROR(COUNTIFS(Datos!$AB$2:$AB$408,"Bot")/COUNTIFS(Datos!$Z$2:$Z$408,"Sí"),"—") -> 0.79261364 | D12: Por tiempo, no por lo que dice el lead.
B13: Entraron fuera de horario (antes de 9 h o desde 21 h) | C13: =IFERROR(COUNTIFS(Datos!$F$2:$F$408,"No")/COUNT(Datos!$B$2:$B$408),"—") -> 0.25061425 | D13: El equipo en la práctica atiende de 7 a 22 h.
B14: Horas hasta el 1er mensaje de una persona (mediana) | C14: =IFERROR(MEDIAN(Datos!$T$2:$T$408)/60,"—") -> 7.4916667 | D14: Mover de etapa llega en minutos; el primer mensaje escrito, no.
B15: Nunca recibieron un mensaje de una persona | C15: =IFERROR(COUNTBLANK(Datos!$T$2:$T$408)/COUNT(Datos!$B$2:$B$408),"—") -> 0.12530713 | D15: Hasta el corte, solo les escribió el bot.
B16: Leads donde intervino auxiliar | C16: =IFERROR(COUNTIFS(Datos!$S$2:$S$408,"Sí")/COUNT(Datos!$B$2:$B$408),"—") -> 0.51351351 | D16: Escribió o movió de etapa al lead.
B17: Ventas | C17: =COUNTIFS(Datos!$AQ$2:$AQ$408,"Sí") -> 10 | D17: Leads en la etapa Ganado al corte.
B18: Conversión (ventas ÷ leads) | C18: =IFERROR(COUNTIFS(Datos!$AQ$2:$AQ$408,"Sí")/COUNT(Datos!$B$2:$B$408),"—") -> 0.024570025
B19: Ventas a precio de lista ($3,999 o más) | C19: =COUNTIFS(Datos!$AQ$2:$AQ$408,"Sí",Datos!$AR$2:$AR$408,">=3999") -> 2 | D19: El resto fueron con descuento.
B20: Precio promedio de venta | C20: =IFERROR(AVERAGEIFS(Datos!$AR$2:$AR$408,Datos!$AQ$2:$AQ$408,"Sí"),"—") -> 3239 | D20: Precio de lista: $3,999.
B21: Leads abiertos al corte | C21: =COUNTIFS(Datos!$AK$2:$AK$408,"Abierto") -> 123 | D21: Todavía pueden avanzar; sobre todo los de la última semana.
B23: Lo más importante
B24: • La mitad de los leads (50%) deja de escribir en el saludo o antes.
B25: • Si el lead contesta el saludo (63%), el bot se detiene y espera a que una persona lo mueva; 29 leads esperaron más de 1 hora.
B26: • El primer mensaje de una persona tarda 7.5 h (mediana); 13% de los leads nunca recibe uno.
B27: • El bot manda las ofertas por tiempo: la primera llega a las 31.6 h (mediana) y el 86% recibe al menos una.
B28: • 10 ventas (2.5%); 8 con descuento y 2 a precio de lista. Precio promedio $3,239.
B29: • Quien abre un link compra 6.7% contra 1.0% de quien no lo abre, y esa señal no detona ninguna acción.
B31: Puntos a mejorar
B32: Punto | C32: Dato | D32: Qué muestra el dato
B33: 1 · La mitad deja de escribir en el saludo o antes | C33: =IFERROR((COUNTIFS(Datos!$AJ$2:$AJ$408,"Solo su primer mensaje")+COUNTIFS(Datos!$AJ$2:$AJ$408,"Saludo: contestó y no volvió"))/COUNT(Datos!$B$2:$B$408),"—") -> 0.5012285 | D33: 27% solo mandó su primer mensaje y 24% contestó el saludo (casi siempre su nombre) y ya no volvió a escribir. Es la caída más grande del embudo.
B34: 2 · Si el lead contesta el saludo, el bot se detiene y espera a una persona | C34: =COUNTIFS(Datos!$J$2:$J$408,">60") -> 29 | D34: Leads que esperaron más de 1 hora para pasar a 1.1. Contesta el 63% y casi siempre lo mueve una persona: en horario tarda 0.5 min (mediana); fuera de horario, 18.4 min, y quien escribe de noche espera hasta la mañana.
B35: 3 · El primer mensaje de una persona llega tarde | C35: =IFERROR(MEDIAN(Datos!$T$2:$T$408)/60,"—") -> 7.4916667 | D35: Horas (mediana). Una persona mueve al lead en 5.3 min, pero su primer mensaje escrito tarda 7.5 h; 36% lo recibe después de 1 día y 13% nunca. Con mensaje en la 1.ª hora compra el 4.8%; después de 1 día, el 0.7% (relación, no causa).
B36: 4 · Las ofertas salen por tiempo y casi todo se vende con descuento | C36: =IFERROR(COUNTIFS(Datos!$AQ$2:$AQ$408,"Sí",Datos!$AR$2:$AR$408,"<3999")/COUNTIFS(Datos!$AQ$2:$AQ$408,"Sí"),"—") -> 0.8 | D36: Ventas con descuento. El 86% recibe al menos una oferta y el bot manda el 79% de las primeras, a las 31.6 h (mediana) de entrar, conteste o no. De 10 ventas, 8 fueron con descuento; precio promedio $3,239 contra $3,999 de lista.
B37: 5 · Los leads que piden cómo pagar se enfrían | C37: =IFERROR(COUNTIFS(Datos!$P$2:$P$408,"Sí",Datos!$AQ$2:$AQ$408,"Sí")/COUNTIFS(Datos!$P$2:$P$408,"Sí"),"—") -> 0.071942446 | D37: Compran de los que llegan a facilidades de pago. 139 leads (34%) llegaron a 1.3 o más lejos y 10 compraron; 56 dejaron de escribir ya en facilidades o en forma de pago.
B38: 6 · La pregunta de ocupación casi no se contesta y no cambia el flujo | C38: =IFERROR(COUNTIFS(Datos!$L$2:$L$408,"Sí",Datos!$M$2:$M$408,"Sí")/COUNTIFS(Datos!$L$2:$L$408,"Sí"),"—") -> 0.39012346 | D38: Contestan su área en 24 h. El bot sigue igual para todos: 2 h después de preguntar pasa al lead a Negativo, haya contestado o no.
B39: 7 · Las señales de interés no detonan una acción | C39: =IFERROR(COUNTIFS(Datos!$AG$2:$AG$408,"Sí",Datos!$AQ$2:$AQ$408,"Sí")/COUNTIFS(Datos!$AG$2:$AG$408,"Sí"),"—") -> 0.066666667 | D39: Compran de los que abren un link. El 26% abrió su ruta, la clase demo o el mapa; de ellos compra el 6.7%, contra 1.0% de los que no. El CRM solo lo deja como nota interna.
B40: 8 · Los Perdidos se cierran a mano y sin diagnóstico | C40: =IFERROR(COUNTIFS(Datos!$AM$2:$AM$408,"No contestaron")/COUNTIFS(Datos!$AK$2:$AK$408,"Perdido"),"—") -> 0.93430657 | D40: De los Perdidos con razón «No contestaron». Una persona marca el 97% de los 274 Perdidos, a las 88.2 h (mediana) de entrar, y la razón no dice en qué etapa ni por qué se fue. 13 leads volvieron a escribir ya en Perdido y 1 de las 10 ventas salió de ahí.
B41: 9 · El reparto de leads está cargado a una sola asesora | C41: =IFERROR(COUNTIFS(Datos!$R$2:$R$408,"Salma")/COUNT(Datos!$B$2:$B$408),"—") -> 0.68304668 | D41: Leads a nombre de Salma. También quedan a su nombre el 84% de los que entran fuera de horario. En horario, su primera acción tarda 7.7 min (mediana) contra 1.7 min del resto del equipo; con los de fuera de horario, 45.4 min.
B42: 10 · Fuera de horario la atención baja | C42: =IFERROR(COUNTIFS(Respuestas!$E$2:$E$1034,"No",Respuestas!$H$2:$H$1034,"<=15")/COUNTIFS(Respuestas!$E$2:$E$1034,"No"),"—") -> 0.6076555 | D42: De los mensajes del lead fuera de horario que una persona contesta en 15 min, contra 81% en horario. El 25% de los leads entra fuera de 9 a 21 h y espera 30.7 h (mediana) su primer mensaje de una persona, contra 2.3 h en horario.
B44: Valor y Dato se calculan con fórmulas sobre las hojas Datos y Respuestas. Los textos se escribieron con los datos al corte del 15 de octubre de 2026.
B45: Muestra chica en ventas (10): un solo caso mueve mucho los porcentajes. 123 leads siguen abiertos.

Sheet Métricas semanales
A1: DESARROLLO PROFESIONAL SyS
A2: Métricas por semana
A3: ISO + Calidad · semana según la fecha en que entró el lead · corte: 15 oct 2026, 23:59 h (Monterrey)
A5: Métrica | B5: 2026-S41 | C5: 2026-S42 | D5: Total | E5: Cómo se calcula
B6: 5 al 11 oct (completa) | C6: 12 al 15 oct (4 días)
A8: Volumen
A9: Leads | B9: =COUNTIFS(Datos!$D$2:$D$408,B$5) -> 253 | C9: =COUNTIFS(Datos!$D$2:$D$408,C$5) -> 154 | D9: =COUNT(Datos!$B$2:$B$408) -> 407 | E9: Leads que entraron.
A10: % que entra fuera de horario | B10: =IFERROR(COUNTIFS(Datos!$D$2:$D$408,B$5,Datos!$F$2:$F$408,"No")/COUNTIFS(Datos!$D$2:$D$408,B$5),"—") -> 0.24901186 | C10: =IFERROR(COUNTIFS(Datos!$D$2:$D$408,C$5,Datos!$F$2:$F$408,"No")/COUNTIFS(Datos!$D$2:$D$408,C$5),"—") -> 0.25324675 | D10: =IFERROR(COUNTIFS(Datos!$F$2:$F$408,"No")/COUNT(Datos!$B$2:$B$408),"—") -> 0.25061425 | E10: Antes de 9 h o desde 21 h (horario de los bots en el CRM).
A12: Saludo
A13: % que contesta el saludo | B13: =IFERROR(COUNTIFS(Datos!$D$2:$D$408,B$5,Datos!$G$2:$G$408,"Sí")/COUNTIFS(Datos!$D$2:$D$408,B$5),"—") -> 0.62055336 | C13: =IFERROR(COUNTIFS(Datos!$D$2:$D$408,C$5,Datos!$G$2:$G$408,"Sí")/COUNTIFS(Datos!$D$2:$D$408,C$5),"—") -> 0.64285714 | D13: =IFERROR(COUNTIFS(Datos!$G$2:$G$408,"Sí")/COUNT(Datos!$B$2:$B$408),"—") -> 0.62899263 | E13: Escribió después de que el bot pidió el nombre y antes de salir de 1 Saludo.
A14: % que da su nombre | B14: =IFERROR(COUNTIFS(Datos!$D$2:$D$408,B$5,Datos!$H$2:$H$408,"Sí")/COUNTIFS(Datos!$D$2:$D$408,B$5),"—") -> 0.60474308 | C14: =IFERROR(COUNTIFS(Datos!$D$2:$D$408,C$5,Datos!$H$2:$H$408,"Sí")/COUNTIFS(Datos!$D$2:$D$408,C$5),"—") -> 0.62337662 | D14: =IFERROR(COUNTIFS(Datos!$H$2:$H$408,"Sí")/COUNT(Datos!$B$2:$B$408),"—") -> 0.61179361 | E14: Su nombre aparece en lo que contestó al saludo.
A15: Minutos de su respuesta al paso a 1.1 · mediana, de 9 a 21 h | B15: {=IFERROR(MEDIAN(IF((Datos!$D$2:$D$408=B$5)*(Datos!$F$2:$F$408="Sí")*(Datos!$J$2:$J$408<>""),Datos!$J$2:$J$408)),"—")} -> 0.5 | C15: {=IFERROR(MEDIAN(IF((Datos!$D$2:$D$408=C$5)*(Datos!$F$2:$F$408="Sí")*(Datos!$J$2:$J$408<>""),Datos!$J$2:$J$408)),"—")} -> 0.4 | D15: {=IFERROR(MEDIAN(IF((Datos!$F$2:$F$408="Sí")*(Datos!$J$2:$J$408<>""),Datos!$J$2:$J$408)),"—")} -> 0.5 | E15: Solo quienes contestaron. La mediana es el caso de en medio: no la mueven los extremos.
A16: Minutos de su respuesta al paso a 1.1 · mediana, fuera de horario | B16: {=IFERROR(MEDIAN(IF((Datos!$D$2:$D$408=B$5)*(Datos!$F$2:$F$408="No")*(Datos!$J$2:$J$408<>""),Datos!$J$2:$J$408)),"—")} -> 25.5 | C16: {=IFERROR(MEDIAN(IF((Datos!$D$2:$D$408=C$5)*(Datos!$F$2:$F$408="No")*(Datos!$J$2:$J$408<>""),Datos!$J$2:$J$408)),"—")} -> 12.9 | D16: {=IFERROR(MEDIAN(IF((Datos!$F$2:$F$408="No")*(Datos!$J$2:$J$408<>""),Datos!$J$2:$J$408)),"—")} -> 18.4
A17: Minutos de su respuesta al paso a 1.1 · promedio, de 9 a 21 h | B17: =IFERROR(AVERAGEIFS(Datos!$J$2:$J$408,Datos!$D$2:$D$408,B$5,Datos!$F$2:$F$408,"Sí"),"—") -> 1.6681034 | C17: =IFERROR(AVERAGEIFS(Datos!$J$2:$J$408,Datos!$D$2:$D$408,C$5,Datos!$F$2:$F$408,"Sí"),"—") -> 1.2619718 | D17: =IFERROR(AVERAGEIFS(Datos!$J$2:$J$408,Datos!$F$2:$F$408,"Sí"),"—") -> 1.5139037
A18: Minutos de su respuesta al paso a 1.1 · promedio, fuera de horario | B18: =IFERROR(AVERAGEIFS(Datos!$J$2:$J$408,Datos!$D$2:$D$408,B$5,Datos!$F$2:$F$408,"No"),"—") -> 170.71707 | C18: =IFERROR(AVERAGEIFS(Datos!$J$2:$J$408,Datos!$D$2:$D$408,C$5,Datos!$F$2:$F$408,"No"),"—") -> 144.7963 | D18: =IFERROR(AVERAGEIFS(Datos!$J$2:$J$408,Datos!$F$2:$F$408,"No"),"—") -> 160.425 | E18: Lo sube quien escribe de noche y espera hasta la mañana.
A19: Esperaron más de 1 hora para pasar a 1.1 | B19: =COUNTIFS(Datos!$D$2:$D$408,B$5,Datos!$J$2:$J$408,">60") -> 19 | C19: =COUNTIFS(Datos!$D$2:$D$408,C$5,Datos!$J$2:$J$408,">60") -> 10 | D19: =COUNTIFS(Datos!$J$2:$J$408,">60") -> 29 | E19: Contestaron y nadie los movió en la primera hora.
A21: Avance
A22: % que pasa de 1.1 a 1.2 | B22: =IFERROR(COUNTIFS(Datos!$D$2:$D$408,B$5,Datos!$I$2:$I$408,"Sí",Datos!$L$2:$L$408,"Sí")/COUNTIFS(Datos!$D$2:$D$408,B$5,Datos!$I$2:$I$408,"Sí"),"—") -> 1 | C22: =IFERROR(COUNTIFS(Datos!$D$2:$D$408,C$5,Datos!$I$2:$I$408,"Sí",Datos!$L$2:$L$408,"Sí")/COUNTIFS(Datos!$D$2:$D$408,C$5,Datos!$I$2:$I$408,"Sí"),"—") -> 1 | D22: =IFERROR(COUNTIFS(Datos!$I$2:$I$408,"Sí",Datos!$L$2:$L$408,"Sí")/COUNTIFS(Datos!$I$2:$I$408,"Sí"),"—") -> 1 | E22: Es automático, a los 8 segundos.
A23: % que contesta la ocupación (de los que llegan a 1.2) | B23: =IFERROR(COUNTIFS(Datos!$D$2:$D$408,B$5,Datos!$L$2:$L$408,"Sí",Datos!$M$2:$M$408,"Sí")/COUNTIFS(Datos!$D$2:$D$408,B$5,Datos!$L$2:$L$408,"Sí"),"—") -> 0.40079365 | C23: =IFERROR(COUNTIFS(Datos!$D$2:$D$408,C$5,Datos!$L$2:$L$408,"Sí",Datos!$M$2:$M$408,"Sí")/COUNTIFS(Datos!$D$2:$D$408,C$5,Datos!$L$2:$L$408,"Sí"),"—") -> 0.37254902 | D23: =IFERROR(COUNTIFS(Datos!$L$2:$L$408,"Sí",Datos!$M$2:$M$408,"Sí")/COUNTIFS(Datos!$L$2:$L$408,"Sí"),"—") -> 0.39012346 | E23: Contestó en 24 h con su área o si estudia.
A24: % que entra a Negativo | B24: =IFERROR(COUNTIFS(Datos!$D$2:$D$408,B$5,Datos!$O$2:$O$408,"Sí")/COUNTIFS(Datos!$D$2:$D$408,B$5),"—") -> 0.91699605 | C24: =IFERROR(COUNTIFS(Datos!$D$2:$D$408,C$5,Datos!$O$2:$O$408,"Sí")/COUNTIFS(Datos!$D$2:$D$408,C$5),"—") -> 0.88961039 | D24: =IFERROR(COUNTIFS(Datos!$O$2:$O$408,"Sí")/COUNT(Datos!$B$2:$B$408),"—") -> 0.90663391 | E24: El bot lo pasa solo si nadie lo mueve en 2 h.
A25: % que llega a facilidades de pago | B25: =IFERROR(COUNTIFS(Datos!$D$2:$D$408,B$5,Datos!$P$2:$P$408,"Sí")/COUNTIFS(Datos!$D$2:$D$408,B$5),"—") -> 0.33992095 | C25: =IFERROR(COUNTIFS(Datos!$D$2:$D$408,C$5,Datos!$P$2:$P$408,"Sí")/COUNTIFS(Datos!$D$2:$D$408,C$5),"—") -> 0.34415584 | D25: =IFERROR(COUNTIFS(Datos!$P$2:$P$408,"Sí")/COUNT(Datos!$B$2:$B$408),"—") -> 0.34152334 | E25: Etapa 1.3 o 1.4, o más lejos.
A26: % que llega a forma de pago | B26: =IFERROR(COUNTIFS(Datos!$D$2:$D$408,B$5,Datos!$Q$2:$Q$408,"Sí")/COUNTIFS(Datos!$D$2:$D$408,B$5),"—") -> 0.071146245 | C26: =IFERROR(COUNTIFS(Datos!$D$2:$D$408,C$5,Datos!$Q$2:$Q$408,"Sí")/COUNTIFS(Datos!$D$2:$D$408,C$5),"—") -> 0.077922078 | D26: =IFERROR(COUNTIFS(Datos!$Q$2:$Q$408,"Sí")/COUNT(Datos!$B$2:$B$408),"—") -> 0.073710074 | E26: Etapas 2.x, MSI y 3.x, o Ganado.
A28: Atención de personas
A29: Minutos hasta la 1a acción de una persona · mediana | B29: {=IFERROR(MEDIAN(IF((Datos!$D$2:$D$408=B$5)*(Datos!$V$2:$V$408<>""),Datos!$V$2:$V$408)),"—")} -> 6.9 | C29: {=IFERROR(MEDIAN(IF((Datos!$D$2:$D$408=C$5)*(Datos!$V$2:$V$408<>""),Datos!$V$2:$V$408)),"—")} -> 3.5 | D29: =IFERROR(MEDIAN(Datos!$V$2:$V$408),"—") -> 5.3 | E29: Un mensaje o un cambio de etapa hecho por una persona.
A30: Horas hasta el 1er mensaje de una persona · mediana | B30: {=IFERROR(MEDIAN(IF((Datos!$D$2:$D$408=B$5)*(Datos!$T$2:$T$408<>""),Datos!$T$2:$T$408))/60,"—")} -> 12.766667 | C30: {=IFERROR(MEDIAN(IF((Datos!$D$2:$D$408=C$5)*(Datos!$T$2:$T$408<>""),Datos!$T$2:$T$408))/60,"—")} -> 1.0583333 | D30: =IFERROR(MEDIAN(Datos!$T$2:$T$408)/60,"—") -> 7.4916667 | E30: Desde que entra el lead. Mover de etapa no cuenta.
A31: % que nunca recibió un mensaje de una persona | B31: =IFERROR(COUNTIFS(Datos!$D$2:$D$408,B$5,Datos!$T$2:$T$408,"")/COUNTIFS(Datos!$D$2:$D$408,B$5),"—") -> 0.015810277 | C31: =IFERROR(COUNTIFS(Datos!$D$2:$D$408,C$5,Datos!$T$2:$T$408,"")/COUNTIFS(Datos!$D$2:$D$408,C$5),"—") -> 0.30519481 | D31: =IFERROR(COUNTBLANK(Datos!$T$2:$T$408)/COUNT(Datos!$B$2:$B$408),"—") -> 0.12530713 | E31: Hasta el corte, solo le escribió el bot.
A32: Minutos que tarda una persona en contestarle al lead · mediana | B32: {=IFERROR(MEDIAN(IF((Datos!$D$2:$D$408=B$5)*(Datos!$W$2:$W$408<>""),Datos!$W$2:$W$408)),"—")} -> 5.9 | C32: {=IFERROR(MEDIAN(IF((Datos!$D$2:$D$408=C$5)*(Datos!$W$2:$W$408<>""),Datos!$W$2:$W$408)),"—")} -> 3.95 | D32: =IFERROR(MEDIAN(Datos!$W$2:$W$408),"—") -> 5.2 | E32: Mediana por lead y luego la de todos. Detalle en la hoja Respuestas.
A33: % con audio del equipo | B33: =IFERROR(COUNTIFS(Datos!$D$2:$D$408,B$5,Datos!$Y$2:$Y$408,"Sí")/COUNTIFS(Datos!$D$2:$D$408,B$5),"—") -> 0.38735178 | C33: =IFERROR(COUNTIFS(Datos!$D$2:$D$408,C$5,Datos!$Y$2:$Y$408,"Sí")/COUNTIFS(Datos!$D$2:$D$408,C$5),"—") -> 0.37662338 | D33: =IFERROR(COUNTIFS(Datos!$Y$2:$Y$408,"Sí")/COUNT(Datos!$B$2:$B$408),"—") -> 0.38329238 | E33: Nota de voz de una persona, no del bot.
A34: % donde intervino auxiliar | B34: =IFERROR(COUNTIFS(Datos!$D$2:$D$408,B$5,Datos!$S$2:$S$408,"Sí")/COUNTIFS(Datos!$D$2:$D$408,B$5),"—") -> 0.54940711 | C34: =IFERROR(COUNTIFS(Datos!$D$2:$D$408,C$5,Datos!$S$2:$S$408,"Sí")/COUNTIFS(Datos!$D$2:$D$408,C$5),"—") -> 0.45454545 | D34: =IFERROR(COUNTIFS(Datos!$S$2:$S$408,"Sí")/COUNT(Datos!$B$2:$B$408),"—") -> 0.51351351 | E34: La auxiliar escribió o movió al lead de etapa.
A36: Ofertas
A37: % que recibe alguna oferta | B37: =IFERROR(COUNTIFS(Datos!$D$2:$D$408,B$5,Datos!$Z$2:$Z$408,"Sí")/COUNTIFS(Datos!$D$2:$D$408,B$5),"—") -> 0.97233202 | C37: =IFERROR(COUNTIFS(Datos!$D$2:$D$408,C$5,Datos!$Z$2:$Z$408,"Sí")/COUNTIFS(Datos!$D$2:$D$408,C$5),"—") -> 0.68831169 | D37: =IFERROR(COUNTIFS(Datos!$Z$2:$Z$408,"Sí")/COUNT(Datos!$B$2:$B$408),"—") -> 0.86486486 | E37: $3,799, $3,400, $2,799 o $1,950 escrito en un mensaje.
A38: % que recibe $3,799 | B38: =IFERROR(COUNTIFS(Datos!$D$2:$D$408,B$5,Datos!$AA$2:$AA$408,"*3,799*")/COUNTIFS(Datos!$D$2:$D$408,B$5),"—") -> 0.95256917 | C38: =IFERROR(COUNTIFS(Datos!$D$2:$D$408,C$5,Datos!$AA$2:$AA$408,"*3,799*")/COUNTIFS(Datos!$D$2:$D$408,C$5),"—") -> 0.68181818 | D38: =IFERROR(COUNTIFS(Datos!$AA$2:$AA$408,"*3,799*")/COUNT(Datos!$B$2:$B$408),"—") -> 0.85012285
A39: % que recibe $2,799 | B39: =IFERROR(COUNTIFS(Datos!$D$2:$D$408,B$5,Datos!$AA$2:$AA$408,"*2,799*")/COUNTIFS(Datos!$D$2:$D$408,B$5),"—") -> 0.96837945 | C39: =IFERROR(COUNTIFS(Datos!$D$2:$D$408,C$5,Datos!$AA$2:$AA$408,"*2,799*")/COUNTIFS(Datos!$D$2:$D$408,C$5),"—") -> 0.3961039 | D39: =IFERROR(COUNTIFS(Datos!$AA$2:$AA$408,"*2,799*")/COUNT(Datos!$B$2:$B$408),"—") -> 0.75184275
A40: % que recibe $1,950 | B40: =IFERROR(COUNTIFS(Datos!$D$2:$D$408,B$5,Datos!$AA$2:$AA$408,"*1,950*")/COUNTIFS(Datos!$D$2:$D$408,B$5),"—") -> 0 | C40: =IFERROR(COUNTIFS(Datos!$D$2:$D$408,C$5,Datos!$AA$2:$AA$408,"*1,950*")/COUNTIFS(Datos!$D$2:$D$408,C$5),"—") -> 0 | D40: =IFERROR(COUNTIFS(Datos!$AA$2:$AA$408,"*1,950*")/COUNT(Datos!$B$2:$B$408),"—") -> 0
A41: % de primeras ofertas que manda el bot | B41: =IFERROR(COUNTIFS(Datos!$D$2:$D$408,B$5,Datos!$Z$2:$Z$408,"Sí",Datos!$AB$2:$AB$408,"Bot")/COUNTIFS(Datos!$D$2:$D$408,B$5,Datos!$Z$2:$Z$408,"Sí"),"—") -> 0.82926829 | C41: =IFERROR(COUNTIFS(Datos!$D$2:$D$408,C$5,Datos!$Z$2:$Z$408,"Sí",Datos!$AB$2:$AB$408,"Bot")/COUNTIFS(Datos!$D$2:$D$408,C$5,Datos!$Z$2:$Z$408,"Sí"),"—") -> 0.70754717 | D41: =IFERROR(COUNTIFS(Datos!$Z$2:$Z$408,"Sí",Datos!$AB$2:$AB$408,"Bot")/COUNTIFS(Datos!$Z$2:$Z$408,"Sí"),"—") -> 0.79261364 | E41: El resto lo manda una persona, casi siempre con plantilla.
A42: Horas hasta la 1a oferta · mediana | B42: {=IFERROR(MEDIAN(IF((Datos!$D$2:$D$408=B$5)*(Datos!$AC$2:$AC$408<>""),Datos!$AC$2:$AC$408)),"—")} -> 37.2 | C42: {=IFERROR(MEDIAN(IF((Datos!$D$2:$D$408=C$5)*(Datos!$AC$2:$AC$408<>""),Datos!$AC$2:$AC$408)),"—")} -> 28.55 | D42: =IFERROR(MEDIAN(Datos!$AC$2:$AC$408),"—") -> 31.6 | E42: Desde que entra el lead.
A44: Interés y volumen de mensajes
A45: % que abrió algún link | B45: =IFERROR(COUNTIFS(Datos!$D$2:$D$408,B$5,Datos!$AG$2:$AG$408,"Sí")/COUNTIFS(Datos!$D$2:$D$408,B$5),"—") -> 0.27272727 | C45: =IFERROR(COUNTIFS(Datos!$D$2:$D$408,C$5,Datos!$AG$2:$AG$408,"Sí")/COUNTIFS(Datos!$D$2:$D$408,C$5),"—") -> 0.23376623 | D45: =IFERROR(COUNTIFS(Datos!$AG$2:$AG$408,"Sí")/COUNT(Datos!$B$2:$B$408),"—") -> 0.25798526 | E45: Ruta, clase demo, mapa o perfil de ejemplo (aviso del CRM).
A46: Mensajes del lead por lead · promedio | B46: =IFERROR(AVERAGEIFS(Datos!$AD$2:$AD$408,Datos!$D$2:$D$408,B$5),"—") -> 4.4782609 | C46: =IFERROR(AVERAGEIFS(Datos!$AD$2:$AD$408,Datos!$D$2:$D$408,C$5),"—") -> 3.8181818 | D46: =IFERROR(AVERAGE(Datos!$AD$2:$AD$408),"—") -> 4.2285012
A47: Mensajes del bot por lead · promedio | B47: =IFERROR(AVERAGEIFS(Datos!$AE$2:$AE$408,Datos!$D$2:$D$408,B$5),"—") -> 19.126482 | C47: =IFERROR(AVERAGEIFS(Datos!$AE$2:$AE$408,Datos!$D$2:$D$408,C$5),"—") -> 16.12987 | D47: =IFERROR(AVERAGE(Datos!$AE$2:$AE$408),"—") -> 17.992629
A48: Mensajes de personas por lead · promedio | B48: =IFERROR(AVERAGEIFS(Datos!$AF$2:$AF$408,Datos!$D$2:$D$408,B$5),"—") -> 6.0790514 | C48: =IFERROR(AVERAGEIFS(Datos!$AF$2:$AF$408,Datos!$D$2:$D$408,C$5),"—") -> 4.6558442 | D48: =IFERROR(AVERAGE(Datos!$AF$2:$AF$408),"—") -> 5.5405405
A50: Ventas y precio
A51: Ventas | B51: =COUNTIFS(Datos!$D$2:$D$408,B$5,Datos!$AQ$2:$AQ$408,"Sí") -> 7 | C51: =COUNTIFS(Datos!$D$2:$D$408,C$5,Datos!$AQ$2:$AQ$408,"Sí") -> 3 | D51: =COUNTIFS(Datos!$AQ$2:$AQ$408,"Sí") -> 10 | E51: Leads en Ganado al corte.
A52: Conversión (ventas ÷ leads) | B52: =IFERROR(COUNTIFS(Datos!$D$2:$D$408,B$5,Datos!$AQ$2:$AQ$408,"Sí")/COUNTIFS(Datos!$D$2:$D$408,B$5),"—") -> 0.027667984 | C52: =IFERROR(COUNTIFS(Datos!$D$2:$D$408,C$5,Datos!$AQ$2:$AQ$408,"Sí")/COUNTIFS(Datos!$D$2:$D$408,C$5),"—") -> 0.019480519 | D52: =IFERROR(COUNTIFS(Datos!$AQ$2:$AQ$408,"Sí")/COUNT(Datos!$B$2:$B$408),"—") -> 0.024570025
A53: Ventas a $3,999 o más | B53: =COUNTIFS(Datos!$D$2:$D$408,B$5,Datos!$AQ$2:$AQ$408,"Sí",Datos!$AR$2:$AR$408,">=3999") -> 1 | C53: =COUNTIFS(Datos!$D$2:$D$408,C$5,Datos!$AQ$2:$AQ$408,"Sí",Datos!$AR$2:$AR$408,">=3999") -> 1 | D53: =COUNTIFS(Datos!$AQ$2:$AQ$408,"Sí",Datos!$AR$2:$AR$408,">=3999") -> 2 | E53: Precio que quedó registrado en el CRM.
A54: Ventas con descuento | B54: =COUNTIFS(Datos!$D$2:$D$408,B$5,Datos!$AQ$2:$AQ$408,"Sí",Datos!$AR$2:$AR$408,"<3999") -> 6 | C54: =COUNTIFS(Datos!$D$2:$D$408,C$5,Datos!$AQ$2:$AQ$408,"Sí",Datos!$AR$2:$AR$408,"<3999") -> 2 | D54: =COUNTIFS(Datos!$AQ$2:$AQ$408,"Sí",Datos!$AR$2:$AR$408,"<3999") -> 8
A55: Precio promedio de venta | B55: =IFERROR(AVERAGEIFS(Datos!$AR$2:$AR$408,Datos!$D$2:$D$408,B$5,Datos!$AQ$2:$AQ$408,"Sí"),"—") -> 3113.2857 | C55: =IFERROR(AVERAGEIFS(Datos!$AR$2:$AR$408,Datos!$D$2:$D$408,C$5,Datos!$AQ$2:$AQ$408,"Sí"),"—") -> 3532.3333 | D55: =IFERROR(AVERAGEIFS(Datos!$AR$2:$AR$408,Datos!$AQ$2:$AQ$408,"Sí"),"—") -> 3239 | E55: Lista: $3,999.
A56: Ingreso registrado | B56: =SUMIFS(Datos!$AR$2:$AR$408,Datos!$D$2:$D$408,B$5,Datos!$AQ$2:$AQ$408,"Sí") -> 21793 | C56: =SUMIFS(Datos!$AR$2:$AR$408,Datos!$D$2:$D$408,C$5,Datos!$AQ$2:$AQ$408,"Sí") -> 10597 | D56: =SUMIFS(Datos!$AR$2:$AR$408,Datos!$AQ$2:$AQ$408,"Sí") -> 32390 | E56: Suma de los precios de venta.
A57: Horas hasta la venta · mediana | B57: {=IFERROR(MEDIAN(IF((Datos!$D$2:$D$408=B$5)*(Datos!$AT$2:$AT$408<>""),Datos!$AT$2:$AT$408)),"—")} -> 54.2 | C57: {=IFERROR(MEDIAN(IF((Datos!$D$2:$D$408=C$5)*(Datos!$AT$2:$AT$408<>""),Datos!$AT$2:$AT$408)),"—")} -> 53.4 | D57: =IFERROR(MEDIAN(Datos!$AT$2:$AT$408),"—") -> 53.8 | E57: Desde que entra el lead hasta Ganado.
A59: Dónde dejó de escribir (% de los leads)
A60: Solo su primer mensaje | B60: =IFERROR(COUNTIFS(Datos!$D$2:$D$408,B$5,Datos!$AJ$2:$AJ$408,"Solo su primer mensaje")/COUNTIFS(Datos!$D$2:$D$408,B$5),"—") -> 0.25296443 | C60: =IFERROR(COUNTIFS(Datos!$D$2:$D$408,C$5,Datos!$AJ$2:$AJ$408,"Solo su primer mensaje")/COUNTIFS(Datos!$D$2:$D$408,C$5),"—") -> 0.28571429 | D60: =IFERROR(COUNTIFS(Datos!$AJ$2:$AJ$408,"Solo su primer mensaje")/COUNT(Datos!$B$2:$B$408),"—") -> 0.26535627
A61: Saludo: contestó y no volvió | B61: =IFERROR(COUNTIFS(Datos!$D$2:$D$408,B$5,Datos!$AJ$2:$AJ$408,"Saludo: contestó y no volvió")/COUNTIFS(Datos!$D$2:$D$408,B$5),"—") -> 0.20948617 | C61: =IFERROR(COUNTIFS(Datos!$D$2:$D$408,C$5,Datos!$AJ$2:$AJ$408,"Saludo: contestó y no volvió")/COUNTIFS(Datos!$D$2:$D$408,C$5),"—") -> 0.27922078 | D61: =IFERROR(COUNTIFS(Datos!$AJ$2:$AJ$408,"Saludo: contestó y no volvió")/COUNT(Datos!$B$2:$B$408),"—") -> 0.23587224
A62: 1.2 Lista de cursos | B62: =IFERROR(COUNTIFS(Datos!$D$2:$D$408,B$5,Datos!$AJ$2:$AJ$408,"1.2 Lista de cursos")/COUNTIFS(Datos!$D$2:$D$408,B$5),"—") -> 0.19762846 | C62: =IFERROR(COUNTIFS(Datos!$D$2:$D$408,C$5,Datos!$AJ$2:$AJ$408,"1.2 Lista de cursos")/COUNTIFS(Datos!$D$2:$D$408,C$5),"—") -> 0.15584416 | D62: =IFERROR(COUNTIFS(Datos!$AJ$2:$AJ$408,"1.2 Lista de cursos")/COUNT(Datos!$B$2:$B$408),"—") -> 0.18181818
A63: Negativo | B63: =IFERROR(COUNTIFS(Datos!$D$2:$D$408,B$5,Datos!$AJ$2:$AJ$408,"Negativo")/COUNTIFS(Datos!$D$2:$D$408,B$5),"—") -> 0.13438735 | C63: =IFERROR(COUNTIFS(Datos!$D$2:$D$408,C$5,Datos!$AJ$2:$AJ$408,"Negativo")/COUNTIFS(Datos!$D$2:$D$408,C$5),"—") -> 0.11038961 | D63: =IFERROR(COUNTIFS(Datos!$AJ$2:$AJ$408,"Negativo")/COUNT(Datos!$B$2:$B$408),"—") -> 0.12530713
A64: Facilidades de pago | B64: =IFERROR(COUNTIFS(Datos!$D$2:$D$408,B$5,Datos!$AJ$2:$AJ$408,"Facilidades de pago")/COUNTIFS(Datos!$D$2:$D$408,B$5),"—") -> 0.11857708 | C64: =IFERROR(COUNTIFS(Datos!$D$2:$D$408,C$5,Datos!$AJ$2:$AJ$408,"Facilidades de pago")/COUNTIFS(Datos!$D$2:$D$408,C$5),"—") -> 0.11688312 | D64: =IFERROR(COUNTIFS(Datos!$AJ$2:$AJ$408,"Facilidades de pago")/COUNT(Datos!$B$2:$B$408),"—") -> 0.11793612
A65: Forma o medio de pago | B65: =IFERROR(COUNTIFS(Datos!$D$2:$D$408,B$5,Datos!$AJ$2:$AJ$408,"Forma o medio de pago")/COUNTIFS(Datos!$D$2:$D$408,B$5),"—") -> 0.015810277 | C65: =IFERROR(COUNTIFS(Datos!$D$2:$D$408,C$5,Datos!$AJ$2:$AJ$408,"Forma o medio de pago")/COUNTIFS(Datos!$D$2:$D$408,C$5),"—") -> 0.025974026 | D65: =IFERROR(COUNTIFS(Datos!$AJ$2:$AJ$408,"Forma o medio de pago")/COUNT(Datos!$B$2:$B$408),"—") -> 0.01965602
A66: Ya marcado como Perdido | B66: =IFERROR(COUNTIFS(Datos!$D$2:$D$408,B$5,Datos!$AJ$2:$AJ$408,"Ya marcado como Perdido")/COUNTIFS(Datos!$D$2:$D$408,B$5),"—") -> 0.043478261 | C66: =IFERROR(COUNTIFS(Datos!$D$2:$D$408,C$5,Datos!$AJ$2:$AJ$408,"Ya marcado como Perdido")/COUNTIFS(Datos!$D$2:$D$408,C$5),"—") -> 0.0064935065 | D66: =IFERROR(COUNTIFS(Datos!$AJ$2:$AJ$408,"Ya marcado como Perdido")/COUNT(Datos!$B$2:$B$408),"—") -> 0.029484029
A67: Compró | B67: =IFERROR(COUNTIFS(Datos!$D$2:$D$408,B$5,Datos!$AJ$2:$AJ$408,"Compró")/COUNTIFS(Datos!$D$2:$D$408,B$5),"—") -> 0.027667984 | C67: =IFERROR(COUNTIFS(Datos!$D$2:$D$408,C$5,Datos!$AJ$2:$AJ$408,"Compró")/COUNTIFS(Datos!$D$2:$D$408,C$5),"—") -> 0.019480519 | D67: =IFERROR(COUNTIFS(Datos!$AJ$2:$AJ$408,"Compró")/COUNT(Datos!$B$2:$B$408),"—") -> 0.024570025
A69: Estado al corte
A70: Abiertos | B70: =COUNTIFS(Datos!$D$2:$D$408,B$5,Datos!$AK$2:$AK$408,"Abierto") -> 7 | C70: =COUNTIFS(Datos!$D$2:$D$408,C$5,Datos!$AK$2:$AK$408,"Abierto") -> 116 | D70: =COUNTIFS(Datos!$AK$2:$AK$408,"Abierto") -> 123 | E70: Todavía pueden avanzar.
A71: Perdidos | B71: =COUNTIFS(Datos!$D$2:$D$408,B$5,Datos!$AK$2:$AK$408,"Perdido") -> 239 | C71: =COUNTIFS(Datos!$D$2:$D$408,C$5,Datos!$AK$2:$AK$408,"Perdido") -> 35 | D71: =COUNTIFS(Datos!$AK$2:$AK$408,"Perdido") -> 274
A72: Ganados | B72: =COUNTIFS(Datos!$D$2:$D$408,B$5,Datos!$AK$2:$AK$408,"Ganado") -> 7 | C72: =COUNTIFS(Datos!$D$2:$D$408,C$5,Datos!$AK$2:$AK$408,"Ganado") -> 3 | D72: =COUNTIFS(Datos!$AK$2:$AK$408,"Ganado") -> 10
A73: % de Perdidos que marcó una persona | B73: =IFERROR(COUNTIFS(Datos!$D$2:$D$408,B$5,Datos!$AK$2:$AK$408,"Perdido",Datos!$AL$2:$AL$408,"Persona")/COUNTIFS(Datos!$D$2:$D$408,B$5,Datos!$AK$2:$AK$408,"Perdido"),"—") -> 0.9665272 | C73: =IFERROR(COUNTIFS(Datos!$D$2:$D$408,C$5,Datos!$AK$2:$AK$408,"Perdido",Datos!$AL$2:$AL$408,"Persona")/COUNTIFS(Datos!$D$2:$D$408,C$5,Datos!$AK$2:$AK$408,"Perdido"),"—") -> 1 | D73: =IFERROR(COUNTIFS(Datos!$AK$2:$AK$408,"Perdido",Datos!$AL$2:$AL$408,"Persona")/COUNTIFS(Datos!$AK$2:$AK$408,"Perdido"),"—") -> 0.97080292 | E73: El resto lo mandó el bot al final de Negativo.
A74: % de Perdidos con razón «No contestaron» | B74: =IFERROR(COUNTIFS(Datos!$D$2:$D$408,B$5,Datos!$AK$2:$AK$408,"Perdido",Datos!$AM$2:$AM$408,"No contestaron")/COUNTIFS(Datos!$D$2:$D$408,B$5,Datos!$AK$2:$AK$408,"Perdido"),"—") -> 0.92887029 | C74: =IFERROR(COUNTIFS(Datos!$D$2:$D$408,C$5,Datos!$AK$2:$AK$408,"Perdido",Datos!$AM$2:$AM$408,"No contestaron")/COUNTIFS(Datos!$D$2:$D$408,C$5,Datos!$AK$2:$AK$408,"Perdido"),"—") -> 0.97142857 | D74: =IFERROR(COUNTIFS(Datos!$AK$2:$AK$408,"Perdido",Datos!$AM$2:$AM$408,"No contestaron")/COUNTIFS(Datos!$AK$2:$AK$408,"Perdido"),"—") -> 0.93430657
A75: Horas hasta Perdido · mediana | B75: {=IFERROR(MEDIAN(IF((Datos!$D$2:$D$408=B$5)*(Datos!$AN$2:$AN$408<>""),Datos!$AN$2:$AN$408)),"—")} -> 91.5 | C75: {=IFERROR(MEDIAN(IF((Datos!$D$2:$D$408=C$5)*(Datos!$AN$2:$AN$408<>""),Datos!$AN$2:$AN$408)),"—")} -> 52.8 | D75: =IFERROR(MEDIAN(Datos!$AN$2:$AN$408),"—") -> 88.15
A76: Leads que escribieron después de marcarlos Perdido | B76: =COUNTIFS(Datos!$D$2:$D$408,B$5,Datos!$AP$2:$AP$408,"Sí") -> 12 | C76: =COUNTIFS(Datos!$D$2:$D$408,C$5,Datos!$AP$2:$AP$408,"Sí") -> 1 | D76: =COUNTIFS(Datos!$AP$2:$AP$408,"Sí") -> 13 | E76: El lead volvió a escribir cuando ya estaba en Perdido.
A77: Ventas de leads que estuvieron en Perdido | B77: =COUNTIFS(Datos!$D$2:$D$408,B$5,Datos!$AO$2:$AO$408,"Sí",Datos!$AQ$2:$AQ$408,"Sí") -> 1 | C77: =COUNTIFS(Datos!$D$2:$D$408,C$5,Datos!$AO$2:$AO$408,"Sí",Datos!$AQ$2:$AQ$408,"Sí") -> 0 | D77: =COUNTIFS(Datos!$AO$2:$AO$408,"Sí",Datos!$AQ$2:$AQ$408,"Sí") -> 1 | E77: Los sacaron de Perdido y compraron.
A80: De 9 a 21 h contra fuera de horario (todo el período)
A81: Métrica | B81: De 9 a 21 h | C81: Fuera | D81: Total | E81: Nota
A82: Leads | B82: =COUNTIFS(Datos!$F$2:$F$408,"Sí") -> 305 | C82: =COUNTIFS(Datos!$F$2:$F$408,"No") -> 102 | D82: =COUNT(Datos!$B$2:$B$408) -> 407
A83: % que contesta el saludo | B83: =IFERROR(COUNTIFS(Datos!$F$2:$F$408,"Sí",Datos!$G$2:$G$408,"Sí")/COUNTIFS(Datos!$F$2:$F$408,"Sí"),"—") -> 0.61639344 | C83: =IFERROR(COUNTIFS(Datos!$F$2:$F$408,"No",Datos!$G$2:$G$408,"Sí")/COUNTIFS(Datos!$F$2:$F$408,"No"),"—") -> 0.66666667 | D83: =IFERROR(COUNTIFS(Datos!$G$2:$G$408,"Sí")/COUNT(Datos!$B$2:$B$408),"—") -> 0.62899263
A84: Minutos de su respuesta a 1.1 · mediana | B84: {=IFERROR(MEDIAN(IF((Datos!$F$2:$F$408="Sí")*(Datos!$J$2:$J$408<>""),Datos!$J$2:$J$408)),"—")} -> 0.5 | C84: {=IFERROR(MEDIAN(IF((Datos!$F$2:$F$408="No")*(Datos!$J$2:$J$408<>""),Datos!$J$2:$J$408)),"—")} -> 18.4 | D84: =IFERROR(MEDIAN(Datos!$J$2:$J$408),"—") -> 0.7
A85: Esperaron más de 1 hora para pasar a 1.1 | B85: =COUNTIFS(Datos!$F$2:$F$408,"Sí",Datos!$J$2:$J$408,">60") -> 0 | C85: =COUNTIFS(Datos!$F$2:$F$408,"No",Datos!$J$2:$J$408,">60") -> 29 | D85: =COUNTIFS(Datos!$J$2:$J$408,">60") -> 29 | E85: Escribieron de noche y los movieron en la mañana.
A86: Horas hasta el 1er mensaje de una persona · mediana | B86: {=IFERROR(MEDIAN(IF((Datos!$F$2:$F$408="Sí")*(Datos!$T$2:$T$408<>""),Datos!$T$2:$T$408))/60,"—")} -> 2.2583333 | C86: {=IFERROR(MEDIAN(IF((Datos!$F$2:$F$408="No")*(Datos!$T$2:$T$408<>""),Datos!$T$2:$T$408))/60,"—")} -> 30.678333 | D86: =IFERROR(MEDIAN(Datos!$T$2:$T$408)/60,"—") -> 7.4916667 | E86: De noche el lead se queda con el bot.
A87: % que llega a facilidades de pago | B87: =IFERROR(COUNTIFS(Datos!$F$2:$F$408,"Sí",Datos!$P$2:$P$408,"Sí")/COUNTIFS(Datos!$F$2:$F$408,"Sí"),"—") -> 0.3704918 | C87: =IFERROR(COUNTIFS(Datos!$F$2:$F$408,"No",Datos!$P$2:$P$408,"Sí")/COUNTIFS(Datos!$F$2:$F$408,"No"),"—") -> 0.25490196 | D87: =IFERROR(COUNTIFS(Datos!$P$2:$P$408,"Sí")/COUNT(Datos!$B$2:$B$408),"—") -> 0.34152334
A88: Ventas | B88: =COUNTIFS(Datos!$F$2:$F$408,"Sí",Datos!$AQ$2:$AQ$408,"Sí") -> 9 | C88: =COUNTIFS(Datos!$F$2:$F$408,"No",Datos!$AQ$2:$AQ$408,"Sí") -> 1 | D88: =COUNTIFS(Datos!$AQ$2:$AQ$408,"Sí") -> 10
A89: Conversión | B89: =IFERROR(COUNTIFS(Datos!$F$2:$F$408,"Sí",Datos!$AQ$2:$AQ$408,"Sí")/COUNTIFS(Datos!$F$2:$F$408,"Sí"),"—") -> 0.029508197 | C89: =IFERROR(COUNTIFS(Datos!$F$2:$F$408,"No",Datos!$AQ$2:$AQ$408,"Sí")/COUNTIFS(Datos!$F$2:$F$408,"No"),"—") -> 0.0098039216 | D89: =IFERROR(COUNTIFS(Datos!$AQ$2:$AQ$408,"Sí")/COUNT(Datos!$B$2:$B$408),"—") -> 0.024570025

Sheet Embudo
A1: DESARROLLO PROFESIONAL SyS
A2: Embudo
A3: ISO + Calidad · 407 leads del 5 al 15 de octubre de 2026 · conteos con fórmulas sobre la hoja Datos
A5: Leads que llegaron a cada etapa
A6: Etapa | B6: Leads | C6: % de la etapa anterior | D6: % de los que entraron | E6: Nota
A7: Entraron a 1 Saludo | B7: =COUNT(Datos!$B$2:$B$408) -> 407 | C7: — | D7: =IFERROR(B7/B$7,"—") -> 1 | E7: Todos reciben el saludo y la petición de nombre.
A8: 1.1 Informes | B8: =COUNTIFS(Datos!$I$2:$I$408,"Sí") -> 405 | C8: =IFERROR(B8/B7,"—") -> 0.995086 | D8: =IFERROR(B8/B$7,"—") -> 0.995086 | E8: Lo mueve una persona si contestó; el bot, si no contestó.
A9: 1.2 Lista de cursos | B9: =COUNTIFS(Datos!$L$2:$L$408,"Sí") -> 405 | C9: =IFERROR(B9/B8,"—") -> 1 | D9: =IFERROR(B9/B$7,"—") -> 0.995086 | E9: Automático.
A10: Facilidades de pago, 1.3 y 1.4 | B10: =COUNTIFS(Datos!$P$2:$P$408,"Sí") -> 139 | C10: =IFERROR(B10/B9,"—") -> 0.34320988 | D10: =IFERROR(B10/B$7,"—") -> 0.34152334 | E10: Lo mueve una persona o el lead contesta la oferta del bot.
A11: Forma o medio de pago, 2.x y 3.x | B11: =COUNTIFS(Datos!$Q$2:$Q$408,"Sí") -> 30 | C11: =IFERROR(B11/B10,"—") -> 0.21582734 | D11: =IFERROR(B11/B$7,"—") -> 0.073710074 | E11: Eligió cómo pagar o recibió los datos.
A12: Compraron | B12: =COUNTIFS(Datos!$AQ$2:$AQ$408,"Sí") -> 10 | C12: =IFERROR(B12/B11,"—") -> 0.33333333 | D12: =IFERROR(B12/B$7,"—") -> 0.024570025 | E12: Etapa Ganado.
A13: Además: entraron a Negativo | B13: =COUNTIFS(Datos!$O$2:$O$408,"Sí") -> 369 | D13: =IFERROR(B13/B$7,"—") -> 0.90663391 | E13: Seguimiento automático del bot si nadie mueve al lead en 2 h.
A16: Dónde dejó de escribir el lead
A17: Etapa de su último mensaje | B17: Leads | C17: % de los leads | D17: Nota
A18: Solo su primer mensaje | B18: =COUNTIFS(Datos!$AJ$2:$AJ$408,A18) -> 108 | C18: =IFERROR(B18/COUNT(Datos!$B$2:$B$408),"—") -> 0.26535627 | D18: No volvió a escribir después de su primer mensaje.
A19: Saludo: contestó y no volvió | B19: =COUNTIFS(Datos!$AJ$2:$AJ$408,A19) -> 96 | C19: =IFERROR(B19/COUNT(Datos!$B$2:$B$408),"—") -> 0.23587224 | D19: Contestó el saludo (casi siempre su nombre) y ya no escribió.
A20: 1.2 Lista de cursos | B20: =COUNTIFS(Datos!$AJ$2:$AJ$408,A20) -> 74 | C20: =IFERROR(B20/COUNT(Datos!$B$2:$B$408),"—") -> 0.18181818 | D20: Incluye 1.1 Informes (dura 8 segundos).
A21: Negativo | B21: =COUNTIFS(Datos!$AJ$2:$AJ$408,A21) -> 51 | C21: =IFERROR(B21/COUNT(Datos!$B$2:$B$408),"—") -> 0.12530713 | D21: Seguimiento automático del bot.
A22: Facilidades de pago | B22: =COUNTIFS(Datos!$AJ$2:$AJ$408,A22) -> 48 | C22: =IFERROR(B22/COUNT(Datos!$B$2:$B$408),"—") -> 0.11793612 | D22: 1.3 y 1.4: ya pidió o recibió cómo pagar.
A23: Forma o medio de pago | B23: =COUNTIFS(Datos!$AJ$2:$AJ$408,A23) -> 8 | C23: =IFERROR(B23/COUNT(Datos!$B$2:$B$408),"—") -> 0.01965602 | D23: 2.x, MSI y 3.x: eligió cómo pagar o recibió los datos.
A24: Ya marcado como Perdido | B24: =COUNTIFS(Datos!$AJ$2:$AJ$408,A24) -> 12 | C24: =IFERROR(B24/COUNT(Datos!$B$2:$B$408),"—") -> 0.029484029 | D24: Escribió cuando ya estaba en Perdido.
A25: Compró | B25: =COUNTIFS(Datos!$AJ$2:$AJ$408,A25) -> 10 | C25: =IFERROR(B25/COUNT(Datos!$B$2:$B$408),"—") -> 0.024570025 | D25: Etapa Ganado.
A26: Total | B26: =SUM(B18:B25) -> 407 | C26: =IFERROR(B26/COUNT(Datos!$B$2:$B$408),"—") -> 1
A28: «Llegó a una etapa» = llegó a esa etapa o a una más lejana. Una venta cuenta como que pasó por todas.

Sheet Tiempos
A1: DESARROLLO PROFESIONAL SyS
A2: Tiempos de atención
A3: ISO + Calidad · desde que entra el lead y cuando el lead escribe · corte: 15 oct 2026, 23:59 h (Monterrey)
A5: ¿Cuánto tarda el primer mensaje de una persona?
A6: Tiempo desde que entró | B6: Leads | C6: % de los leads | D6: % que contestó el saludo | E6: % que llegó a facilidades | F6: Ventas | G6: Conversión
A7: 5 min o menos | B7: =COUNTIFS(Datos!$T$2:$T$408,"<=5") -> 30 | C7: =IFERROR(B7/COUNT(Datos!$B$2:$B$408),"—") -> 0.073710074 | D7: =IFERROR(COUNTIFS(Datos!$T$2:$T$408,"<=5",Datos!$G$2:$G$408,"Sí")/B7,"—") -> 0.76666667 | E7: =IFERROR(COUNTIFS(Datos!$T$2:$T$408,"<=5",Datos!$P$2:$P$408,"Sí")/B7,"—") -> 0.7 | F7: =COUNTIFS(Datos!$T$2:$T$408,"<=5",Datos!$AQ$2:$AQ$408,"Sí") -> 3 | G7: =IFERROR(F7/B7,"—") -> 0.1
A8: 5 a 15 min | B8: =COUNTIFS(Datos!$T$2:$T$408,">5",Datos!$T$2:$T$408,"<=15") -> 66 | C8: =IFERROR(B8/COUNT(Datos!$B$2:$B$408),"—") -> 0.16216216 | D8: =IFERROR(COUNTIFS(Datos!$T$2:$T$408,">5",Datos!$T$2:$T$408,"<=15",Datos!$G$2:$G$408,"Sí")/B8,"—") -> 1 | E8: =IFERROR(COUNTIFS(Datos!$T$2:$T$408,">5",Datos!$T$2:$T$408,"<=15",Datos!$P$2:$P$408,"Sí")/B8,"—") -> 0.74242424 | F8: =COUNTIFS(Datos!$T$2:$T$408,">5",Datos!$T$2:$T$408,"<=15",Datos!$AQ$2:$AQ$408,"Sí") -> 2 | G8: =IFERROR(F8/B8,"—") -> 0.03030303
A9: 15 a 60 min | B9: =COUNTIFS(Datos!$T$2:$T$408,">15",Datos!$T$2:$T$408,"<=60") -> 49 | C9: =IFERROR(B9/COUNT(Datos!$B$2:$B$408),"—") -> 0.12039312 | D9: =IFERROR(COUNTIFS(Datos!$T$2:$T$408,">15",Datos!$T$2:$T$408,"<=60",Datos!$G$2:$G$408,"Sí")/B9,"—") -> 0.7755102 | E9: =IFERROR(COUNTIFS(Datos!$T$2:$T$408,">15",Datos!$T$2:$T$408,"<=60",Datos!$P$2:$P$408,"Sí")/B9,"—") -> 0.7755102 | F9: =COUNTIFS(Datos!$T$2:$T$408,">15",Datos!$T$2:$T$408,"<=60",Datos!$AQ$2:$AQ$408,"Sí") -> 2 | G9: =IFERROR(F9/B9,"—") -> 0.040816327
A10: 1 a 4 h | B10: =COUNTIFS(Datos!$T$2:$T$408,">60",Datos!$T$2:$T$408,"<=240") -> 29 | C10: =IFERROR(B10/COUNT(Datos!$B$2:$B$408),"—") -> 0.071253071 | D10: =IFERROR(COUNTIFS(Datos!$T$2:$T$408,">60",Datos!$T$2:$T$408,"<=240",Datos!$G$2:$G$408,"Sí")/B10,"—") -> 0.51724138 | E10: =IFERROR(COUNTIFS(Datos!$T$2:$T$408,">60",Datos!$T$2:$T$408,"<=240",Datos!$P$2:$P$408,"Sí")/B10,"—") -> 0.5862069 | F10: =COUNTIFS(Datos!$T$2:$T$408,">60",Datos!$T$2:$T$408,"<=240",Datos!$AQ$2:$AQ$408,"Sí") -> 0 | G10: =IFERROR(F10/B10,"—") -> 0
A11: 4 a 24 h | B11: =COUNTIFS(Datos!$T$2:$T$408,">240",Datos!$T$2:$T$408,"<=1440") -> 35 | C11: =IFERROR(B11/COUNT(Datos!$B$2:$B$408),"—") -> 0.085995086 | D11: =IFERROR(COUNTIFS(Datos!$T$2:$T$408,">240",Datos!$T$2:$T$408,"<=1440",Datos!$G$2:$G$408,"Sí")/B11,"—") -> 0.62857143 | E11: =IFERROR(COUNTIFS(Datos!$T$2:$T$408,">240",Datos!$T$2:$T$408,"<=1440",Datos!$P$2:$P$408,"Sí")/B11,"—") -> 0.28571429 | F11: =COUNTIFS(Datos!$T$2:$T$408,">240",Datos!$T$2:$T$408,"<=1440",Datos!$AQ$2:$AQ$408,"Sí") -> 2 | G11: =IFERROR(F11/B11,"—") -> 0.057142857
A12: Más de 1 día | B12: =COUNTIFS(Datos!$T$2:$T$408,">1440") -> 147 | C12: =IFERROR(B12/COUNT(Datos!$B$2:$B$408),"—") -> 0.36117936 | D12: =IFERROR(COUNTIFS(Datos!$T$2:$T$408,">1440",Datos!$G$2:$G$408,"Sí")/B12,"—") -> 0.44897959 | E12: =IFERROR(COUNTIFS(Datos!$T$2:$T$408,">1440",Datos!$P$2:$P$408,"Sí")/B12,"—") -> 0.020408163 | F12: =COUNTIFS(Datos!$T$2:$T$408,">1440",Datos!$AQ$2:$AQ$408,"Sí") -> 1 | G12: =IFERROR(F12/B12,"—") -> 0.0068027211
A13: Nunca (solo el bot) | B13: =COUNTIFS(Datos!$T$2:$T$408,"") -> 51 | C13: =IFERROR(B13/COUNT(Datos!$B$2:$B$408),"—") -> 0.12530713 | D13: =IFERROR(COUNTIFS(Datos!$T$2:$T$408,"",Datos!$G$2:$G$408,"Sí")/B13,"—") -> 0.47058824 | E13: =IFERROR(COUNTIFS(Datos!$T$2:$T$408,"",Datos!$P$2:$P$408,"Sí")/B13,"—") -> 0.019607843 | F13: =COUNTIFS(Datos!$T$2:$T$408,"",Datos!$AQ$2:$AQ$408,"Sí") -> 0 | G13: =IFERROR(F13/B13,"—") -> 0
A14: Total | B14: =SUM(B7:B13) -> 407 | F14: =SUM(F7:F13) -> 10 | G14: =IFERROR(F14/B14,"—") -> 0.024570025
A15: Relación, no causa: quien contesta más rápido también recibe antes el mensaje de una persona.
A17: Cuando el lead escribe, ¿cuánto tarda una persona en contestar?
A18: Tiempo de respuesta | B18: De 9 a 21 h | C18: % de 9 a 21 h | D18: Fuera de horario | E18: % fuera | F18: Total | G18: % total
A19: 5 min o menos | B19: =COUNTIFS(Respuestas!$H$2:$H$1034,"<=5",Respuestas!$E$2:$E$1034,"Sí") -> 527 | C19: =IFERROR(B19/COUNTIFS(Respuestas!$E$2:$E$1034,"Sí"),"—") -> 0.63956311 | D19: =COUNTIFS(Respuestas!$H$2:$H$1034,"<=5",Respuestas!$E$2:$E$1034,"No") -> 111 | E19: =IFERROR(D19/COUNTIFS(Respuestas!$E$2:$E$1034,"No"),"—") -> 0.53110048 | F19: =COUNTIFS(Respuestas!$H$2:$H$1034,"<=5") -> 638 | G19: =IFERROR(F19/COUNT(Respuestas!$B$2:$B$1034),"—") -> 0.61761859
A20: 5 a 15 min | B20: =COUNTIFS(Respuestas!$H$2:$H$1034,">5",Respuestas!$H$2:$H$1034,"<=15",Respuestas!$E$2:$E$1034,"Sí") -> 144 | C20: =IFERROR(B20/COUNTIFS(Respuestas!$E$2:$E$1034,"Sí"),"—") -> 0.17475728 | D20: =COUNTIFS(Respuestas!$H$2:$H$1034,">5",Respuestas!$H$2:$H$1034,"<=15",Respuestas!$E$2:$E$1034,"No") -> 16 | E20: =IFERROR(D20/COUNTIFS(Respuestas!$E$2:$E$1034,"No"),"—") -> 0.076555024 | F20: =COUNTIFS(Respuestas!$H$2:$H$1034,">5",Respuestas!$H$2:$H$1034,"<=15") -> 160 | G20: =IFERROR(F20/COUNT(Respuestas!$B$2:$B$1034),"—") -> 0.15488867
A21: 15 a 60 min | B21: =COUNTIFS(Respuestas!$H$2:$H$1034,">15",Respuestas!$H$2:$H$1034,"<=60",Respuestas!$E$2:$E$1034,"Sí") -> 43 | C21: =IFERROR(B21/COUNTIFS(Respuestas!$E$2:$E$1034,"Sí"),"—") -> 0.052184466 | D21: =COUNTIFS(Respuestas!$H$2:$H$1034,">15",Respuestas!$H$2:$H$1034,"<=60",Respuestas!$E$2:$E$1034,"No") -> 16 | E21: =IFERROR(D21/COUNTIFS(Respuestas!$E$2:$E$1034,"No"),"—") -> 0.076555024 | F21: =COUNTIFS(Respuestas!$H$2:$H$1034,">15",Respuestas!$H$2:$H$1034,"<=60") -> 59 | G21: =IFERROR(F21/COUNT(Respuestas!$B$2:$B$1034),"—") -> 0.057115198
A22: 1 a 4 h | B22: =COUNTIFS(Respuestas!$H$2:$H$1034,">60",Respuestas!$H$2:$H$1034,"<=240",Respuestas!$E$2:$E$1034,"Sí") -> 14 | C22: =IFERROR(B22/COUNTIFS(Respuestas!$E$2:$E$1034,"Sí"),"—") -> 0.016990291 | D22: =COUNTIFS(Respuestas!$H$2:$H$1034,">60",Respuestas!$H$2:$H$1034,"<=240",Respuestas!$E$2:$E$1034,"No") -> 13 | E22: =IFERROR(D22/COUNTIFS(Respuestas!$E$2:$E$1034,"No"),"—") -> 0.062200957 | F22: =COUNTIFS(Respuestas!$H$2:$H$1034,">60",Respuestas!$H$2:$H$1034,"<=240") -> 27 | G22: =IFERROR(F22/COUNT(Respuestas!$B$2:$B$1034),"—") -> 0.026137464
A23: Más de 4 h | B23: =COUNTIFS(Respuestas!$H$2:$H$1034,">240",Respuestas!$E$2:$E$1034,"Sí") -> 71 | C23: =IFERROR(B23/COUNTIFS(Respuestas!$E$2:$E$1034,"Sí"),"—") -> 0.086165049 | D23: =COUNTIFS(Respuestas!$H$2:$H$1034,">240",Respuestas!$E$2:$E$1034,"No") -> 42 | E23: =IFERROR(D23/COUNTIFS(Respuestas!$E$2:$E$1034,"No"),"—") -> 0.20095694 | F23: =COUNTIFS(Respuestas!$H$2:$H$1034,">240") -> 113 | G23: =IFERROR(F23/COUNT(Respuestas!$B$2:$B$1034),"—") -> 0.10939013
A24: Sin respuesta de una persona | B24: =COUNTIFS(Respuestas!$H$2:$H$1034,"",Respuestas!$E$2:$E$1034,"Sí") -> 24 | C24: =IFERROR(B24/COUNTIFS(Respuestas!$E$2:$E$1034,"Sí"),"—") -> 0.029126214 | D24: =COUNTIFS(Respuestas!$H$2:$H$1034,"",Respuestas!$E$2:$E$1034,"No") -> 9 | E24: =IFERROR(D24/COUNTIFS(Respuestas!$E$2:$E$1034,"No"),"—") -> 0.043062201 | F24: =COUNTIFS(Respuestas!$H$2:$H$1034,"") -> 36 | G24: =IFERROR(F24/COUNT(Respuestas!$B$2:$B$1034),"—") -> 0.034849952
A25: Mensajes del lead (rachas) | B25: =COUNTIFS(Respuestas!$E$2:$E$1034,"Sí") -> 824 | D25: =COUNTIFS(Respuestas!$E$2:$E$1034,"No") -> 209 | F25: =COUNT(Respuestas!$B$2:$B$1034) -> 1033
A26: Minutos de respuesta · mediana | B26: {=IFERROR(MEDIAN(IF((Respuestas!$E$2:$E$1034="Sí")*(Respuestas!$H$2:$H$1034<>""),Respuestas!$H$2:$H$1034)),"—")} -> 2.9 | D26: {=IFERROR(MEDIAN(IF((Respuestas!$E$2:$E$1034="No")*(Respuestas!$H$2:$H$1034<>""),Respuestas!$H$2:$H$1034)),"—")} -> 4.1 | F26: =IFERROR(MEDIAN(Respuestas!$H$2:$H$1034),"—") -> 3.1
A27: % en que el bot contestó primero | C27: =IFERROR(COUNTIFS(Respuestas!$E$2:$E$1034,"Sí",Respuestas!$I$2:$I$1034,"Bot")/B25,"—") -> 0.30582524 | E27: =IFERROR(COUNTIFS(Respuestas!$E$2:$E$1034,"No",Respuestas!$I$2:$I$1034,"Bot")/D25,"—") -> 0.37799043 | G27: =IFERROR(COUNTIFS(Respuestas!$I$2:$I$1034,"Bot")/F25,"—") -> 0.32042594
A28: Racha = uno o varios mensajes seguidos del lead, después de que el bot pidió el nombre. Se mide hasta el siguiente mensaje de una persona.
A30: Según la hora en que entró el lead
A31: Hora de entrada | B31: Leads | C31: % de los leads | D31: % que contestó el saludo | E31: Min. a 1.1 (mediana) | F31: Ventas | G31: Conversión
A32: 00:00 a 00:59 (fuera de horario) | B32: =COUNTIFS(Datos!$E$2:$E$408,0) -> 5 | C32: =IFERROR(B32/COUNT(Datos!$B$2:$B$408),"—") -> 0.012285012 | D32: =IFERROR(COUNTIFS(Datos!$E$2:$E$408,0,Datos!$G$2:$G$408,"Sí")/B32,"—") -> 0.4 | E32: {=IFERROR(MEDIAN(IF((Datos!$E$2:$E$408=0)*(Datos!$J$2:$J$408<>""),Datos!$J$2:$J$408)),"—")} -> 423.6 | F32: =COUNTIFS(Datos!$E$2:$E$408,0,Datos!$AQ$2:$AQ$408,"Sí") -> 0 | G32: =IFERROR(F32/B32,"—") -> 0
A33: 01:00 a 01:59 (fuera de horario) | B33: =COUNTIFS(Datos!$E$2:$E$408,1) -> 5 | C33: =IFERROR(B33/COUNT(Datos!$B$2:$B$408),"—") -> 0.012285012 | D33: =IFERROR(COUNTIFS(Datos!$E$2:$E$408,1,Datos!$G$2:$G$408,"Sí")/B33,"—") -> 0.4 | E33: {=IFERROR(MEDIAN(IF((Datos!$E$2:$E$408=1)*(Datos!$J$2:$J$408<>""),Datos!$J$2:$J$408)),"—")} -> 320.2 | F33: =COUNTIFS(Datos!$E$2:$E$408,1,Datos!$AQ$2:$AQ$408,"Sí") -> 0 | G33: =IFERROR(F33/B33,"—") -> 0
A34: 02:00 a 02:59 (fuera de horario) | B34: =COUNTIFS(Datos!$E$2:$E$408,2) -> 3 | C34: =IFERROR(B34/COUNT(Datos!$B$2:$B$408),"—") -> 0.0073710074 | D34: =IFERROR(COUNTIFS(Datos!$E$2:$E$408,2,Datos!$G$2:$G$408,"Sí")/B34,"—") -> 0.33333333 | E34: {=IFERROR(MEDIAN(IF((Datos!$E$2:$E$408=2)*(Datos!$J$2:$J$408<>""),Datos!$J$2:$J$408)),"—")} -> 269.5 | F34: =COUNTIFS(Datos!$E$2:$E$408,2,Datos!$AQ$2:$AQ$408,"Sí") -> 0 | G34: =IFERROR(F34/B34,"—") -> 0
A35: 03:00 a 03:59 (fuera de horario) | B35: =COUNTIFS(Datos!$E$2:$E$408,3) -> 0 | C35: =IFERROR(B35/COUNT(Datos!$B$2:$B$408),"—") -> 0 | D35: =IFERROR(COUNTIFS(Datos!$E$2:$E$408,3,Datos!$G$2:$G$408,"Sí")/B35,"—") -> — | E35: {=IFERROR(MEDIAN(IF((Datos!$E$2:$E$408=3)*(Datos!$J$2:$J$408<>""),Datos!$J$2:$J$408)),"—")} -> — | F35: =COUNTIFS(Datos!$E$2:$E$408,3,Datos!$AQ$2:$AQ$408,"Sí") -> 0 | G35: =IFERROR(F35/B35,"—") -> —
A36: 04:00 a 04:59 (fuera de horario) | B36: =COUNTIFS(Datos!$E$2:$E$408,4) -> 3 | C36: =IFERROR(B36/COUNT(Datos!$B$2:$B$408),"—") -> 0.0073710074 | D36: =IFERROR(COUNTIFS(Datos!$E$2:$E$408,4,Datos!$G$2:$G$408,"Sí")/B36,"—") -> 0.33333333 | E36: {=IFERROR(MEDIAN(IF((Datos!$E$2:$E$408=4)*(Datos!$J$2:$J$408<>""),Datos!$J$2:$J$408)),"—")} -> 191.4 | F36: =COUNTIFS(Datos!$E$2:$E$408,4,Datos!$AQ$2:$AQ$408,"Sí") -> 0 | G36: =IFERROR(F36/B36,"—") -> 0
A37: 05:00 a 05:59 (fuera de horario) | B37: =COUNTIFS(Datos!$E$2:$E$408,5) -> 3 | C37: =IFERROR(B37/COUNT(Datos!$B$2:$B$408),"—") -> 0.0073710074 | D37: =IFERROR(COUNTIFS(Datos!$E$2:$E$408,5,Datos!$G$2:$G$408,"Sí")/B37,"—") -> 1 | E37: {=IFERROR(MEDIAN(IF((Datos!$E$2:$E$408=5)*(Datos!$J$2:$J$408<>""),Datos!$J$2:$J$408)),"—")} -> 117.6 | F37: =COUNTIFS(Datos!$E$2:$E$408,5,Datos!$AQ$2:$AQ$408,"Sí") -> 0 | G37: =IFERROR(F37/B37,"—") -> 0
A38: 06:00 a 06:59 (fuera de horario) | B38: =COUNTIFS(Datos!$E$2:$E$408,6) -> 9 | C38: =IFERROR(B38/COUNT(Datos!$B$2:$B$408),"—") -> 0.022113022 | D38: =IFERROR(COUNTIFS(Datos!$E$2:$E$408,6,Datos!$G$2:$G$408,"Sí")/B38,"—") -> 0.55555556 | E38: {=IFERROR(MEDIAN(IF((Datos!$E$2:$E$408=6)*(Datos!$J$2:$J$408<>""),Datos!$J$2:$J$408)),"—")} -> 75.4 | F38: =COUNTIFS(Datos!$E$2:$E$408,6,Datos!$AQ$2:$AQ$408,"Sí") -> 0 | G38: =IFERROR(F38/B38,"—") -> 0
A39: 07:00 a 07:59 (fuera de horario) | B39: =COUNTIFS(Datos!$E$2:$E$408,7) -> 14 | C39: =IFERROR(B39/COUNT(Datos!$B$2:$B$408),"—") -> 0.034398034 | D39: =IFERROR(COUNTIFS(Datos!$E$2:$E$408,7,Datos!$G$2:$G$408,"Sí")/B39,"—") -> 0.92857143 | E39: {=IFERROR(MEDIAN(IF((Datos!$E$2:$E$408=7)*(Datos!$J$2:$J$408<>""),Datos!$J$2:$J$408)),"—")} -> 2.9 | F39: =COUNTIFS(Datos!$E$2:$E$408,7,Datos!$AQ$2:$AQ$408,"Sí") -> 0 | G39: =IFERROR(F39/B39,"—") -> 0
A40: 08:00 a 08:59 (fuera de horario) | B40: =COUNTIFS(Datos!$E$2:$E$408,8) -> 11 | C40: =IFERROR(B40/COUNT(Datos!$B$2:$B$408),"—") -> 0.027027027 | D40: =IFERROR(COUNTIFS(Datos!$E$2:$E$408,8,Datos!$G$2:$G$408,"Sí")/B40,"—") -> 0.72727273 | E40: {=IFERROR(MEDIAN(IF((Datos!$E$2:$E$408=8)*(Datos!$J$2:$J$408<>""),Datos!$J$2:$J$408)),"—")} -> 1.3 | F40: =COUNTIFS(Datos!$E$2:$E$408,8,Datos!$AQ$2:$AQ$408,"Sí") -> 0 | G40: =IFERROR(F40/B40,"—") -> 0
A41: 09:00 a 09:59 | B41: =COUNTIFS(Datos!$E$2:$E$408,9) -> 15 | C41: =IFERROR(B41/COUNT(Datos!$B$2:$B$408),"—") -> 0.036855037 | D41: =IFERROR(COUNTIFS(Datos!$E$2:$E$408,9,Datos!$G$2:$G$408,"Sí")/B41,"—") -> 0.26666667 | E41: {=IFERROR(MEDIAN(IF((Datos!$E$2:$E$408=9)*(Datos!$J$2:$J$408<>""),Datos!$J$2:$J$408)),"—")} -> 0.45 | F41: =COUNTIFS(Datos!$E$2:$E$408,9,Datos!$AQ$2:$AQ$408,"Sí") -> 1 | G41: =IFERROR(F41/B41,"—") -> 0.066666667
A42: 10:00 a 10:59 | B42: =COUNTIFS(Datos!$E$2:$E$408,10) -> 27 | C42: =IFERROR(B42/COUNT(Datos!$B$2:$B$408),"—") -> 0.066339066 | D42: =IFERROR(COUNTIFS(Datos!$E$2:$E$408,10,Datos!$G$2:$G$408,"Sí")/B42,"—") -> 0.7037037 | E42: {=IFERROR(MEDIAN(IF((Datos!$E$2:$E$408=10)*(Datos!$J$2:$J$408<>""),Datos!$J$2:$J$408)),"—")} -> 0.55 | F42: =COUNTIFS(Datos!$E$2:$E$408,10,Datos!$AQ$2:$AQ$408,"Sí") -> 0 | G42: =IFERROR(F42/B42,"—") -> 0
A43: 11:00 a 11:59 | B43: =COUNTIFS(Datos!$E$2:$E$408,11) -> 34 | C43: =IFERROR(B43/COUNT(Datos!$B$2:$B$408),"—") -> 0.083538084 | D43: =IFERROR(COUNTIFS(Datos!$E$2:$E$408,11,Datos!$G$2:$G$408,"Sí")/B43,"—") -> 0.61764706 | E43: {=IFERROR(MEDIAN(IF((Datos!$E$2:$E$408=11)*(Datos!$J$2:$J$408<>""),Datos!$J$2:$J$408)),"—")} -> 0.4 | F43: =COUNTIFS(Datos!$E$2:$E$408,11,Datos!$AQ$2:$AQ$408,"Sí") -> 2 | G43: =IFERROR(F43/B43,"—") -> 0.058823529
A44: 12:00 a 12:59 | B44: =COUNTIFS(Datos!$E$2:$E$408,12) -> 29 | C44: =IFERROR(B44/COUNT(Datos!$B$2:$B$408),"—") -> 0.071253071 | D44: =IFERROR(COUNTIFS(Datos!$E$2:$E$408,12,Datos!$G$2:$G$408,"Sí")/B44,"—") -> 0.65517241 | E44: {=IFERROR(MEDIAN(IF((Datos!$E$2:$E$408=12)*(Datos!$J$2:$J$408<>""),Datos!$J$2:$J$408)),"—")} -> 0.5 | F44: =COUNTIFS(Datos!$E$2:$E$408,12,Datos!$AQ$2:$AQ$408,"Sí") -> 0 | G44: =IFERROR(F44/B44,"—") -> 0
A45: 13:00 a 13:59 | B45: =COUNTIFS(Datos!$E$2:$E$408,13) -> 23 | C45: =IFERROR(B45/COUNT(Datos!$B$2:$B$408),"—") -> 0.056511057 | D45: =IFERROR(COUNTIFS(Datos!$E$2:$E$408,13,Datos!$G$2:$G$408,"Sí")/B45,"—") -> 0.60869565 | E45: {=IFERROR(MEDIAN(IF((Datos!$E$2:$E$408=13)*(Datos!$J$2:$J$408<>""),Datos!$J$2:$J$408)),"—")} -> 0.45 | F45: =COUNTIFS(Datos!$E$2:$E$408,13,Datos!$AQ$2:$AQ$408,"Sí") -> 2 | G45: =IFERROR(F45/B45,"—") -> 0.086956522
A46: 14:00 a 14:59 | B46: =COUNTIFS(Datos!$E$2:$E$408,14) -> 22 | C46: =IFERROR(B46/COUNT(Datos!$B$2:$B$408),"—") -> 0.054054054 | D46: =IFERROR(COUNTIFS(Datos!$E$2:$E$408,14,Datos!$G$2:$G$408,"Sí")/B46,"—") -> 0.77272727 | E46: {=IFERROR(MEDIAN(IF((Datos!$E$2:$E$408=14)*(Datos!$J$2:$J$408<>""),Datos!$J$2:$J$408)),"—")} -> 0.4 | F46: =COUNTIFS(Datos!$E$2:$E$408,14,Datos!$AQ$2:$AQ$408,"Sí") -> 0 | G46: =IFERROR(F46/B46,"—") -> 0
A47: 15:00 a 15:59 | B47: =COUNTIFS(Datos!$E$2:$E$408,15) -> 26 | C47: =IFERROR(B47/COUNT(Datos!$B$2:$B$408),"—") -> 0.063882064 | D47: =IFERROR(COUNTIFS(Datos!$E$2:$E$408,15,Datos!$G$2:$G$408,"Sí")/B47,"—") -> 0.53846154 | E47: {=IFERROR(MEDIAN(IF((Datos!$E$2:$E$408=15)*(Datos!$J$2:$J$408<>""),Datos!$J$2:$J$408)),"—")} -> 0.65 | F47: =COUNTIFS(Datos!$E$2:$E$408,15,Datos!$AQ$2:$AQ$408,"Sí") -> 0 | G47: =IFERROR(F47/B47,"—") -> 0
A48: 16:00 a 16:59 | B48: =COUNTIFS(Datos!$E$2:$E$408,16) -> 35 | C48: =IFERROR(B48/COUNT(Datos!$B$2:$B$408),"—") -> 0.085995086 | D48: =IFERROR(COUNTIFS(Datos!$E$2:$E$408,16,Datos!$G$2:$G$408,"Sí")/B48,"—") -> 0.54285714 | E48: {=IFERROR(MEDIAN(IF((Datos!$E$2:$E$408=16)*(Datos!$J$2:$J$408<>""),Datos!$J$2:$J$408)),"—")} -> 0.4 | F48: =COUNTIFS(Datos!$E$2:$E$408,16,Datos!$AQ$2:$AQ$408,"Sí") -> 0 | G48: =IFERROR(F48/B48,"—") -> 0
A49: 17:00 a 17:59 | B49: =COUNTIFS(Datos!$E$2:$E$408,17) -> 18 | C49: =IFERROR(B49/COUNT(Datos!$B$2:$B$408),"—") -> 0.044226044 | D49: =IFERROR(COUNTIFS(Datos!$E$2:$E$408,17,Datos!$G$2:$G$408,"Sí")/B49,"—") -> 0.83333333 | E49: {=IFERROR(MEDIAN(IF((Datos!$E$2:$E$408=17)*(Datos!$J$2:$J$408<>""),Datos!$J$2:$J$408)),"—")} -> 0.7 | F49: =COUNTIFS(Datos!$E$2:$E$408,17,Datos!$AQ$2:$AQ$408,"Sí") -> 1 | G49: =IFERROR(F49/B49,"—") -> 0.055555556
A50: 18:00 a 18:59 | B50: =COUNTIFS(Datos!$E$2:$E$408,18) -> 27 | C50: =IFERROR(B50/COUNT(Datos!$B$2:$B$408),"—") -> 0.066339066 | D50: =IFERROR(COUNTIFS(Datos!$E$2:$E$408,18,Datos!$G$2:$G$408,"Sí")/B50,"—") -> 0.59259259 | E50: {=IFERROR(MEDIAN(IF((Datos!$E$2:$E$408=18)*(Datos!$J$2:$J$408<>""),Datos!$J$2:$J$408)),"—")} -> 0.35 | F50: =COUNTIFS(Datos!$E$2:$E$408,18,Datos!$AQ$2:$AQ$408,"Sí") -> 1 | G50: =IFERROR(F50/B50,"—") -> 0.037037037
A51: 19:00 a 19:59 | B51: =COUNTIFS(Datos!$E$2:$E$408,19) -> 26 | C51: =IFERROR(B51/COUNT(Datos!$B$2:$B$408),"—") -> 0.063882064 | D51: =IFERROR(COUNTIFS(Datos!$E$2:$E$408,19,Datos!$G$2:$G$408,"Sí")/B51,"—") -> 0.57692308 | E51: {=IFERROR(MEDIAN(IF((Datos!$E$2:$E$408=19)*(Datos!$J$2:$J$408<>""),Datos!$J$2:$J$408)),"—")} -> 0.5 | F51: =COUNTIFS(Datos!$E$2:$E$408,19,Datos!$AQ$2:$AQ$408,"Sí") -> 1 | G51: =IFERROR(F51/B51,"—") -> 0.038461538
A52: 20:00 a 20:59 | B52: =COUNTIFS(Datos!$E$2:$E$408,20) -> 23 | C52: =IFERROR(B52/COUNT(Datos!$B$2:$B$408),"—") -> 0.056511057 | D52: =IFERROR(COUNTIFS(Datos!$E$2:$E$408,20,Datos!$G$2:$G$408,"Sí")/B52,"—") -> 0.65217391 | E52: {=IFERROR(MEDIAN(IF((Datos!$E$2:$E$408=20)*(Datos!$J$2:$J$408<>""),Datos!$J$2:$J$408)),"—")} -> 1.6 | F52: =COUNTIFS(Datos!$E$2:$E$408,20,Datos!$AQ$2:$AQ$408,"Sí") -> 1 | G52: =IFERROR(F52/B52,"—") -> 0.043478261
A53: 21:00 a 21:59 (fuera de horario) | B53: =COUNTIFS(Datos!$E$2:$E$408,21) -> 19 | C53: =IFERROR(B53/COUNT(Datos!$B$2:$B$408),"—") -> 0.046683047 | D53: =IFERROR(COUNTIFS(Datos!$E$2:$E$408,21,Datos!$G$2:$G$408,"Sí")/B53,"—") -> 0.63157895 | E53: {=IFERROR(MEDIAN(IF((Datos!$E$2:$E$408=21)*(Datos!$J$2:$J$408<>""),Datos!$J$2:$J$408)),"—")} -> 0.9 | F53: =COUNTIFS(Datos!$E$2:$E$408,21,Datos!$AQ$2:$AQ$408,"Sí") -> 0 | G53: =IFERROR(F53/B53,"—") -> 0
A54: 22:00 a 22:59 (fuera de horario) | B54: =COUNTIFS(Datos!$E$2:$E$408,22) -> 14 | C54: =IFERROR(B54/COUNT(Datos!$B$2:$B$408),"—") -> 0.034398034 | D54: =IFERROR(COUNTIFS(Datos!$E$2:$E$408,22,Datos!$G$2:$G$408,"Sí")/B54,"—") -> 0.64285714 | E54: {=IFERROR(MEDIAN(IF((Datos!$E$2:$E$408=22)*(Datos!$J$2:$J$408<>""),Datos!$J$2:$J$408)),"—")} -> 487.2 | F54: =COUNTIFS(Datos!$E$2:$E$408,22,Datos!$AQ$2:$AQ$408,"Sí") -> 1 | G54: =IFERROR(F54/B54,"—") -> 0.071428571
A55: 23:00 a 23:59 (fuera de horario) | B55: =COUNTIFS(Datos!$E$2:$E$408,23) -> 16 | C55: =IFERROR(B55/COUNT(Datos!$B$2:$B$408),"—") -> 0.039312039 | D55: =IFERROR(COUNTIFS(Datos!$E$2:$E$408,23,Datos!$G$2:$G$408,"Sí")/B55,"—") -> 0.75 | E55: {=IFERROR(MEDIAN(IF((Datos!$E$2:$E$408=23)*(Datos!$J$2:$J$408<>""),Datos!$J$2:$J$408)),"—")} -> 458.2 | F55: =COUNTIFS(Datos!$E$2:$E$408,23,Datos!$AQ$2:$AQ$408,"Sí") -> 0 | G55: =IFERROR(F55/B55,"—") -> 0

Sheet Ofertas y ventas
A1: DESARROLLO PROFESIONAL SyS
A2: Ofertas y ventas
A3: ISO + Calidad · ofertas escritas en mensajes y ventas registradas en el CRM · corte: 15 oct 2026, 23:59 h (Monterrey)
A5: Ofertas que recibió el lead
A6: Oferta | B6: Leads | C6: % de los leads | D6: Compraron | E6: Conversión
A7: Alguna oferta | B7: =COUNTIFS(Datos!$Z$2:$Z$408,"Sí") -> 352 | C7: =IFERROR(B7/COUNT(Datos!$B$2:$B$408),"—") -> 0.86486486 | D7: =COUNTIFS(Datos!$Z$2:$Z$408,"Sí",Datos!$AQ$2:$AQ$408,"Sí") -> 8 | E7: =IFERROR(D7/B7,"—") -> 0.022727273
A8: $3,799 | B8: =COUNTIFS(Datos!$AA$2:$AA$408,"*3,799*") -> 346 | C8: =IFERROR(B8/COUNT(Datos!$B$2:$B$408),"—") -> 0.85012285 | D8: =COUNTIFS(Datos!$AA$2:$AA$408,"*3,799*",Datos!$AQ$2:$AQ$408,"Sí") -> 5 | E8: =IFERROR(D8/B8,"—") -> 0.014450867
A9: $3,400 | B9: =COUNTIFS(Datos!$AA$2:$AA$408,"*3,400*") -> 1 | C9: =IFERROR(B9/COUNT(Datos!$B$2:$B$408),"—") -> 0.0024570025 | D9: =COUNTIFS(Datos!$AA$2:$AA$408,"*3,400*",Datos!$AQ$2:$AQ$408,"Sí") -> 0 | E9: =IFERROR(D9/B9,"—") -> 0
A10: $2,799 | B10: =COUNTIFS(Datos!$AA$2:$AA$408,"*2,799*") -> 306 | C10: =IFERROR(B10/COUNT(Datos!$B$2:$B$408),"—") -> 0.75184275 | D10: =COUNTIFS(Datos!$AA$2:$AA$408,"*2,799*",Datos!$AQ$2:$AQ$408,"Sí") -> 6 | E10: =IFERROR(D10/B10,"—") -> 0.019607843
A11: $1,950 | B11: =COUNTIFS(Datos!$AA$2:$AA$408,"*1,950*") -> 0 | C11: =IFERROR(B11/COUNT(Datos!$B$2:$B$408),"—") -> 0 | D11: =COUNTIFS(Datos!$AA$2:$AA$408,"*1,950*",Datos!$AQ$2:$AQ$408,"Sí") -> 0 | E11: =IFERROR(D11/B11,"—") -> —
A12: Ninguna oferta | B12: =COUNTIFS(Datos!$Z$2:$Z$408,"No") -> 55 | C12: =IFERROR(B12/COUNT(Datos!$B$2:$B$408),"—") -> 0.13513514 | D12: =COUNTIFS(Datos!$Z$2:$Z$408,"No",Datos!$AQ$2:$AQ$408,"Sí") -> 2 | E12: =IFERROR(D12/B12,"—") -> 0.036363636
A13: Un lead puede recibir varias ofertas. «Compraron» incluye a quien compró a otro precio.
A15: ¿Quién mandó la primera oferta?
A16: Primera oferta enviada por | B16: Leads | C16: % de las primeras ofertas | D16: Horas a la 1a oferta (mediana)
A17: Bot | B17: =COUNTIFS(Datos!$AB$2:$AB$408,"Bot") -> 279 | C17: =IFERROR(B17/COUNTIFS(Datos!$Z$2:$Z$408,"Sí"),"—") -> 0.79261364 | D17: {=IFERROR(MEDIAN(IF((Datos!$AB$2:$AB$408="Bot")*(Datos!$AC$2:$AC$408<>""),Datos!$AC$2:$AC$408)),"—")} -> 30.2
A18: Joceline | B18: =COUNTIFS(Datos!$AB$2:$AB$408,"Joceline") -> 43 | C18: =IFERROR(B18/COUNTIFS(Datos!$Z$2:$Z$408,"Sí"),"—") -> 0.12215909 | D18: {=IFERROR(MEDIAN(IF((Datos!$AB$2:$AB$408="Joceline")*(Datos!$AC$2:$AC$408<>""),Datos!$AC$2:$AC$408)),"—")} -> 31.6
A19: Salma | B19: =COUNTIFS(Datos!$AB$2:$AB$408,"Salma") -> 14 | C19: =IFERROR(B19/COUNTIFS(Datos!$Z$2:$Z$408,"Sí"),"—") -> 0.039772727 | D19: {=IFERROR(MEDIAN(IF((Datos!$AB$2:$AB$408="Salma")*(Datos!$AC$2:$AC$408<>""),Datos!$AC$2:$AC$408)),"—")} -> 40.65
A20: Alexander | B20: =COUNTIFS(Datos!$AB$2:$AB$408,"Alexander") -> 13 | C20: =IFERROR(B20/COUNTIFS(Datos!$Z$2:$Z$408,"Sí"),"—") -> 0.036931818 | D20: {=IFERROR(MEDIAN(IF((Datos!$AB$2:$AB$408="Alexander")*(Datos!$AC$2:$AC$408<>""),Datos!$AC$2:$AC$408)),"—")} -> 48.5
A21: Victoria | B21: =COUNTIFS(Datos!$AB$2:$AB$408,"Victoria") -> 3 | C21: =IFERROR(B21/COUNTIFS(Datos!$Z$2:$Z$408,"Sí"),"—") -> 0.0085227273 | D21: {=IFERROR(MEDIAN(IF((Datos!$AB$2:$AB$408="Victoria")*(Datos!$AC$2:$AC$408<>""),Datos!$AC$2:$AC$408)),"—")} -> 24.1
A22: Cuando una persona manda la oferta casi siempre es con una plantilla de Meta (imagen con el precio y botones).
A24: Precio al que se vendió
A25: Precio de venta | B25: Ventas | C25: % de las ventas | D25: Ingreso
A26: $3,999 o más (lista) | B26: =COUNTIFS(Datos!$AQ$2:$AQ$408,"Sí",Datos!$AR$2:$AR$408,">=3999") -> 2 | C26: =IFERROR(B26/COUNTIFS(Datos!$AQ$2:$AQ$408,"Sí"),"—") -> 0.2 | D26: =SUMIFS(Datos!$AR$2:$AR$408,Datos!$AQ$2:$AQ$408,"Sí",Datos!$AR$2:$AR$408,">=3999") -> 7998
A27: $3,799 | B27: =COUNTIFS(Datos!$AQ$2:$AQ$408,"Sí",Datos!$AR$2:$AR$408,3799) -> 2 | C27: =IFERROR(B27/COUNTIFS(Datos!$AQ$2:$AQ$408,"Sí"),"—") -> 0.2 | D27: =SUMIFS(Datos!$AR$2:$AR$408,Datos!$AQ$2:$AQ$408,"Sí",Datos!$AR$2:$AR$408,3799) -> 7598
A28: $3,400 | B28: =COUNTIFS(Datos!$AQ$2:$AQ$408,"Sí",Datos!$AR$2:$AR$408,3400) -> 0 | C28: =IFERROR(B28/COUNTIFS(Datos!$AQ$2:$AQ$408,"Sí"),"—") -> 0 | D28: =SUMIFS(Datos!$AR$2:$AR$408,Datos!$AQ$2:$AQ$408,"Sí",Datos!$AR$2:$AR$408,3400) -> 0
A29: $2,799 | B29: =COUNTIFS(Datos!$AQ$2:$AQ$408,"Sí",Datos!$AR$2:$AR$408,2799) -> 6 | C29: =IFERROR(B29/COUNTIFS(Datos!$AQ$2:$AQ$408,"Sí"),"—") -> 0.6 | D29: =SUMIFS(Datos!$AR$2:$AR$408,Datos!$AQ$2:$AQ$408,"Sí",Datos!$AR$2:$AR$408,2799) -> 16794
A30: $2,000 | B30: =COUNTIFS(Datos!$AQ$2:$AQ$408,"Sí",Datos!$AR$2:$AR$408,2000) -> 0 | C30: =IFERROR(B30/COUNTIFS(Datos!$AQ$2:$AQ$408,"Sí"),"—") -> 0 | D30: =SUMIFS(Datos!$AR$2:$AR$408,Datos!$AQ$2:$AQ$408,"Sí",Datos!$AR$2:$AR$408,2000) -> 0
A31: $1,950 | B31: =COUNTIFS(Datos!$AQ$2:$AQ$408,"Sí",Datos!$AR$2:$AR$408,1950) -> 0 | C31: =IFERROR(B31/COUNTIFS(Datos!$AQ$2:$AQ$408,"Sí"),"—") -> 0 | D31: =SUMIFS(Datos!$AR$2:$AR$408,Datos!$AQ$2:$AQ$408,"Sí",Datos!$AR$2:$AR$408,1950) -> 0
A32: Total | B32: =COUNTIFS(Datos!$AQ$2:$AQ$408,"Sí") -> 10 | D32: =SUMIFS(Datos!$AR$2:$AR$408,Datos!$AQ$2:$AQ$408,"Sí") -> 32390
A33: Ingreso si todas fueran a $3,999 | D33: =B32*3999 -> 39990
A34: Precio = presupuesto registrado al pasar a Ganado.
A36: Las ventas, una por una
A37: ID (#) | B37: Entrada | C37: Asesor asignado | D37: Ofertas recibidas | E37: Primera oferta enviada por | F37: Precio de venta | G37: Estado del cobro | H37: Horas hasta la venta
A38: =IF(Datos!B39="","—",Datos!B39) -> 370 | B38: =IF(Datos!C39="","—",Datos!C39) -> 46301.459 | C38: =IF(Datos!R39="","—",Datos!R39) -> Salma | D38: =IF(Datos!AA39="","—",Datos!AA39) -> $2,799 | E38: =IF(Datos!AB39="","—",Datos!AB39) -> Joceline | F38: =IF(Datos!AR39="","—",Datos!AR39) -> 2799 | G38: =IF(Datos!AS39="","—",Datos!AS39) -> Pagada completa | H38: =IF(Datos!AT39="","—",Datos!AT39) -> 22
A39: =IF(Datos!B67="","—",Datos!B67) -> 477 | B39: =IF(Datos!C67="","—",Datos!C67) -> 46301.86 | C39: =IF(Datos!R67="","—",Datos!R67) -> Victoria | D39: =IF(Datos!AA67="","—",Datos!AA67) -> $2,799 | E39: =IF(Datos!AB67="","—",Datos!AB67) -> Joceline | F39: =IF(Datos!AR67="","—",Datos!AR67) -> 2799 | G39: =IF(Datos!AS67="","—",Datos!AS67) -> Con saldo pendiente | H39: =IF(Datos!AT67="","—",Datos!AT67) -> 15.7
A40: =IF(Datos!B178="","—",Datos!B178) -> 1001 | B40: =IF(Datos!C178="","—",Datos!C178) -> 46304.399 | C40: =IF(Datos!R178="","—",Datos!R178) -> Salma | D40: =IF(Datos!AA178="","—",Datos!AA178) -> $2,799 | E40: =IF(Datos!AB178="","—",Datos!AB178) -> Salma | F40: =IF(Datos!AR178="","—",Datos!AR178) -> 2799 | G40: =IF(Datos!AS178="","—",Datos!AS178) -> Con saldo pendiente | H40: =IF(Datos!AT178="","—",Datos!AT178) -> 98.8
A41: =IF(Datos!B206="","—",Datos!B206) -> 1181 | B41: =IF(Datos!C206="","—",Datos!C206) -> 46305.485 | C41: =IF(Datos!R206="","—",Datos!R206) -> Alexander | D41: =IF(Datos!AA206="","—",Datos!AA206) -> — | E41: =IF(Datos!AB206="","—",Datos!AB206) -> — | F41: =IF(Datos!AR206="","—",Datos!AR206) -> 3999 | G41: =IF(Datos!AS206="","—",Datos!AS206) -> Con saldo pendiente | H41: =IF(Datos!AT206="","—",Datos!AT206) -> 101.6
A42: =IF(Datos!B211="","—",Datos!B211) -> 1194 | B42: =IF(Datos!C211="","—",Datos!C211) -> 46305.564 | C42: =IF(Datos!R211="","—",Datos!R211) -> Alexander | D42: =IF(Datos!AA211="","—",Datos!AA211) -> $3,799, $2,799 | E42: =IF(Datos!AB211="","—",Datos!AB211) -> Bot | F42: =IF(Datos!AR211="","—",Datos!AR211) -> 2799 | G42: =IF(Datos!AS211="","—",Datos!AS211) -> Pagada completa | H42: =IF(Datos!AT211="","—",Datos!AT211) -> 54.2
A43: =IF(Datos!B222="","—",Datos!B222) -> 1237 | B43: =IF(Datos!C222="","—",Datos!C222) -> 46305.833 | C43: =IF(Datos!R222="","—",Datos!R222) -> Victoria | D43: =IF(Datos!AA222="","—",Datos!AA222) -> $3,799, $2,799 | E43: =IF(Datos!AB222="","—",Datos!AB222) -> Victoria | F43: =IF(Datos!AR222="","—",Datos!AR222) -> 2799 | G43: =IF(Datos!AS222="","—",Datos!AS222) -> Pagada completa | H43: =IF(Datos!AT222="","—",Datos!AT222) -> 89.9
A44: =IF(Datos!B246="","—",Datos!B246) -> 1338 | B44: =IF(Datos!C246="","—",Datos!C246) -> 46306.743 | C44: =IF(Datos!R246="","—",Datos!R246) -> Salma | D44: =IF(Datos!AA246="","—",Datos!AA246) -> $3,799 | E44: =IF(Datos!AB246="","—",Datos!AB246) -> Bot | F44: =IF(Datos!AR246="","—",Datos!AR246) -> 3799 | G44: =IF(Datos!AS246="","—",Datos!AS246) -> Pagada completa | H44: =IF(Datos!AT246="","—",Datos!AT246) -> 44.4
A45: =IF(Datos!B289="","—",Datos!B289) -> 1533 | B45: =IF(Datos!C289="","—",Datos!C289) -> 46307.756 | C45: =IF(Datos!R289="","—",Datos!R289) -> Salma | D45: =IF(Datos!AA289="","—",Datos!AA289) -> $3,799, $2,799 | E45: =IF(Datos!AB289="","—",Datos!AB289) -> Joceline | F45: =IF(Datos!AR289="","—",Datos!AR289) -> 2799 | G45: =IF(Datos!AS289="","—",Datos!AS289) -> Con saldo pendiente | H45: =IF(Datos!AT289="","—",Datos!AT289) -> 72.1
A46: =IF(Datos!B299="","—",Datos!B299) -> 1591 | B46: =IF(Datos!C299="","—",Datos!C299) -> 46307.951 | C46: =IF(Datos!R299="","—",Datos!R299) -> Victoria | D46: =IF(Datos!AA299="","—",Datos!AA299) -> — | E46: =IF(Datos!AB299="","—",Datos!AB299) -> — | F46: =IF(Datos!AR299="","—",Datos!AR299) -> 3999 | G46: =IF(Datos!AS299="","—",Datos!AS299) -> Pagada completa | H46: =IF(Datos!AT299="","—",Datos!AT299) -> 13.6
A47: =IF(Datos!B315="","—",Datos!B315) -> 1661 | B47: =IF(Datos!C315="","—",Datos!C315) -> 46308.572 | C47: =IF(Datos!R315="","—",Datos!R315) -> Victoria | D47: =IF(Datos!AA315="","—",Datos!AA315) -> $3,799 | E47: =IF(Datos!AB315="","—",Datos!AB315) -> Joceline | F47: =IF(Datos!AR315="","—",Datos!AR315) -> 3799 | G47: =IF(Datos!AS315="","—",Datos!AS315) -> Pagada completa | H47: =IF(Datos!AT315="","—",Datos!AT315) -> 53.4
A48: Cada celda apunta a su fila en la hoja Datos.

Sheet Perfil y asesores
A1: DESARROLLO PROFESIONAL SyS
A2: Perfil del lead, señales y asesores
A3: ISO + Calidad · corte: 15 oct 2026, 23:59 h (Monterrey)
A5: Ocupación (de quienes la contestaron)
A6: Ocupación | B6: Leads | C6: % de los que contestaron | D6: Llegaron a facilidades | E6: Ventas | F6: Conversión
A7: Calidad | B7: =COUNTIFS(Datos!$N$2:$N$408,"Calidad") -> 55 | C7: =IFERROR(B7/COUNTIFS(Datos!$M$2:$M$408,"Sí"),"—") -> 0.34810127 | D7: =COUNTIFS(Datos!$N$2:$N$408,"Calidad",Datos!$P$2:$P$408,"Sí") -> 47 | E7: =COUNTIFS(Datos!$N$2:$N$408,"Calidad",Datos!$AQ$2:$AQ$408,"Sí") -> 3 | F7: =IFERROR(E7/B7,"—") -> 0.054545455
A8: Producción u operaciones | B8: =COUNTIFS(Datos!$N$2:$N$408,"Producción u operaciones") -> 24 | C8: =IFERROR(B8/COUNTIFS(Datos!$M$2:$M$408,"Sí"),"—") -> 0.15189873 | D8: =COUNTIFS(Datos!$N$2:$N$408,"Producción u operaciones",Datos!$P$2:$P$408,"Sí") -> 18 | E8: =COUNTIFS(Datos!$N$2:$N$408,"Producción u operaciones",Datos!$AQ$2:$AQ$408,"Sí") -> 0 | F8: =IFERROR(E8/B8,"—") -> 0
A9: Supervisión o jefatura | B9: =COUNTIFS(Datos!$N$2:$N$408,"Supervisión o jefatura") -> 15 | C9: =IFERROR(B9/COUNTIFS(Datos!$M$2:$M$408,"Sí"),"—") -> 0.094936709 | D9: =COUNTIFS(Datos!$N$2:$N$408,"Supervisión o jefatura",Datos!$P$2:$P$408,"Sí") -> 12 | E9: =COUNTIFS(Datos!$N$2:$N$408,"Supervisión o jefatura",Datos!$AQ$2:$AQ$408,"Sí") -> 0 | F9: =IFERROR(E9/B9,"—") -> 0
A10: Ingeniería | B10: =COUNTIFS(Datos!$N$2:$N$408,"Ingeniería") -> 18 | C10: =IFERROR(B10/COUNTIFS(Datos!$M$2:$M$408,"Sí"),"—") -> 0.11392405 | D10: =COUNTIFS(Datos!$N$2:$N$408,"Ingeniería",Datos!$P$2:$P$408,"Sí") -> 13 | E10: =COUNTIFS(Datos!$N$2:$N$408,"Ingeniería",Datos!$AQ$2:$AQ$408,"Sí") -> 0 | F10: =IFERROR(E10/B10,"—") -> 0
A11: Estudiante o recién egresado | B11: =COUNTIFS(Datos!$N$2:$N$408,"Estudiante o recién egresado") -> 30 | C11: =IFERROR(B11/COUNTIFS(Datos!$M$2:$M$408,"Sí"),"—") -> 0.18987342 | D11: =COUNTIFS(Datos!$N$2:$N$408,"Estudiante o recién egresado",Datos!$P$2:$P$408,"Sí") -> 23 | E11: =COUNTIFS(Datos!$N$2:$N$408,"Estudiante o recién egresado",Datos!$AQ$2:$AQ$408,"Sí") -> 0 | F11: =IFERROR(E11/B11,"—") -> 0
A12: Sin empleo o buscando | B12: =COUNTIFS(Datos!$N$2:$N$408,"Sin empleo o buscando") -> 6 | C12: =IFERROR(B12/COUNTIFS(Datos!$M$2:$M$408,"Sí"),"—") -> 0.037974684 | D12: =COUNTIFS(Datos!$N$2:$N$408,"Sin empleo o buscando",Datos!$P$2:$P$408,"Sí") -> 6 | E12: =COUNTIFS(Datos!$N$2:$N$408,"Sin empleo o buscando",Datos!$AQ$2:$AQ$408,"Sí") -> 0 | F12: =IFERROR(E12/B12,"—") -> 0
A13: Otra área | B13: =COUNTIFS(Datos!$N$2:$N$408,"Otra área") -> 10 | C13: =IFERROR(B13/COUNTIFS(Datos!$M$2:$M$408,"Sí"),"—") -> 0.063291139 | D13: =COUNTIFS(Datos!$N$2:$N$408,"Otra área",Datos!$P$2:$P$408,"Sí") -> 6 | E13: =COUNTIFS(Datos!$N$2:$N$408,"Otra área",Datos!$AQ$2:$AQ$408,"Sí") -> 0 | F13: =IFERROR(E13/B13,"—") -> 0
A14: Agrupado por palabras de lo que contestó en 24 h. Si trabaja y estudia, cuenta su área de trabajo.
A16: Señales y conversión
A17: Señal | B17: Sí: leads | C17: Sí: ventas | D17: Sí: conversión | E17: No: leads | F17: No: ventas | G17: No: conversión
A18: Contestó el saludo | B18: =COUNTIFS(Datos!$G$2:$G$408,"Sí") -> 256 | C18: =COUNTIFS(Datos!$G$2:$G$408,"Sí",Datos!$AQ$2:$AQ$408,"Sí") -> 7 | D18: =IFERROR(C18/B18,"—") -> 0.02734375 | E18: =COUNTIFS(Datos!$G$2:$G$408,"No") -> 151 | F18: =COUNTIFS(Datos!$G$2:$G$408,"No",Datos!$AQ$2:$AQ$408,"Sí") -> 3 | G18: =IFERROR(F18/E18,"—") -> 0.01986755
A19: Contestó la ocupación | B19: =COUNTIFS(Datos!$M$2:$M$408,"Sí") -> 158 | C19: =COUNTIFS(Datos!$M$2:$M$408,"Sí",Datos!$AQ$2:$AQ$408,"Sí") -> 3 | D19: =IFERROR(C19/B19,"—") -> 0.018987342 | E19: =COUNTIFS(Datos!$M$2:$M$408,"No") -> 249 | F19: =COUNTIFS(Datos!$M$2:$M$408,"No",Datos!$AQ$2:$AQ$408,"Sí") -> 7 | G19: =IFERROR(F19/E19,"—") -> 0.02811245
A20: Abrió algún link | B20: =COUNTIFS(Datos!$AG$2:$AG$408,"Sí") -> 105 | C20: =COUNTIFS(Datos!$AG$2:$AG$408,"Sí",Datos!$AQ$2:$AQ$408,"Sí") -> 7 | D20: =IFERROR(C20/B20,"—") -> 0.066666667 | E20: =COUNTIFS(Datos!$AG$2:$AG$408,"No") -> 302 | F20: =COUNTIFS(Datos!$AG$2:$AG$408,"No",Datos!$AQ$2:$AQ$408,"Sí") -> 3 | G20: =IFERROR(F20/E20,"—") -> 0.0099337748
A21: Recibió audio del equipo | B21: =COUNTIFS(Datos!$Y$2:$Y$408,"Sí") -> 156 | C21: =COUNTIFS(Datos!$Y$2:$Y$408,"Sí",Datos!$AQ$2:$AQ$408,"Sí") -> 4 | D21: =IFERROR(C21/B21,"—") -> 0.025641026 | E21: =COUNTIFS(Datos!$Y$2:$Y$408,"No") -> 251 | F21: =COUNTIFS(Datos!$Y$2:$Y$408,"No",Datos!$AQ$2:$AQ$408,"Sí") -> 6 | G21: =IFERROR(F21/E21,"—") -> 0.023904382
A22: Intervino auxiliar | B22: =COUNTIFS(Datos!$S$2:$S$408,"Sí") -> 209 | C22: =COUNTIFS(Datos!$S$2:$S$408,"Sí",Datos!$AQ$2:$AQ$408,"Sí") -> 8 | D22: =IFERROR(C22/B22,"—") -> 0.038277512 | E22: =COUNTIFS(Datos!$S$2:$S$408,"No") -> 198 | F22: =COUNTIFS(Datos!$S$2:$S$408,"No",Datos!$AQ$2:$AQ$408,"Sí") -> 2 | G22: =IFERROR(F22/E22,"—") -> 0.01010101
A23: Entró de 9 a 21 h | B23: =COUNTIFS(Datos!$F$2:$F$408,"Sí") -> 305 | C23: =COUNTIFS(Datos!$F$2:$F$408,"Sí",Datos!$AQ$2:$AQ$408,"Sí") -> 9 | D23: =IFERROR(C23/B23,"—") -> 0.029508197 | E23: =COUNTIFS(Datos!$F$2:$F$408,"No") -> 102 | F23: =COUNTIFS(Datos!$F$2:$F$408,"No",Datos!$AQ$2:$AQ$408,"Sí") -> 1 | G23: =IFERROR(F23/E23,"—") -> 0.0098039216
A24: Recibió oferta | B24: =COUNTIFS(Datos!$Z$2:$Z$408,"Sí") -> 352 | C24: =COUNTIFS(Datos!$Z$2:$Z$408,"Sí",Datos!$AQ$2:$AQ$408,"Sí") -> 8 | D24: =IFERROR(C24/B24,"—") -> 0.022727273 | E24: =COUNTIFS(Datos!$Z$2:$Z$408,"No") -> 55 | F24: =COUNTIFS(Datos!$Z$2:$Z$408,"No",Datos!$AQ$2:$AQ$408,"Sí") -> 2 | G24: =IFERROR(F24/E24,"—") -> 0.036363636
A25: Relación, no causa. Con pocas ventas, cada caso pesa mucho.
A27: Links que abrió el lead (aviso del CRM)
A28: Link | B28: Leads | C28: % de los leads | D28: Ventas | E28: Conversión
A29: Su ruta (temario) | B29: =COUNTIFS(Datos!$AH$2:$AH$408,"*Ruta*") -> 81 | C29: =IFERROR(B29/COUNT(Datos!$B$2:$B$408),"—") -> 0.1990172 | D29: =COUNTIFS(Datos!$AH$2:$AH$408,"*Ruta*",Datos!$AQ$2:$AQ$408,"Sí") -> 5 | E29: =IFERROR(D29/B29,"—") -> 0.061728395
A30: Clase demo | B30: =COUNTIFS(Datos!$AH$2:$AH$408,"*Clase demo*") -> 27 | C30: =IFERROR(B30/COUNT(Datos!$B$2:$B$408),"—") -> 0.066339066 | D30: =COUNTIFS(Datos!$AH$2:$AH$408,"*Clase demo*",Datos!$AQ$2:$AQ$408,"Sí") -> 4 | E30: =IFERROR(D30/B30,"—") -> 0.14814815
A31: Mapa de las 64 certificaciones | B31: =COUNTIFS(Datos!$AH$2:$AH$408,"*Mapa 64*") -> 13 | C31: =IFERROR(B31/COUNT(Datos!$B$2:$B$408),"—") -> 0.031941032 | D31: =COUNTIFS(Datos!$AH$2:$AH$408,"*Mapa 64*",Datos!$AQ$2:$AQ$408,"Sí") -> 2 | E31: =IFERROR(D31/B31,"—") -> 0.15384615
A32: Perfil profesional de ejemplo | B32: =COUNTIFS(Datos!$AH$2:$AH$408,"*Perfil ejemplo*") -> 3 | C32: =IFERROR(B32/COUNT(Datos!$B$2:$B$408),"—") -> 0.0073710074 | D32: =COUNTIFS(Datos!$AH$2:$AH$408,"*Perfil ejemplo*",Datos!$AQ$2:$AQ$408,"Sí") -> 0 | E32: =IFERROR(D32/B32,"—") -> 0
A34: Por asesor asignado
A35: Asesor | B35: Leads | C35: % de los leads | D35: % que contestó el saludo | E35: Min. a la 1a acción (mediana) | F35: Horas al 1er mensaje (mediana) | G35: Ventas | H35: Conversión | I35: % de los leads fuera de horario
A36: Salma | B36: =COUNTIFS(Datos!$R$2:$R$408,"Salma") -> 278 | C36: =IFERROR(B36/COUNT(Datos!$B$2:$B$408),"—") -> 0.68304668 | D36: =IFERROR(COUNTIFS(Datos!$R$2:$R$408,"Salma",Datos!$G$2:$G$408,"Sí")/B36,"—") -> 0.52517986 | E36: {=IFERROR(MEDIAN(IF((Datos!$R$2:$R$408="Salma")*(Datos!$V$2:$V$408<>""),Datos!$V$2:$V$408)),"—")} -> 45.35 | F36: {=IFERROR(MEDIAN(IF((Datos!$R$2:$R$408="Salma")*(Datos!$T$2:$T$408<>""),Datos!$T$2:$T$408))/60,"—")} -> 35.635 | G36: =COUNTIFS(Datos!$R$2:$R$408,"Salma",Datos!$AQ$2:$AQ$408,"Sí") -> 4 | H36: =IFERROR(G36/B36,"—") -> 0.014388489 | I36: =IFERROR(COUNTIFS(Datos!$R$2:$R$408,"Salma",Datos!$F$2:$F$408,"No")/COUNTIFS(Datos!$F$2:$F$408,"No"),"—") -> 0.84313725
A37: Alexander | B37: =COUNTIFS(Datos!$R$2:$R$408,"Alexander") -> 77 | C37: =IFERROR(B37/COUNT(Datos!$B$2:$B$408),"—") -> 0.18918919 | D37: =IFERROR(COUNTIFS(Datos!$R$2:$R$408,"Alexander",Datos!$G$2:$G$408,"Sí")/B37,"—") -> 0.83116883 | E37: {=IFERROR(MEDIAN(IF((Datos!$R$2:$R$408="Alexander")*(Datos!$V$2:$V$408<>""),Datos!$V$2:$V$408)),"—")} -> 1.8 | F37: {=IFERROR(MEDIAN(IF((Datos!$R$2:$R$408="Alexander")*(Datos!$T$2:$T$408<>""),Datos!$T$2:$T$408))/60,"—")} -> 0.33666667 | G37: =COUNTIFS(Datos!$R$2:$R$408,"Alexander",Datos!$AQ$2:$AQ$408,"Sí") -> 2 | H37: =IFERROR(G37/B37,"—") -> 0.025974026 | I37: =IFERROR(COUNTIFS(Datos!$R$2:$R$408,"Alexander",Datos!$F$2:$F$408,"No")/COUNTIFS(Datos!$F$2:$F$408,"No"),"—") -> 0.098039216
A38: Victoria | B38: =COUNTIFS(Datos!$R$2:$R$408,"Victoria") -> 48 | C38: =IFERROR(B38/COUNT(Datos!$B$2:$B$408),"—") -> 0.11793612 | D38: =IFERROR(COUNTIFS(Datos!$R$2:$R$408,"Victoria",Datos!$G$2:$G$408,"Sí")/B38,"—") -> 0.875 | E38: {=IFERROR(MEDIAN(IF((Datos!$R$2:$R$408="Victoria")*(Datos!$V$2:$V$408<>""),Datos!$V$2:$V$408)),"—")} -> 2 | F38: {=IFERROR(MEDIAN(IF((Datos!$R$2:$R$408="Victoria")*(Datos!$T$2:$T$408<>""),Datos!$T$2:$T$408))/60,"—")} -> 0.37833333 | G38: =COUNTIFS(Datos!$R$2:$R$408,"Victoria",Datos!$AQ$2:$AQ$408,"Sí") -> 4 | H38: =IFERROR(G38/B38,"—") -> 0.083333333 | I38: =IFERROR(COUNTIFS(Datos!$R$2:$R$408,"Victoria",Datos!$F$2:$F$408,"No")/COUNTIFS(Datos!$F$2:$F$408,"No"),"—") -> 0.049019608
A39: Sin asignar | B39: =COUNTIFS(Datos!$R$2:$R$408,"Sin asignar") -> 4 | C39: =IFERROR(B39/COUNT(Datos!$B$2:$B$408),"—") -> 0.0098280098 | D39: =IFERROR(COUNTIFS(Datos!$R$2:$R$408,"Sin asignar",Datos!$G$2:$G$408,"Sí")/B39,"—") -> 1 | E39: {=IFERROR(MEDIAN(IF((Datos!$R$2:$R$408="Sin asignar")*(Datos!$V$2:$V$408<>""),Datos!$V$2:$V$408)),"—")} -> 1.3 | F39: {=IFERROR(MEDIAN(IF((Datos!$R$2:$R$408="Sin asignar")*(Datos!$T$2:$T$408<>""),Datos!$T$2:$T$408))/60,"—")} -> 0.42166667 | G39: =COUNTIFS(Datos!$R$2:$R$408,"Sin asignar",Datos!$AQ$2:$AQ$408,"Sí") -> 0 | H39: =IFERROR(G39/B39,"—") -> 0 | I39: =IFERROR(COUNTIFS(Datos!$R$2:$R$408,"Sin asignar",Datos!$F$2:$F$408,"No")/COUNTIFS(Datos!$F$2:$F$408,"No"),"—") -> 0.0098039216
A40: La última columna dice qué parte de los leads que entran fuera de horario queda a nombre de cada asesor.
A41: Asesor = a nombre de quién quedó el lead. Joceline apoya como auxiliar: los leads no quedan a su nombre.
A43: Cómo se cierran los Perdidos
A44: Concepto | B44: Leads | C44: % de los Perdidos | D44: Horas hasta Perdido (mediana)
A45: Los marcó una persona | B45: =COUNTIFS(Datos!$AL$2:$AL$408,"Persona") -> 266 | C45: =IFERROR(B45/COUNTIFS(Datos!$AK$2:$AK$408,"Perdido"),"—") -> 0.97080292 | D45: {=IFERROR(MEDIAN(IF((Datos!$AL$2:$AL$408="Persona")*(Datos!$AN$2:$AN$408<>""),Datos!$AN$2:$AN$408)),"—")} -> 87.4
A46: Los pasó el bot | B46: =COUNTIFS(Datos!$AL$2:$AL$408,"Bot") -> 8 | C46: =IFERROR(B46/COUNTIFS(Datos!$AK$2:$AK$408,"Perdido"),"—") -> 0.02919708 | D46: {=IFERROR(MEDIAN(IF((Datos!$AL$2:$AL$408="Bot")*(Datos!$AN$2:$AN$408<>""),Datos!$AN$2:$AN$408)),"—")} -> 129.3
A47: Razón: No contestaron | B47: =COUNTIFS(Datos!$AM$2:$AM$408,"No contestaron") -> 256 | C47: =IFERROR(B47/COUNTIFS(Datos!$AK$2:$AK$408,"Perdido"),"—") -> 0.93430657 | D47: {=IFERROR(MEDIAN(IF((Datos!$AM$2:$AM$408="No contestaron")*(Datos!$AN$2:$AN$408<>""),Datos!$AN$2:$AN$408)),"—")} -> 87
A48: Razón: Por el momento no | B48: =COUNTIFS(Datos!$AM$2:$AM$408,"Por el momento no") -> 3 | C48: =IFERROR(B48/COUNTIFS(Datos!$AK$2:$AK$408,"Perdido"),"—") -> 0.010948905 | D48: {=IFERROR(MEDIAN(IF((Datos!$AM$2:$AM$408="Por el momento no")*(Datos!$AN$2:$AN$408<>""),Datos!$AN$2:$AN$408)),"—")} -> 101.4
A49: Razón: No le interesa | B49: =COUNTIFS(Datos!$AM$2:$AM$408,"No le interesa") -> 4 | C49: =IFERROR(B49/COUNTIFS(Datos!$AK$2:$AK$408,"Perdido"),"—") -> 0.01459854 | D49: {=IFERROR(MEDIAN(IF((Datos!$AM$2:$AM$408="No le interesa")*(Datos!$AN$2:$AN$408<>""),Datos!$AN$2:$AN$408)),"—")} -> 42.2
A50: Sin razón | B50: =COUNTIFS(Datos!$AM$2:$AM$408,"Sin razón") -> 8 | C50: =IFERROR(B50/COUNTIFS(Datos!$AK$2:$AK$408,"Perdido"),"—") -> 0.02919708 | D50: {=IFERROR(MEDIAN(IF((Datos!$AM$2:$AM$408="Sin razón")*(Datos!$AN$2:$AN$408<>""),Datos!$AN$2:$AN$408)),"—")} -> 129.3
A51: Otra razón | B51: =COUNTIFS(Datos!$AK$2:$AK$408,"Perdido")-SUM(B47:B50) -> 3 | C51: =IFERROR(B51/COUNTIFS(Datos!$AK$2:$AK$408,"Perdido"),"—") -> 0.010948905

Sheet Datos
A1: Embudo | B1: ID (#) | C1: Entrada | D1: Semana | E1: Hora de entrada | F1: ¿Entró de 9 a 21 h? | G1: ¿Contestó el saludo? | H1: ¿Dio su nombre? | I1: ¿Llegó a 1.1? | J1: Minutos de su respuesta a 1.1 | K1: Lo pasó a 1.1 | L1: ¿Llegó a 1.2? | M1: ¿Contestó la ocupación? | N1: Ocupación | O1: ¿Entró a Negativo? | P1: ¿Llegó a facilidades de pago? | Q1: ¿Llegó a forma de pago? | R1: Asesor asignado | S1: ¿Intervino auxiliar? | T1: Minutos hasta el 1er mensaje de una persona | U1: 1er mensaje de una persona por | V1: Minutos hasta la 1a acción de una persona | W1: Mediana de minutos de respuesta de una persona | X1: Mensajes del lead sin respuesta de una persona | Y1: ¿Audio del equipo? | Z1: ¿Recibió oferta? | AA1: Ofertas recibidas | AB1: Primera oferta enviada por | AC1: Horas hasta la 1a oferta | AD1: Mensajes del lead | AE1: Mensajes del bot | AF1: Mensajes de personas | AG1: ¿Abrió algún link? | AH1: Links abiertos | AI1: Mensajes del bot bloqueados (24 h) | AJ1: Dejó de escribir en | AK1: Estado | AL1: Cómo llegó a Perdido | AM1: Razón de pérdida | AN1: Horas hasta Perdido | AO1: ¿Lo marcaron Perdido alguna vez? | AP1: ¿Escribió después de marcarlo Perdido? | AQ1: ¿Compró? | AR1: Precio de venta | AS1: Estado del cobro | AT1: Horas hasta la venta | AU1: Anuncio (utm_medium)
A2: ISO + Calidad | B2: 263 | C2: 46300.46 | D2: 2026-S41 | E2: 11 | F2: Sí | G2: No | H2: No | I2: No | L2: No | M2: No | O2: No | P2: No | Q2: No | R2: Alexander | S2: No | V2: 1619.3 | X2: 0 | Y2: No | Z2: No | AD2: 1 | AE2: 2 | AF2: 0 | AG2: No | AI2: 0 | AJ2: Solo su primer mensaje | AK2: Perdido | AL2: Persona | AM2: Lo está atendiendo Kommo: desde Kommo le escribieron a este cliente y se apagó | AN2: 27 | AO2: Sí | AP2: No | AQ2: No | AU2: plano
A3: ISO + Calidad | B3: 271 | C3: 46300.494 | D3: 2026-S41 | E3: 11 | F3: Sí | G3: No | H3: No | I3: Sí | K3: Bot | L3: Sí | M3: No | O3: Sí | P3: No | Q3: No | R3: Salma | S3: No | T3: 4649 | U3: Salma | V3: 4649 | X3: 0 | Y3: No | Z3: Sí | AA3: $3,799, $2,799 | AB3: Bot | AC3: 26.6 | AD3: 1 | AE3: 22 | AF3: 1 | AG3: No | AI3: 0 | AJ3: Solo su primer mensaje | AK3: Perdido | AL3: Persona | AM3: No contestaron | AN3: 77.5 | AO3: Sí | AP3: No | AQ3: No | AU3: Plano
A4: ISO + Calidad | B4: 276 | C4: 46300.516 | D4: 2026-S41 | E4: 12 | F4: Sí | G4: Sí | H4: Sí | I4: Sí | J4: 0.3 | K4: Salma | L4: Sí | M4: Sí | N4: Supervisión o jefatura | O4: Sí | P4: Sí | Q4: No | R4: Salma | S4: No | T4: 3.8 | U4: Salma | V4: 0.5 | W4: 0.2 | X4: 0 | Y4: Sí | Z4: Sí | AA4: $3,799, $2,799 | AB4: Bot | AC4: 28.4 | AD4: 5 | AE4: 23 | AF4: 7 | AG4: Sí | AH4: Ruta | AI4: 0 | AJ4: 1.2 Lista de cursos | AK4: Perdido | AL4: Persona | AM4: No contestaron | AN4: 76.6 | AO4: Sí | AP4: No | AQ4: No | AU4: GreenBelt
A5: ISO + Calidad | B5: 277 | C5: 46300.519 | D5: 2026-S41 | E5: 12 | F5: Sí | G5: No | H5: No | I5: Sí | K5: Bot | L5: Sí | M5: Sí | N5: Calidad | O5: Sí | P5: Sí | Q5: No | R5: Alexander | S5: Sí | T5: 106.2 | U5: Alexander | V5: 104.3 | W5: 1.6 | X5: 0 | Y5: Sí | Z5: Sí | AA5: $3,799, $2,799 | AB5: Bot | AC5: 30.2 | AD5: 3 | AE5: 30 | AF5: 4 | AG5: Sí | AH5: Ruta | AI5: 0 | AJ5: 1.2 Lista de cursos | AK5: Perdido | AL5: Persona | AM5: No contestaron | AN5: 72.8 | AO5: Sí | AP5: No | AQ5: No | AU5: 50% Descuento DC-3👉
A6: ISO + Calidad | B6: 278 | C6: 46300.521 | D6: 2026-S41 | E6: 12 | F6: Sí | G6: Sí | H6: Sí | I6: Sí | J6: 0.2 | K6: Joceline | L6: Sí | M6: Sí | N6: Calidad | O6: Sí | P6: Sí | Q6: No | R6: Salma | S6: Sí | T6: 3.9 | U6: Salma | V6: 0.5 | W6: 2 | X6: 0 | Y6: Sí | Z6: Sí | AA6: $3,799, $2,799 | AB6: Bot | AC6: 28.4 | AD6: 5 | AE6: 23 | AF6: 6 | AG6: Sí | AH6: Ruta | AI6: 0 | AJ6: Facilidades de pago | AK6: Perdido | AL6: Persona | AM6: No contestaron | AN6: 76.5 | AO6: Sí | AP6: No | AQ6: No | AU6: PLANO #2
A7: ISO + Calidad | B7: 280 | C7: 46300.523 | D7: 2026-S41 | E7: 12 | F7: Sí | G7: No | H7: No | I7: Sí | K7: Bot | L7: Sí | M7: No | O7: Sí | P7: No | Q7: No | R7: Salma | S7: No | T7: 4591.9 | U7: Salma | V7: 4591.9 | X7: 0 | Y7: No | Z7: Sí | AA7: $3,799, $2,799 | AB7: Bot | AC7: 26.6 | AD7: 1 | AE7: 22 | AF7: 1 | AG7: No | AI7: 0 | AJ7: Solo su primer mensaje | AK7: Perdido | AL7: Persona | AM7: No contestaron | AN7: 76.5 | AO7: Sí | AP7: No | AQ7: No | AU7: 50% Descuento DC-3👉
A8: ISO + Calidad | B8: 282 | C8: 46300.535 | D8: 2026-S41 | E8: 12 | F8: Sí | G8: No | H8: No | I8: Sí | K8: Salma | L8: Sí | M8: No | O8: Sí | P8: Sí | Q8: Sí | R8: Salma | S8: No | T8: 0.4 | U8: Salma | V8: 0.3 | W8: 0.4 | X8: 0 | Y8: Sí | Z8: Sí | AA8: $3,799, $2,799 | AB8: Bot | AC8: 26.1 | AD8: 1 | AE8: 23 | AF8: 2 | AG8: No | AI8: 4 | AJ8: Saludo: contestó y no volvió | AK8: Abierto | AO8: Sí | AP8: No | AQ8: No
A9: ISO + Calidad | B9: 285 | C9: 46300.55 | D9: 2026-S41 | E9: 13 | F9: Sí | G9: No | H9: No | I9: Sí | K9: Bot | L9: Sí | M9: No | O9: Sí | P9: No | Q9: No | R9: Alexander | S9: No | T9: 6024.2 | U9: Alexander | V9: 6024.2 | X9: 0 | Y9: No | Z9: Sí | AA9: $3,799, $2,799 | AB9: Bot | AC9: 26.6 | AD9: 1 | AE9: 23 | AF9: 1 | AG9: No | AI9: 0 | AJ9: Solo su primer mensaje | AK9: Perdido | AL9: Persona | AM9: No contestaron | AN9: 100.4 | AO9: Sí | AP9: No | AQ9: No | AU9: 50% Descuento DC-3👉
A10: ISO + Calidad | B10: 287 | C10: 46300.559 | D10: 2026-S41 | E10: 13 | F10: Sí | G10: No | H10: No | I10: Sí | K10: Bot | L10: Sí | M10: Sí | N10: Producción u operaciones | O10: Sí | P10: Sí | Q10: No | R10: Victoria | S10: No | T10: 65.4 | U10: Salma | V10: 65.4 | W10: 4 | X10: 1 | Y10: Sí | Z10: Sí | AA10: $3,799, $2,799 | AB10: Bot | AC10: 29.5 | AD10: 5 | AE10: 24 | AF10: 5 | AG10: No | AI10: 0 | AJ10: Ya marcado como Perdido | AK10: Perdido | AL10: Persona | AM10: No contestaron | AN10: 75.7 | AO10: Sí | AP10: Sí | AQ10: No | AU10: 50% Descuento DC-3👉
A11: ISO + Calidad | B11: 291 | C11: 46300.572 | D11: 2026-S41 | E11: 13 | F11: Sí | G11: Sí | H11: Sí | I11: Sí | J11: 0.5 | K11: Victoria | L11: Sí | M11: No | O11: Sí | P11: No | Q11: No | R11: Victoria | S11: No | T11: 4538.3 | U11: Salma | V11: 0.8 | W11: 4538 | X11: 0 | Y11: No | Z11: Sí | AA11: $3,799, $2,799 | AB11: Bot | AC11: 26.1 | AD11: 2 | AE11: 21 | AF11: 1 | AG11: No | AI11: 0 | AJ11: Saludo: contestó y no volvió | AK11: Perdido | AL11: Persona | AM11: No contestaron | AN11: 75.6 | AO11: Sí | AP11: No | AQ11: No | AU11: 50% Descuento DC-3👉
A12: ISO + Calidad | B12: 292 | C12: 46300.576 | D12: 2026-S41 | E12: 13 | F12: Sí | G12: No | H12: No | I12: Sí | K12: Bot | L12: Sí | M12: No | O12: Sí | P12: No | Q12: No | R12: Salma | S12: No | T12: 4531.8 | U12: Salma | V12: 4531.8 | X12: 0 | Y12: No | Z12: Sí | AA12: $3,799, $2,799 | AB12: Bot | AC12: 26.6 | AD12: 1 | AE12: 22 | AF12: 1 | AG12: No | AI12: 0 | AJ12: Solo su primer mensaje | AK12: Perdido | AL12: Persona | AM12: No contestaron | AN12: 75.5 | AO12: Sí | AP12: No | AQ12: No | AU12: 50% Descuento DC-3👉
A13: ISO + Calidad | B13: 295 | C13: 46300.611 | D13: 2026-S41 | E13: 14 | F13: Sí | G13: Sí | H13: Sí | I13: Sí | J13: 0.5 | K13: Joceline | L13: Sí | M13: Sí | N13: Estudiante o recién egresado | O13: Sí | P13: No | Q13: No | R13: Victoria | S13: Sí | T13: 12.6 | U13: Victoria | V13: 2.4 | W13: 1.1 | X13: 0 | Y13: No | Z13: Sí | AA13: $3,799, $2,799 | AB13: Bot | AC13: 26.1 | AD13: 6 | AE13: 22 | AF13: 5 | AG13: No | AI13: 0 | AJ13: 1.2 Lista de cursos | AK13: Perdido | AL13: Bot | AM13: Sin razón | AN13: 118.3 | AO13: Sí | AP13: No | AQ13: No | AU13: 50% Descuento DC-3👉
A14: ISO + Calidad | B14: 296 | C14: 46300.613 | D14: 2026-S41 | E14: 14 | F14: Sí | G14: Sí | H14: Sí | I14: Sí | J14: 0.2 | K14: Victoria | L14: Sí | M14: Sí | N14: Estudiante o recién egresado | O14: Sí | P14: Sí | Q14: No | R14: Victoria | S14: No | T14: 32.8 | U14: Salma | V14: 0.4 | W14: 4.3 | X14: 0 | Y14: Sí | Z14: Sí | AA14: $3,799, $2,799 | AB14: Bot | AC14: 46.3 | AD14: 4 | AE14: 21 | AF14: 5 | AG14: No | AI14: 0 | AJ14: 1.2 Lista de cursos | AK14: Perdido | AL14: Persona | AM14: No contestaron | AN14: 139.1 | AO14: Sí | AP14: No | AQ14: No | AU14: 50% Descuento DC-3👉
A15: ISO + Calidad | B15: 298 | C15: 46300.617 | D15: 2026-S41 | E15: 14 | F15: Sí | G15: Sí | H15: Sí | I15: Sí | J15: 0.4 | K15: Salma | L15: Sí | M15: Sí | N15: Estudiante o recién egresado | O15: Sí | P15: Sí | Q15: No | R15: Salma | S15: No | T15: 5.1 | U15: Salma | V15: 1.8 | W15: 0.9 | X15: 0 | Y15: Sí | Z15: Sí | AA15: $3,799, $2,799 | AB15: Bot | AC15: 46.2 | AD15: 6 | AE15: 22 | AF15: 8 | AG15: Sí | AH15: Ruta | AI15: 0 | AJ15: Facilidades de pago | AK15: Perdido | AL15: Persona | AM15: No contestaron | AN15: 139 | AO15: Sí | AP15: No | AQ15: No | AU15: 50% Descuento DC-3👉
A16: ISO + Calidad | B16: 307 | C16: 46300.662 | D16: 2026-S41 | E16: 15 | F16: Sí | G16: Sí | H16: Sí | I16: Sí | J16: 0.2 | K16: Alexander | L16: Sí | M16: No | O16: Sí | P16: No | Q16: No | R16: Alexander | S16: No | T16: 5859.8 | U16: Alexander | V16: 0.6 | W16: 5858.7 | X16: 0 | Y16: No | Z16: Sí | AA16: $3,799, $2,799 | AB16: Bot | AC16: 26.1 | AD16: 3 | AE16: 22 | AF16: 1 | AG16: No | AI16: 0 | AJ16: 1.2 Lista de cursos | AK16: Perdido | AL16: Persona | AM16: No contestaron | AN16: 97.7 | AO16: Sí | AP16: No | AQ16: No | AU16: 50% Descuento DC-3👉
A17: ISO + Calidad | B17: 308 | C17: 46300.663 | D17: 2026-S41 | E17: 15 | F17: Sí | G17: No | H17: No | I17: Sí | K17: Bot | L17: Sí | M17: Sí | N17: Ingeniería | O17: Sí | P17: Sí | Q17: No | R17: Salma | S17: No | T17: 96 | U17: Salma | V17: 96 | W17: 4.8 | X17: 0 | Y17: Sí | Z17: Sí | AA17: $3,799, $2,799 | AB17: Salma | AC17: 73.5 | AD17: 7 | AE17: 16 | AF17: 11 | AG17: Sí | AH17: Ruta | AI17: 0 | AJ17: Facilidades de pago | AK17: Perdido | AL17: Persona | AM17: No contestaron | AN17: 160.9 | AO17: Sí | AP17: No | AQ17: No | AU17: 50% Descuento DC-3👉
A18: ISO + Calidad | B18: 311 | C18: 46300.682 | D18: 2026-S41 | E18: 16 | F18: Sí | G18: No | H18: No | I18: Sí | K18: Bot | L18: Sí | M18: No | O18: Sí | P18: No | Q18: No | R18: Alexander | S18: No | T18: 5834.1 | U18: Alexander | V18: 5834.1 | X18: 0 | Y18: No | Z18: Sí | AA18: $3,799, $2,799 | AB18: Bot | AC18: 26.6 | AD18: 1 | AE18: 23 | AF18: 1 | AG18: No | AI18: 0 | AJ18: Solo su primer mensaje | AK18: Perdido | AL18: Persona | AM18: No contestaron | AN18: 97.2 | AO18: Sí | AP18: No | AQ18: No | AU18: 50% Descuento DC-3👉
A19: ISO + Calidad | B19: 313 | C19: 46300.693 | D19: 2026-S41 | E19: 16 | F19: Sí | G19: Sí | H19: Sí | I19: Sí | J19: 0.3 | K19: Victoria | L19: Sí | M19: Sí | N19: Sin empleo o buscando | O19: Sí | P19: Sí | Q19: No | R19: Victoria | S19: No | T19: 14.3 | U19: Victoria | V19: 0.6 | W19: 7.8 | X19: 0 | Y19: No | Z19: Sí | AA19: $3,799, $2,799 | AB19: Bot | AC19: 44.4 | AD19: 5 | AE19: 24 | AF19: 2 | AG19: No | AI19: 0 | AJ19: 1.2 Lista de cursos | AK19: Perdido | AL19: Bot | AM19: Sin razón | AN19: 140.4 | AO19: Sí | AP19: No | AQ19: No | AU19: 50% Descuento DC-3👉
A20: ISO + Calidad | B20: 314 | C20: 46300.698 | D20: 2026-S41 | E20: 16 | F20: Sí | G20: Sí | H20: No | I20: Sí | J20: 9.6 | K20: Bot | L20: Sí | M20: No | O20: Sí | P20: No | Q20: No | R20: Salma | S20: No | T20: 4363.9 | U20: Salma | V20: 4363.9 | W20: 4343.3 | X20: 0 | Y20: No | Z20: Sí | AA20: $3,799, $2,799 | AB20: Bot | AC20: 44.3 | AD20: 2 | AE20: 22 | AF20: 2 | AG20: No | AI20: 0 | AJ20: Saludo: contestó y no volvió | AK20: Perdido | AL20: Persona | AM20: No contestaron | AN20: 91.5 | AO20: Sí | AP20: No | AQ20: No | AU20: 50% Descuento DC-3👉
A21: ISO + Calidad | B21: 317 | C21: 46300.747 | D21: 2026-S41 | E21: 17 | F21: Sí | G21: Sí | H21: Sí | I21: Sí | J21: 0.2 | K21: Victoria | L21: Sí | M21: Sí | N21: Calidad | O21: Sí | P21: Sí | Q21: Sí | R21: Victoria | S21: No | T21: 10.6 | U21: Victoria | V21: 2.8 | W21: 0.7 | X21: 0 | Y21: No | Z21: Sí | AA21: $3,799, $2,799 | AB21: Bot | AC21: 43.1 | AD21: 16 | AE21: 31 | AF21: 13 | AG21: No | AI21: 0 | AJ21: Facilidades de pago | AK21: Perdido | AL21: Bot | AM21: Sin razón | AN21: 139.1 | AO21: Sí | AP21: No | AQ21: No | AU21: Verde
A22: ISO + Calidad | B22: 319 | C22: 46300.758 | D22: 2026-S41 | E22: 18 | F22: Sí | G22: No | H22: No | I22: Sí | K22: Bot | L22: Sí | M22: No | O22: Sí | P22: No | Q22: No | R22: Alexander | S22: No | T22: 5714.9 | U22: Alexander | V22: 5714.9 | X22: 0 | Y22: No | Z22: Sí | AA22: $3,799, $2,799 | AB22: Bot | AC22: 42.8 | AD22: 1 | AE22: 22 | AF22: 2 | AG22: No | AI22: 0 | AJ22: Solo su primer mensaje | AK22: Perdido | AL22: Persona | AM22: No contestaron | AN22: 95.3 | AO22: Sí | AP22: No | AQ22: No | AU22: 50% Descuento DC-3👉
A23: ISO + Calidad | B23: 321 | C23: 46300.761 | D23: 2026-S41 | E23: 18 | F23: Sí | G23: Sí | H23: Sí | I23: Sí | J23: 0.4 | K23: Victoria | L23: Sí | M23: No | O23: Sí | P23: No | Q23: No | R23: Victoria | S23: No | T23: 935.8 | U23: Victoria | V23: 6.9 | W23: 929.2 | X23: 0 | Y23: No | Z23: Sí | AA23: $3,799, $2,799 | AB23: Bot | AC23: 42.8 | AD23: 2 | AE23: 22 | AF23: 1 | AG23: No | AI23: 0 | AJ23: Saludo: contestó y no volvió | AK23: Perdido | AL23: Bot | AM23: Sin razón | AN23: 138.7 | AO23: Sí | AP23: No | AQ23: No | AU23: 50% Descuento DC-3👉
A24: ISO + Calidad | B24: 322 | C24: 46300.781 | D24: 2026-S41 | E24: 18 | F24: Sí | G24: No | H24: No | I24: Sí | K24: Bot | L24: Sí | M24: No | O24: Sí | P24: No | Q24: No | R24: Salma | S24: No | T24: 4244.9 | U24: Salma | V24: 4244.9 | X24: 0 | Y24: No | Z24: Sí | AA24: $3,799, $2,799 | AB24: Bot | AC24: 42.3 | AD24: 1 | AE24: 23 | AF24: 1 | AG24: No | AI24: 0 | AJ24: Solo su primer mensaje | AK24: Perdido | AL24: Bot | AM24: Sin razón | AN24: 138.3 | AO24: Sí | AP24: No | AQ24: No | AU24: 50% Descuento DC-3👉
A25: ISO + Calidad | B25: 323 | C25: 46300.798 | D25: 2026-S41 | E25: 19 | F25: Sí | G25: No | H25: No | I25: Sí | K25: Bot | L25: Sí | M25: No | O25: Sí | P25: No | Q25: No | R25: Salma | S25: No | T25: 4219.4 | U25: Salma | V25: 4219.4 | X25: 0 | Y25: No | Z25: Sí | AA25: $3,799, $2,799 | AB25: Bot | AC25: 41.9 | AD25: 1 | AE25: 23 | AF25: 2 | AG25: No | AI25: 0 | AJ25: Solo su primer mensaje | AK25: Perdido | AL25: Persona | AM25: No contestaron | AN25: 134.6 | AO25: Sí | AP25: No | AQ25: No | AU25: 50% Descuento DC-3👉
A26: ISO + Calidad | B26: 330 | C26: 46300.88 | D26: 2026-S41 | E26: 21 | F26: No | G26: Sí | H26: Sí | I26: Sí | J26: 2.1 | K26: Victoria | L26: Sí | M26: No | O26: Sí | P26: No | Q26: No | R26: Salma | S26: No | T26: 4102 | U26: Salma | V26: 2.4 | W26: 4101.8 | X26: 0 | Y26: No | Z26: Sí | AA26: $3,799, $2,799 | AB26: Bot | AC26: 39.9 | AD26: 3 | AE26: 19 | AF26: 1 | AG26: No | AI26: 0 | AJ26: Saludo: contestó y no volvió | AK26: Perdido | AL26: Persona | AM26: No contestaron | AN26: 132.7 | AO26: Sí | AP26: No | AQ26: No | AU26: 50% Descuento DC-3👉
A27: ISO + Calidad | B27: 331 | C27: 46300.882 | D27: 2026-S41 | E27: 21 | F27: No | G27: No | H27: No | I27: Sí | K27: Bot | L27: Sí | M27: No | O27: Sí | P27: No | Q27: No | R27: Salma | S27: No | T27: 4098.3 | U27: Salma | V27: 4098.3 | X27: 0 | Y27: No | Z27: Sí | AA27: $3,799, $2,799 | AB27: Bot | AC27: 39.9 | AD27: 1 | AE27: 20 | AF27: 1 | AG27: No | AI27: 0 | AJ27: Solo su primer mensaje | AK27: Perdido | AL27: Persona | AM27: No contestaron | AN27: 132.6 | AO27: Sí | AP27: No | AQ27: No | AU27: 50% Descuento DC-3👉
A28: ISO + Calidad | B28: 334 | C28: 46300.897 | D28: 2026-S41 | E28: 21 | F28: No | G28: No | H28: No | I28: Sí | K28: Bot | L28: Sí | M28: No | O28: Sí | P28: No | Q28: No | R28: Salma | S28: No | T28: 4076.7 | U28: Salma | V28: 4076.7 | X28: 0 | Y28: No | Z28: Sí | AA28: $3,799, $2,799 | AB28: Bot | AC28: 39.5 | AD28: 1 | AE28: 19 | AF28: 2 | AG28: No | AI28: 0 | AJ28: Solo su primer mensaje | AK28: Perdido | AL28: Persona | AM28: No contestaron | AN28: 84.8 | AO28: Sí | AP28: No | AQ28: No | AU28: 50% Descuento DC-3👉
A29: ISO + Calidad | B29: 335 | C29: 46300.9 | D29: 2026-S41 | E29: 21 | F29: No | G29: No | H29: No | I29: Sí | K29: Bot | L29: Sí | M29: No | O29: Sí | P29: No | Q29: No | R29: Salma | S29: No | T29: 4072.1 | U29: Salma | V29: 4072.1 | X29: 0 | Y29: No | Z29: Sí | AA29: $3,799, $2,799 | AB29: Bot | AC29: 39.4 | AD29: 1 | AE29: 20 | AF29: 1 | AG29: No | AI29: 0 | AJ29: Solo su primer mensaje | AK29: Perdido | AL29: Persona | AM29: No contestaron | AN29: 132.2 | AO29: Sí | AP29: No | AQ29: No | AU29: 50% Descuento DC-3👉
A30: ISO + Calidad | B30: 336 | C30: 46300.901 | D30: 2026-S41 | E30: 21 | F30: No | G30: Sí | H30: Sí | I30: Sí | J30: 0.3 | K30: Victoria | L30: Sí | M30: No | O30: Sí | P30: No | Q30: No | R30: Alexander | S30: No | T30: 5516.2 | U30: Alexander | V30: 1.2 | W30: 5515.3 | X30: 1 | Y30: No | Z30: Sí | AA30: $3,799, $2,799 | AB30: Bot | AC30: 39.4 | AD30: 3 | AE30: 21 | AF30: 1 | AG30: Sí | AH30: Ruta | AI30: 0 | AJ30: Ya marcado como Perdido | AK30: Perdido | AL30: Persona | AM30: No contestaron | AN30: 91.9 | AO30: Sí | AP30: Sí | AQ30: No | AU30: 50% Descuento DC-3👉
A31: ISO + Calidad | B31: 342 | C31: 46300.978 | D31: 2026-S41 | E31: 23 | F31: No | G31: No | H31: No | I31: Sí | K31: Bot | L31: Sí | M31: No | O31: Sí | P31: No | Q31: No | R31: Salma | S31: No | T31: 3960 | U31: Salma | V31: 3960 | X31: 0 | Y31: No | Z31: Sí | AA31: $3,799, $2,799 | AB31: Bot | AC31: 37.6 | AD31: 1 | AE31: 19 | AF31: 2 | AG31: Sí | AH31: Ruta | AI31: 0 | AJ31: Solo su primer mensaje | AK31: Perdido | AL31: Persona | AM31: No contestaron | AN31: 82.9 | AO31: Sí | AP31: No | AQ31: No | AU31: 50% Descuento DC-3👉
A32: ISO + Calidad | B32: 348 | C32: 46301.323 | D32: 2026-S41 | E32: 7 | F32: No | G32: Sí | H32: Sí | I32: Sí | J32: 0.2 | K32: Salma | L32: Sí | M32: Sí | N32: Calidad | O32: Sí | P32: Sí | Q32: Sí | R32: Salma | S32: Sí | T32: 26.4 | U32: Joceline | V32: 0.9 | W32: 1.9 | X32: 0 | Y32: Sí | Z32: Sí | AA32: $3,799, $2,799 | AB32: Salma | AC32: 53.2 | AD32: 15 | AE32: 16 | AF32: 26 | AG32: Sí | AH32: Clase demo | AI32: 0 | AJ32: Ya marcado como Perdido | AK32: Perdido | AL32: Persona | AM32: Por el momento no | AN32: 97.9 | AO32: Sí | AP32: Sí | AQ32: No | AU32: 50% Descuento DC-3👉
A33: ISO + Calidad | B33: 350 | C33: 46301.326 | D33: 2026-S41 | E33: 7 | F33: No | G33: No | H33: No | I33: Sí | K33: Bot | L33: Sí | M33: Sí | N33: Supervisión o jefatura | O33: No | P33: No | Q33: No | R33: Salma | S33: Sí | T33: 41.3 | U33: Joceline | V33: 41.3 | W33: 0.7 | X33: 0 | Y33: Sí | Z33: Sí | AA33: $3,799, $2,799 | AB33: Salma | AC33: 57.9 | AD33: 6 | AE33: 9 | AF33: 11 | AG33: No | AI33: 0 | AJ33: 1.2 Lista de cursos | AK33: Perdido | AL33: Persona | AM33: No contestaron | AN33: 122 | AO33: Sí | AP33: No | AQ33: No | AU33: 50% Descuento DC-3👉
A34: ISO + Calidad | B34: 357 | C34: 46301.351 | D34: 2026-S41 | E34: 8 | F34: No | G34: Sí | H34: No | I34: Sí | J34: 2.8 | K34: Joceline | L34: Sí | M34: No | O34: Sí | P34: No | Q34: No | R34: Salma | S34: Sí | T34: 0.6 | U34: Joceline | V34: 0.6 | W34: 0.4 | X34: 0 | Y34: No | Z34: Sí | AA34: $3,799, $2,799 | AB34: Bot | AC34: 28.6 | AD34: 2 | AE34: 18 | AF34: 4 | AG34: No | AI34: 0 | AJ34: Saludo: contestó y no volvió | AK34: Perdido | AL34: Persona | AM34: No contestaron | AN34: 76.2 | AO34: Sí | AP34: No | AQ34: No | AU34: 50% Descuento DC-3👉
A35: ISO + Calidad | B35: 359 | C35: 46301.375 | D35: 2026-S41 | E35: 8 | F35: No | G35: Sí | H35: Sí | I35: Sí | J35: 0.2 | K35: Salma | L35: Sí | M35: Sí | N35: Estudiante o recién egresado | O35: Sí | P35: Sí | Q35: No | R35: Salma | S35: Sí | T35: 9 | U35: Joceline | V35: 0.7 | W35: 3.5 | X35: 0 | Y35: Sí | Z35: Sí | AA35: $3,799, $2,799 | AB35: Bot | AC35: 28.6 | AD35: 6 | AE35: 24 | AF35: 8 | AG35: Sí | AH35: Ruta, Clase demo | AI35: 0 | AJ35: Negativo | AK35: Perdido | AL35: Persona | AM35: Por el momento no | AN35: 101.4 | AO35: Sí | AP35: No | AQ35: No | AU35: 50% Descuento DC-3👉
A36: ISO + Calidad | B36: 366 | C36: 46301.44 | D36: 2026-S41 | E36: 10 | F36: Sí | G36: Sí | H36: Sí | I36: Sí | J36: 0.5 | K36: Salma | L36: Sí | M36: Sí | N36: Producción u operaciones | O36: Sí | P36: No | Q36: No | R36: Salma | S36: Sí | T36: 9.8 | U36: Joceline | V36: 1 | W36: 1.6 | X36: 0 | Y36: Sí | Z36: Sí | AA36: $3,799, $2,799 | AB36: Salma | AC36: 55.3 | AD36: 56 | AE36: 10 | AF36: 63 | AG36: No | AI36: 0 | AJ36: Negativo | AK36: Abierto | AO36: No | AQ36: No | AU36: 50% Descuento DC-3👉
A37: ISO + Calidad | B37: 367 | C37: 46301.445 | D37: 2026-S41 | E37: 10 | F37: Sí | G37: Sí | H37: Sí | I37: Sí | J37: 0.7 | K37: Joceline | L37: Sí | M37: Sí | N37: Calidad | O37: Sí | P37: No | Q37: No | R37: Salma | S37: Sí | T37: 13.7 | U37: Joceline | V37: 1.3 | W37: 6.9 | X37: 0 | Y37: Sí | Z37: Sí | AA37: $3,799, $2,799 | AB37: Bot | AC37: 26.4 | AD37: 8 | AE37: 22 | AF37: 9 | AG37: No | AI37: 0 | AJ37: Negativo | AK37: Perdido | AL37: Persona | AM37: No le interesa | AN37: 50.6 | AO37: Sí | AP37: No | AQ37: No | AU37: 50% Descuento DC-3👉
A38: ISO + Calidad | B38: 369 | C38: 46301.455 | D38: 2026-S41 | E38: 10 | F38: Sí | G38: Sí | H38: Sí | I38: Sí | J38: 0.5 | K38: Salma | L38: Sí | M38: Sí | N38: Ingeniería | O38: Sí | P38: Sí | Q38: No | R38: Salma | S38: No | T38: 20.6 | U38: Salma | V38: 9.2 | W38: 0.2 | X38: 0 | Y38: Sí | Z38: Sí | AA38: $3,799, $2,799 | AB38: Bot | AC38: 28.7 | AD38: 4 | AE38: 20 | AF38: 6 | AG38: No | AI38: 0 | AJ38: 1.2 Lista de cursos | AK38: Perdido | AL38: Persona | AM38: No contestaron | AN38: 75.4 | AO38: Sí | AP38: No | AQ38: No | AU38: 50% Descuento DC-3👉
A39: ISO + Calidad | B39: 370 | C39: 46301.459 | D39: 2026-S41 | E39: 11 | F39: Sí | G39: Sí | H39: Sí | I39: Sí | J39: 0.9 | K39: Salma | L39: Sí | M39: No | O39: No | P39: Sí | Q39: Sí | R39: Salma | S39: Sí | T39: 1315.7 | U39: Salma | V39: 0.9 | W39: 1313.7 | X39: 0 | Y39: No | Z39: Sí | AA39: $2,799 | AB39: Joceline | AC39: 22 | AD39: 10 | AE39: 9 | AF39: 2 | AG39: No | AI39: 0 | AJ39: Compró | AK39: Ganado | AO39: No | AQ39: Sí | AR39: 2799 | AS39: Pagada completa | AT39: 22 | AU39: 50% Descuento DC-3👉
A40: ISO + Calidad | B40: 376 | C40: 46301.486 | D40: 2026-S41 | E40: 11 | F40: Sí | G40: Sí | H40: Sí | I40: Sí | J40: 0.4 | K40: Salma | L40: Sí | M40: Sí | N40: Producción u operaciones | O40: Sí | P40: Sí | Q40: No | R40: Salma | S40: No | T40: 3.5 | U40: Salma | V40: 1.8 | W40: 2.1 | X40: 0 | Y40: Sí | Z40: Sí | AA40: $3,799, $2,799 | AB40: Bot | AC40: 28.7 | AD40: 4 | AE40: 20 | AF40: 7 | AG40: No | AI40: 0 | AJ40: 1.2 Lista de cursos | AK40: Perdido | AL40: Persona | AM40: No contestaron | AN40: 74.7 | AO40: Sí | AP40: No | AQ40: No | AU40: 50% Descuento DC-3👉
A41: ISO + Calidad | B41: 378 | C41: 46301.494 | D41: 2026-S41 | E41: 11 | F41: Sí | G41: No | H41: No | I41: Sí | K41: Bot | L41: Sí | M41: No | O41: Sí | P41: No | Q41: No | R41: Salma | S41: No | T41: 3246.1 | U41: Salma | V41: 3246.1 | X41: 0 | Y41: No | Z41: Sí | AA41: $3,799, $2,799 | AB41: Bot | AC41: 26.6 | AD41: 1 | AE41: 22 | AF41: 2 | AG41: No | AI41: 0 | AJ41: Solo su primer mensaje | AK41: Perdido | AL41: Persona | AM41: No contestaron | AN41: 118 | AO41: Sí | AP41: No | AQ41: No | AU41: Plano
A42: ISO + Calidad | B42: 379 | C42: 46301.495 | D42: 2026-S41 | E42: 11 | F42: Sí | G42: No | H42: No | I42: Sí | K42: Salma | L42: Sí | M42: No | O42: Sí | P42: Sí | Q42: No | R42: Salma | S42: Sí | T42: 135.5 | U42: Salma | V42: 135.5 | W42: 135.5 | X42: 0 | Y42: Sí | Z42: Sí | AA42: $3,799, $2,799 | AB42: Bot | AC42: 30.6 | AD42: 7 | AE42: 13 | AF42: 6 | AG42: No | AI42: 0 | AJ42: Saludo: contestó y no volvió | AK42: Perdido | AL42: Persona | AM42: No contestaron | AN42: 72.4 | AO42: Sí | AP42: No | AQ42: No
A43: ISO + Calidad | B43: 388 | C43: 46301.517 | D43: 2026-S41 | E43: 12 | F43: Sí | G43: Sí | H43: Sí | I43: Sí | J43: 0.7 | K43: Salma | L43: Sí | M43: Sí | N43: Calidad | O43: Sí | P43: Sí | Q43: No | R43: Salma | S43: No | T43: 6 | U43: Salma | V43: 0.9 | W43: 3.5 | X43: 0 | Y43: Sí | Z43: Sí | AA43: $3,799, $2,799 | AB43: Bot | AC43: 28.4 | AD43: 3 | AE43: 20 | AF43: 5 | AG43: No | AI43: 0 | AJ43: 1.2 Lista de cursos | AK43: Perdido | AL43: Persona | AM43: No contestaron | AN43: 74.1 | AO43: Sí | AP43: No | AQ43: No | AU43: 50% Descuento DC-3👉
A44: ISO + Calidad | B44: 392 | C44: 46301.521 | D44: 2026-S41 | E44: 12 | F44: Sí | G44: No | H44: No | I44: Sí | K44: Bot | L44: Sí | M44: No | O44: Sí | P44: No | Q44: No | R44: Salma | S44: No | T44: 6910.4 | U44: Salma | V44: 6910.4 | X44: 0 | Y44: No | Z44: Sí | AA44: $3,799, $2,799 | AB44: Bot | AC44: 26.6 | AD44: 1 | AE44: 23 | AF44: 1 | AG44: No | AI44: 0 | AJ44: Solo su primer mensaje | AK44: Perdido | AL44: Persona | AM44: No contestaron | AN44: 115.2 | AO44: Sí | AP44: No | AQ44: No | AU44: 50% Descuento DC-3👉
A45: ISO + Calidad | B45: 398 | C45: 46301.528 | D45: 2026-S41 | E45: 12 | F45: Sí | G45: Sí | H45: Sí | I45: Sí | J45: 0.1 | K45: Joceline | L45: Sí | M45: No | O45: Sí | P45: No | Q45: No | R45: Sin asignar | S45: Sí | V45: 1.5 | X45: 1 | Y45: No | Z45: Sí | AA45: $3,799, $2,799 | AB45: Bot | AC45: 26.1 | AD45: 2 | AE45: 22 | AF45: 0 | AG45: No | AI45: 0 | AJ45: Saludo: contestó y no volvió | AK45: Perdido | AL45: Bot | AM45: Sin razón | AN45: 120.3 | AO45: Sí | AP45: No | AQ45: No | AU45: 50% Descuento DC-3👉
A46: ISO + Calidad | B46: 404 | C46: 46301.537 | D46: 2026-S41 | E46: 12 | F46: Sí | G46: Sí | H46: Sí | I46: Sí | J46: 4.1 | K46: Victoria | L46: Sí | M46: No | O46: Sí | P46: No | Q46: No | R46: Victoria | S46: No | V46: 4.4 | X46: 1 | Y46: No | Z46: Sí | AA46: $3,799, $2,799 | AB46: Bot | AC46: 26.1 | AD46: 2 | AE46: 22 | AF46: 0 | AG46: Sí | AH46: Clase demo | AI46: 0 | AJ46: Saludo: contestó y no volvió | AK46: Perdido | AL46: Bot | AM46: Sin razón | AN46: 120.1 | AO46: Sí | AP46: No | AQ46: No | AU46: 50% Descuento DC-3👉
A47: ISO + Calidad | B47: 406 | C47: 46301.548 | D47: 2026-S41 | E47: 13 | F47: Sí | G47: Sí | H47: Sí | I47: Sí | J47: 0.3 | K47: Victoria | L47: Sí | M47: No | O47: Sí | P47: No | Q47: No | R47: Victoria | S47: No | V47: 0.7 | X47: 1 | Y47: No | Z47: Sí | AA47: $3,799, $2,799 | AB47: Bot | AC47: 26.1 | AD47: 2 | AE47: 22 | AF47: 0 | AG47: No | AI47: 0 | AJ47: Saludo: contestó y no volvió | AK47: Perdido | AL47: Bot | AM47: Sin razón | AN47: 119.9 | AO47: Sí | AP47: No | AQ47: No | AU47: 50% Descuento DC-3👉
A48: ISO + Calidad | B48: 407 | C48: 46301.548 | D48: 2026-S41 | E48: 13 | F48: Sí | G48: Sí | H48: Sí | I48: Sí | J48: 0.5 | K48: Alexander | L48: Sí | M48: No | O48: Sí | P48: No | Q48: No | R48: Alexander | S48: No | T48: 4582.6 | U48: Alexander | V48: 0.7 | W48: 4581.8 | X48: 0 | Y48: No | Z48: Sí | AA48: $3,799, $2,799 | AB48: Bot | AC48: 26.1 | AD48: 3 | AE48: 21 | AF48: 1 | AG48: No | AI48: 0 | AJ48: 1.2 Lista de cursos | AK48: Perdido | AL48: Persona | AM48: No contestaron | AN48: 76.4 | AO48: Sí | AP48: No | AQ48: No | AU48: 50% Descuento DC-3👉
A49: ISO + Calidad | B49: 413 | C49: 46301.569 | D49: 2026-S41 | E49: 13 | F49: Sí | G49: Sí | H49: Sí | I49: Sí | J49: 0.3 | K49: Alexander | L49: Sí | M49: No | O49: Sí | P49: No | Q49: No | R49: Alexander | S49: No | T49: 4552.7 | U49: Alexander | V49: 11 | W49: 4542 | X49: 0 | Y49: No | Z49: Sí | AA49: $3,799, $2,799 | AB49: Bot | AC49: 26.3 | AD49: 2 | AE49: 21 | AF49: 1 | AG49: No | AI49: 0 | AJ49: Saludo: contestó y no volvió | AK49: Perdido | AL49: Persona | AM49: No contestaron | AN49: 75.9 | AO49: Sí | AP49: No | AQ49: No | AU49: 50% Descuento DC-3👉
A50: ISO + Calidad | B50: 417 | C50: 46301.595 | D50: 2026-S41 | E50: 14 | F50: Sí | G50: Sí | H50: Sí | I50: Sí | J50: 3.2 | K50: Alexander | L50: Sí | M50: Sí | N50: Calidad | O50: Sí | P50: Sí | Q50: No | R50: Alexander | S50: No | T50: 12.6 | U50: Alexander | V50: 5.3 | W50: 2.1 | X50: 0 | Y50: Sí | Z50: Sí | AA50: $3,799, $2,799 | AB50: Alexander | AC50: 47.1 | AD50: 7 | AE50: 15 | AF50: 14 | AG50: No | AI50: 0 | AJ50: Negativo | AK50: Perdido | AL50: Persona | AM50: No contestaron | AN50: 75.4 | AO50: Sí | AP50: No | AQ50: No | AU50: 50% Descuento DC-3👉
A51: ISO + Calidad | B51: 422 | C51: 46301.623 | D51: 2026-S41 | E51: 14 | F51: Sí | G51: Sí | H51: Sí | I51: Sí | J51: 2.2 | K51: Alexander | L51: Sí | M51: No | O51: Sí | P51: No | Q51: No | R51: Alexander | S51: No | T51: 4471.9 | U51: Alexander | V51: 3.5 | W51: 4470.6 | X51: 0 | Y51: No | Z51: Sí | AA51: $3,799, $2,799 | AB51: Bot | AC51: 26.1 | AD51: 3 | AE51: 21 | AF51: 1 | AG51: Sí | AH51: Ruta | AI51: 0 | AJ51: Saludo: contestó y no volvió | AK51: Perdido | AL51: Persona | AM51: No contestaron | AN51: 74.5 | AO51: Sí | AP51: No | AQ51: No | AU51: 50% Descuento DC-3👉
A52: ISO + Calidad | B52: 423 | C52: 46301.626 | D52: 2026-S41 | E52: 15 | F52: Sí | G52: Sí | H52: Sí | I52: Sí | J52: 0.8 | K52: Joceline | L52: Sí | M52: Sí | N52: Producción u operaciones | O52: Sí | P52: Sí | Q52: No | R52: Alexander | S52: Sí | T52: 9 | U52: Alexander | V52: 2.6 | W52: 4.8 | X52: 0 | Y52: Sí | Z52: Sí | AA52: $3,799, $2,799 | AB52: Bot | AC52: 46 | AD52: 3 | AE52: 20 | AF52: 7 | AG52: Sí | AH52: Ruta | AI52: 0 | AJ52: 1.2 Lista de cursos | AK52: Perdido | AL52: Persona | AM52: No contestaron | AN52: 74.7 | AO52: Sí | AP52: No | AQ52: No | AU52: 50% Descuento DC-3👉
A53: ISO + Calidad | B53: 424 | C53: 46301.635 | D53: 2026-S41 | E53: 15 | F53: Sí | G53: No | H53: No | I53: Sí | K53: Bot | L53: Sí | M53: No | O53: Sí | P53: No | Q53: No | R53: Alexander | S53: No | T53: 4460.5 | U53: Alexander | V53: 4460.5 | X53: 0 | Y53: No | Z53: Sí | AA53: $3,799, $2,799 | AB53: Bot | AC53: 26.6 | AD53: 1 | AE53: 22 | AF53: 1 | AG53: No | AI53: 0 | AJ53: Solo su primer mensaje | AK53: Perdido | AL53: Persona | AM53: No contestaron | AN53: 74.4 | AO53: Sí | AP53: No | AQ53: No | AU53: Plano
A54: ISO + Calidad | B54: 430 | C54: 46301.652 | D54: 2026-S41 | E54: 15 | F54: Sí | G54: No | H54: No | I54: Sí | K54: Alexander | L54: Sí | M54: No | O54: No | P54: Sí | Q54: No | R54: Alexander | S54: Sí | T54: 0.6 | U54: Alexander | V54: 0.6 | W54: 2.6 | X54: 0 | Y54: No | Z54: No | AD54: 9 | AE54: 2 | AF54: 12 | AG54: No | AI54: 0 | AJ54: Facilidades de pago | AK54: Perdido | AL54: Persona | AM54: nos bloqueo | AN54: 214.4 | AO54: Sí | AP54: No | AQ54: No
A55: ISO + Calidad | B55: 433 | C55: 46301.664 | D55: 2026-S41 | E55: 15 | F55: Sí | G55: Sí | H55: Sí | I55: Sí | J55: 1 | K55: Alexander | L55: Sí | M55: Sí | N55: Calidad | O55: Sí | P55: Sí | Q55: No | R55: Salma | S55: No | T55: 6.4 | U55: Salma | V55: 1.4 | W55: 3.2 | X55: 1 | Y55: Sí | Z55: Sí | AA55: $3,799, $2,799 | AB55: Bot | AC55: 45.1 | AD55: 4 | AE55: 20 | AF55: 6 | AG55: Sí | AH55: Ruta, Clase demo | AI55: 0 | AJ55: Ya marcado como Perdido | AK55: Perdido | AL55: Persona | AM55: No contestaron | AN55: 114 | AO55: Sí | AP55: Sí | AQ55: No | AU55: 50% Descuento DC-3👉
A56: ISO + Calidad | B56: 435 | C56: 46301.675 | D56: 2026-S41 | E56: 16 | F56: Sí | G56: Sí | H56: Sí | I56: Sí | J56: 0.4 | K56: Victoria | L56: Sí | M56: Sí | N56: Producción u operaciones | O56: Sí | P56: Sí | Q56: No | R56: Victoria | S56: Sí | T56: 3.9 | U56: Victoria | V56: 0.7 | W56: 2.8 | X56: 0 | Y56: Sí | Z56: Sí | AA56: $3,799, $2,799 | AB56: Bot | AC56: 44.8 | AD56: 5 | AE56: 24 | AF56: 6 | AG56: No | AI56: 0 | AJ56: 1.2 Lista de cursos | AK56: Perdido | AL56: Persona | AM56: No contestaron | AN56: 139.9 | AO56: Sí | AP56: No | AQ56: No | AU56: 50% Descuento DC-3👉
A57: ISO + Calidad | B57: 438 | C57: 46301.695 | D57: 2026-S41 | E57: 16 | F57: Sí | G57: Sí | H57: Sí | I57: Sí | J57: 0.4 | K57: Victoria | L57: Sí | M57: Sí | N57: Calidad | O57: Sí | P57: Sí | Q57: No | R57: Victoria | S57: Sí | T57: 12.6 | U57: Victoria | V57: 1.7 | W57: 7.5 | X57: 0 | Y57: Sí | Z57: Sí | AA57: $3,799, $2,799 | AB57: Bot | AC57: 44.4 | AD57: 3 | AE57: 24 | AF57: 5 | AG57: No | AI57: 0 | AJ57: 1.2 Lista de cursos | AK57: Perdido | AL57: Persona | AM57: No contestaron | AN57: 139.5 | AO57: Sí | AP57: No | AQ57: No | AU57: 50% Descuento DC-3👉
A58: ISO + Calidad | B58: 440 | C58: 46301.7 | D58: 2026-S41 | E58: 16 | F58: Sí | G58: Sí | H58: Sí | I58: Sí | J58: 8.3 | K58: Victoria | L58: Sí | M58: No | O58: Sí | P58: No | Q58: No | R58: Salma | S58: No | T58: 4251.3 | U58: Salma | V58: 9.3 | W58: 4250.2 | X58: 0 | Y58: No | Z58: Sí | AA58: $3,799, $2,799 | AB58: Bot | AC58: 44.2 | AD58: 2 | AE58: 18 | AF58: 2 | AG58: Sí | AH58: Clase demo | AI58: 0 | AJ58: Saludo: contestó y no volvió | AK58: Perdido | AL58: Persona | AM58: No contestaron | AN58: 113.5 | AO58: Sí | AP58: No | AQ58: No | AU58: 50% Descuento DC-3👉
A59: ISO + Calidad | B59: 442 | C59: 46301.704 | D59: 2026-S41 | E59: 16 | F59: Sí | G59: Sí | H59: Sí | I59: Sí | J59: 0.9 | K59: Victoria | L59: Sí | M59: No | O59: Sí | P59: No | Q59: No | R59: Salma | S59: No | T59: 2977.5 | U59: Salma | V59: 1.3 | W59: 2977 | X59: 0 | Y59: No | Z59: Sí | AA59: $3,799, $2,799 | AB59: Bot | AC59: 26.1 | AD59: 2 | AE59: 21 | AF59: 2 | AG59: No | AI59: 0 | AJ59: Saludo: contestó y no volvió | AK59: Perdido | AL59: Persona | AM59: No contestaron | AN59: 113.4 | AO59: Sí | AP59: No | AQ59: No | AU59: 50% Descuento DC-3👉
A60: ISO + Calidad | B60: 450 | C60: 46301.736 | D60: 2026-S41 | E60: 17 | F60: Sí | G60: Sí | H60: Sí | I60: Sí | J60: 0.7 | K60: Victoria | L60: Sí | M60: Sí | N60: Calidad | O60: Sí | P60: Sí | Q60: No | R60: Alexander | S60: Sí | T60: 11.7 | U60: Alexander | V60: 0.9 | W60: 11.6 | X60: 0 | Y60: Sí | Z60: Sí | AA60: $3,799, $2,799 | AB60: Bot | AC60: 43.4 | AD60: 6 | AE60: 26 | AF60: 9 | AG60: No | AI60: 0 | AJ60: Facilidades de pago | AK60: Perdido | AL60: Persona | AM60: No contestaron | AN60: 138.5 | AO60: Sí | AP60: No | AQ60: No | AU60: 50% Descuento DC-3👉
A61: ISO + Calidad | B61: 454 | C61: 46301.768 | D61: 2026-S41 | E61: 18 | F61: Sí | G61: No | H61: No | I61: Sí | K61: Bot | L61: Sí | M61: No | O61: Sí | P61: No | Q61: No | R61: Salma | S61: No | T61: 4154.9 | U61: Salma | V61: 4154.9 | X61: 0 | Y61: No | Z61: Sí | AA61: $3,799, $2,799 | AB61: Bot | AC61: 42.6 | AD61: 1 | AE61: 19 | AF61: 2 | AG61: No | AI61: 0 | AJ61: Solo su primer mensaje | AK61: Perdido | AL61: Persona | AM61: No contestaron | AN61: 111.9 | AO61: Sí | AP61: No | AQ61: No | AU61: 50% Descuento DC-3👉
A62: ISO + Calidad | B62: 455 | C62: 46301.771 | D62: 2026-S41 | E62: 18 | F62: Sí | G62: Sí | H62: Sí | I62: Sí | J62: 0.3 | K62: Victoria | L62: Sí | M62: Sí | N62: Estudiante o recién egresado | O62: Sí | P62: Sí | Q62: No | R62: Alexander | S62: No | T62: 14.5 | U62: Alexander | V62: 0.6 | W62: 8 | X62: 0 | Y62: Sí | Z62: Sí | AA62: $3,799, $2,799 | AB62: Bot | AC62: 42.5 | AD62: 3 | AE62: 20 | AF62: 5 | AG62: No | AI62: 0 | AJ62: 1.2 Lista de cursos | AK62: Perdido | AL62: Persona | AM62: No contestaron | AN62: 71.2 | AO62: Sí | AP62: No | AQ62: No | AU62: 50% Descuento DC-3👉
A63: ISO + Calidad | B63: 459 | C63: 46301.796 | D63: 2026-S41 | E63: 19 | F63: Sí | G63: Sí | H63: Sí | I63: Sí | J63: 0.6 | K63: Alexander | L63: Sí | M63: Sí | N63: Calidad | O63: Sí | P63: Sí | Q63: No | R63: Alexander | S63: Sí | T63: 4.8 | U63: Alexander | V63: 0.8 | W63: 2.4 | X63: 0 | Y63: Sí | Z63: Sí | AA63: $3,799, $2,799 | AB63: Bot | AC63: 41.9 | AD63: 6 | AE63: 23 | AF63: 9 | AG63: Sí | AH63: Perfil ejemplo | AI63: 0 | AJ63: Negativo | AK63: Perdido | AL63: Persona | AM63: No contestaron | AN63: 158.4 | AO63: Sí | AP63: No | AQ63: No | AU63: 50% Descuento DC-3👉
A64: ISO + Calidad | B64: 461 | C64: 46301.814 | D64: 2026-S41 | E64: 19 | F64: Sí | G64: Sí | H64: Sí | I64: Sí | J64: 0.7 | K64: Alexander | L64: Sí | M64: Sí | N64: Sin empleo o buscando | O64: Sí | P64: Sí | Q64: No | R64: Alexander | S64: No | T64: 5.6 | U64: Alexander | V64: 1.2 | W64: 2.1 | X64: 0 | Y64: Sí | Z64: Sí | AA64: $3,799, $2,799 | AB64: Bot | AC64: 41.5 | AD64: 6 | AE64: 23 | AF64: 8 | AG64: Sí | AH64: Ruta | AI64: 0 | AJ64: Facilidades de pago | AK64: Perdido | AL64: Persona | AM64: No contestaron | AN64: 93.6 | AO64: Sí | AP64: No | AQ64: No | AU64: 50% Descuento DC-3👉
A65: ISO + Calidad | B65: 467 | C65: 46301.839 | D65: 2026-S41 | E65: 20 | F65: Sí | G65: No | H65: No | I65: Sí | K65: Bot | L65: Sí | M65: No | O65: Sí | P65: No | Q65: No | R65: Salma | S65: Sí | T65: 2224.9 | U65: Joceline | V65: 2224.9 | W65: 0.8 | X65: 0 | Y65: Sí | Z65: Sí | AA65: $3,799, $2,799 | AB65: Bot | AC65: 40.9 | AD65: 6 | AE65: 19 | AF65: 9 | AG65: No | AI65: 0 | AJ65: Negativo | AK65: Perdido | AL65: Persona | AM65: No contestaron | AN65: 110.2 | AO65: Sí | AP65: No | AQ65: No | AU65: 50% Descuento DC-3👉
A66: ISO + Calidad | B66: 474 | C66: 46301.853 | D66: 2026-S41 | E66: 20 | F66: Sí | G66: Sí | H66: Sí | I66: Sí | J66: 1.6 | K66: Victoria | L66: Sí | M66: No | O66: Sí | P66: No | Q66: No | R66: Salma | S66: No | T66: 4031.1 | U66: Salma | V66: 2.1 | W66: 4030.7 | X66: 0 | Y66: No | Z66: Sí | AA66: $3,799, $2,799 | AB66: Bot | AC66: 40.6 | AD66: 2 | AE66: 18 | AF66: 2 | AG66: No | AI66: 0 | AJ66: Saludo: contestó y no volvió | AK66: Perdido | AL66: Persona | AM66: No contestaron | AN66: 109.8 | AO66: Sí | AP66: No | AQ66: No | AU66: 50% Descuento DC-3👉
A67: ISO + Calidad | B67: 477 | C67: 46301.86 | D67: 2026-S41 | E67: 20 | F67: Sí | G67: No | H67: No | I67: Sí | K67: Joceline | L67: Sí | M67: No | O67: No | P67: Sí | Q67: Sí | R67: Victoria | S67: Sí | T67: 16.6 | U67: Victoria | V67: 16.6 | W67: 9 | X67: 0 | Y67: No | Z67: Sí | AA67: $2,799 | AB67: Joceline | AC67: 15.7 | AD67: 9 | AE67: 2 | AF67: 10 | AG67: No | AI67: 0 | AJ67: Compró | AK67: Ganado | AO67: No | AQ67: Sí | AR67: 2799 | AS67: Con saldo pendiente | AT67: 15.7
A68: ISO + Calidad | B68: 478 | C68: 46301.868 | D68: 2026-S41 | E68: 20 | F68: Sí | G68: Sí | H68: Sí | I68: Sí | J68: 0.2 | K68: Victoria | L68: Sí | M68: Sí | N68: Calidad | O68: Sí | P68: Sí | Q68: No | R68: Alexander | S68: Sí | T68: 20.2 | U68: Alexander | V68: 0.5 | W68: 10.2 | X68: 0 | Y68: Sí | Z68: Sí | AA68: $3,799, $2,799 | AB68: Bot | AC68: 40.2 | AD68: 3 | AE68: 24 | AF68: 3 | AG68: Sí | AH68: Mapa 64 | AI68: 0 | AJ68: 1.2 Lista de cursos | AK68: Perdido | AL68: Persona | AM68: No contestaron | AN68: 135.2 | AO68: Sí | AP68: No | AQ68: No | AU68: 50% Descuento DC-3👉
A69: ISO + Calidad | B69: 484 | C69: 46301.903 | D69: 2026-S41 | E69: 21 | F69: No | G69: Sí | H69: Sí | I69: Sí | J69: 0.6 | K69: Alexander | L69: Sí | M69: Sí | N69: Estudiante o recién egresado | O69: Sí | P69: Sí | Q69: No | R69: Alexander | S69: No | T69: 4.5 | U69: Alexander | V69: 1 | W69: 2.5 | X69: 0 | Y69: Sí | Z69: Sí | AA69: $3,799, $2,799 | AB69: Bot | AC69: 39.4 | AD69: 5 | AE69: 23 | AF69: 7 | AG69: No | AI69: 0 | AJ69: Facilidades de pago | AK69: Perdido | AL69: Persona | AM69: No contestaron | AN69: 91.5 | AO69: Sí | AP69: No | AQ69: No | AU69: 50% Descuento DC-3👉
A70: ISO + Calidad | B70: 487 | C70: 46301.91 | D70: 2026-S41 | E70: 21 | F70: No | G70: Sí | H70: Sí | I70: Sí | J70: 1 | K70: Victoria | L70: Sí | M70: Sí | N70: Sin empleo o buscando | O70: Sí | P70: Sí | Q70: No | R70: Victoria | S70: Sí | T70: 38.9 | U70: Victoria | V70: 1.4 | W70: 34.6 | X70: 0 | Y70: Sí | Z70: Sí | AA70: $3,799, $2,799 | AB70: Bot | AC70: 39.2 | AD70: 4 | AE70: 24 | AF70: 6 | AG70: No | AI70: 0 | AJ70: 1.2 Lista de cursos | AK70: Perdido | AL70: Persona | AM70: No contestaron | AN70: 134.3 | AO70: Sí | AP70: No | AQ70: No | AU70: 50% Descuento DC-3👉
A71: ISO + Calidad | B71: 489 | C71: 46301.918 | D71: 2026-S41 | E71: 22 | F71: No | G71: Sí | H71: Sí | I71: Sí | J71: 0.5 | K71: Alexander | L71: Sí | M71: No | O71: Sí | P71: No | Q71: No | R71: Alexander | S71: No | T71: 3925 | U71: Salma | V71: 1.7 | W71: 3923.8 | X71: 0 | Y71: No | Z71: Sí | AA71: $3,799, $2,799 | AB71: Bot | AC71: 39 | AD71: 3 | AE71: 18 | AF71: 2 | AG71: No | AI71: 0 | AJ71: Saludo: contestó y no volvió | AK71: Perdido | AL71: Persona | AM71: No contestaron | AN71: 108.1 | AO71: Sí | AP71: No | AQ71: No | AU71: 50% Descuento DC-3👉
A72: ISO + Calidad | B72: 492 | C72: 46301.935 | D72: 2026-S41 | E72: 22 | F72: No | G72: Sí | H72: Sí | I72: Sí | J72: 0.2 | K72: Victoria | L72: Sí | M72: No | O72: Sí | P72: No | Q72: No | R72: Salma | S72: No | T72: 3901.9 | U72: Salma | V72: 0.5 | W72: 3901.6 | X72: 0 | Y72: No | Z72: Sí | AA72: $3,799, $2,799 | AB72: Bot | AC72: 38.6 | AD72: 2 | AE72: 18 | AF72: 2 | AG72: No | AI72: 0 | AJ72: Saludo: contestó y no volvió | AK72: Perdido | AL72: Persona | AM72: No contestaron | AN72: 107.7 | AO72: Sí | AP72: No | AQ72: No | AU72: 50% Descuento DC-3👉
A73: ISO + Calidad | B73: 500 | C73: 46301.971 | D73: 2026-S41 | E73: 23 | F73: No | G73: No | H73: No | I73: Sí | K73: Bot | L73: Sí | M73: No | O73: Sí | P73: No | Q73: No | R73: Salma | S73: No | T73: 3851.9 | U73: Salma | V73: 3851.9 | X73: 0 | Y73: No | Z73: Sí | AA73: $3,799, $2,799 | AB73: Bot | AC73: 37.7 | AD73: 1 | AE73: 22 | AF73: 2 | AG73: No | AI73: 0 | AJ73: Solo su primer mensaje | AK73: Perdido | AL73: Persona | AM73: No contestaron | AN73: 106.8 | AO73: Sí | AP73: No | AQ73: No | AU73: 50% Descuento DC-3👉
A74: ISO + Calidad | B74: 502 | C74: 46301.973 | D74: 2026-S41 | E74: 23 | F74: No | G74: No | H74: No | I74: Sí | K74: Bot | L74: Sí | M74: No | O74: Sí | P74: No | Q74: No | R74: Salma | S74: No | T74: 3849.6 | U74: Salma | V74: 3849.6 | X74: 0 | Y74: No | Z74: Sí | AA74: $3,799, $2,799 | AB74: Bot | AC74: 37.7 | AD74: 1 | AE74: 19 | AF74: 2 | AG74: No | AI74: 0 | AJ74: Solo su primer mensaje | AK74: Perdido | AL74: Persona | AM74: No contestaron | AN74: 106.8 | AO74: Sí | AP74: No | AQ74: No | AU74: 50% Descuento DC-3👉
A75: ISO + Calidad | B75: 503 | C75: 46301.975 | D75: 2026-S41 | E75: 23 | F75: No | G75: Sí | H75: Sí | I75: Sí | J75: 457.9 | K75: Salma | L75: Sí | M75: No | O75: Sí | P75: No | Q75: No | R75: Salma | S75: No | T75: 3834.5 | U75: Salma | V75: 458.2 | W75: 3834.2 | X75: 0 | Y75: No | Z75: Sí | AA75: $3,799, $2,799 | AB75: Bot | AC75: 37.6 | AD75: 2 | AE75: 18 | AF75: 2 | AG75: No | AI75: 0 | AJ75: Saludo: contestó y no volvió | AK75: Perdido | AL75: Persona | AM75: No contestaron | AN75: 106.6 | AO75: Sí | AP75: No | AQ75: No | AU75: 50% Descuento DC-3👉
A76: ISO + Calidad | B76: 507 | C76: 46301.984 | D76: 2026-S41 | E76: 23 | F76: No | G76: Sí | H76: Sí | I76: Sí | J76: 446.9 | K76: Salma | L76: Sí | M76: No | O76: Sí | P76: No | Q76: No | R76: Salma | S76: No | T76: 3823.6 | U76: Salma | V76: 447.2 | W76: 3823.3 | X76: 0 | Y76: No | Z76: Sí | AA76: $3,799, $2,799 | AB76: Bot | AC76: 37.4 | AD76: 3 | AE76: 18 | AF76: 2 | AG76: No | AI76: 0 | AJ76: Saludo: contestó y no volvió | AK76: Perdido | AL76: Persona | AM76: No contestaron | AN76: 106.4 | AO76: Sí | AP76: No | AQ76: No | AU76: Plano
A77: ISO + Calidad | B77: 510 | C77: 46301.994 | D77: 2026-S41 | E77: 23 | F77: No | G77: Sí | H77: Sí | I77: Sí | J77: 432.7 | K77: Salma | L77: Sí | M77: Sí | N77: Producción u operaciones | O77: Sí | P77: Sí | Q77: No | R77: Salma | S77: No | T77: 438.7 | U77: Salma | V77: 432.9 | W77: 0.3 | X77: 0 | Y77: Sí | Z77: Sí | AA77: $3,799, $2,799 | AB77: Bot | AC77: 37.2 | AD77: 4 | AE77: 20 | AF77: 6 | AG77: No | AI77: 0 | AJ77: 1.2 Lista de cursos | AK77: Perdido | AL77: Persona | AM77: No contestaron | AN77: 106.2 | AO77: Sí | AP77: No | AQ77: No | AU77: 50% Descuento DC-3👉
A78: ISO + Calidad | B78: 512 | C78: 46302.061 | D78: 2026-S41 | E78: 1 | F78: No | G78: No | H78: No | I78: Sí | K78: Bot | L78: Sí | M78: No | O78: Sí | P78: No | Q78: No | R78: Salma | S78: No | T78: 3724 | U78: Salma | V78: 3724 | X78: 0 | Y78: No | Z78: Sí | AA78: $3,799, $2,799 | AB78: Bot | AC78: 35.6 | AD78: 1 | AE78: 19 | AF78: 2 | AG78: No | AI78: 0 | AJ78: Solo su primer mensaje | AK78: Perdido | AL78: Persona | AM78: No contestaron | AN78: 104.7 | AO78: Sí | AP78: No | AQ78: No | AU78: 50% Descuento DC-3👉
A79: ISO + Calidad | B79: 516 | C79: 46302.108 | D79: 2026-S41 | E79: 2 | F79: No | G79: Sí | H79: Sí | I79: Sí | J79: 269.5 | K79: Salma | L79: Sí | M79: No | O79: Sí | P79: No | Q79: No | R79: Salma | S79: No | T79: 3645.5 | U79: Salma | V79: 269.7 | W79: 3645.3 | X79: 0 | Y79: No | Z79: Sí | AA79: $3,799, $2,799 | AB79: Bot | AC79: 34.5 | AD79: 2 | AE79: 18 | AF79: 2 | AG79: No | AI79: 0 | AJ79: Saludo: contestó y no volvió | AK79: Perdido | AL79: Persona | AM79: No contestaron | AN79: 103.5 | AO79: Sí | AP79: No | AQ79: No | AU79: 50% Descuento DC-3👉
A80: ISO + Calidad | B80: 518 | C80: 46302.206 | D80: 2026-S41 | E80: 4 | F80: No | G80: No | H80: No | I80: Sí | K80: Bot | L80: Sí | M80: No | O80: Sí | P80: No | Q80: No | R80: Salma | S80: No | T80: 3516.5 | U80: Salma | V80: 3516.5 | X80: 0 | Y80: No | Z80: Sí | AA80: $3,799, $2,799 | AB80: Bot | AC80: 32.1 | AD80: 1 | AE80: 19 | AF80: 2 | AG80: No | AI80: 0 | AJ80: Solo su primer mensaje | AK80: Perdido | AL80: Persona | AM80: No contestaron | AN80: 101.2 | AO80: Sí | AP80: No | AQ80: No | AU80: 50% Descuento DC-3👉
A81: ISO + Calidad | B81: 520 | C81: 46302.257 | D81: 2026-S41 | E81: 6 | F81: No | G81: No | H81: No | I81: Sí | K81: Bot | L81: Sí | M81: No | O81: Sí | P81: No | Q81: No | R81: Salma | S81: No | T81: 3446.4 | U81: Salma | V81: 3446.4 | X81: 0 | Y81: No | Z81: Sí | AA81: $3,799, $2,799 | AB81: Bot | AC81: 30.9 | AD81: 1 | AE81: 19 | AF81: 2 | AG81: No | AI81: 0 | AJ81: Solo su primer mensaje | AK81: Perdido | AL81: Persona | AM81: No contestaron | AN81: 100.1 | AO81: Sí | AP81: No | AQ81: No | AU81: 50% Descuento DC-3👉
A82: ISO + Calidad | B82: 524 | C82: 46302.29 | D82: 2026-S41 | E82: 6 | F82: No | G82: No | H82: No | I82: Sí | K82: Bot | L82: Sí | M82: No | O82: Sí | P82: No | Q82: No | R82: Salma | S82: No | T82: 3401.3 | U82: Salma | V82: 3401.3 | X82: 0 | Y82: No | Z82: Sí | AA82: $3,799, $2,799 | AB82: Bot | AC82: 30.1 | AD82: 1 | AE82: 19 | AF82: 2 | AG82: No | AI82: 0 | AJ82: Solo su primer mensaje | AK82: Perdido | AL82: Persona | AM82: No contestaron | AN82: 99.3 | AO82: Sí | AP82: No | AQ82: No | AU82: 50% Descuento DC-3👉
A83: ISO + Calidad | B83: 530 | C83: 46302.317 | D83: 2026-S41 | E83: 7 | F83: No | G83: Sí | H83: Sí | I83: Sí | J83: 0.8 | K83: Salma | L83: Sí | M83: No | O83: Sí | P83: No | Q83: No | R83: Salma | S83: No | T83: 3355.8 | U83: Salma | V83: 1.4 | W83: 3355.2 | X83: 0 | Y83: No | Z83: Sí | AA83: $3,799, $2,799 | AB83: Bot | AC83: 29.4 | AD83: 2 | AE83: 18 | AF83: 2 | AG83: No | AI83: 0 | AJ83: Saludo: contestó y no volvió | AK83: Perdido | AL83: Persona | AM83: No contestaron | AN83: 98.5 | AO83: Sí | AP83: No | AQ83: No | AU83: 50% Descuento DC-3👉
A84: ISO + Calidad | B84: 549 | C84: 46302.38 | D84: 2026-S41 | E84: 9 | F84: Sí | G84: No | H84: No | I84: Sí | K84: Bot | L84: Sí | M84: No | O84: Sí | P84: No | Q84: No | R84: Salma | S84: No | T84: 3434 | U84: Salma | V84: 3434 | X84: 0 | Y84: No | Z84: Sí | AA84: $3,799, $2,799 | AB84: Bot | AC84: 27.9 | AD84: 1 | AE84: 22 | AF84: 2 | AG84: No | AI84: 0 | AJ84: Solo su primer mensaje | AK84: Perdido | AL84: Persona | AM84: No contestaron | AN84: 97.6 | AO84: Sí | AP84: No | AQ84: No | AU84: 50% Descuento DC-3👉
A85: ISO + Calidad | B85: 551 | C85: 46302.383 | D85: 2026-S41 | E85: 9 | F85: Sí | G85: Sí | H85: Sí | I85: Sí | J85: 0.4 | K85: Joceline | L85: Sí | M85: Sí | N85: Otra área | O85: Sí | P85: Sí | Q85: No | R85: Sin asignar | S85: Sí | T85: 25.3 | U85: Joceline | V85: 0.2 | W85: 20.6 | X85: 0 | Y85: Sí | Z85: Sí | AA85: $3,799, $2,799 | AB85: Bot | AC85: 28.7 | AD85: 4 | AE85: 24 | AF85: 10 | AG85: No | AI85: 0 | AJ85: 1.2 Lista de cursos | AK85: Perdido | AL85: Persona | AM85: No contestaron | AN85: 123.1 | AO85: Sí | AP85: No | AQ85: No
A86: ISO + Calidad | B86: 568 | C86: 46302.424 | D86: 2026-S41 | E86: 10 | F86: Sí | G86: Sí | H86: Sí | I86: Sí | J86: 0.6 | K86: Joceline | L86: Sí | M86: Sí | N86: Ingeniería | O86: Sí | P86: No | Q86: No | R86: Salma | S86: Sí | T86: 7.8 | U86: Joceline | V86: 3.4 | W86: 4.1 | X86: 0 | Y86: Sí | Z86: Sí | AA86: $3,799, $2,799 | AB86: Bot | AC86: 26.8 | AD86: 5 | AE86: 18 | AF86: 8 | AG86: No | AI86: 0 | AJ86: 1.2 Lista de cursos | AK86: Perdido | AL86: Persona | AM86: No contestaron | AN86: 96.5 | AO86: Sí | AP86: No | AQ86: No | AU86: 50% Descuento DC-3👉
A87: ISO + Calidad | B87: 570 | C87: 46302.427 | D87: 2026-S41 | E87: 10 | F87: Sí | G87: Sí | H87: Sí | I87: Sí | J87: 0.8 | K87: Joceline | L87: Sí | M87: No | O87: Sí | P87: No | Q87: No | R87: Alexander | S87: Sí | T87: 460.3 | U87: Alexander | V87: 1 | W87: 232.1 | X87: 0 | Y87: No | Z87: Sí | AA87: $3,799, $2,799 | AB87: Alexander | AC87: 30.9 | AD87: 3 | AE87: 13 | AF87: 7 | AG87: Sí | AH87: Ruta | AI87: 0 | AJ87: Negativo | AK87: Perdido | AL87: Persona | AM87: No contestaron | AN87: 75.5 | AO87: Sí | AP87: No | AQ87: No | AU87: 50% Descuento DC-3👉
A88: ISO + Calidad | B88: 572 | C88: 46302.432 | D88: 2026-S41 | E88: 10 | F88: Sí | G88: Sí | H88: Sí | I88: Sí | J88: 1.4 | K88: Joceline | L88: Sí | M88: Sí | N88: Estudiante o recién egresado | O88: Sí | P88: No | Q88: No | R88: Salma | S88: Sí | T88: 11.2 | U88: Joceline | V88: 2.3 | W88: 6.2 | X88: 0 | Y88: Sí | Z88: Sí | AA88: $3,799, $2,799 | AB88: Bot | AC88: 26.7 | AD88: 5 | AE88: 18 | AF88: 7 | AG88: No | AI88: 0 | AJ88: 1.2 Lista de cursos | AK88: Perdido | AL88: Persona | AM88: No contestaron | AN88: 96.2 | AO88: Sí | AP88: No | AQ88: No | AU88: 50% Descuento DC-3👉
A89: ISO + Calidad | B89: 575 | C89: 46302.441 | D89: 2026-S41 | E89: 10 | F89: Sí | G89: Sí | H89: Sí | I89: Sí | J89: 2.2 | K89: Joceline | L89: Sí | M89: Sí | N89: Calidad | O89: Sí | P89: Sí | Q89: No | R89: Salma | S89: Sí | T89: 26.1 | U89: Joceline | V89: 3.1 | W89: 16.7 | X89: 0 | Y89: Sí | Z89: Sí | AA89: $3,799, $2,799 | AB89: Bot | AC89: 28.8 | AD89: 3 | AE89: 20 | AF89: 5 | AG89: Sí | AH89: Ruta | AI89: 0 | AJ89: 1.2 Lista de cursos | AK89: Perdido | AL89: Persona | AM89: No contestaron | AN89: 95.8 | AO89: Sí | AP89: No | AQ89: No | AU89: 50% Descuento DC-3👉
A90: ISO + Calidad | B90: 578 | C90: 46302.46 | D90: 2026-S41 | E90: 11 | F90: Sí | G90: No | H90: No | I90: Sí | K90: Bot | L90: Sí | M90: No | O90: Sí | P90: No | Q90: No | R90: Salma | S90: No | T90: 3313.4 | U90: Salma | V90: 3313.4 | X90: 0 | Y90: No | Z90: Sí | AA90: $3,799, $2,799 | AB90: Bot | AC90: 26.6 | AD90: 1 | AE90: 19 | AF90: 2 | AG90: No | AI90: 0 | AJ90: Solo su primer mensaje | AK90: Perdido | AL90: Persona | AM90: No contestaron | AN90: 95.5 | AO90: Sí | AP90: No | AQ90: No | AU90: 50% Descuento DC-3👉
A91: ISO + Calidad | B91: 579 | C91: 46302.461 | D91: 2026-S41 | E91: 11 | F91: Sí | G91: Sí | H91: Sí | I91: Sí | J91: 0.3 | K91: Salma | L91: Sí | M91: No | O91: Sí | P91: No | Q91: No | R91: Salma | S91: No | T91: 3306.5 | U91: Salma | V91: 0.7 | W91: 3306.2 | X91: 2 | Y91: No | Z91: Sí | AA91: $3,799, $2,799 | AB91: Bot | AC91: 26.1 | AD91: 4 | AE91: 31 | AF91: 1 | AG91: Sí | AH91: Clase demo | AI91: 0 | AJ91: Saludo: contestó y no volvió | AK91: Perdido | AL91: Persona | AM91: No contestaron | AN91: 118.1 | AO91: Sí | AP91: No | AQ91: No | AU91: 50% Descuento DC-3👉
A92: ISO + Calidad | B92: 580 | C92: 46302.464 | D92: 2026-S41 | E92: 11 | F92: Sí | G92: Sí | H92: Sí | I92: Sí | J92: 0.4 | K92: Salma | L92: Sí | M92: No | O92: Sí | P92: No | Q92: No | R92: Salma | S92: No | T92: 3302.8 | U92: Salma | V92: 0.6 | W92: 3302.5 | X92: 0 | Y92: No | Z92: Sí | AA92: $3,799, $2,799 | AB92: Bot | AC92: 26.1 | AD92: 2 | AE92: 18 | AF92: 2 | AG92: No | AI92: 0 | AJ92: Saludo: contestó y no volvió | AK92: Perdido | AL92: Persona | AM92: No contestaron | AN92: 95.3 | AO92: Sí | AP92: No | AQ92: No | AU92: 50% Descuento DC-3👉
A93: ISO + Calidad | B93: 581 | C93: 46302.464 | D93: 2026-S41 | E93: 11 | F93: Sí | G93: Sí | H93: Sí | I93: Sí | J93: 0.4 | K93: Salma | L93: Sí | M93: No | O93: Sí | P93: No | Q93: No | R93: Salma | S93: No | T93: 3302.9 | U93: Salma | V93: 0.7 | W93: 3302.6 | X93: 0 | Y93: No | Z93: Sí | AA93: $3,799, $2,799 | AB93: Bot | AC93: 26.1 | AD93: 2 | AE93: 18 | AF93: 2 | AG93: No | AI93: 0 | AJ93: Saludo: contestó y no volvió | AK93: Perdido | AL93: Persona | AM93: No contestaron | AN93: 95.3 | AO93: Sí | AP93: No | AQ93: No | AU93: 50% Descuento DC-3👉
A94: ISO + Calidad | B94: 585 | C94: 46302.477 | D94: 2026-S41 | E94: 11 | F94: Sí | G94: Sí | H94: Sí | I94: Sí | J94: 1.5 | K94: Salma | L94: Sí | M94: Sí | N94: Supervisión o jefatura | O94: No | P94: Sí | Q94: No | R94: Salma | S94: Sí | T94: 5.2 | U94: Salma | V94: 1.7 | W94: 2.7 | X94: 0 | Y94: Sí | Z94: Sí | AA94: $3,799, $2,799 | AB94: Joceline | AC94: 50.5 | AD94: 5 | AE94: 10 | AF94: 10 | AG94: Sí | AH94: Ruta | AI94: 0 | AJ94: Facilidades de pago | AK94: Perdido | AL94: Persona | AM94: No contestaron | AN94: 99.7 | AO94: Sí | AP94: No | AQ94: No | AU94: 50% Descuento DC-3👉
A95: ISO + Calidad | B95: 586 | C95: 46302.483 | D95: 2026-S41 | E95: 11 | F95: Sí | G95: Sí | H95: Sí | I95: Sí | J95: 1.5 | K95: Salma | L95: Sí | M95: Sí | N95: Producción u operaciones | O95: Sí | P95: No | Q95: No | R95: Salma | S95: Sí | T95: 179.5 | U95: Salma | V95: 1.9 | W95: 1.2 | X95: 0 | Y95: Sí | Z95: Sí | AA95: $3,799, $2,799 | AB95: Bot | AC95: 26.1 | AD95: 5 | AE95: 18 | AF95: 11 | AG95: Sí | AH95: Ruta | AI95: 0 | AJ95: Negativo | AK95: Perdido | AL95: Persona | AM95: No contestaron | AN95: 94.9 | AO95: Sí | AP95: No | AQ95: No | AU95: 50% Descuento DC-3👉
A96: ISO + Calidad | B96: 590 | C96: 46302.506 | D96: 2026-S41 | E96: 12 | F96: Sí | G96: Sí | H96: Sí | I96: Sí | J96: 0.5 | K96: Salma | L96: Sí | M96: No | O96: Sí | P96: Sí | Q96: No | R96: Salma | S96: No | T96: 1484.3 | U96: Salma | V96: 7.3 | W96: 1477.5 | X96: 0 | Y96: No | Z96: Sí | AA96: $3,799, $2,799 | AB96: Bot | AC96: 26.2 | AD96: 4 | AE96: 28 | AF96: 3 | AG96: Sí | AH96: Clase demo, Mapa 64, Perfil ejemplo | AI96: 0 | AJ96: Negativo | AK96: Perdido | AL96: Persona | AM96: No contestaron | AN96: 117.2 | AO96: Sí | AP96: No | AQ96: No | AU96: 50% Descuento DC-3👉
A97: ISO + Calidad | B97: 592 | C97: 46302.51 | D97: 2026-S41 | E97: 12 | F97: Sí | G97: Sí | H97: Sí | I97: Sí | J97: 1 | K97: Salma | L97: Sí | M97: No | O97: Sí | P97: No | Q97: No | R97: Salma | S97: No | T97: 3245.1 | U97: Salma | V97: 1.2 | W97: 3244.9 | X97: 0 | Y97: No | Z97: Sí | AA97: $3,799, $2,799 | AB97: Bot | AC97: 26.1 | AD97: 2 | AE97: 18 | AF97: 2 | AG97: Sí | AH97: Ruta | AI97: 0 | AJ97: Saludo: contestó y no volvió | AK97: Perdido | AL97: Persona | AM97: No contestaron | AN97: 94.5 | AO97: Sí | AP97: No | AQ97: No | AU97: GreenBelt
A98: ISO + Calidad | B98: 600 | C98: 46302.533 | D98: 2026-S41 | E98: 12 | F98: Sí | G98: No | H98: No | I98: Sí | K98: Bot | L98: Sí | M98: No | O98: Sí | P98: No | Q98: No | R98: Salma | S98: No | T98: 3214.7 | U98: Salma | V98: 3214.7 | X98: 0 | Y98: No | Z98: Sí | AA98: $3,799, $2,799 | AB98: Bot | AC98: 26.6 | AD98: 1 | AE98: 19 | AF98: 2 | AG98: No | AI98: 0 | AJ98: Solo su primer mensaje | AK98: Perdido | AL98: Persona | AM98: No contestaron | AN98: 94 | AO98: Sí | AP98: No | AQ98: No | AU98: 50% Descuento DC-3👉
A99: ISO + Calidad | B99: 601 | C99: 46302.534 | D99: 2026-S41 | E99: 12 | F99: Sí | G99: Sí | H99: Sí | I99: Sí | J99: 2.8 | K99: Joceline | L99: Sí | M99: Sí | N99: Calidad | O99: Sí | P99: Sí | Q99: No | R99: Victoria | S99: Sí | T99: 24.7 | U99: Victoria | V99: 3 | W99: 17.6 | X99: 0 | Y99: Sí | Z99: Sí | AA99: $3,799, $2,799 | AB99: Bot | AC99: 28.7 | AD99: 4 | AE99: 30 | AF99: 9 | AG99: Sí | AH99: Ruta, Mapa 64 | AI99: 0 | AJ99: Negativo | AK99: Perdido | AL99: Persona | AM99: No contestaron | AN99: 140.2 | AO99: Sí | AP99: No | AQ99: No | AU99: 50% Descuento DC-3👉
A100: ISO + Calidad | B100: 611 | C100: 46302.558 | D100: 2026-S41 | E100: 13 | F100: Sí | G100: No | H100: No | I100: Sí | K100: Bot | L100: Sí | M100: No | O100: Sí | P100: No | Q100: No | R100: Salma | S100: No | T100: 3178.7 | U100: Salma | V100: 3178.7 | X100: 0 | Y100: No | Z100: Sí | AA100: $3,799, $2,799 | AB100: Bot | AC100: 26.6 | AD100: 1 | AE100: 19 | AF100: 2 | AG100: No | AI100: 0 | AJ100: Solo su primer mensaje | AK100: Perdido | AL100: Persona | AM100: No contestaron | AN100: 93.4 | AO100: Sí | AP100: No | AQ100: No | AU100: 50% Descuento DC-3👉
...

Sheet Respuestas
A1: Embudo | B1: ID (#) | C1: Mensaje del lead | D1: Hora | E1: ¿De 9 a 21 h? | F1: Etapa en ese momento | G1: ¿Le contestó una persona? | H1: Minutos hasta la respuesta de una persona | I1: Primero le contestó
A2: ISO + Calidad | B2: 276 | C2: 46300.516 | D2: 12 | E2: Sí | F2: 1 Saludo | G2: Sí | H2: 3.5 | I2: Bot
A3: ISO + Calidad | B3: 276 | C3: 46300.518 | D3: 12 | E3: Sí | F3: 1.1 / 1.2 Informes y lista | G3: Sí | H3: 0.2 | I3: Persona
A4: ISO + Calidad | B4: 276 | C4: 46300.519 | D4: 12 | E4: Sí | F4: 1.1 / 1.2 Informes y lista | G4: Sí | H4: 0.1 | I4: Persona
A5: ISO + Calidad | B5: 276 | C5: 46300.52 | D5: 12 | E5: Sí | F5: 1.1 / 1.2 Informes y lista | G5: Sí | H5: 0.2 | I5: Persona
A6: ISO + Calidad | B6: 278 | C6: 46300.521 | D6: 12 | E6: Sí | F6: 1 Saludo | G6: Sí | H6: 3.6 | I6: Bot
A7: ISO + Calidad | B7: 278 | C7: 46300.524 | D7: 12 | E7: Sí | F7: 1.1 / 1.2 Informes y lista | G7: Sí | H7: 0.2 | I7: Persona
A8: ISO + Calidad | B8: 278 | C8: 46300.526 | D8: 12 | E8: Sí | F8: Facilidades de pago | G8: Sí | H8: 0.5 | I8: Persona
A9: ISO + Calidad | B9: 278 | C9: 46300.527 | D9: 12 | E9: Sí | F9: Facilidades de pago | G9: Sí | H9: 4584.4 | I9: Bot
A10: ISO + Calidad | B10: 282 | C10: 46300.535 | D10: 12 | E10: Sí | F10: 1 Saludo | G10: Sí | H10: 0.4 | I10: Bot
A11: ISO + Calidad | B11: 291 | C11: 46300.572 | D11: 13 | E11: Sí | F11: 1 Saludo | G11: Sí | H11: 4538 | I11: Bot
A12: ISO + Calidad | B12: 277 | C12: 46300.592 | D12: 14 | E12: Sí | F12: 1.1 / 1.2 Informes y lista | G12: Sí | H12: 2.2 | I12: Bot
A13: ISO + Calidad | B13: 277 | C13: 46300.592 | D13: 14 | E13: Sí | F13: 1.1 / 1.2 Informes y lista | G13: Sí | H13: 1 | I13: Persona
... A83: ISO + Calidad | B83: 366 | C83: 46301.522 | D83: 12 | E83: Sí | F83: 1.1 / 1.2 Informes y lista | G83: Sí | H83: 5.7 | I83: Bot
A84: ISO + Calidad | B84: 398 | C84: 46301.529 | D84: 12 | E84: Sí | F84: 1 Saludo | G84: No | I84: Bot
A85: ISO + Calidad | B85: 404 | C85: 46301.538 | D85: 12 | E85: Sí | F85: 1 Saludo | G85: No | I85: Bot
A86: ISO + Calidad | B86: 406 | C86: 46301.548 | D86: 13 | E86: Sí | F86: 1 Saludo | G86: No | I86: Bot
A87: ISO + Calidad | B87: 407 | C87: 46301.548 | D87: 13 | E87: Sí | F87: 1 Saludo | G87: Sí | H87: 4582.4 | I87: Bot
A88: ISO + Calidad | B88: 407 | C88: 46301.549 | D88: 13 | E88: Sí | F88: 1.1 / 1.2 Informes y lista | G88: Sí | H88: 4581.2 | I88: Bot
A89: ISO + Calidad | B89: 413 | C89: 46301.577 | D89: 13 | E89: Sí | F89: 1 Saludo | G89: Sí | H89: 4542 | I89: Bot
A90: ISO + Calidad | B90: 417 | C90: 46301.596 | D90: 14 | E90: Sí | F90: 1 Saludo | G90: Sí | H90: 10.5 | I90: Bot
A91: ISO + Calidad | B91: 417 | C91: 46301.603 | D91: 14 | E91: Sí | F91: 1.1 / 1.2 Informes y lista | G91: Sí | H91: 0.8 | I91: Persona
A92: ISO + Calidad | B92: 417 | C92: 46301.609 | D92: 14 | E92: Sí | F92: Facilidades de pago | G92: Sí | H92: 0.8 | I92: Persona
A93: ISO + Calidad | B93: 422 | C93: 46301.624 | D93: 14 | E93: Sí | F93: 1 Saludo | G93: Sí | H93: 4470.6 | I93: Bot
A94: ISO + Calidad | B94: 423 | C94: 46301.627 | D94: 15 | E94: Sí | F94: 1 Saludo | G94: Sí | H94: 7.2 | I94: Bot
A95: ISO + Calidad | B95: 423 | C95: 46301.63 | D95: 15 | E95: Sí | F95: 1.1 / 1.2 Informes y lista | G95: Sí | H95: 2.5 | I95: Persona
A96: ISO + Calidad | B96: 366 | C96: 46301.649 | D96: 15 | E96: Sí | F96: Negativo | G96: Sí | H96: 0.6 | I96: Persona
A97: ISO + Calidad | B97: 430 | C97: 46301.652 | D97: 15 | E97: Sí | F97: 1 Saludo | G97: Sí | H97: 0.6 | I97: Persona
A98: ISO + Calidad | B98: 430 | C98: 46301.657 | D98: 15 | E98: Sí | F98: 1 Saludo | G98: Sí | H98: 1.3 | I98: Persona
... A349: ISO + Calidad | B349: 892 | C349: 46303.803 | D349: 19 | E349: Sí | F349: Negativo | G349: Sí | H349: 0.7 | I349: Persona
A350: ISO + Calidad | B350: 287 | C350: 46303.826 | D350: 19 | E350: Sí | F350: Perdido | G350: No | I350: Nadie
A351: ISO + Calidad | B351: 937 | C351: 46303.866 | D351: 20 | E351: Sí | F351: 1 Saludo | G351: Sí | H351: 4.8 | I351: Bot
A352: ISO + Calidad | B352: 590 | C352: 46303.867 | D352: 20 | E352: Sí | F352: Negativo | G352: Sí | H352: 5070.3 | I352: Bot
A353: ISO + Calidad | B353: 937 | C353: 46303.869 | D353: 20 | E353: Sí | F353: 1.1 / 1.2 Informes y lista | G353: Sí | H353: 1.5 | I353: Persona
A354: ISO + Calidad | B354: 937 | C354: 46303.87 | D354: 20 | E354: Sí | F354: 1.1 / 1.2 Informes y lista | G354: Sí | H354: 1.1 | I354: Persona
A355: ISO + Calidad | B355: 937 | C355: 46303.873 | D355: 20 | E355: Sí | F355: 1.1 / 1.2 Informes y lista | G355: Sí | H355: 0.3 | I355: Persona
A356: ISO + Calidad | B356: 937 | C356: 46303.876 | D356: 21 | E356: No | F356: 1.1 / 1.2 Informes y lista | G356: Sí | H356: 11.6 | I356: Persona
A357: ISO + Calidad | B357: 937 | C357: 46303.885 | D357: 21 | E357: No | F357: 1.1 / 1.2 Informes y lista | G357: Sí | H357: 1.2 | I357: Persona
A358: ISO + Calidad | B358: 944 | C358: 46303.887 | D358: 21 | E358: No | F358: 1 Saludo | G358: Sí | H358: 3776 | I358: Bot
A359: ISO + Calidad | B359: 959 | C359: 46304.004 | D359: 0 | E359: No | F359: 1 Saludo | G359: Sí | H359: 3603.3 | I359: Bot
A360: ISO + Calidad | B360: 961 | C360: 46304.088 | D360: 2 | E360: No | F360: 1.1 / 1.2 Informes y lista | G360: Sí | H360: 311 | I360: Persona
A361: ISO + Calidad | B361: 973 | C361: 46304.31 | D361: 7 | E361: No | F361: 1 Saludo | G361: Sí | H361: 6.4 | I361: Bot
A362: ISO + Calidad | B362: 973 | C362: 46304.312 | D362: 7 | E362: No | F362: 1.1 / 1.2 Informes y lista | G362: Sí | H362: 2.9 | I362: Bot
... A417: ISO + Calidad | B417: 1082 | C417: 46304.787 | D417: 18 | E417: Sí | F417: 1.1 / 1.2 Informes y lista | G417: Sí | H417: 3.6 | I417: Persona
A418: ISO + Calidad | B418: 336 | C418: 46304.835 | D418: 20 | E418: Sí | F418: Perdido | G418: No | I418: Nadie
A419: ISO + Calidad | B419: 762 | C419: 46304.836 | D419: 20 | E419: Sí | F419: Negativo | G419: Sí | H419: 57.2 | I419: Persona
A420: ISO + Calidad | B420: 1109 | C420: 46304.843 | D420: 20 | E420: Sí | F420: 1 Saludo | G420: Sí | H420: 3845.1 | I420: Bot
A421: ISO + Calidad | B421: 1106 | C421: 46304.843 | D421: 20 | E421: Sí | F421: 1.1 / 1.2 Informes y lista | G421: Sí | H421: 2.2 | I421: Persona
A422: ISO + Calidad | B422: 348 | C422: 46304.852 | D422: 20 | E422: Sí | F422: Forma o medio de pago | G422: Sí | H422: 34.3 | I422: Persona
A423: ISO + Calidad | B423: 1112 | C423: 46304.875 | D423: 20 | E423: Sí | F423: 1 Saludo | G423: Sí | H423: 8.8 | I423: Bot
A424: ISO + Calidad | B424: 1112 | C424: 46304.877 | D424: 21 | E424: No | F424: 1.1 / 1.2 Informes y lista | G424: Sí | H424: 4.9 | I424: Bot
A425: ISO + Calidad | B425: 1112 | C425: 46304.877 | D425: 21 | E425: No | F425: 1.1 / 1.2 Informes y lista | G425: Sí | H425: 4.9 | I425: Persona
A426: ISO + Calidad | B426: 1122 | C426: 46304.924 | D426: 22 | E426: No | F426: 1 Saludo | G426: Sí | H426: 576.3 | I426: Bot
A427: ISO + Calidad | B427: 1122 | C427: 46304.927 | D427: 22 | E427: No | F427: 1.1 / 1.2 Informes y lista | G427: Sí | H427: 573 | I427: Persona
A428: ISO + Calidad | B428: 1131 | C428: 46304.993 | D428: 23 | E428: No | F428: 1 Saludo | G428: Sí | H428: 506.6 | I428: Bot
A429: ISO + Calidad | B429: 1137 | C429: 46305.196 | D429: 4 | E429: No | F429: 1 Saludo | G429: Sí | H429: 230.2 | I429: Bot
A430: ISO + Calidad | B430: 1142 | C430: 46305.262 | D430: 6 | E430: No | F430: 1 Saludo | G430: Sí | H430: 3243.3 | I430: Bot
... A514: ISO + Calidad | B514: 1001 | C514: 46305.625 | D514: 15 | E514: Sí | F514: 1 Saludo | G514: Sí | H514: 23.4 | I514: Persona
A515: ISO + Calidad | B515: 579 | C515: 46305.636 | D515: 15 | E515: Sí | F515: Negativo | G515: No | I515: Bot
A516: ISO + Calidad | B516: 579 | C516: 46305.638 | D516: 15 | E516: Sí | F516: 1 Saludo | G516: No | I516: Bot
A517: ISO + Calidad | B517: 1204 | C517: 46305.668 | D517: 16 | E517: Sí | F517: 1 Saludo | G517: Sí | H517: 1316 | I517: Bot
A518: ISO + Calidad | B518: 1213 | C518: 46305.728 | D518: 17 | E518: Sí | F518: 1 Saludo | G518: Sí | H518: 4.5 | I518: Bot
A519: ISO + Calidad | B519: 1213 | C519: 46305.731 | D519: 17 | E519: Sí | F519: 1.1 / 1.2 Informes y lista | G519: Sí | H519: 0.4 | I519: Persona
A520: ISO + Calidad | B520: 1213 | C520: 46305.731 | D520: 17 | E520: Sí | F520: 1.1 / 1.2 Informes y lista | G520: Sí | H520: 4.6 | I520: Persona
A521: ISO + Calidad | B521: 1213 | C521: 46305.742 | D521: 17 | E521: Sí | F521: Facilidades de pago | G521: Sí | H521: 2.9 | I521: Persona
A522: ISO + Calidad | B522: 1213 | C522: 46305.76 | D522: 18 | E522: Sí | F522: Facilidades de pago | G522: Sí | H522: 1.9 | I522: Persona
A523: ISO + Calidad | B523: 1213 | C523: 46305.779 | D523: 18 | E523: Sí | F523: Facilidades de pago | G523: Sí | H523: 2.9 | I523: Persona
A524: ISO + Calidad | B524: 1234 | C524: 46305.818 | D524: 19 | E524: Sí | F524: 1 Saludo | G524: Sí | H524: 3.4 | I524: Bot
A525: ISO + Calidad | B525: 1233 | C525: 46305.82 | D525: 19 | E525: Sí | F525: 1 Saludo | G525: Sí | H525: 5.3 | I525: Bot
A526: ISO + Calidad | B526: 1234 | C526: 46305.82 | D526: 19 | E526: Sí | F526: 1.1 / 1.2 Informes y lista | G526: Sí | H526: 0.6 | I526: Persona
A527: ISO + Calidad | B527: 1234 | C527: 46305.821 | D527: 19 | E527: Sí | F527: 1.1 / 1.2 Informes y lista | G527: Sí | H527: 2.7 | I527: Persona
A528: ISO + Calidad | B528: 1233 | C528: 46305.822 | D528: 19 | E528: Sí | F528: 1.1 / 1.2 Informes y lista | G528: Sí | H528: 1.7 | I528: Persona
... A570: ISO + Calidad | B570: 752 | C570: 46306.638 | D570: 15 | E570: Sí | F570: Negativo | G570: Sí | H570: 0.6 | I570: Persona
A571: ISO + Calidad | B571: 433 | C571: 46306.642 | D571: 15 | E571: Sí | F571: Perdido | G571: No | I571: Nadie
A572: ISO + Calidad | B572: 1299 | C572: 46306.657 | D572: 15 | E572: Sí | F572: Negativo | G572: Sí | H572: 0.1 | I572: Persona
A573: ISO + Calidad | B573: 1330 | C573: 46306.702 | D573: 16 | E573: Sí | F573: 1 Saludo | G573: Sí | H573: 1178.1 | I573: Bot
A574: ISO + Calidad | B574: 1324 | C574: 46306.705 | D574: 16 | E574: Sí | F574: 1.1 / 1.2 Informes y lista | G574: Sí | H574: 283.3 | I574: Bot
A575: ISO + Calidad | B575: 1334 | C575: 46306.721 | D575: 17 | E575: Sí | F575: 1 Saludo | G575: Sí | H575: 7.7 | I575: Bot
A576: ISO + Calidad | B576: 1334 | C576: 46306.723 | D576: 17 | E576: Sí | F576: 1.1 / 1.2 Informes y lista | G576: Sí | H576: 4.4 | I576: Persona
A577: ISO + Calidad | B577: 1338 | C577: 46306.744 | D577: 17 | E577: Sí | F577: 1 Saludo | G577: Sí | H577: 2649.1 | I577: Bot
A578: ISO + Calidad | B578: 1270 | C578: 46306.762 | D578: 18 | E578: Sí | F578: Negativo | G578: Sí | H578: 4.1 | I578: Persona
A579: ISO + Calidad | B579: 1340 | C579: 46306.763 | D579: 18 | E579: Sí | F579: 1 Saludo | G579: Sí | H579: 2904.9 | I579: Bot
A580: ISO + Calidad | B580: 1343 | C580: 46306.791 | D580: 18 | E580: Sí | F580: 1 Saludo | G580: Sí | H580: 13.5 | I580: Bot
A581: ISO + Calidad | B581: 1343 | C581: 46306.794 | D581: 19 | E581: Sí | F581: 1.1 / 1.2 Informes y lista | G581: Sí | H581: 9.6 | I581: Persona
A582: ISO + Calidad | B582: 1368 | C582: 46306.893 | D582: 21 | E582: No | F582: 1 Saludo | G582: Sí | H582: 4.3 | I582: Bot
A583: ISO + Calidad | B583: 1368 | C583: 46306.896 | D583: 21 | E583: No | F583: 1.1 / 1.2 Informes y lista | G583: Sí | H583: 1 | I583: Persona
... A613: ISO + Calidad | B613: 1439 | C613: 46307.449 | D613: 10 | E613: Sí | F613: 1.1 / 1.2 Informes y lista | G613: Sí | H613: 0.3 | I613: Persona
A614: ISO + Calidad | B614: 1014 | C614: 46307.462 | D614: 11 | E614: Sí | F614: Perdido | G614: No | I614: Nadie
A615: ISO + Calidad | B615: 366 | C615: 46307.469 | D615: 11 | E615: Sí | F615: Negativo | G615: Sí | H615: 1 | I615: Persona
A616: ISO + Calidad | B616: 366 | C616: 46307.47 | D616: 11 | E616: Sí | F616: Negativo | G616: Sí | H616: 0.2 | I616: Persona
A617: ISO + Calidad | B617: 366 | C617: 46307.47 | D617: 11 | E617: Sí | F617: Negativo | G617: Sí | H617: 0.4 | I617: Persona
A618: ISO + Calidad | B618: 366 | C618: 46307.476 | D618: 11 | E618: Sí | F618: Negativo | G618: Sí | H618: 0.5 | I618: Persona
A619: ISO + Calidad | B619: 1456 | C619: 46307.481 | D619: 11 | E619: Sí | F619: 1 Saludo | G619: Sí | H619: 7.9 | I619: Bot
A620: ISO + Calidad | B620: 1456 | C620: 46307.485 | D620: 11 | E620: Sí | F620: 1.1 / 1.2 Informes y lista | G620: Sí | H620: 2 | I620: Persona
A621: ISO + Calidad | B621: 1456 | C621: 46307.486 | D621: 11 | E621: Sí | F621: 1.1 / 1.2 Informes y lista | G621: Sí | H621: 0.6 | I621: Persona
A622: ISO + Calidad | B622: 1456 | C622: 46307.487 | D622: 11 | E622: Sí | F622: 1.1 / 1.2 Informes y lista | G622: Sí | H622: 0.1 | I622: Persona
A623: ISO + Calidad | B623: 670 | C623: 46307.491 | D623: 11 | E623: Sí | F623: Forma o medio de pago | G623: Sí | H623: 1.1 | I623: Persona
A624: ISO + Calidad | B624: 1456 | C624: 46307.497 | D624: 11 | E624: Sí | F624: Facilidades de pago | G624: Sí | H624: 0.4 | I624: Persona
A625: ISO + Calidad | B625: 1456 | C625: 46307.5 | D625: 12 | E625: Sí | F625: Facilidades de pago | G625: Sí | H625: 1.2 | I625: Persona
A626: ISO + Calidad | B626: 1456 | C626: 46307.506 | D626: 12 | E626: Sí | F626: Facilidades de pago | G626: Sí | H626: 0.6 | I626: Persona
...

Sheet Notas
A1: DESARROLLO PROFESIONAL SyS
A2: Notas y definiciones
A3: ISO + Calidad · cómo se midió cada dato
A5: Período | B5: Del 5 al 15 de octubre de 2026: la semana completa del 5 al 11 (S41) y 4 días de la siguiente (S42, del 12 al 15). El CRM atiende leads nuevos desde el 5 de octubre; lo anterior está en Kommo y no se incluye.
A6: Corte | B6: Todo se midió hasta el 15 de octubre a las 23:59 h (hora de Monterrey): solo cuentan leads que entraron hasta esa hora, y los mensajes, cambios de etapa y ventas que pasaron hasta esa hora, aunque el lead haya avanzado el 16. Así el As Is no se mueve.
A7: Fuente | B7: CRM de SyS. Se usó el usuario de Joceline, que ve todos los embudos.
A8: Cómo se midió | B8: Solo lectura: tablero de cada embudo, historial de etapas y mensajes de cada lead, y la configuración de los bots. Solo se hicieron consultas: no se movió, editó ni envió nada, y ni siquiera se marcaron los chats como vistos.
A9: A qué embudo pertenece un lead | B9: Al primer embudo de venta al que entró (sin contar «Leads entrantes», que solo reparte). 4 leads de los 3 embudos se movieron después a otro embudo y siguen contando en el de entrada.
A10: Entrada | B10: Cuando el lead escribió por primera vez. Casi todos pasan al embudo en menos de un segundo. 5 leads (4 de ISO + Calidad y 1 de Core Tools Premium) los atendió una persona desde «Leads entrantes», sin bot, y pasaron al embudo ya avanzados; 3 de ellos son ventas.
A11: Exclusiones | B11: Se excluyeron 2 leads de prueba interna del 8 de septiembre (#1 «Prueba» y #7 «Hoolaa»), creados cuando se armó el embudo.
A12: Privacidad | B12: Sin nombres, teléfonos ni textos de los leads. Del equipo solo aparece el nombre con el que se le conoce. En los textos del bot se ocultan los datos bancarios.
A13: Horario | B13: «De 9 a 21 h» es el horario de los bots en el CRM (los 7 días). En la práctica el equipo escribe de 7 a 22 h.
A14: Contestó el saludo | B14: Escribió algo después de que el bot pidió el nombre y antes de salir de 1 Saludo. Es la misma regla que usa el bot: si contesta en 30 min, el bot reacciona y se detiene.
A15: Dio su nombre | B15: El nombre que quedó en el contacto aparece en lo que contestó al saludo. A quien no contestó, el bot lo llama «Inge».
A16: Minutos de su respuesta a 1.1 | B16: Desde su primera respuesta al saludo hasta que pasó a 1.1 (o a una etapa más lejana). Solo para quien contestó.
... A29: Etapas de este embudo | B29: Saludo = «1 Saludo» · Negativo = «1 Negativo» · Facilidades de pago = «1.3 Llamadita y facilidades de pago», «1.4 Facilidades de pago» · Forma de pago = «2 Una sola exhibición», «2 Parcialidades», «MSI», «2 MSI 3999», «MSI 2799», «3 Transferencia / OXXO», «3 PayPal», «3 Débito / Crédito»
A31: Textos del bot por etapa · ISO + Calidad (configuración vigente desde el 5 de octubre)
A32: Etapa | B32: Mensaje o acción | C32: Espera
A33: 1 Saludo | B33: ¡Hola excelente día Inge👋! Te saluda *Salma Pérez* de _*SyS*_ 😊 Con mucho gusto te comparto la información referente a los cursos que solicitas.
A34: 1 Saludo | B34: (pausa) | C34: 3 s
A35: 1 Saludo | B35: Para continuar, ¿Me puedes compartir tu nombre? 🙌
A36: 1 Saludo | B36: Espera la respuesta del lead | C36: 30 min
A37: 1 Saludo | B37: (pausa) | C37: 5 s
A38: 1 Saludo | B38: Reacciona al mensaje del lead
A39: 1 Saludo | B39: Se detiene y espera a una persona
A40: 1 Saludo | B40: Hola Inge👋 no te preocupes, igual te comparto la información del curso por si te interesa. Si después me pasas tu nombre, con gusto te la personalizo 😊
A41: 1 Saludo | B41: Guarda nombre = «Inge»
A42: 1 Saludo | B42: (pausa) | C42: 8 s
A43: 1 Saludo | B43: Pasa a «1.1 Informes»
A44: 1.1 Informes | B44: Excelente {{nombre}} que gustazo! Muchas gracias por interesarte🙌 Te explico rapidito, tu programa *ISO + Calidad* son *9 certificaciones*, y por cada una se entrega diploma y constancia *DC-3 avalada ante la STPS*. Van en ruta: arrancas con ISO 9001 y cierras con Liderazgo, para que al final tengas el perfil completo de Calidad y no cursos sueltos. Y algunas cuentan con *Certificación Internacional*, que le da más peso a tu currículum 🏅
A45: 1.1 Informes | B45: (pausa) | C45: 8 s
A46: 1.1 Informes | B46: Pasa a «1.2 Lista de cursos»
A47: 1.2 Lista de cursos | B47: Aquí te comparto tus *9 certificaciones* con sus horas académicas y costo total😊 [con archivo]
A48: 1.2 Lista de cursos | B48: (pausa) | C48: 7 s
A49: 1.2 Lista de cursos | B49: Y aquí puedes abrir el temario de cada una, ver cuánto dura y qué documento te llevas 👇 https://academy.dpsys.com.mx/ruta-iso/{{numero}}
A50: 1.2 Lista de cursos | B50: (pausa) | C50: 7 s
A51: 1.2 Lista de cursos | B51: Y para que sepas cómo funciona aquí en SyS {{nombre}} 🙌 Cuando compras una ruta con nosotros, tienes acceso a *todas las demás rutas* y a todo nuestro catálogo — que actualmente son *64 certificaciones*. Tu ruta es *ISO + Calidad*: esas 9 son las que te voy llevando en orden hasta que las termines. El resto se queda abierto por si algún día lo ocupas.
A52: 1.2 Lista de cursos | B52: (pausa) | C52: 2 min
A53: 1.2 Lista de cursos | B53: Solo una pregunta {{nombre}}, ¿en qué área trabajas actualmente? o ¿estás estudiando? Así te armo cuáles de los otros cursos del catálogo te conviene tomar *además de tus 9* 🙌
A54: 1.2 Lista de cursos | B54: (pausa) | C54: 2 h
A55: 1.2 Lista de cursos | B55: Pasa a «1 Negativo»
A56: 1 Negativo (solo en horario) | B56: Si Paso del negativo = «1», salta a otro paso
A57: 1 Negativo (solo en horario) | B57: Si Paso del negativo = «2», salta a otro paso
A58: 1 Negativo (solo en horario) | B58: Si Paso del negativo = «3», salta a otro paso
A59: 1 Negativo (solo en horario) | B59: [con archivo]
A60: 1 Negativo (solo en horario) | B60: (pausa) | C60: 3 s
A61: 1 Negativo (solo en horario) | B61: [con archivo]
A62: 1 Negativo (solo en horario) | B62: (pausa) | C62: 8 s
A63: 1 Negativo (solo en horario) | B63: Además, aquí puedes buscar por nombre a cualquiera de nuestros egresados y verificar su certificación tú mismo. Es una bitácora pública, no un testimonio que yo te cuente 👇 https://academy.dpsys.com.mx/egresados
A64: 1 Negativo (solo en horario) | B64: Guarda Paso del negativo = «1»
A65: 1 Negativo (solo en horario) | B65: (pausa) | C65: 2 h
A66: 1 Negativo (solo en horario) | B66: {{nombre}}, antes de que tomes una decisión, quiero que conozcas exactamente lo que vas a recibir 🙌 Aquí puedes ver una *clase demo completa, gratis y sin registro:* https://academy.dpsys.com.mx/clase-demo/{{numero}} Así puedes conocer la plataforma y nuestra forma de explicar antes de inscribirte.
A67: 1 Negativo (solo en horario) | B67: (pausa) | C67: 8 s
A68: 1 Negativo (solo en horario) | B68: Cuando la veas, dime qué te pareció y te ayudo con lo siguiente 😊
A69: 1 Negativo (solo en horario) | B69: Guarda Paso del negativo = «2»
A70: 1 Negativo (solo en horario) | B70: (pausa) | C70: 18 h
A71: 1 Negativo (solo en horario) | B71: Que onda {{nombre}}, recuerda que esta membresía incluye las demás rutas🦾
A72: 1 Negativo (solo en horario) | B72: (pausa) | C72: 8 s
A73: 1 Negativo (solo en horario) | B73: En total son *64 certificaciones*. Estoy seguro de que te van a ayudar un montón
A74: 1 Negativo (solo en horario) | B74: (pausa) | C74: 8 s
A75: 1 Negativo (solo en horario) | B75: Puedes empezar por tu ruta que son 9 certificaciones y de ahí pasarte a otros cursos🙌 https://academy.dpsys.com.mx/mapa/{{numero}} Te comparto *todos los cursos* que vas a obtener☝️
A76: 1 Negativo (solo en horario) | B76: (pausa) | C76: 1 min
A77: 1 Negativo (solo en horario) | B77: Si te interesa aprovechar la membresía, dime y te comparto las *facilidades de pago y los medios disponibles para que puedas iniciar*🙌
A78: 1 Negativo (solo en horario) | B78: (pausa) | C78: 4 h
A79: 1 Negativo (solo en horario) | B79: ¡Qué tal, Inge! 😊 ⚡ ¡Tenemos una OFERTA RELÁMPAGO disponible solo por hoy! ⚡ Esta oferta está disponible únicamente para las primeras 3 personas que realicen su apartado o pago. 🎓 Llévate los 64 cursos de la membresía + sus certificaciones correspondientes por solo $3,799 MXN. Contamos con diferentes opciones de pago para facilitar tu inscripción. 🙌 ¿Quieres que te comparta los medios de pago disponibles para aprovechar la oferta? 🤗
A80: 1 Negativo (solo en horario) | B80: Espera la respuesta del lead | C80: 18 h
A81: 1 Negativo (solo en horario) | B81: Si mensaje = «Reservar mi lugar», salta a otro paso
A82: 1 Negativo (solo en horario) | B82: Si mensaje = «Ver métodos pago», salta a otro paso
A83: 1 Negativo (solo en horario) | B83: Guarda Paso del negativo = «3»
A84: 1 Negativo (solo en horario) | B84: (pausa) | C84: 18 h
A85: 1 Negativo (solo en horario) | B85: Da clic en *"leer más"* para darle más valor a tu *CV* 👇 Algo que debes saber es que algunos de nuestros cursos incluidos en la membresía cuentan con *Certificación Internacional*, lo que respalda los conocimientos y habilidades que desarrollas durante tu formación. Al finalizar tus cursos puedes contar con un *perfil profesional público con tus certificaciones*, horas de capacitación, DC-3 y competencias desarrolladas, para compartirlo en tu CV o LinkedIn. Así puede verse tu perfil👇: https://academy.dpsys.com.mx/demo-perfil-ingeniero/{{numero}} ¿Qué tanto valor crees que tendría esto para tu crecimiento profesional? 🙌
A86: 1 Negativo (solo en horario) | B86: (pausa) | C86: 4 h
A87: 1 Negativo (solo en horario) | B87: Inge, te aviso antes de cerrar la promoción 👌 [con archivo]
A88: 1 Negativo (solo en horario) | B88: (pausa) | C88: 8 s
A89: 1 Negativo (solo en horario) | B89: Nos quedan 4 lugares y hoy puedo dejarte la membresía anual de _$3,999_ en *$2,799 MXN.*
A90: 1 Negativo (solo en horario) | B90: (pausa) | C90: 24 h
A91: 1 Negativo (solo en horario) | B91: La promoción la cerramos *hoy.* *¿Te aparto uno de los 4 lugares?*
A92: 1 Negativo (solo en horario) | B92: (pausa) | C92: 24 h
A93: 1 Negativo (solo en horario) | B93: Pasa a «Perdido»
A94: 1 Negativo (solo en horario) | B94: (pausa) | C94: 10 s
A95: 1 Negativo (solo en horario) | B95: Pasa a «1.4 Facilidades de pago»
A96: 1.3 Llamadita y facilidades de pago | B96: (pausa) | C96: 5 min
A97: 1.3 Llamadita y facilidades de pago | B97: Igual si gustas {{nombre}} te puedo hacer una llamadita para explicarte todo más claro
A98: 1.3 Llamadita y facilidades de pago | B98: (pausa) | C98: 10 min
A99: 1.3 Llamadita y facilidades de pago | B99: También para que sea más accesible, tenemos facilidades de pago💳 ¿Quieres que te muestre cómo quedaría en tu caso?
A100: 1.3 Llamadita y facilidades de pago | B100: (pausa) | C100: 4 h
A101: 1.3 Llamadita y facilidades de pago | B101: Pasa a «1 Negativo»
A102: 1.4 Facilidades de pago | B102: Manejamos 3 facilidades de pago: *Pago en una sola exhibición *Pago en 3 parcialidades *Meses sin intereses (3, 6 , 9 Y 12 meses) con tu tarjeta de crédito
A103: 1.4 Facilidades de pago | B103: (pausa) | C103: 5 s
A104: 1.4 Facilidades de pago | B104: Cuál de estos 3 te interesa más {{nombre}}?
A105: 1.4 Facilidades de pago | B105: (pausa) | C105: 4 h
A106: 1.4 Facilidades de pago | B106: Pasa a «1 Negativo»
A107: 2 Una sola exhibición | B107: Excelente, mira lo puedes realizar a través de: -Paypal -Tarjetas de débito/crédito. -Transferencias electrónicas. -Depósitos/Pago en Oxxo Que opción tomarías {{nombre}}?
A108: 2 Una sola exhibición | B108: (pausa) | C108: 4 h
A109: 2 Una sola exhibición | B109: Pasa a «1 Negativo»
A110: 2 Parcialidades | B110: Excelente, mira te comparto como quedaría el desglose de tus pagos a continuación 🤗
A111: 2 Parcialidades | B111: (pausa) | C111: 5 min
A112: 2 Parcialidades | B112: Lo puedes realizar a través de: -Paypal -Tarjetas de débito/crédito. -Transferencias electrónicas. -Depósitos/Pago en Oxxo Que opción tomarías {{nombre}} ?
A113: 2 Parcialidades | B113: (pausa) | C113: 4 h
A114: 2 Parcialidades | B114: Pasa a «1 Negativo»
...
